Workbook

Sheet Competitive Analysis
C2: BELLA MIRAGE — 5-Mile Competitive Supply
B3: 2022–2026 New Construction | 5-mile radius | As of 2026 Q2 QTD | Stabilization Target: | G3: 95% target
B4: # | C4: Property | D4: Units | E4: Est. Delivery | F4: Occupancy | G4: Avg Mkt Rent | H4: Owner | I4: Proximity | J4: Type | K4: Notes
C5: STABILIZED / STABILIZING (22 properties, 5,296 units)
B6: 1 | C6: Luna Bear 94 | D6: 94 | E6: Q1 2022 | F6: 0.989362 | G6: 1913 | H6: Luna Bear Properties LLC | I6: 4.1 | J6: Single Family
B7: 2 | C7: Cyrene at Estrella | D7: 64 | E7: Q1 2022 | F7: 0.984375 | G7: 2442 | H7: BGO | I7: 4.4 | J7: Single Family | K7: Year built: 2022/2023; Delivery quarter estimated; Rent: CoStar ask $2,442 vs RealPage eff $2,261
B8: 3 | C8: Sunset View Apartments | D8: 286 | E8: Q2 2022 | F8: 0.902098 | G8: 1338 | H8: Sunrise Multifamily LLC | I8: 3.7 | J8: Garden | K8: Occ: CoStar 90% vs RealPage 96%; Rent: CoStar ask $1,338 vs RealPage eff $1,167
B9: 4 | C9: Avari Apartments | D9: 354 | E9: Q3 2022 | F9: 0.951977 | G9: 1574 | H9: Brett C. & Lorraine M. Heers | I9: 2.6 | J9: Mid-Rise | K9: Year built: 2022/2023; Delivery quarter estimated; Occ: CoStar 95% vs RealPage 100%
B10: 5 | C10: Prose Desert River | D10: 384 | E10: Q1 2023 | F10: 0.895833 | G10: 1429 | H10: Alliance Residential Company | I10: 4.8 | J10: Garden | K10: Year built: 2023/2024; Delivery quarter estimated; Occ: CoStar 90% vs RealPage 97%; Rent: CoStar ask $1,429 vs RealPage eff $1,313
B11: 6 | C11: District at Civic Square | D11: 352 | E11: Q1 2023 | F11: 0.920455 | G11: 1526 | H11: Billah Khan | I11: 4 | J11: Mid-Rise | K11: Year built: 2023/2024; Delivery quarter estimated; Occ: CoStar 92% vs RealPage 100%; Rent: CoStar ask $1,526 vs RealPage eff $1,263
B12: 7 | C12: Acero Roosevelt | D12: 352 | E12: Q1 2023 | F12: 0.892045 | G12: 1632 | H12: IDM Companies | I12: 5.8 | J12: Garden | K12: Year built: 2023/2024; Delivery quarter estimated; Occ: CoStar 89% vs RealPage 94%; Rent: CoStar ask $1,632 vs RealPage eff $1,236
B13: 8 | C13: Cabana Bullard | D13: 336 | E13: Q1 2023 | F13: 0.949405 | G13: 1335 | H13: Greenlight Communities | I13: 4.1 | J13: Garden | K13: Delivery quarter estimated
B14: 9 | C14: Bungalows at Camelback | D14: 334 | E14: Q1 2023 | F14: 0.763473 | G14: 2026 | H14: Cavan Companies | I14: 3.3 | J14: Garden | K14: Year built: 2023/2024; Delivery quarter estimated; Occ: CoStar 76% vs RealPage 92%; Rent: CoStar ask $2,026 vs RealPage eff $1,385
B15: 10 | C15: Cuvee Apartments | D15: 310 | E15: Q1 2023 | F15: 0.926 | G15: — | H15: Pillar Communities | I15: 5.3 | J15: Mid-Rise | K15: Delivery quarter estimated
B16: 11 | C16: Springs At Westgate | D16: 292 | E16: Q1 2023 | F16: 0.784247 | G16: 1516 | H16: Continental Properties Company, Inc. | I16: 4.3 | J16: Garden | K16: Year built: 2023/2024; Delivery quarter estimated; Occ: CoStar 78% vs RealPage 87%
B17: 12 | C17: BB Living at Civic Square | D17: 290 | E17: Q1 2023 | F17: 0.934483 | G17: 2812 | H17: BB Living | I17: 3.7 | J17: Townhome | K17: Year built: 2023/2024; Delivery quarter estimated; Occ: CoStar 93% vs RealPage 96%; Rent: CoStar ask $2,812 vs RealPage eff $2,575
B18: 13 | C18: Village at Paseo de Luces | D18: 272 | E18: Q1 2023 | F18: 0.926471 | G18: 1820 | H18: Empire Group of Companies | I18: 4.1 | J18: Garden | K18: Year built: 2023/2024; Delivery quarter estimated; Occ: CoStar 93% vs RealPage 97%; Rent: CoStar ask $1,820 vs RealPage eff $1,597
B19: 14 | C19: Parc Lofts | D19: 258 | E19: Q1 2023 | F19: 0.899225 | G19: 1567 | H19: Millburn & Company | I19: 4.6 | J19: Garden | K19: Delivery quarter estimated; Occ: CoStar 90% vs RealPage 94%
B20: 15 | C20: Christopher Todd Communities at McDowell | D20: 217 | E20: Q1 2023 | F20: 0.949309 | G20: 1576 | H20: Christopher Todd Communities | I20: 1.9 | J20: Garden | K20: Year built: 2023/2024; Delivery quarter estimated
B21: 16 | C21: Village Camelback Park | D21: 194 | E21: Q1 2023 | F21: 0.773196 | G21: 1874 | H21: The Empire Group | I21: 1.9 | J21: Single Family | K21: Delivery quarter estimated; Occ: CoStar 77% vs RealPage 92%
B22: 17 | C22: Village at the BLVD | D22: 187 | E22: Q1 2023 | F22: 0.935829 | G22: 1964 | H22: Empire Group of Companies | I22: 4 | J22: Single Family | K22: Year built: 2023/2024; Delivery quarter estimated; Occ: CoStar 94% vs RealPage 96%
B23: 18 | C23: The Crofton at Sheely Farms | D23: 167 | E23: Q1 2023 | F23: 0.952096 | G23: 1607 | H23: Atlantic Creek Real Estate Partners | I23: 5.3 | J23: Garden | K23: Delivery quarter estimated; Rent: CoStar ask $1,607 vs RealPage eff $1,388
B24: 19 | C24: TerraLane at Park McDowell | D24: 162 | E24: Q1 2023 | F24: 0.851852 | G24: 1576 | H24: TerraLane Communities | I24: 3.5 | J24: Garden | K24: Delivery quarter estimated; Occ: CoStar 85% vs RealPage 88%; Rent: CoStar ask $1,576 vs RealPage eff $1,211
B25: 20 | C25: Ironwood Homes at River Run | D25: 103 | E25: Q1 2023 | F25: 0.893204 | G25: 2523 | H25: Sunstone Properties Trust | I25: 1.1 | J25: Garden | K25: Delivery quarter estimated
B26: 21 | C26: Avery | D26: 185 | E26: Q2 2024 | F26: 0.924324 | G26: 1750 | H26: Larson Capital Management | I26: 1.1 | J26: Garden | K26: Rent: CoStar ask $1,750 vs RealPage eff $1,875
B27: 22 | C27: Ironwood at River Run | D27: 103 | E27: Q2 2024 | F27: 0.961 | G27: — | H27: Rockpoint Group | I27: 1.3 | J27: Single Family | K27: Delivery quarter estimated
C29: LEASING UP (28 properties, 7,249 units)
B30: 23 | C30: Radia Avondale Station | D30: 407 | E30: Q1 2024 | F30: 0.616708 | G30: 1743 | H30: Goodman Real Estate Inc. | I30: 3.1 | J30: Garden | K30: Units: CoStar 407 vs RealPage 212; Year built: 2024/2025; Delivery quarter estimated; Occ: CoStar 62% vs RealPage 51%; Verify rent/occ w/ HelloData
B31: 24 | C31: Alta 99th | D31: 402 | E31: Q1 2024 | F31: 0.855721 | G31: 1542 | H31: Wood Partners | I31: 3.1 | J31: Garden | K31: Delivery quarter estimated; Occ: CoStar 86% vs RealPage 90%; Rent: CoStar ask $1,542 vs RealPage eff $1,154; Verify rent/occ w/ HelloData
B32: 25 | C32: Alta Avondale | D32: 360 | E32: Q2 2024 | F32: 0.783333 | G32: 1610 | H32: Wood Partners | I32: 2.9 | J32: Mid-Rise | K32: Year built: 2024/2025; Delivery quarter estimated; Occ: CoStar 78% vs RealPage 84%; Rent: CoStar ask $1,610 vs RealPage eff $1,339; Verify rent/occ w/ HelloData
B33: 26 | C33: Livano Avondale | D33: 316 | E33: Q2 2024 | F33: 0.829114 | G33: 1663 | H33: LIV Development | I33: 2.5 | J33: Mid-Rise | K33: Year built: 2024/2025; Delivery quarter estimated; Rent: CoStar ask $1,663 vs RealPage eff $1,263; Verify rent/occ w/ HelloData
B34: 27 | C34: Cardinal 95 | D34: 198 | E34: Q2 2024 | F34: 0.878788 | G34: 1691 | H34: Quarry Capital | I34: 4.4 | J34: Garden | K34: Delivery quarter estimated; Verify rent/occ w/ HelloData
B35: 28 | C35: Moderne at Roosevelt | D35: 185 | E35: Q2 2024 | F35: 0.891892 | G35: 1900 | H35: MODERNE Communities | I35: 3.9 | J35: Low-Rise | K35: Year built: 2024/2025; Occ: CoStar 89% vs RealPage 94%; Rent: CoStar ask $1,900 vs RealPage eff $1,769; Verify rent/occ w/ HelloData
B36: 29 | C36: Canopy at the Trails | D36: 124 | E36: Q2 2024 | F36: 0.879032 | G36: 2183 | H36: Mark-Taylor Companies | I36: 2.3 | J36: Townhome | K36: Delivery quarter estimated; Occ: CoStar 88% vs RealPage 92%; Verify rent/occ w/ HelloData
B37: 30 | C37: Meritum Sheely Farms | D37: 680 | E37: Q4 2024 | F37: 0.797059 | G37: 1680 | H37: IDM Companies | I37: 3.2 | J37: Mid-Rise | K37: Year built: 2024/2025; Delivery quarter estimated; Rent: CoStar ask $1,680 vs RealPage eff $1,356; Verify rent/occ w/ HelloData
B38: 31 | C38: Alta Goodyear | D38: 342 | E38: Q2 2025 | F38: 0.789474 | G38: 1638 | H38: Wood Partners | I38: 3.5 | J38: Mid-Rise | K38: Delivery quarter estimated; Rent: CoStar ask $1,638 vs RealPage eff $1,433; Verify rent/occ w/ HelloData
B39: 32 | C39: Agave Ranch | D39: 324 | E39: Q2 2025 | F39: 0.802469 | G39: 1747 | H39: The Garrett Companies | I39: 3.5 | J39: Mid-Rise | K39: Delivery quarter estimated; Occ: CoStar 80% vs RealPage 0%; Rent: CoStar ask $1,747 vs RealPage eff $1,582; Verify rent/occ w/ HelloData
B40: 33 | C40: Avondale Commons | D40: 324 | E40: Q2 2025 | F40: 0.37037 | G40: 1632 | H40: Overland Group | I40: 1.9 | J40: Mid-Rise | K40: Year built: 2025/2026; Delivery quarter estimated; Occ: CoStar 37% vs RealPage 85%; Rent: CoStar ask $1,632 vs RealPage eff $1,321; Verify rent/occ w/ HelloData
B41: 34 | C41: Broadstone Westgate | D41: 308 | E41: Q2 2025 | F41: 0.89 | G41: — | H41: Alliance Residential Company/American Realty Advisors | I41: 4.9 | J41: Mid-Rise | K41: Delivery quarter estimated; Verify rent/occ w/ HelloData
B42: 35 | C42: The Douglas | D42: 307 | E42: Q2 2025 | F42: 0.583062 | G42: 2076 | H42: UrbanStreet Group | I42: 4.1 | J42: Townhome | K42: Delivery quarter estimated; Rent: CoStar ask $2,076 vs RealPage eff $1,561; Verify rent/occ w/ HelloData
B43: 36 | C43: Streamliner Aldea | D43: 282 | E43: Q2 2025 | F43: 0.844 | G43: — | H43: Greenlight Communities LLC | I43: 4.3 | J43: Garden | K43: Delivery quarter estimated; Verify rent/occ w/ HelloData
B44: 37 | C44: Cabana Aldea | D44: 257 | E44: Q2 2025 | F44: 0.7393 | G44: 1330 | H44: Greenlight Communities | I44: 3.6 | J44: Garden | K44: Delivery quarter estimated; Occ: CoStar 74% vs RealPage 67%; Rent: CoStar ask $1,330 vs RealPage eff $1,253; Verify rent/occ w/ HelloData
B45: 38 | C45: Somerset Upscale Apartments | D45: 234 | E45: Q2 2025 | F45: 0.256 | G45: — | H45: Ridgehouse Companies | I45: 5.1 | J45: Mid-Rise | K45: Delivery quarter estimated; Verify rent/occ w/ HelloData
B46: 39 | C46: Village at Skyline Ranch | D46: 167 | E46: Q2 2025 | F46: 0.39521 | G46: 1773 | H46: Empire Group of Companies | I46: 3.7 | J46: Single Family | K46: Year built: 2025/2026; Delivery quarter estimated; Occ: CoStar 40% vs RealPage 0%; Rent: CoStar ask $1,773 vs RealPage eff $1,632; Verify rent/occ w/ HelloData
B47: 40 | C47: Villas Litchfield Park | D47: 153 | E47: Q3 2025 | F47: 0.810458 | G47: 1913 | H47: Family Development | I47: 1.5 | J47: Single Family | K47: Delivery quarter estimated; Occ: CoStar 81% vs RealPage 86%; Rent: CoStar ask $1,913 vs RealPage eff $1,538; Verify rent/occ w/ HelloData
B48: 41 | C48: Villas on Van Buren | D48: 143 | E48: Q3 2025 | F48: 0.496503 | G48: 2085 | H48: Sunstone Properties Trust | I48: 4 | J48: Townhome | K48: Year built: 2025/2026; Delivery quarter estimated; Occ: CoStar 50% vs RealPage 0%; Verify rent/occ w/ HelloData
B49: 42 | C49: Pradera Estates | D49: 86 | E49: Q3 2025 | F49: 0.895349 | G49: 2474 | H49: AMH | I49: 3.3 | J49: Garden | K49: Delivery quarter estimated; Verify rent/occ w/ HelloData
B50: 43 | C50: Rev3 Encanto West | D50: 84 | E50: Q3 2025 | F50: 0.52381 | G50: 2319 | H50: Trilogy Investment Company | I50: 1.6 | J50: Townhome | K50: Units: CoStar 84 vs RealPage 78; Year built: 2025/2026; Occ: CoStar 52% vs RealPage 71%; Rent: CoStar ask $2,319 vs RealPage eff $1,833; Verify rent/occ w/ HelloData
B51: 44 | C51: Avalon Townhomes | D51: 70 | E51: Q3 2025 | F51: 0.857143 | G51: 2325 | H51: LVP Partners Group | I51: 1.1 | J51: Townhome | K51: Delivery quarter estimated; Rent: CoStar ask $2,325 vs RealPage eff $2,169; Verify rent/occ w/ HelloData
B52: 45 | C52: Broadstone Ascend | D52: 432 | E52: Q4 2025 | F52: 0.875 | G52: 1506 | H52: Alliance Residential Company | I52: 0.7 | J52: Garden | K52: Year built: 2025/2026; Delivery quarter estimated; Occ: CoStar 88% vs RealPage 51%; Rent: CoStar ask $1,506 vs RealPage eff $1,107; Verify rent/occ w/ HelloData
B53: 46 | C53: Flatz 623 | D53: 360 | E53: Q2 2026 | F53: 0.133333 | G53: 1411 | H53: Zekelman Industries | I53: 2.9 | J53: Low-Rise | K53: Delivery quarter estimated; Verify rent/occ w/ HelloData
B54: 47 | C54: Stately Avondale | D54: 286 | E54: Q2 2026 | F54: 0.297203 | G54: 1728 | H54: Ascent Companies | I54: 2.7 | J54: Garden | K54: Year built: 2026/2027; Delivery quarter estimated; Occ: CoStar 30% vs RealPage 0%; Rent: CoStar ask $1,728 vs RealPage eff $1,243; Verify rent/occ w/ HelloData
B55: 48 | C55: Avilla Western Garden | D55: 195 | E55: Q2 2026 | F55: 0.446154 | G55: 1829 | H55: NexMetro Communities | I55: 3.2 | J55: Garden | K55: Delivery quarter estimated; Occ: CoStar 45% vs RealPage 0%; Rent: CoStar ask $1,829 vs RealPage eff $1,681; Verify rent/occ w/ HelloData
B56: 49 | C56: Rev3 at Avondale Station | D56: 117 | E56: Q2 2026 | F56: 0.273504 | G56: 2537 | H56: Trilogy Investment Company | I56: 3.1 | J56: Single Family | K56: Units: CoStar 117 vs RealPage 107; Delivery quarter estimated; Occ: CoStar 27% vs RealPage 0%; Rent: CoStar ask $2,537 vs RealPage eff $2,273; Verify rent/occ w/ HelloData
B57: 50 | C57: Liberty at Estrella Falls | D57: 106 | E57: Q2 2026 | F57: 0.056604 | G57: 2966 | H57: Ronald D Newman | I57: 4.3 | J57: Garden | K57: Delivery quarter estimated; Occ: CoStar 6% vs RealPage 21%; Rent: CoStar ask $2,966 vs RealPage eff $1,938; Verify rent/occ w/ HelloData
C59: UNDER CONSTRUCTION (11 properties, 2,307 units)
B60: 51 | C60: Flatz623 | D60: 360 | E60: Q3 2026 | G60: — | H60: Zekelman Industries | I60: 2.9 | J60: Low-Rise
B61: 52 | C61: FUZE Ballpark | D61: 321 | E61: Q3 2026 | G61: — | H61: Zekelman Industries | I61: 3.1 | J61: Mid-Rise
B62: 53 | C62: HARMON Ascend | D62: 125 | E62: Q1 2027 | G62: 2788 | H62: Crescent Communities LLC | I62: 0.7 | J62: Townhome
B63: 54 | C63: Pointe Grand Estrella at Phoenix | D63: 288 | E63: Q2 2027 | G63: 1650 | H63: Hillpointe, LLC | I63: 5 | J63: Garden | K63: Year built: 2026/2027
B64: 55 | C64: Marbella Ranch East I | D64: 144 | E64: Q2 2027 | G64: — | H64: Symmetry Companies | I64: 4 | J64: Garden
B65: 56 | C65: Villages at Northern | D65: 74 | E65: Q2 2027 | G65: — | H65: — | I65: 4.7 | J65: Garden
B66: 57 | C66: Prosper 47 | D66: 47 | E66: Q2 2027 | G66: — | H66: — | I66: 6.1 | J66: Townhome | K66: RealPage only (sub-50 unit)
B67: 58 | C67: Yardly Algodon | D67: 262 | E67: Q4 2027 | G67: 1781 | H67: Taylor Morrison, Inc. | I67: 3.8 | J67: Single Family | K67: Units: CoStar 262 vs RealPage 291; Year built: 2026/2027
B68: 59 | C68: Cerro Vista | D68: 255 | E68: Q4 2027 | G68: — | H68: Virtua Partners | I68: 2.7 | J68: Low-Rise
B69: 60 | C69: Zanjero III | D69: 301 | E69: Q2 2028 | G69: — | H69: Fore Property Company/Privately Owned | I69: 5.4 | J69: Mid-Rise
B70: 61 | C70: Zen @ Angelina | D70: 130 | E70: Q2 2028 | G70: — | H70: F & S Consulting & Management, LLC | I70: 1.1 | J70: Townhome | K70: Year built: 2027/2028
C72: PROPOSED (45 properties, 9,225 units)
B73: 62 | C73: The Waverly | D73: 323 | E73: Q3 2028 | G73: — | H73: Dominium | I73: 4.3 | J73: Mid-Rise
B74: 63 | C74: Encore Avondale | D74: 300 | E74: Q3 2028 | G74: — | H74: Encore Enterprises | I74: 2.4 | J74: Mid-Rise
B75: 64 | C75: The Statler at Estrella Parkway | D75: 284 | E75: Q3 2028 | G75: — | H75: Leon Capital Group | I75: 4.8 | J75: Mid-Rise
B76: 65 | C76: Ascent Goodyear | D76: 113 | E76: Q3 2028 | G76: — | H76: Ascent Companies | I76: 4.7 | J76: Garden
B77: 66 | C77: Northern 107 | D77: 74 | E77: Q4 2028 | G77: — | H77: Jacob Reuben | I77: 4.5 | J77: Garden
B78: 67 | C78: Sheely Center Future Phase | D78: 697 | E78: TBD | G78: — | H78: — | I78: 3.1 | J78: Garden | K78: RealPage pipeline (not yet in CoStar)
B79: 68 | C79: Urban 95 Parcel C | D79: 500 | E79: TBD | G79: — | H79: Fisher Industries | I79: 5.1 | J79: Garden | K79: RealPage pipeline (not yet in CoStar)
B80: 69 | C80: Urban 95 Parcel B | D80: 478 | E80: TBD | G80: — | H80: Fisher Industries | I80: 5.1 | J80: High-Rise | K80: RealPage pipeline (not yet in CoStar)
B81: 70 | C81: Celebration Plaza Parcel B | D81: 410 | E81: TBD | G81: — | H81: Privately Owned | I81: 4.5 | J81: Mid-Rise | K81: RealPage pipeline (not yet in CoStar)
B82: 71 | C82: The District at Westgate | D82: 384 | E82: TBD | G82: — | H82: Privately Owned | I82: 5.1 | J82: Garden | K82: RealPage pipeline (not yet in CoStar)
B83: 72 | C83: Picerne at Palm Valley | D83: 383 | E83: TBD | G83: — | H83: Picerne | I83: 4.1 | J83: Garden | K83: RealPage pipeline (not yet in CoStar)
B84: 73 | C84: Liv Avondale | D84: 333 | E84: TBD | G84: — | H84: Liv Communities LLC | I84: 1.2 | J84: Garden | K84: RealPage pipeline (not yet in CoStar)
B85: 74 | C85: Urban 95 Parcel A | D85: 324 | E85: TBD | G85: — | H85: Fisher Industries | I85: 5.2 | J85: High-Rise | K85: RealPage pipeline (not yet in CoStar)
B86: 75 | C86: Fuze 623 | D86: 321 | E86: TBD | G86: — | H86: — | I86: 2.6 | J86: Garden | K86: RealPage pipeline (not yet in CoStar)
B87: 76 | C87: Anton Glendale | D87: 320 | E87: TBD | G87: — | H87: — | I87: 3.2 | J87: Mid-Rise | K87: RealPage pipeline (not yet in CoStar)
B88: 77 | C88: Western Garden II | D88: 314 | E88: TBD | G88: — | H88: John F Long Properties LLLP | I88: 3 | J88: Single Family | K88: RealPage pipeline (not yet in CoStar)
B89: 78 | C89: Sanctuair at Centerscape | D89: 303 | E89: TBD | G89: — | H89: Sunbelt Investment Holdings Inc | I89: 3.9 | J89: Garden | K89: RealPage pipeline (not yet in CoStar)
... B105: 94 | C105: Zenn @ Sierra Verde | D105: 66 | E105: TBD | G105: — | H105: — | I105: 7.2 | J105: Townhome | K105: RealPage pipeline (not yet in CoStar)
B106: 95 | C106: The BLVD Residential District | E106: TBD | G106: — | H106: — | I106: 4.1 | J106: Garden | K106: RealPage pipeline (not yet in CoStar)
B107: 96 | C107: The BLVD Park Avenue District | E107: TBD | G107: — | H107: — | I107: 4 | J107: Garden | K107: RealPage pipeline (not yet in CoStar)
B108: 97 | C108: Globe Land Investors Development | E108: TBD | G108: — | H108: Globe Corporation | I108: 4.4 | J108: Garden | K108: RealPage pipeline (not yet in CoStar)
B109: 98 | C109: Ball Park | E109: TBD | G109: — | H109: VT LandGroup | I109: 4.1 | J109: Garden | K109: RealPage pipeline (not yet in CoStar)
B110: 99 | C110: Vision 2 Parcel A | E110: TBD | G110: — | H110: — | I110: 3.5 | J110: Mid-Rise | K110: RealPage pipeline (not yet in CoStar)
B111: 100 | C111: Firststreet Verde | E111: TBD | G111: — | H111: — | I111: 4.6 | J111: Single Family | K111: RealPage pipeline (not yet in CoStar)
B112: 101 | C112: Goodyear Civic Square at Estrella Falls | E112: TBD | G112: — | H112: — | I112: 4.1 | J112: Garden | K112: RealPage pipeline (not yet in CoStar)
B113: 102 | C113: I-10 Innovation Center II | E113: TBD | G113: — | H113: Privately Owned | I113: 4.5 | J113: Garden | K113: RealPage pipeline (not yet in CoStar)
B114: 103 | C114: Celebration Plaza Parcel D | E114: TBD | G114: — | H114: Privately Owned | I114: 5 | J114: Garden | K114: RealPage pipeline (not yet in CoStar)
B115: 104 | C115: SimonMed Development II | E115: TBD | G115: — | H115: — | I115: 3.5 | J115: Mid-Rise | K115: RealPage pipeline (not yet in CoStar)
B116: 105 | C116: 182 South 95th Avenue | E116: TBD | G116: — | H116: — | I116: 4.6 | J116: Garden | K116: RealPage pipeline (not yet in CoStar)
B117: 106 | C117: Envision Encore | E117: TBD | G117: — | H117: — | I117: 5.4 | J117: Garden | K117: RealPage pipeline (not yet in CoStar)
B120: * 5-Mile radius. Rent ($) = market asking. Proximity (mi) = straight-line distance from the subject (geocoded); lease-up rent/occupancy to be verified w/ HelloData. See the 'Supply & Absorption' tab for the forward supply / absorption / overall-occupancy forecast.

Sheet Supply & Absorption
Z1: 8105
B2: SUPPLY & ABSORPTION — 5-MILE MARKET (relative-year / TTM) | Z2: =IFERROR(VALUE(RIGHT($C$5,4))*4+MATCH(LEFT($C$5,2),{"Q1","Q2","Q3","Q4"},0)-1,0)
R3: UNDER CONSTRUCTION (linked from Competitive Analysis) | Z3: =IF($C$7="Bear",3,IF($C$7="Base",2,1))
B4: As-of Quarter | C4: Q2 2026 | R4: Property | S4: Units | T4: Est. Delivery
B5: Close Quarter (Y1 start) | C5: Q4 2026 | R5: ='Competitive Analysis'!C60 | S5: ='Competitive Analysis'!D60 | T5: ='Competitive Analysis'!E60 | V5: =IFERROR(VALUE(RIGHT(T5,4))*4+MATCH(LEFT(T5,2),{"Q1","Q2","Q3","Q4"},0)-1,"") | W5: =IF(V5="","",IF(V5<=$Z$1,0,MAX(1,INT((V5-$Z$2)/4)+1)))
B6: Stabilization Target | C6: 0.95 | R6: ='Competitive Analysis'!C61 | S6: ='Competitive Analysis'!D61 | T6: ='Competitive Analysis'!E61 | V6: =IFERROR(VALUE(RIGHT(T6,4))*4+MATCH(LEFT(T6,2),{"Q1","Q2","Q3","Q4"},0)-1,"") | W6: =IF(V6="","",IF(V6<=$Z$1,0,MAX(1,INT((V6-$Z$2)/4)+1)))
B7: Demand Scenario | C7: Base | R7: ='Competitive Analysis'!C69 | S7: ='Competitive Analysis'!D69 | T7: ='Competitive Analysis'!E69 | V7: =IFERROR(VALUE(RIGHT(T7,4))*4+MATCH(LEFT(T7,2),{"Q1","Q2","Q3","Q4"},0)-1,"") | W7: =IF(V7="","",IF(V7<=$Z$1,0,MAX(1,INT((V7-$Z$2)/4)+1)))
B8: Bear Annual Absorption | C8: 1250 | R8: ='Competitive Analysis'!C63 | S8: ='Competitive Analysis'!D63 | T8: ='Competitive Analysis'!E63 | V8: =IFERROR(VALUE(RIGHT(T8,4))*4+MATCH(LEFT(T8,2),{"Q1","Q2","Q3","Q4"},0)-1,"") | W8: =IF(V8="","",IF(V8<=$Z$1,0,MAX(1,INT((V8-$Z$2)/4)+1)))
B9: Base Annual Absorption | C9: 2525 | R9: ='Competitive Analysis'!C67 | S9: ='Competitive Analysis'!D67 | T9: ='Competitive Analysis'!E67 | V9: =IFERROR(VALUE(RIGHT(T9,4))*4+MATCH(LEFT(T9,2),{"Q1","Q2","Q3","Q4"},0)-1,"") | W9: =IF(V9="","",IF(V9<=$Z$1,0,MAX(1,INT((V9-$Z$2)/4)+1)))
B10: Bull Annual Absorption | C10: 3800 | R10: ='Competitive Analysis'!C68 | S10: ='Competitive Analysis'!D68 | T10: ='Competitive Analysis'!E68 | V10: =IFERROR(VALUE(RIGHT(T10,4))*4+MATCH(LEFT(T10,2),{"Q1","Q2","Q3","Q4"},0)-1,"") | W10: =IF(V10="","",IF(V10<=$Z$1,0,MAX(1,INT((V10-$Z$2)/4)+1)))
B11: Selected Annual Demand | C11: =IF($C$7="Bear",$C$8,IF($C$7="Bull",$C$10,$C$9)) | R11: ='Competitive Analysis'!C64 | S11: ='Competitive Analysis'!D64 | T11: ='Competitive Analysis'!E64 | V11: =IFERROR(VALUE(RIGHT(T11,4))*4+MATCH(LEFT(T11,2),{"Q1","Q2","Q3","Q4"},0)-1,"") | W11: =IF(V11="","",IF(V11<=$Z$1,0,MAX(1,INT((V11-$Z$2)/4)+1)))
R12: ='Competitive Analysis'!C70 | S12: ='Competitive Analysis'!D70 | T12: ='Competitive Analysis'!E70 | V12: =IFERROR(VALUE(RIGHT(T12,4))*4+MATCH(LEFT(T12,2),{"Q1","Q2","Q3","Q4"},0)-1,"") | W12: =IF(V12="","",IF(V12<=$Z$1,0,MAX(1,INT((V12-$Z$2)/4)+1)))
R13: ='Competitive Analysis'!C62 | S13: ='Competitive Analysis'!D62 | T13: ='Competitive Analysis'!E62 | V13: =IFERROR(VALUE(RIGHT(T13,4))*4+MATCH(LEFT(T13,2),{"Q1","Q2","Q3","Q4"},0)-1,"") | W13: =IF(V13="","",IF(V13<=$Z$1,0,MAX(1,INT((V13-$Z$2)/4)+1)))
R14: ='Competitive Analysis'!C65 | S14: ='Competitive Analysis'!D65 | T14: ='Competitive Analysis'!E65 | V14: =IFERROR(VALUE(RIGHT(T14,4))*4+MATCH(LEFT(T14,2),{"Q1","Q2","Q3","Q4"},0)-1,"") | W14: =IF(V14="","",IF(V14<=$Z$1,0,MAX(1,INT((V14-$Z$2)/4)+1)))
R15: ='Competitive Analysis'!C66 | S15: ='Competitive Analysis'!D66 | T15: ='Competitive Analysis'!E66 | V15: =IFERROR(VALUE(RIGHT(T15,4))*4+MATCH(LEFT(T15,2),{"Q1","Q2","Q3","Q4"},0)-1,"") | W15: =IF(V15="","",IF(V15<=$Z$1,0,MAX(1,INT((V15-$Z$2)/4)+1)))
B17: 5-MILE MARKET | C17: -Y6 | D17: -Y5 | E17: -Y4 | F17: -Y3 | G17: -Y2 | H17: -Y1 | I17: Y0 | J17: Y1 | K17: Y2 | L17: Y3 | M17: Y4 | N17: Y5 | O17: Y6 | R17: PROPOSED PIPELINE (scenario toggle)
C18: Q3'19-Q2'20 | D18: Q3'20-Q2'21 | E18: Q3'21-Q2'22 | F18: Q3'22-Q2'23 | G18: Q3'23-Q2'24 | H18: Q3'24-Q2'25 | I18: Q3'25-Q2'26 | J18: Hold Yr 1 | K18: Hold Yr 2 | L18: Hold Yr 3 | M18: Hold Yr 4 | N18: Hold Yr 5 | O18: Hold Yr 6 | R18: Property | S18: Units | T18: Est. Delivery | U18: Built In
B19: NEW SUPPLY (5-mi) | C19: 1133 | D19: 1860 | E19: 1336 | F19: 2280 | G19: 2823 | H19: 4043 | I19: 1860 | J19: =SUMIFS($S$5:$S$15,$W$5:$W$15,1)+SUMIFS($S$19:$S$63,$W$19:$W$63,1,$X$19:$X$63,1) | K19: =SUMIFS($S$5:$S$15,$W$5:$W$15,2)+SUMIFS($S$19:$S$63,$W$19:$W$63,2,$X$19:$X$63,1) | L19: =SUMIFS($S$5:$S$15,$W$5:$W$15,3)+SUMIFS($S$19:$S$63,$W$19:$W$63,3,$X$19:$X$63,1) | M19: =SUMIFS($S$5:$S$15,$W$5:$W$15,4)+SUMIFS($S$19:$S$63,$W$19:$W$63,4,$X$19:$X$63,1) | N19: =SUMIFS($S$5:$S$15,$W$5:$W$15,5)+SUMIFS($S$19:$S$63,$W$19:$W$63,5,$X$19:$X$63,1) | O19: =SUMIFS($S$5:$S$15,$W$5:$W$15,6)+SUMIFS($S$19:$S$63,$W$19:$W$63,6,$X$19:$X$63,1) | R19: Sheely Center Future Phase | S19: 697 | U19: Bear only | V19: =IFERROR(VALUE(RIGHT(T19,4))*4+MATCH(LEFT(T19,2),{"Q1","Q2","Q3","Q4"},0)-1,"") | W19: =IF(V19="","",IF(V19<=$Z$1,0,MAX(1,INT((V19-$Z$2)/4)+1))) | X19: =IF(U19="All",1,IF(U19="Bear+Base",IF($Z$3>=2,1,0),IF(U19="Bear only",IF($Z$3>=3,1,0),0)))
B20: ABSORPTION (5-mi) | C20: 719 | D20: 1876 | E20: 1210 | F20: 685 | G20: 2514 | H20: 2655 | I20: 2369 | J20: =J31-I31 | K20: =K31-J31 | L20: =L31-K31 | M20: =M31-L31 | N20: =N31-M31 | O20: =O31-N31 | R20: Urban 95 Parcel C | S20: 500 | U20: Bear only | V20: =IFERROR(VALUE(RIGHT(T20,4))*4+MATCH(LEFT(T20,2),{"Q1","Q2","Q3","Q4"},0)-1,"") | W20: =IF(V20="","",IF(V20<=$Z$1,0,MAX(1,INT((V20-$Z$2)/4)+1))) | X20: =IF(U20="All",1,IF(U20="Bear+Base",IF($Z$3>=2,1,0),IF(U20="Bear only",IF($Z$3>=3,1,0),0)))
B21: OCCUPANCY (5-mi) | C21: 0.909 | D21: 0.922 | E21: 0.921 | F21: 0.842 | G21: 0.848 | H21: 0.817 | I21: 0.849 | J21: =IFERROR(J31/J30,0) | K21: =IFERROR(K31/K30,0) | L21: =IFERROR(L31/L30,0) | M21: =IFERROR(M31/M30,0) | N21: =IFERROR(N31/N30,0) | O21: =IFERROR(O31/O30,0) | R21: Urban 95 Parcel B | S21: 478 | U21: Bear only | V21: =IFERROR(VALUE(RIGHT(T21,4))*4+MATCH(LEFT(T21,2),{"Q1","Q2","Q3","Q4"},0)-1,"") | W21: =IF(V21="","",IF(V21<=$Z$1,0,MAX(1,INT((V21-$Z$2)/4)+1))) | X21: =IF(U21="All",1,IF(U21="Bear+Base",IF($Z$3>=2,1,0),IF(U21="Bear only",IF($Z$3>=3,1,0),0)))
B22: SUBJECT (Bella Mirage) | R22: Celebration Plaza Parcel B | S22: 410 | U22: Bear only | V22: =IFERROR(VALUE(RIGHT(T22,4))*4+MATCH(LEFT(T22,2),{"Q1","Q2","Q3","Q4"},0)-1,"") | W22: =IF(V22="","",IF(V22<=$Z$1,0,MAX(1,INT((V22-$Z$2)/4)+1))) | X22: =IF(U22="All",1,IF(U22="Bear+Base",IF($Z$3>=2,1,0),IF(U22="Bear only",IF($Z$3>=3,1,0),0)))
B23: Market Rent (CoStar→HD) | C23: 1088 | D23: 1437 | E23: 1730 | F23: 1572 | G23: 1497 | H23: 1444 | I23: =IFERROR('Cash Flow (Annual)'!$F$4,1332) | J23: =IFERROR('Cash Flow (Annual)'!$K$4,"") | K23: =IFERROR('Cash Flow (Annual)'!$L$4,"") | L23: =IFERROR('Cash Flow (Annual)'!$M$4,"") | M23: =IFERROR('Cash Flow (Annual)'!$N$4,"") | N23: =IFERROR('Cash Flow (Annual)'!$O$4,"") | O23: =IFERROR('Cash Flow (Annual)'!$P$4,"") | R23: The District at Westgate | S23: 384 | U23: Bear only | V23: =IFERROR(VALUE(RIGHT(T23,4))*4+MATCH(LEFT(T23,2),{"Q1","Q2","Q3","Q4"},0)-1,"") | W23: =IF(V23="","",IF(V23<=$Z$1,0,MAX(1,INT((V23-$Z$2)/4)+1))) | X23: =IF(U23="All",1,IF(U23="Bear+Base",IF($Z$3>=2,1,0),IF(U23="Bear only",IF($Z$3>=3,1,0),0)))
B24: Market Rent YoY % | D24: =IFERROR(D23/C23-1,"") | E24: =IFERROR(E23/D23-1,"") | F24: =IFERROR(F23/E23-1,"") | G24: =IFERROR(G23/F23-1,"") | H24: =IFERROR(H23/G23-1,"") | I24: =IFERROR(I23/H23-1,"") | J24: =IFERROR(J23/I23-1,"") | K24: =IFERROR(K23/J23-1,"") | ... O24: =IFERROR(O23/N23-1,"") | R24: Picerne at Palm Valley | S24: 383 | U24: Bear only | V24: =IFERROR(VALUE(RIGHT(T24,4))*4+MATCH(LEFT(T24,2),{"Q1","Q2","Q3","Q4"},0)-1,"") | W24: =IF(V24="","",IF(V24<=$Z$1,0,MAX(1,INT((V24-$Z$2)/4)+1))) | X24: =IF(U24="All",1,IF(U24="Bear+Base",IF($Z$3>=2,1,0),IF(U24="Bear only",IF($Z$3>=3,1,0),0)))
B25: Effective Rent | C25: 1086 | D25: 1434 | E25: 1730 | F25: 1555 | G25: 1402 | H25: 1369 | I25: =IFERROR('Cash Flow (Annual)'!$F$5,1301) | J25: =IFERROR('Cash Flow (Annual)'!$K$5,"") | K25: =IFERROR('Cash Flow (Annual)'!$L$5,"") | L25: =IFERROR('Cash Flow (Annual)'!$M$5,"") | M25: =IFERROR('Cash Flow (Annual)'!$N$5,"") | N25: =IFERROR('Cash Flow (Annual)'!$O$5,"") | O25: =IFERROR('Cash Flow (Annual)'!$P$5,"") | R25: Liv Avondale | S25: 333 | U25: Bear only | V25: =IFERROR(VALUE(RIGHT(T25,4))*4+MATCH(LEFT(T25,2),{"Q1","Q2","Q3","Q4"},0)-1,"") | W25: =IF(V25="","",IF(V25<=$Z$1,0,MAX(1,INT((V25-$Z$2)/4)+1))) | X25: =IF(U25="All",1,IF(U25="Bear+Base",IF($Z$3>=2,1,0),IF(U25="Bear only",IF($Z$3>=3,1,0),0)))
B26: Effective Rent YoY % | D26: =IFERROR(D25/C25-1,"") | E26: =IFERROR(E25/D25-1,"") | F26: =IFERROR(F25/E25-1,"") | G26: =IFERROR(G25/F25-1,"") | H26: =IFERROR(H25/G25-1,"") | I26: =IFERROR(I25/H25-1,"") | J26: =IFERROR(J25/I25-1,"") | K26: =IFERROR(K25/J25-1,"") | ... O26: =IFERROR(O25/N25-1,"") | R26: Urban 95 Parcel A | S26: 324 | U26: Bear only | V26: =IFERROR(VALUE(RIGHT(T26,4))*4+MATCH(LEFT(T26,2),{"Q1","Q2","Q3","Q4"},0)-1,"") | W26: =IF(V26="","",IF(V26<=$Z$1,0,MAX(1,INT((V26-$Z$2)/4)+1))) | X26: =IF(U26="All",1,IF(U26="Bear+Base",IF($Z$3>=2,1,0),IF(U26="Bear only",IF($Z$3>=3,1,0),0)))
B27: Occupancy (financials / CoStar) | C27: 0.95034965 | D27: 0.95769231 | E27: 0.9458042 | F27: 0.87889712 | G27: 0.91737132 | H27: 0.93348546 | I27: =IFERROR('Cash Flow (Annual)'!$F$14,0.9206643232607364) | J27: =IFERROR('Cash Flow (Annual)'!$K$14,"") | K27: =IFERROR('Cash Flow (Annual)'!$L$14,"") | L27: =IFERROR('Cash Flow (Annual)'!$M$14,"") | M27: =IFERROR('Cash Flow (Annual)'!$N$14,"") | N27: =IFERROR('Cash Flow (Annual)'!$O$14,"") | O27: =IFERROR('Cash Flow (Annual)'!$P$14,"") | R27: The Waverly | S27: 323 | T27: Q3 2028 | U27: Bear only | V27: =IFERROR(VALUE(RIGHT(T27,4))*4+MATCH(LEFT(T27,2),{"Q1","Q2","Q3","Q4"},0)-1,"") | W27: =IF(V27="","",IF(V27<=$Z$1,0,MAX(1,INT((V27-$Z$2)/4)+1))) | X27: =IF(U27="All",1,IF(U27="Bear+Base",IF($Z$3>=2,1,0),IF(U27="Bear only",IF($Z$3>=3,1,0),0)))
B28: Concession % | C28: =IFERROR((C23-C25)/C23,"") | D28: =IFERROR((D23-D25)/D23,"") | E28: =IFERROR((E23-E25)/E23,"") | F28: =IFERROR((F23-F25)/F23,"") | G28: =IFERROR((G23-G25)/G23,"") | H28: =IFERROR((H23-H25)/H23,"") | I28: =IFERROR((I23-I25)/I23,"") | J28: =IFERROR((J23-J25)/J23,"") | ... O28: =IFERROR((O23-O25)/O23,"") | R28: Fuze 623 | S28: 321 | U28: Bear only | V28: =IFERROR(VALUE(RIGHT(T28,4))*4+MATCH(LEFT(T28,2),{"Q1","Q2","Q3","Q4"},0)-1,"") | W28: =IF(V28="","",IF(V28<=$Z$1,0,MAX(1,INT((V28-$Z$2)/4)+1))) | X28: =IF(U28="All",1,IF(U28="Bear+Base",IF($Z$3>=2,1,0),IF(U28="Bear only",IF($Z$3>=3,1,0),0)))
R29: Anton Glendale | S29: 320 | U29: Bear only | V29: =IFERROR(VALUE(RIGHT(T29,4))*4+MATCH(LEFT(T29,2),{"Q1","Q2","Q3","Q4"},0)-1,"") | W29: =IF(V29="","",IF(V29<=$Z$1,0,MAX(1,INT((V29-$Z$2)/4)+1))) | X29: =IF(U29="All",1,IF(U29="Bear+Base",IF($Z$3>=2,1,0),IF(U29="Bear only",IF($Z$3>=3,1,0),0)))
B30: inventory | C30: 12401 | D30: 14261 | E30: 15597 | F30: 17877 | G30: 20700 | H30: 24743 | I30: 26603 | J30: =I30+J19 | K30: =J30+K19 | L30: =K30+L19 | M30: =L30+M19 | N30: =M30+N19 | O30: =N30+O19 | R30: Western Garden II | S30: 314 | U30: Bear only | V30: =IFERROR(VALUE(RIGHT(T30,4))*4+MATCH(LEFT(T30,2),{"Q1","Q2","Q3","Q4"},0)-1,"") | W30: =IF(V30="","",IF(V30<=$Z$1,0,MAX(1,INT((V30-$Z$2)/4)+1))) | X30: =IF(U30="All",1,IF(U30="Bear+Base",IF($Z$3>=2,1,0),IF(U30="Bear only",IF($Z$3>=3,1,0),0)))
B31: occupied | C31: 11277 | D31: 13152 | E31: 14362 | F31: 15047 | G31: 17560 | H31: 20215 | I31: 22585 | J31: =MIN($C$6*J30,I31+$C$11) | K31: =MIN($C$6*K30,J31+$C$11) | L31: =MIN($C$6*L30,K31+$C$11) | M31: =MIN($C$6*M30,L31+$C$11) | N31: =MIN($C$6*N30,M31+$C$11) | O31: =MIN($C$6*O30,N31+$C$11) | R31: Sanctuair at Centerscape | S31: 303 | U31: Bear only | V31: =IFERROR(VALUE(RIGHT(T31,4))*4+MATCH(LEFT(T31,2),{"Q1","Q2","Q3","Q4"},0)-1,"") | W31: =IF(V31="","",IF(V31<=$Z$1,0,MAX(1,INT((V31-$Z$2)/4)+1))) | X31: =IF(U31="All",1,IF(U31="Bear+Base",IF($Z$3>=2,1,0),IF(U31="Bear only",IF($Z$3>=3,1,0),0)))
R32: Encore Avondale | S32: 300 | T32: Q3 2028 | U32: Bear only | V32: =IFERROR(VALUE(RIGHT(T32,4))*4+MATCH(LEFT(T32,2),{"Q1","Q2","Q3","Q4"},0)-1,"") | W32: =IF(V32="","",IF(V32<=$Z$1,0,MAX(1,INT((V32-$Z$2)/4)+1))) | X32: =IF(U32="All",1,IF(U32="Bear+Base",IF($Z$3>=2,1,0),IF(U32="Bear only",IF($Z$3>=3,1,0),0)))
B33: MARKET-RENT GROWTH — TMG vs 3RD-PARTY FORECAST | J33: Y1 | K33: Y2 | L33: Y3 | M33: Y4 | N33: Y5 | O33: Y6 | P33: AVG | R33: Banyan Avondale | S33: 296 | U33: Bear only | V33: =IFERROR(VALUE(RIGHT(T33,4))*4+MATCH(LEFT(T33,2),{"Q1","Q2","Q3","Q4"},0)-1,"") | W33: =IF(V33="","",IF(V33<=$Z$1,0,MAX(1,INT((V33-$Z$2)/4)+1))) | X33: =IF(U33="All",1,IF(U33="Bear+Base",IF($Z$3>=2,1,0),IF(U33="Bear only",IF($Z$3>=3,1,0),0)))
B34: CoStar | J34: =IFERROR('Rent & Occ Data'!$C$31,"") | K34: =IFERROR('Rent & Occ Data'!$D$31,"") | L34: =IFERROR('Rent & Occ Data'!$E$31,"") | M34: =IFERROR('Rent & Occ Data'!$F$31,"") | N34: =IFERROR('Rent & Occ Data'!$G$31,"") | O34: =IFERROR('Rent & Occ Data'!$H$31,"") | P34: =IFERROR(AVERAGE(J34:O34),"") | R34: Rosilian Villas | S34: 291 | U34: Bear only | V34: =IFERROR(VALUE(RIGHT(T34,4))*4+MATCH(LEFT(T34,2),{"Q1","Q2","Q3","Q4"},0)-1,"") | W34: =IF(V34="","",IF(V34<=$Z$1,0,MAX(1,INT((V34-$Z$2)/4)+1))) | X34: =IF(U34="All",1,IF(U34="Bear+Base",IF($Z$3>=2,1,0),IF(U34="Bear only",IF($Z$3>=3,1,0),0)))
B35: RealPage | J35: =IFERROR('Rent & Occ Data'!$C$32,"") | K35: =IFERROR('Rent & Occ Data'!$D$32,"") | L35: =IFERROR('Rent & Occ Data'!$E$32,"") | M35: =IFERROR('Rent & Occ Data'!$F$32,"") | N35: =IFERROR('Rent & Occ Data'!$G$32,"") | O35: =IFERROR('Rent & Occ Data'!$H$32,"") | P35: =IFERROR(AVERAGE(J35:O35),"") | R35: The Statler at Estrella Parkway | S35: 284 | T35: Q3 2028 | U35: Bear only | V35: =IFERROR(VALUE(RIGHT(T35,4))*4+MATCH(LEFT(T35,2),{"Q1","Q2","Q3","Q4"},0)-1,"") | W35: =IF(V35="","",IF(V35<=$Z$1,0,MAX(1,INT((V35-$Z$2)/4)+1))) | X35: =IF(U35="All",1,IF(U35="Bear+Base",IF($Z$3>=2,1,0),IF(U35="Bear only",IF($Z$3>=3,1,0),0)))
B36: Yardi | J36: =IFERROR('Rent & Occ Data'!$C$33,"") | K36: =IFERROR('Rent & Occ Data'!$D$33,"") | L36: =IFERROR('Rent & Occ Data'!$E$33,"") | M36: =IFERROR('Rent & Occ Data'!$F$33,"") | N36: =IFERROR('Rent & Occ Data'!$G$33,"") | O36: =IFERROR('Rent & Occ Data'!$H$33,"") | P36: =IFERROR(AVERAGE(J36:O36),"") | R36: Orion Avondale | S36: 268 | U36: Bear only | V36: =IFERROR(VALUE(RIGHT(T36,4))*4+MATCH(LEFT(T36,2),{"Q1","Q2","Q3","Q4"},0)-1,"") | W36: =IF(V36="","",IF(V36<=$Z$1,0,MAX(1,INT((V36-$Z$2)/4)+1))) | X36: =IF(U36="All",1,IF(U36="Bear+Base",IF($Z$3>=2,1,0),IF(U36="Bear only",IF($Z$3>=3,1,0),0)))
B37: GreenStreet | J37: =IFERROR('Rent & Occ Data'!$C$34,"") | K37: =IFERROR('Rent & Occ Data'!$D$34,"") | L37: =IFERROR('Rent & Occ Data'!$E$34,"") | M37: =IFERROR('Rent & Occ Data'!$F$34,"") | N37: =IFERROR('Rent & Occ Data'!$G$34,"") | O37: =IFERROR('Rent & Occ Data'!$H$34,"") | P37: =IFERROR(AVERAGE(J37:O37),"") | R37: Tavalo at Avondale | S37: 266 | U37: Bear only | V37: =IFERROR(VALUE(RIGHT(T37,4))*4+MATCH(LEFT(T37,2),{"Q1","Q2","Q3","Q4"},0)-1,"") | W37: =IF(V37="","",IF(V37<=$Z$1,0,MAX(1,INT((V37-$Z$2)/4)+1))) | X37: =IF(U37="All",1,IF(U37="Bear+Base",IF($Z$3>=2,1,0),IF(U37="Bear only",IF($Z$3>=3,1,0),0)))
B38: Consensus (4-source avg) | J38: =IFERROR(AVERAGE(J34:J37),"") | K38: =IFERROR(AVERAGE(K34:K37),"") | L38: =IFERROR(AVERAGE(L34:L37),"") | M38: =IFERROR(AVERAGE(M34:M37),"") | N38: =IFERROR(AVERAGE(N34:N37),"") | O38: =IFERROR(AVERAGE(O34:O37),"") | P38: =IFERROR(AVERAGE(P34:P37),"") | R38: Marbella Ranch East Future Phase | S38: 266 | U38: Bear only | V38: =IFERROR(VALUE(RIGHT(T38,4))*4+MATCH(LEFT(T38,2),{"Q1","Q2","Q3","Q4"},0)-1,"") | W38: =IF(V38="","",IF(V38<=$Z$1,0,MAX(1,INT((V38-$Z$2)/4)+1))) | X38: =IF(U38="All",1,IF(U38="Bear+Base",IF($Z$3>=2,1,0),IF(U38="Bear only",IF($Z$3>=3,1,0),0)))
B39: TMG — our market-rent growth ◄ | J39: =IFERROR(J24,"") | K39: =IFERROR(K24,"") | L39: =IFERROR(L24,"") | M39: =IFERROR(M24,"") | N39: =IFERROR(N24,"") | O39: =IFERROR(O24,"") | P39: =IFERROR(AVERAGE(J39:O39),"") | R39: Crystal Cove | S39: 260 | U39: Bear only | V39: =IFERROR(VALUE(RIGHT(T39,4))*4+MATCH(LEFT(T39,2),{"Q1","Q2","Q3","Q4"},0)-1,"") | W39: =IF(V39="","",IF(V39<=$Z$1,0,MAX(1,INT((V39-$Z$2)/4)+1))) | X39: =IF(U39="All",1,IF(U39="Bear+Base",IF($Z$3>=2,1,0),IF(U39="Bear only",IF($Z$3>=3,1,0),0)))
R40: SimonMed Development I | S40: 239 | U40: Bear only | V40: =IFERROR(VALUE(RIGHT(T40,4))*4+MATCH(LEFT(T40,2),{"Q1","Q2","Q3","Q4"},0)-1,"") | W40: =IF(V40="","",IF(V40<=$Z$1,0,MAX(1,INT((V40-$Z$2)/4)+1))) | X40: =IF(U40="All",1,IF(U40="Bear+Base",IF($Z$3>=2,1,0),IF(U40="Bear only",IF($Z$3>=3,1,0),0)))
B41: ▸ SCENARIO INPUTS — Bear / Base / Bull (implied occupancy, rent-growth & concession assumptions — click + to expand) | R41: Cornerstone at the Wigwam | S41: 212 | U41: Bear only | V41: =IFERROR(VALUE(RIGHT(T41,4))*4+MATCH(LEFT(T41,2),{"Q1","Q2","Q3","Q4"},0)-1,"") | W41: =IF(V41="","",IF(V41<=$Z$1,0,MAX(1,INT((V41-$Z$2)/4)+1))) | X41: =IF(U41="All",1,IF(U41="Bear+Base",IF($Z$3>=2,1,0),IF(U41="Bear only",IF($Z$3>=3,1,0),0)))
B42: IMPLIED 5-MI OCCUPANCY BY DEMAND SCENARIO | J42: Y1 | K42: Y2 | L42: Y3 | M42: Y4 | N42: Y5 | O42: Y6 | R42: Radia Avondale Station III | S42: 212 | U42: Bear only | V42: =IFERROR(VALUE(RIGHT(T42,4))*4+MATCH(LEFT(T42,2),{"Q1","Q2","Q3","Q4"},0)-1,"") | W42: =IF(V42="","",IF(V42<=$Z$1,0,MAX(1,INT((V42-$Z$2)/4)+1))) | X42: =IF(U42="All",1,IF(U42="Bear+Base",IF($Z$3>=2,1,0),IF(U42="Bear only",IF($Z$3>=3,1,0),0)))
B43: Bear | J43: =MIN($C$6,($I$31+$C$8*1)/J30) | K43: =MIN($C$6,($I$31+$C$8*2)/K30) | L43: =MIN($C$6,($I$31+$C$8*3)/L30) | M43: =MIN($C$6,($I$31+$C$8*4)/M30) | N43: =MIN($C$6,($I$31+$C$8*5)/N30) | O43: =MIN($C$6,($I$31+$C$8*6)/O30) | R43: Celebration Plaza Parcel A | S43: 181 | U43: Bear only | V43: =IFERROR(VALUE(RIGHT(T43,4))*4+MATCH(LEFT(T43,2),{"Q1","Q2","Q3","Q4"},0)-1,"") | W43: =IF(V43="","",IF(V43<=$Z$1,0,MAX(1,INT((V43-$Z$2)/4)+1))) | X43: =IF(U43="All",1,IF(U43="Bear+Base",IF($Z$3>=2,1,0),IF(U43="Bear only",IF($Z$3>=3,1,0),0)))
B44: Base | J44: =MIN($C$6,($I$31+$C$9*1)/J30) | K44: =MIN($C$6,($I$31+$C$9*2)/K30) | L44: =MIN($C$6,($I$31+$C$9*3)/L30) | M44: =MIN($C$6,($I$31+$C$9*4)/M30) | N44: =MIN($C$6,($I$31+$C$9*5)/N30) | O44: =MIN($C$6,($I$31+$C$9*6)/O30) | R44: Villages at River Grove | S44: 180 | U44: Bear only | V44: =IFERROR(VALUE(RIGHT(T44,4))*4+MATCH(LEFT(T44,2),{"Q1","Q2","Q3","Q4"},0)-1,"") | W44: =IF(V44="","",IF(V44<=$Z$1,0,MAX(1,INT((V44-$Z$2)/4)+1))) | X44: =IF(U44="All",1,IF(U44="Bear+Base",IF($Z$3>=2,1,0),IF(U44="Bear only",IF($Z$3>=3,1,0),0)))
B45: Bull | J45: =MIN($C$6,($I$31+$C$10*1)/J30) | K45: =MIN($C$6,($I$31+$C$10*2)/K30) | L45: =MIN($C$6,($I$31+$C$10*3)/L30) | M45: =MIN($C$6,($I$31+$C$10*4)/M30) | N45: =MIN($C$6,($I$31+$C$10*5)/N30) | O45: =MIN($C$6,($I$31+$C$10*6)/O30) | R45: District 99 | S45: 172 | U45: Bear only | V45: =IFERROR(VALUE(RIGHT(T45,4))*4+MATCH(LEFT(T45,2),{"Q1","Q2","Q3","Q4"},0)-1,"") | W45: =IF(V45="","",IF(V45<=$Z$1,0,MAX(1,INT((V45-$Z$2)/4)+1))) | X45: =IF(U45="All",1,IF(U45="Bear+Base",IF($Z$3>=2,1,0),IF(U45="Bear only",IF($Z$3>=3,1,0),0)))
R46: McDowell Villas | S46: 164 | U46: Bear only | V46: =IFERROR(VALUE(RIGHT(T46,4))*4+MATCH(LEFT(T46,2),{"Q1","Q2","Q3","Q4"},0)-1,"") | W46: =IF(V46="","",IF(V46<=$Z$1,0,MAX(1,INT((V46-$Z$2)/4)+1))) | X46: =IF(U46="All",1,IF(U46="Bear+Base",IF($Z$3>=2,1,0),IF(U46="Bear only",IF($Z$3>=3,1,0),0)))
B47: MARKET RENT GROWTH (editable assumptions) | J47: Y1 | K47: Y2 | L47: Y3 | M47: Y4 | N47: Y5 | O47: Y6 | R47: Avondale | S47: 156 | U47: Bear only | V47: =IFERROR(VALUE(RIGHT(T47,4))*4+MATCH(LEFT(T47,2),{"Q1","Q2","Q3","Q4"},0)-1,"") | W47: =IF(V47="","",IF(V47<=$Z$1,0,MAX(1,INT((V47-$Z$2)/4)+1))) | X47: =IF(U47="All",1,IF(U47="Bear+Base",IF($Z$3>=2,1,0),IF(U47="Bear only",IF($Z$3>=3,1,0),0)))
B48: Bear | J48: -0.0025 | K48: 0.0175 | L48: 0.0275 | M48: 0.0375 | N48: 0.0275 | O48: 0.0175 | R48: Porter Kyle Development | S48: 135 | U48: Bear only | V48: =IFERROR(VALUE(RIGHT(T48,4))*4+MATCH(LEFT(T48,2),{"Q1","Q2","Q3","Q4"},0)-1,"") | W48: =IF(V48="","",IF(V48<=$Z$1,0,MAX(1,INT((V48-$Z$2)/4)+1))) | X48: =IF(U48="All",1,IF(U48="Bear+Base",IF($Z$3>=2,1,0),IF(U48="Bear only",IF($Z$3>=3,1,0),0)))
B49: Base | J49: 0.01 | K49: 0.03 | L49: 0.04 | M49: 0.05 | N49: 0.04 | O49: 0.03 | R49: Ascent Goodyear | S49: 113 | T49: Q3 2028 | U49: Bear only | V49: =IFERROR(VALUE(RIGHT(T49,4))*4+MATCH(LEFT(T49,2),{"Q1","Q2","Q3","Q4"},0)-1,"") | W49: =IF(V49="","",IF(V49<=$Z$1,0,MAX(1,INT((V49-$Z$2)/4)+1))) | X49: =IF(U49="All",1,IF(U49="Bear+Base",IF($Z$3>=2,1,0),IF(U49="Bear only",IF($Z$3>=3,1,0),0)))
B50: Bull | J50: 0.02 | K50: 0.04 | L50: 0.05 | M50: 0.06 | N50: 0.05 | O50: 0.04 | R50: Northern 107 | S50: 74 | T50: Q4 2028 | U50: Bear only | V50: =IFERROR(VALUE(RIGHT(T50,4))*4+MATCH(LEFT(T50,2),{"Q1","Q2","Q3","Q4"},0)-1,"") | W50: =IF(V50="","",IF(V50<=$Z$1,0,MAX(1,INT((V50-$Z$2)/4)+1))) | X50: =IF(U50="All",1,IF(U50="Bear+Base",IF($Z$3>=2,1,0),IF(U50="Bear only",IF($Z$3>=3,1,0),0)))
B51: CONCESSIONS % — forward assumption (editable) | R51: Zenn @ Sierra Verde | S51: 66 | U51: Bear only | V51: =IFERROR(VALUE(RIGHT(T51,4))*4+MATCH(LEFT(T51,2),{"Q1","Q2","Q3","Q4"},0)-1,"") | W51: =IF(V51="","",IF(V51<=$Z$1,0,MAX(1,INT((V51-$Z$2)/4)+1))) | X51: =IF(U51="All",1,IF(U51="Bear+Base",IF($Z$3>=2,1,0),IF(U51="Bear only",IF($Z$3>=3,1,0),0)))
B52: Bear | J52: 0.06 | K52: 0.045 | L52: 0.035 | M52: 0.035 | N52: 0.035 | O52: 0.035 | R52: The BLVD Residential District | U52: Bear only | V52: =IFERROR(VALUE(RIGHT(T52,4))*4+MATCH(LEFT(T52,2),{"Q1","Q2","Q3","Q4"},0)-1,"") | W52: =IF(V52="","",IF(V52<=$Z$1,0,MAX(1,INT((V52-$Z$2)/4)+1))) | X52: =IF(U52="All",1,IF(U52="Bear+Base",IF($Z$3>=2,1,0),IF(U52="Bear only",IF($Z$3>=3,1,0),0)))
B53: Base | J53: 0.03 | K53: 0.015 | L53: 0.005 | M53: 0.005 | N53: 0.005 | O53: 0.005 | R53: The BLVD Park Avenue District | U53: Bear only | V53: =IFERROR(VALUE(RIGHT(T53,4))*4+MATCH(LEFT(T53,2),{"Q1","Q2","Q3","Q4"},0)-1,"") | W53: =IF(V53="","",IF(V53<=$Z$1,0,MAX(1,INT((V53-$Z$2)/4)+1))) | X53: =IF(U53="All",1,IF(U53="Bear+Base",IF($Z$3>=2,1,0),IF(U53="Bear only",IF($Z$3>=3,1,0),0)))
B54: Bull | J54: 0.02 | K54: 0.005 | L54: 0 | M54: 0 | N54: 0 | O54: 0 | R54: Globe Land Investors Development | U54: Bear only | V54: =IFERROR(VALUE(RIGHT(T54,4))*4+MATCH(LEFT(T54,2),{"Q1","Q2","Q3","Q4"},0)-1,"") | W54: =IF(V54="","",IF(V54<=$Z$1,0,MAX(1,INT((V54-$Z$2)/4)+1))) | X54: =IF(U54="All",1,IF(U54="Bear+Base",IF($Z$3>=2,1,0),IF(U54="Bear only",IF($Z$3>=3,1,0),0)))
B55: EFFECTIVE RENT GROWTH (derived) | R55: Ball Park | U55: Bear only | V55: =IFERROR(VALUE(RIGHT(T55,4))*4+MATCH(LEFT(T55,2),{"Q1","Q2","Q3","Q4"},0)-1,"") | W55: =IF(V55="","",IF(V55<=$Z$1,0,MAX(1,INT((V55-$Z$2)/4)+1))) | X55: =IF(U55="All",1,IF(U55="Bear+Base",IF($Z$3>=2,1,0),IF(U55="Bear only",IF($Z$3>=3,1,0),0)))
B56: Bear | J56: =(1+J48)*(1-J52)-1 | K56: =(1+K48)*(1-K52)/(1-J52)-1 | L56: =(1+L48)*(1-L52)/(1-K52)-1 | M56: =(1+M48)*(1-M52)/(1-L52)-1 | N56: =(1+N48)*(1-N52)/(1-M52)-1 | O56: =(1+O48)*(1-O52)/(1-N52)-1 | R56: Vision 2 Parcel A | U56: Bear only | V56: =IFERROR(VALUE(RIGHT(T56,4))*4+MATCH(LEFT(T56,2),{"Q1","Q2","Q3","Q4"},0)-1,"") | W56: =IF(V56="","",IF(V56<=$Z$1,0,MAX(1,INT((V56-$Z$2)/4)+1))) | X56: =IF(U56="All",1,IF(U56="Bear+Base",IF($Z$3>=2,1,0),IF(U56="Bear only",IF($Z$3>=3,1,0),0)))
B57: Base | J57: =(1+J49)*(1-J53)-1 | K57: =(1+K49)*(1-K53)/(1-J53)-1 | L57: =(1+L49)*(1-L53)/(1-K53)-1 | M57: =(1+M49)*(1-M53)/(1-L53)-1 | N57: =(1+N49)*(1-N53)/(1-M53)-1 | O57: =(1+O49)*(1-O53)/(1-N53)-1 | R57: Firststreet Verde | U57: Bear only | V57: =IFERROR(VALUE(RIGHT(T57,4))*4+MATCH(LEFT(T57,2),{"Q1","Q2","Q3","Q4"},0)-1,"") | W57: =IF(V57="","",IF(V57<=$Z$1,0,MAX(1,INT((V57-$Z$2)/4)+1))) | X57: =IF(U57="All",1,IF(U57="Bear+Base",IF($Z$3>=2,1,0),IF(U57="Bear only",IF($Z$3>=3,1,0),0)))
B58: Bull | J58: =(1+J50)*(1-J54)-1 | K58: =(1+K50)*(1-K54)/(1-J54)-1 | L58: =(1+L50)*(1-L54)/(1-K54)-1 | M58: =(1+M50)*(1-M54)/(1-L54)-1 | N58: =(1+N50)*(1-N54)/(1-M54)-1 | O58: =(1+O50)*(1-O54)/(1-N54)-1 | R58: Goodyear Civic Square at Estrella Falls | U58: Bear only | V58: =IFERROR(VALUE(RIGHT(T58,4))*4+MATCH(LEFT(T58,2),{"Q1","Q2","Q3","Q4"},0)-1,"") | W58: =IF(V58="","",IF(V58<=$Z$1,0,MAX(1,INT((V58-$Z$2)/4)+1))) | X58: =IF(U58="All",1,IF(U58="Bear+Base",IF($Z$3>=2,1,0),IF(U58="Bear only",IF($Z$3>=3,1,0),0)))
R59: I-10 Innovation Center II | U59: Bear only | V59: =IFERROR(VALUE(RIGHT(T59,4))*4+MATCH(LEFT(T59,2),{"Q1","Q2","Q3","Q4"},0)-1,"") | W59: =IF(V59="","",IF(V59<=$Z$1,0,MAX(1,INT((V59-$Z$2)/4)+1))) | X59: =IF(U59="All",1,IF(U59="Bear+Base",IF($Z$3>=2,1,0),IF(U59="Bear only",IF($Z$3>=3,1,0),0)))
B60: ▸ DETAIL: subject rent source by year & reconciliation (grouped — click − to collapse) | R60: Celebration Plaza Parcel D | U60: Bear only | V60: =IFERROR(VALUE(RIGHT(T60,4))*4+MATCH(LEFT(T60,2),{"Q1","Q2","Q3","Q4"},0)-1,"") | W60: =IF(V60="","",IF(V60<=$Z$1,0,MAX(1,INT((V60-$Z$2)/4)+1))) | X60: =IF(U60="All",1,IF(U60="Bear+Base",IF($Z$3>=2,1,0),IF(U60="Bear only",IF($Z$3>=3,1,0),0)))
B61: -Y6 Q3 2019–Q2 2020 | E61: CoStar | R61: SimonMed Development II | U61: Bear only | V61: =IFERROR(VALUE(RIGHT(T61,4))*4+MATCH(LEFT(T61,2),{"Q1","Q2","Q3","Q4"},0)-1,"") | W61: =IF(V61="","",IF(V61<=$Z$1,0,MAX(1,INT((V61-$Z$2)/4)+1))) | X61: =IF(U61="All",1,IF(U61="Bear+Base",IF($Z$3>=2,1,0),IF(U61="Bear only",IF($Z$3>=3,1,0),0)))
B62: -Y5 Q3 2020–Q2 2021 | E62: CoStar | R62: 182 South 95th Avenue | U62: Bear only | V62: =IFERROR(VALUE(RIGHT(T62,4))*4+MATCH(LEFT(T62,2),{"Q1","Q2","Q3","Q4"},0)-1,"") | W62: =IF(V62="","",IF(V62<=$Z$1,0,MAX(1,INT((V62-$Z$2)/4)+1))) | X62: =IF(U62="All",1,IF(U62="Bear+Base",IF($Z$3>=2,1,0),IF(U62="Bear only",IF($Z$3>=3,1,0),0)))
B63: -Y4 Q3 2021–Q2 2022 | E63: CoStar | R63: Envision Encore | U63: Bear only | V63: =IFERROR(VALUE(RIGHT(T63,4))*4+MATCH(LEFT(T63,2),{"Q1","Q2","Q3","Q4"},0)-1,"") | W63: =IF(V63="","",IF(V63<=$Z$1,0,MAX(1,INT((V63-$Z$2)/4)+1))) | X63: =IF(U63="All",1,IF(U63="Bear+Base",IF($Z$3>=2,1,0),IF(U63="Bear only",IF($Z$3>=3,1,0),0)))
B64: -Y3 Q3 2022–Q2 2023 | E64: CoStar
B65: -Y2 Q3 2023–Q2 2024 | E65: HD
B66: -Y1 Q3 2024–Q2 2025 | E66: HD
B67: Y0 Q3 2025–Q2 2026 | E67: HD
B68: UC scheduled vs CoStar UC | E68: 2,307 / 1,251
B69: As-of 2026 Q2 QTD is partial (QTD); occupancy is point-in-time, Y0 flow sums partial.

Sheet Reconciliation Log
A1: Property | B1: Address | C1: Units | D1: Year Built | E1: Est. Delivery | F1: Bucket | G1: CoStar Occ | H1: RealPage Occ | I1: CoStar Ask Rent | J1: RealPage Eff Rent | K1: Sources | L1: Notes
A2: Avery | B2: 1700 N Harbor Shore Blvd | C2: 185 | D2: 2024 | E2: Q2 2024 | F2: STABILIZED / STABILIZING | G2: 0.924324 | H2: 0.924 | I2: 1750 | J2: 1875 | K2: CoStar+RealPage | L2: Rent: CoStar ask $1,750 vs RealPage eff $1,875
A3: Ironwood at River Run | B3: 11951 W Windsor Ave | C3: 103 | D3: 2024 | E3: Q2 2024 | F3: STABILIZED / STABILIZING | H3: 0.961 | J3: 2090 | K3: RealPage | L3: Delivery quarter estimated
A4: TerraLane at Park McDowell | B4: 2250 N 95th Ave | C4: 162 | D4: 2023 | E4: Q1 2023 | F4: STABILIZED / STABILIZING | G4: 0.851852 | H4: 0.877 | I4: 1576 | J4: 1211 | K4: CoStar+RealPage | L4: Delivery quarter estimated; Occ: CoStar 85% vs RealPage 88%; Rent: CoStar ask $1,576 vs RealPage eff $1,211
A5: Bungalows at Camelback | B5: 4747 N 99th Ave | C5: 334 | D5: 2023 | E5: Q1 2023 | F5: STABILIZED / STABILIZING | G5: 0.763473 | H5: 0.916 | I5: 2026 | J5: 1385 | K5: CoStar+RealPage | L5: Year built: 2023/2024; Delivery quarter estimated; Occ: CoStar 76% vs RealPage 92%; Rent: CoStar ask $2,026 vs RealPage eff $1,385
A6: Prose Desert River | B6: 7430 N 100th Ave | C6: 384 | D6: 2023 | E6: Q1 2023 | F6: STABILIZED / STABILIZING | G6: 0.895833 | H6: 0.966 | I6: 1429 | J6: 1313 | K6: CoStar+RealPage | L6: Year built: 2023/2024; Delivery quarter estimated; Occ: CoStar 90% vs RealPage 97%; Rent: CoStar ask $1,429 vs RealPage eff $1,313
A7: Christopher Todd Communities at McDowell | B7: 1350 N 117th Ave | C7: 217 | D7: 2023 | E7: Q1 2023 | F7: STABILIZED / STABILIZING | G7: 0.949309 | H7: 0.968 | I7: 1576 | J7: 1602 | K7: CoStar+RealPage | L7: Year built: 2023/2024; Delivery quarter estimated
A8: Village Camelback Park | B8: 11200 W Camelback Rd | C8: 194 | D8: 2023 | E8: Q1 2023 | F8: STABILIZED / STABILIZING | G8: 0.773196 | H8: 0.918 | I8: 1874 | J8: 1794 | K8: CoStar+RealPage | L8: Delivery quarter estimated; Occ: CoStar 77% vs RealPage 92%
A9: Springs At Westgate | B9: 10020 W Glendale Ave | C9: 292 | D9: 2023 | E9: Q1 2023 | F9: STABILIZED / STABILIZING | G9: 0.784247 | H9: 0.87 | I9: 1516 | J9: 1517 | K9: CoStar+RealPage | L9: Year built: 2023/2024; Delivery quarter estimated; Occ: CoStar 78% vs RealPage 87%
A10: Parc Lofts | B10: 8727 W McDowell Rd | C10: 258 | D10: 2023 | E10: Q1 2023 | F10: STABILIZED / STABILIZING | G10: 0.899225 | H10: 0.942 | I10: 1567 | J10: 1591 | K10: CoStar+RealPage | L10: Delivery quarter estimated; Occ: CoStar 90% vs RealPage 94%
A11: The Crofton at Sheely Farms | B11: 9200 W McDowell Rd | C11: 167 | D11: 2023 | E11: Q1 2023 | F11: STABILIZED / STABILIZING | G11: 0.952096 | H11: 0.946 | I11: 1607 | J11: 1388 | K11: CoStar+RealPage | L11: Delivery quarter estimated; Rent: CoStar ask $1,607 vs RealPage eff $1,388
A12: District at Civic Square | B12: 15400 W Monte Vista Rd | C12: 352 | D12: 2023 | E12: Q1 2023 | F12: STABILIZED / STABILIZING | G12: 0.920455 | H12: 1 | I12: 1526 | J12: 1263 | K12: CoStar+RealPage | L12: Year built: 2023/2024; Delivery quarter estimated; Occ: CoStar 92% vs RealPage 100%; Rent: CoStar ask $1,526 vs RealPage eff $1,263
A13: BB Living at Civic Square | B13: 15125 W Oak St | C13: 290 | D13: 2023 | E13: Q1 2023 | F13: STABILIZED / STABILIZING | G13: 0.934483 | H13: 0.959 | I13: 2812 | J13: 2575 | K13: CoStar+RealPage | L13: Year built: 2023/2024; Delivery quarter estimated; Occ: CoStar 93% vs RealPage 96%; Rent: CoStar ask $2,812 vs RealPage eff $2,575
A14: Village at the BLVD | B14: 11175 W Roosevelt Rd | C14: 187 | D14: 2023 | E14: Q1 2023 | F14: STABILIZED / STABILIZING | G14: 0.935829 | H14: 0.963 | I14: 1964 | J14: 1902 | K14: CoStar+RealPage | L14: Year built: 2023/2024; Delivery quarter estimated; Occ: CoStar 94% vs RealPage 96%
A15: Acero Roosevelt | B15: 15400 W Roosevelt St | C15: 352 | D15: 2023 | E15: Q1 2023 | F15: STABILIZED / STABILIZING | G15: 0.892045 | H15: 0.94 | I15: 1632 | J15: 1236 | K15: CoStar+RealPage | L15: Year built: 2023/2024; Delivery quarter estimated; Occ: CoStar 89% vs RealPage 94%; Rent: CoStar ask $1,632 vs RealPage eff $1,236
... A17: Cabana Bullard | B17: 14780 W Van Buren St | C17: 336 | D17: 2023 | E17: Q1 2023 | F17: STABILIZED / STABILIZING | G17: 0.949405 | H17: 0.949 | I17: 1335 | J17: 1325 | K17: CoStar+RealPage | L17: Delivery quarter estimated
A18: Ironwood Homes at River Run | B18: 11901 W Windsor Ave | C18: 103 | D18: 2023 | E18: Q1 2023 | F18: STABILIZED / STABILIZING | G18: 0.893204 | I18: 2523 | K18: CoStar | L18: Delivery quarter estimated
A19: Cuvee Apartments | B19: 7200 N 91st Ave | C19: 310 | D19: 2023 | E19: Q1 2023 | F19: STABILIZED / STABILIZING | H19: 0.926 | J19: 1629 | K19: RealPage | L19: Delivery quarter estimated
A20: Avari Apartments | B20: 11580 W Corporate Dr | C20: 354 | D20: 2022 | E20: Q3 2022 | F20: STABILIZED / STABILIZING | G20: 0.951977 | H20: 1 | I20: 1574 | J20: 1583 | K20: CoStar+RealPage | L20: Year built: 2022/2023; Delivery quarter estimated; Occ: CoStar 95% vs RealPage 100%
A21: Sunset View Apartments | B21: 2323 N 150th Dr | C21: 286 | D21: 2022 | E21: Q2 2022 | F21: STABILIZED / STABILIZING | G21: 0.902098 | H21: 0.955 | I21: 1338 | J21: 1167 | K21: CoStar+RealPage | L21: Occ: CoStar 90% vs RealPage 96%; Rent: CoStar ask $1,338 vs RealPage eff $1,167
A22: Cyrene at Estrella | B22: 15430 W Baden St | C22: 64 | D22: 2022 | E22: Q1 2022 | F22: STABILIZED / STABILIZING | G22: 0.984375 | H22: 0.984 | I22: 2442 | J22: 2261 | K22: CoStar+RealPage | L22: Year built: 2022/2023; Delivery quarter estimated; Rent: CoStar ask $2,442 vs RealPage eff $2,261
A23: Luna Bear 94 | B23: 9000 W Indian School Rd | C23: 94 | D23: 2022 | E23: Q1 2022 | F23: STABILIZED / STABILIZING | G23: 0.989362 | H23: 1 | I23: 1913 | J23: 1982 | K23: CoStar+RealPage
A24: Avilla Western Garden | B24: 4041 N 97th Ave | C24: 195 | D24: 2026 | E24: Q2 2026 | F24: LEASING UP | G24: 0.446154 | H24: 0 | I24: 1829 | J24: 1681 | K24: CoStar+RealPage | L24: Delivery quarter estimated; Occ: CoStar 45% vs RealPage 0%; Rent: CoStar ask $1,829 vs RealPage eff $1,681; Verify rent/occ w/ HelloData
A25: Liberty at Estrella Falls | B25: 2505 N 153rd Dr | C25: 106 | D25: 2026 | E25: Q2 2026 | F25: LEASING UP | G25: 0.056604 | H25: 0.208 | I25: 2966 | J25: 1938 | K25: CoStar+RealPage | L25: Delivery quarter estimated; Occ: CoStar 6% vs RealPage 21%; Rent: CoStar ask $2,966 vs RealPage eff $1,938; Verify rent/occ w/ HelloData
A26: Rev3 at Avondale Station | B26: 9980 W Encanto Blvd | C26: 117 | D26: 2026 | E26: Q2 2026 | F26: LEASING UP | G26: 0.273504 | H26: 0 | I26: 2537 | J26: 2273 | K26: CoStar+RealPage | L26: Units: CoStar 117 vs RealPage 107; Delivery quarter estimated; Occ: CoStar 27% vs RealPage 0%; Rent: CoStar ask $2,537 vs RealPage eff $2,273; Verify rent/occ w/ HelloData
A27: Flatz 623 | B27: 11850 W Fillmore St | C27: 360 | D27: 2026 | E27: Q2 2026 | F27: LEASING UP | G27: 0.133333 | I27: 1411 | K27: CoStar | L27: Delivery quarter estimated; Verify rent/occ w/ HelloData
A28: Stately Avondale | B28: 12375 W Van Buren St | C28: 286 | D28: 2026 | E28: Q2 2026 | F28: LEASING UP | G28: 0.297203 | H28: 0 | I28: 1728 | J28: 1243 | K28: CoStar+RealPage | L28: Year built: 2026/2027; Delivery quarter estimated; Occ: CoStar 30% vs RealPage 0%; Rent: CoStar ask $1,728 vs RealPage eff $1,243; Verify rent/occ w/ HelloData
A29: Broadstone Ascend | B29: 12905 W Indian School Rd | C29: 432 | D29: 2025 | E29: Q4 2025 | F29: LEASING UP | G29: 0.875 | H29: 0.512 | I29: 1506 | J29: 1107 | K29: CoStar+RealPage | L29: Year built: 2025/2026; Delivery quarter estimated; Occ: CoStar 88% vs RealPage 51%; Rent: CoStar ask $1,506 vs RealPage eff $1,107; Verify rent/occ w/ HelloData
A30: Pradera Estates | B30: 12616 W Adair Dr | C30: 86 | D30: 2025 | E30: Q3 2025 | F30: LEASING UP | G30: 0.895349 | I30: 2474 | K30: CoStar | L30: Delivery quarter estimated; Verify rent/occ w/ HelloData
A31: Rev3 Encanto West | B31: 2150 N Avondale Blvd | C31: 84 | D31: 2025 | E31: Q3 2025 | F31: LEASING UP | G31: 0.52381 | H31: 0.714 | I31: 2319 | J31: 1833 | K31: CoStar+RealPage | L31: Units: CoStar 84 vs RealPage 78; Year built: 2025/2026; Occ: CoStar 52% vs RealPage 71%; Rent: CoStar ask $2,319 vs RealPage eff $1,833; Verify rent/occ w/ HelloData
A32: Villas Litchfield Park | B32: 12730 W Camelback Rd | C32: 153 | D32: 2025 | E32: Q3 2025 | F32: LEASING UP | G32: 0.810458 | H32: 0.856 | I32: 1913 | J32: 1538 | K32: CoStar+RealPage | L32: Delivery quarter estimated; Occ: CoStar 81% vs RealPage 86%; Rent: CoStar ask $1,913 vs RealPage eff $1,538; Verify rent/occ w/ HelloData
A33: Avalon Townhomes | B33: 13025 W Thomas Rd | C33: 70 | D33: 2025 | E33: Q3 2025 | F33: LEASING UP | G33: 0.857143 | H33: 0.857 | I33: 2325 | J33: 2169 | K33: CoStar+RealPage | L33: Delivery quarter estimated; Rent: CoStar ask $2,325 vs RealPage eff $2,169; Verify rent/occ w/ HelloData
A34: Villas on Van Buren | B34: 9835 W Van Buren St | C34: 143 | D34: 2025 | E34: Q3 2025 | F34: LEASING UP | G34: 0.496503 | H34: 0 | I34: 2085 | J34: 2095 | K34: CoStar+RealPage | L34: Year built: 2025/2026; Delivery quarter estimated; Occ: CoStar 50% vs RealPage 0%; Verify rent/occ w/ HelloData
A35: Agave Ranch | B35: 10060 W Desert Blvd | C35: 324 | D35: 2025 | E35: Q2 2025 | F35: LEASING UP | G35: 0.802469 | H35: 0 | I35: 1747 | J35: 1582 | K35: CoStar+RealPage | L35: Delivery quarter estimated; Occ: CoStar 80% vs RealPage 0%; Rent: CoStar ask $1,747 vs RealPage eff $1,582; Verify rent/occ w/ HelloData
A36: Alta Goodyear | B36: 14965 W Encanto Blvd | C36: 342 | D36: 2025 | E36: Q2 2025 | F36: LEASING UP | G36: 0.789474 | H36: 0.784 | I36: 1638 | J36: 1433 | K36: CoStar+RealPage | L36: Delivery quarter estimated; Rent: CoStar ask $1,638 vs RealPage eff $1,433; Verify rent/occ w/ HelloData
A37: Village at Skyline Ranch | B37: 13215 W Glendale Ave | C37: 167 | D37: 2025 | E37: Q2 2025 | F37: LEASING UP | G37: 0.39521 | H37: 0 | I37: 1773 | J37: 1632 | K37: CoStar+RealPage | L37: Year built: 2025/2026; Delivery quarter estimated; Occ: CoStar 40% vs RealPage 0%; Rent: CoStar ask $1,773 vs RealPage eff $1,632; Verify rent/occ w/ HelloData
A38: Avondale Commons | B38: 11650 W McDowell Rd | C38: 324 | D38: 2025 | E38: Q2 2025 | F38: LEASING UP | G38: 0.37037 | H38: 0.852 | I38: 1632 | J38: 1321 | K38: CoStar+RealPage | L38: Year built: 2025/2026; Delivery quarter estimated; Occ: CoStar 37% vs RealPage 85%; Rent: CoStar ask $1,632 vs RealPage eff $1,321; Verify rent/occ w/ HelloData
A39: Cabana Aldea | B39: 9910 W Montebello Ave | C39: 257 | D39: 2025 | E39: Q2 2025 | F39: LEASING UP | G39: 0.7393 | H39: 0.673 | I39: 1330 | J39: 1253 | K39: CoStar+RealPage | L39: Delivery quarter estimated; Occ: CoStar 74% vs RealPage 67%; Rent: CoStar ask $1,330 vs RealPage eff $1,253; Verify rent/occ w/ HelloData
A40: The Douglas | B40: 14935 W Van Buren St | C40: 307 | D40: 2025 | E40: Q2 2025 | F40: LEASING UP | G40: 0.583062 | H40: 0.59 | I40: 2076 | J40: 1561 | K40: CoStar+RealPage | L40: Delivery quarter estimated; Rent: CoStar ask $2,076 vs RealPage eff $1,561; Verify rent/occ w/ HelloData
A41: Broadstone Westgate | B41: 6851 N 93RD Ave | C41: 308 | D41: 2025 | E41: Q2 2025 | F41: LEASING UP | H41: 0.89 | J41: 1438 | K41: RealPage | L41: Delivery quarter estimated; Verify rent/occ w/ HelloData
A42: Somerset Upscale Apartments | B42: 7811 N 99th Ave | C42: 234 | D42: 2025 | E42: Q2 2025 | F42: LEASING UP | H42: 0.256 | J42: 1671 | K42: RealPage | L42: Delivery quarter estimated; Verify rent/occ w/ HelloData
A43: Streamliner Aldea | B43: 5900 N 99th Ave | C43: 282 | D43: 2025 | E43: Q2 2025 | F43: LEASING UP | H43: 0.844 | J43: 1025 | K43: RealPage | L43: Delivery quarter estimated; Verify rent/occ w/ HelloData
A44: Meritum Sheely Farms | B44: 2121 N 99th Ave | C44: 680 | D44: 2024 | E44: Q4 2024 | F44: LEASING UP | G44: 0.797059 | H44: 0.808 | I44: 1680 | J44: 1356 | K44: CoStar+RealPage | L44: Year built: 2024/2025; Delivery quarter estimated; Rent: CoStar ask $1,680 vs RealPage eff $1,356; Verify rent/occ w/ HelloData
A45: Moderne at Roosevelt | B45: 805 N 97th Ave | C45: 185 | D45: 2024 | E45: Q2 2024 | F45: LEASING UP | G45: 0.891892 | H45: 0.935 | I45: 1900 | J45: 1769 | K45: CoStar+RealPage | L45: Year built: 2024/2025; Occ: CoStar 89% vs RealPage 94%; Rent: CoStar ask $1,900 vs RealPage eff $1,769; Verify rent/occ w/ HelloData
A46: Canopy at the Trails | B46: 4141 N 104th Dr | C46: 124 | D46: 2024 | E46: Q2 2024 | F46: LEASING UP | G46: 0.879032 | H46: 0.919 | I46: 2183 | J46: 2093 | K46: CoStar+RealPage | L46: Delivery quarter estimated; Occ: CoStar 88% vs RealPage 92%; Verify rent/occ w/ HelloData
A47: Cardinal 95 | B47: 9600 W Georgia Ave | C47: 198 | D47: 2024 | E47: Q2 2024 | F47: LEASING UP | G47: 0.878788 | H47: 0.889 | I47: 1691 | J47: 1646 | K47: CoStar+RealPage | L47: Delivery quarter estimated; Verify rent/occ w/ HelloData
A48: Livano Avondale | B48: 11575 W Roosevelt St | C48: 316 | D48: 2024 | E48: Q2 2024 | F48: LEASING UP | G48: 0.829114 | H48: 0.842 | I48: 1663 | J48: 1263 | K48: CoStar+RealPage | L48: Year built: 2024/2025; Delivery quarter estimated; Rent: CoStar ask $1,663 vs RealPage eff $1,263; Verify rent/occ w/ HelloData
A49: Alta Avondale | B49: 11330 W Van Buren St | C49: 360 | D49: 2024 | E49: Q2 2024 | F49: LEASING UP | G49: 0.783333 | H49: 0.836 | I49: 1610 | J49: 1339 | K49: CoStar+RealPage | L49: Year built: 2024/2025; Delivery quarter estimated; Occ: CoStar 78% vs RealPage 84%; Rent: CoStar ask $1,610 vs RealPage eff $1,339; Verify rent/occ w/ HelloData
A50: Alta 99th | B50: 4411 N 99th Ave | C50: 402 | D50: 2024 | E50: Q1 2024 | F50: LEASING UP | G50: 0.855721 | H50: 0.901 | I50: 1542 | J50: 1154 | K50: CoStar+RealPage | L50: Delivery quarter estimated; Occ: CoStar 86% vs RealPage 90%; Rent: CoStar ask $1,542 vs RealPage eff $1,154; Verify rent/occ w/ HelloData
A51: Radia Avondale Station | B51: 9975 W Encanto Blvd | C51: 407 | D51: 2024 | E51: Q1 2024 | F51: LEASING UP | G51: 0.616708 | H51: 0.514 | I51: 1743 | J51: 1676 | K51: CoStar+RealPage | L51: Units: CoStar 407 vs RealPage 212; Year built: 2024/2025; Delivery quarter estimated; Occ: CoStar 62% vs RealPage 51%; Verify rent/occ w/ HelloData
A52: Zen @ Angelina | B52: 956 Castillo Dr S | C52: 130 | D52: 2027 | E52: Q2 2028 | F52: UNDER CONSTRUCTION | K52: CoStar+RealPage | L52: Year built: 2027/2028
A53: Zanjero III | B53: 7151 N Zanjero Blvd | C53: 301 | D53: 2028 | E53: Q2 2028 | F53: UNDER CONSTRUCTION | K53: RealPage
A54: Yardly Algodon | B54: 9225 W Indian School Rd | C54: 262 | D54: 2026 | E54: Q4 2027 | F54: UNDER CONSTRUCTION | I54: 1781 | K54: CoStar+RealPage | L54: Units: CoStar 262 vs RealPage 291; Year built: 2026/2027
A55: Cerro Vista | B55: 12116 W Van Buren St | C55: 255 | D55: 2026 | E55: Q4 2027 | F55: UNDER CONSTRUCTION | K55: CoStar
A56: Pointe Grand Estrella at Phoenix | B56: 10649 W Buckeye Rd | C56: 288 | D56: 2026 | E56: Q2 2027 | F56: UNDER CONSTRUCTION | I56: 1650 | K56: CoStar+RealPage | L56: Year built: 2026/2027
A57: Marbella Ranch East I | B57: 7725 El Mirage Rd | C57: 144 | D57: 2027 | E57: Q2 2027 | F57: UNDER CONSTRUCTION | K57: RealPage
A58: Villages at Northern | B58: 7910 N 107th Ave | C58: 74 | D58: 2027 | E58: Q2 2027 | F58: UNDER CONSTRUCTION | K58: RealPage
A59: Prosper 47 | B59: 13426 W Van Buren St | C59: 47 | D59: 2027 | E59: Q2 2027 | F59: UNDER CONSTRUCTION | K59: RealPage | L59: RealPage only (sub-50 unit)
A60: HARMON Ascend | B60: 12805 W Indian School Rd | C60: 125 | D60: 2026 | E60: Q1 2027 | F60: UNDER CONSTRUCTION | I60: 2788 | K60: CoStar+RealPage
A61: FUZE Ballpark | B61: 6255 N Ball Park Blvd | C61: 321 | D61: 2026 | E61: Q3 2026 | F61: UNDER CONSTRUCTION | K61: CoStar+RealPage
A62: Flatz623 | B62: 11850 W Fillmore St | C62: 360 | D62: 2026 | E62: Q3 2026 | F62: UNDER CONSTRUCTION | H62: 0 | J62: 1145 | K62: RealPage
A63: Northern 107 | B63: N 107th Ave | C63: 74 | E63: Q4 2028 | F63: PROPOSED | K63: CoStar
A64: The Waverly | B64: 391 S 99th Ave | C64: 323 | D64: 2028 | E64: Q3 2028 | F64: PROPOSED | K64: CoStar+RealPage
A65: The Statler at Estrella Parkway | B65: 240 N Estrella Pky | C65: 284 | E65: Q3 2028 | F65: PROPOSED | K65: CoStar
A66: Encore Avondale | B66: 11295 W Roosevelt St | C66: 300 | D66: 2027 | E66: Q3 2028 | F66: PROPOSED | K66: CoStar+RealPage
A67: Ascent Goodyear | B67: 15681 W Roosevelt St | C67: 113 | D67: 2027 | E67: Q3 2028 | F67: PROPOSED | K67: CoStar
A68: District 99 | B68: N 99th Ave & W McDowell Rd | C68: 172 | F68: PROPOSED | K68: RealPage | L68: RealPage pipeline (not yet in CoStar)
A69: Liv Avondale | B69: W Indian School Rd & N 99th Ave | C69: 333 | F69: PROPOSED | K69: RealPage | L69: RealPage pipeline (not yet in CoStar)
A70: Sanctuair at Centerscape | B70: 1450 N 145th Ave | C70: 303 | F70: PROPOSED | K70: RealPage | L70: RealPage pipeline (not yet in CoStar)
A71: Cornerstone at the Wigwam | B71: Litchfield Rd & Wigwam Blvd | C71: 212 | F71: PROPOSED | K71: RealPage | L71: RealPage pipeline (not yet in CoStar)
A72: The BLVD Residential District | B72: W Roosevelt St & W Hilton Way | F72: PROPOSED | K72: RealPage | L72: RealPage pipeline (not yet in CoStar)
A73: Crystal Cove | B73: 290 E La Canada Blvd | C73: 260 | F73: PROPOSED | K73: RealPage | L73: RealPage pipeline (not yet in CoStar)
A74: The BLVD Park Avenue District | B74: N Avondale Blvd & W Van Buren St | F74: PROPOSED | K74: RealPage | L74: RealPage pipeline (not yet in CoStar)
A75: Western Garden II | B75: 3301 N 99th Ave | C75: 314 | F75: PROPOSED | K75: RealPage | L75: RealPage pipeline (not yet in CoStar)
A76: Tavalo at Avondale | B76: 12451 W Buckeye Rd | C76: 266 | F76: PROPOSED | K76: RealPage | L76: RealPage pipeline (not yet in CoStar)
A77: Globe Land Investors Development | B77: N Bullard Ave & W McDowell Rd | F77: PROPOSED | K77: RealPage | L77: RealPage pipeline (not yet in CoStar)
A78: Ball Park | B78: 6450 N 99th Ave | F78: PROPOSED | K78: RealPage | L78: RealPage pipeline (not yet in CoStar)
A79: Urban 95 Parcel B | B79: N 95th Ave & W Georgia Ave | C79: 478 | F79: PROPOSED | K79: RealPage | L79: RealPage pipeline (not yet in CoStar)
A80: The District at Westgate | B80: 6801 N 91st Ave | C80: 384 | F80: PROPOSED | K80: RealPage | L80: RealPage pipeline (not yet in CoStar)
A81: Vision 2 Parcel A | B81: W Glendale Ave & N 99th Ave | F81: PROPOSED | K81: RealPage | L81: RealPage pipeline (not yet in CoStar)
A82: Anton Glendale | B82: 5149 & 5205 N 99th Ave | C82: 320 | F82: PROPOSED | K82: RealPage | L82: RealPage pipeline (not yet in CoStar)
A83: Banyan Avondale | B83: Dysart Rd & E Madison St | C83: 296 | F83: PROPOSED | K83: RealPage | L83: RealPage pipeline (not yet in CoStar)
A84: Celebration Plaza Parcel B | B84: 844 Litchfield Rd | C84: 410 | F84: PROPOSED | K84: RealPage | L84: RealPage pipeline (not yet in CoStar)
A85: Urban 95 Parcel A | B85: W Georgia Ave & N 95th Ave | C85: 324 | F85: PROPOSED | K85: RealPage | L85: RealPage pipeline (not yet in CoStar)
A86: Urban 95 Parcel C | B86: W Georgia Ave & N 95th Ave | C86: 500 | F86: PROPOSED | K86: RealPage | L86: RealPage pipeline (not yet in CoStar)
A87: Firststreet Verde | B87: 9275 W Van Buren St | F87: PROPOSED | K87: RealPage | L87: RealPage pipeline (not yet in CoStar)
A88: Radia Avondale Station III | B88: W Encanto Blvd & N 99th Ave | C88: 212 | F88: PROPOSED | K88: RealPage | L88: RealPage pipeline (not yet in CoStar)
A89: Rosilian Villas | B89: N Dysart Rd & E Van Buren St | C89: 291 | F89: PROPOSED | K89: RealPage | L89: RealPage pipeline (not yet in CoStar)
A90: Goodyear Civic Square at Estrella Falls | B90: W Monte Vista & N 150th Dr | F90: PROPOSED | K90: RealPage | L90: RealPage pipeline (not yet in CoStar)
A91: I-10 Innovation Center II | B91: N 91st Ave & W Roosevelt St | F91: PROPOSED | K91: RealPage | L91: RealPage pipeline (not yet in CoStar)
A92: Orion Avondale | B92: W McDowell Rd & Avondale Blvd | C92: 268 | F92: PROPOSED | K92: RealPage | L92: RealPage pipeline (not yet in CoStar)
A93: Celebration Plaza Parcel A | B93: Celebrate Life Way & N Litchfield Rd | C93: 181 | F93: PROPOSED | K93: RealPage | L93: RealPage pipeline (not yet in CoStar)
A94: Celebration Plaza Parcel D | B94: Celebrate Life Way & N Litchfield Rd | F94: PROPOSED | K94: RealPage | L94: RealPage pipeline (not yet in CoStar)
A95: Sheely Center Future Phase | B95: 2215 N 99th Ave | C95: 697 | F95: PROPOSED | K95: RealPage | L95: RealPage pipeline (not yet in CoStar)
A96: Porter Kyle Development | B96: W Camelback Rd & S Denny Blvd | C96: 135 | F96: PROPOSED | K96: RealPage | L96: RealPage pipeline (not yet in CoStar)
A97: McDowell Villas | B97: 11791 W McDowell Rd | C97: 164 | F97: PROPOSED | K97: RealPage | L97: RealPage pipeline (not yet in CoStar)
A98: SimonMed Development II | B98: W Glendale Ave & N 99th Ave | F98: PROPOSED | K98: RealPage | L98: RealPage pipeline (not yet in CoStar)
A99: SimonMed Development I | B99: 10020 W Glendale Ave | C99: 239 | F99: PROPOSED | K99: RealPage | L99: RealPage pipeline (not yet in CoStar)
A100: 182 South 95th Avenue | B100: 182 S 95th Ave | F100: PROPOSED | K100: RealPage | L100: RealPage pipeline (not yet in CoStar)
A101: Picerne at Palm Valley | B101: 2128 Pebble Creek Pkwy | C101: 383 | F101: PROPOSED | K101: RealPage | L101: RealPage pipeline (not yet in CoStar)
...
