Workbook
Name CodeList: Codes!$A$5:$A$59

Sheet Dashboard
A1: Bella Mirage — Underwriting Intake
A2: Generated June 19, 2026 · RR-T12 Processor intake · Operating period Jan 2023 – Dec 2025 (36 mo, 3 statements stitched)
A3: Data vintage · Rent roll as-of 05/23/2026 · Latest financial statement thru Dec 2025
A4: SNAPSHOT | D4: UNIT MIX — mix-weighted market-rent indicators
A5: Units | B5: 715 | D5: Floor Plan | E5: Bed | F5: Bath | G5: Units | H5: Occ | I5: Vac | J5: Avg SF | K5: Avg Market Rent (per RR — not a mkt signal) | L5: Avg Contract Rent | M5: New Leases | N5: Renew Leases | O5: Avg New-Lease (last 5) | P5: New #1 | Q5: New #2 | R5: New #3 | S5: New #4 | T5: New #5 | U5: HD T90 Asking | V5: HD T90 Effective | W5: HD T365 Asking | X5: HD T365 Effective | Y5: HD90 YoY Asking | Z5: HD90 YoY Effective | AA5: Bed/Bath Src | AB5: HD Plan (website)
A6: Occupied / Vacant / Non-Rev | B6: 643 / 72 / 0 | D6: A1 | E6: 1 | F6: 1 | G6: 71 | H6: 65 | I6: 6 | J6: 739 | K6: 1153 | L6: 1196 | M6: 34 | N6: 31 | O6: 1088 | P6: 1055 | Q6: 1092 | R6: 1167 | S6: 1119 | T6: 1008 | U6: 1079 | V6: 1079 | W6: 1125 | X6: 1093 | Y6: -0.11545106 | Z6: -0.041378435 | AA6: inferred | AB6: Brook
A7: Occupancy % | B7: 0.8993007 | D7: A1R | E7: 1 | F7: 1 | G7: 16 | H7: 12 | I7: 4 | J7: 739 | K7: 1290 | L7: 1325 | M7: 5 | N7: 7 | O7: 1215 | P7: 1218 | Q7: 1134 | R7: 1102 | S7: 1408 | T7: 1215 | U7: 1178 | V7: 1178 | W7: 1211 | X7: 1175 | Y7: -0.16370739 | Z7: -0.094230769 | AA7: inferred | AB7: Brook
A8: Total Rentable SF | B8: 677256 | D8: A2 | E8: 1 | F8: 1 | G8: 196 | H8: 179 | I8: 17 | J8: 777 | K8: 1206 | L8: 1246 | M8: 88 | N8: 91 | O8: 1164 | P8: 1066 | Q8: 1180 | R8: 1148 | S8: 1143 | T8: 1281 | U8: 1160 | V8: 1160 | W8: 1162 | X8: 1142 | Y8: -0.077481014 | Z8: 0.0034438034 | AA8: inferred | AB8: Cascade
A9: New / Renewal leases | B9: 318 / 325 | D9: A2R | E9: 1 | F9: 1 | G9: 50 | H9: 40 | I9: 10 | J9: 777 | K9: 1320 | L9: 1321 | M9: 27 | N9: 13 | O9: 1226 | P9: 1266 | Q9: 1238 | R9: 1249 | S9: 1192 | T9: 1184 | U9: 1234 | V9: 1234 | W9: 1256 | X9: 1223 | Y9: -0.04894027 | Z9: 0.031772575 | AA9: inferred | AB9: Cascade
A10: — Market Rent Indicators (true signal) — | D10: B1 | E10: 2 | F10: 2 | G10: 116 | H10: 111 | I10: 5 | J10: 947 | K10: 1418 | L10: 1445 | M10: 53 | N10: 58 | O10: 1347 | P10: 1466 | Q10: 1207 | R10: 1290 | S10: 1333 | T10: 1438 | U10: 1340 | V10: 1340 | W10: 1329 | X10: 1299 | Y10: -0.039404893 | Z10: 0.044571503 | AA10: inferred | AB10: Rain
A11: HelloData asking, T90 (mix-wtd) | B11: 1391 | D11: B1R | E11: 2 | F11: 2 | G11: 34 | H11: 28 | I11: 6 | J11: 947 | K11: 1543 | L11: 1504 | M11: 20 | N11: 8 | O11: 1471 | P11: 1394 | Q11: 1449 | R11: 1606 | S11: 1423 | T11: 1484 | U11: 1383 | V11: 1383 | W11: 1470 | X11: 1438 | Y11: -0.063219688 | Z11: 0.017244197 | AA11: inferred | AB11: Rain
A12: HelloData effective, T90 (mix-wtd) | B12: 1391 | D12: B2 | E12: 2 | F12: 2 | G12: 17 | H12: 16 | I12: 1 | J12: 1040 | K12: 1586 | L12: 1574 | M12: 7 | N12: 9 | O12: 1559 | P12: 1586 | Q12: 1638 | R12: 1443 | S12: 1623 | T12: 1505 | U12: 1579 | V12: 1579 | W12: 1540 | X12: 1500 | Y12: 0.035862672 | Z12: 0.12491095 | AA12: inferred | AB12: Isla
A13: New-lease contract, T90 (avg) | B13: 1329 | D13: B2R | E13: 2 | F13: 2 | G13: 4 | H13: 4 | I13: 0 | J13: 1040 | K13: 1702 | L13: 1822 | M13: 2 | N13: 2 | O13: 1792 | P13: 1771 | Q13: 1813 | U13: 1813 | V13: 1813 | W13: 1813 | X13: 1813 | Y13: 0.1893724 | Z13: 0.29161719 | AA13: inferred | AB13: Isla
A14: — T12 Annualized (most recent 12 mo.) — | D14: B3 | E14: 2 | F14: 2 | G14: 15 | H14: 13 | I14: 2 | J14: 1173 | K14: 1824 | L14: 1702 | M14: 5 | N14: 8 | O14: 1653 | P14: 1617 | Q14: 1543 | R14: 1659 | S14: 1654 | T14: 1791 | U14: 1780 | V14: 1780 | W14: 1638 | X14: 1593 | Y14: 0.031884058 | Z14: 0.11809045 | AA14: inferred | AB14: Harbor
A15: Effective Gross Revenue (T12) | B15: 13325549 | D15: B4 | E15: 2 | F15: 2 | G15: 86 | H15: 77 | I15: 9 | J15: 1187 | K15: 1690 | L15: 1589 | M15: 32 | N15: 45 | O15: 1699 | P15: 1716 | Q15: 1868 | R15: 1589 | S15: 1618 | T15: 1706 | U15: 1630 | V15: 1630 | W15: 1514 | X15: 1475 | Y15: 0.013573723 | Z15: 0.10132853 | AA15: inferred | AB15: Maya
A16: Operating Expenses (T12) | B16: 4420512.9 | D16: B4.2 | E16: 2 | F16: 2 | G16: 15 | H16: 12 | I16: 3 | J16: 1184 | K16: 1833 | L16: 1731 | M16: 5 | N16: 7 | O16: 1729 | P16: 1588 | Q16: 1608 | R16: 1745 | S16: 1850 | T16: 1855 | U16: 1766 | V16: 1766 | W16: 1709 | X16: 1672 | Y16: 0.012034384 | Z16: 0.10375 | AA16: inferred | AB16: Reef
A17: Net Operating Income (T12) | B17: 8905036.4 | D17: B4R | E17: 2 | F17: 2 | G17: 16 | H17: 15 | I17: 1 | J17: 1187 | K17: 1821 | L17: 1635 | M17: 9 | N17: 6 | O17: 1545 | P17: 1523 | Q17: 1530 | R17: 1552 | S17: 1543 | T17: 1578 | U17: 1618 | V17: 1618 | W17: 1535 | X17: 1535 | Y17: -0.063638993 | Z17: 0.017924528 | AA17: inferred | AB17: Maya
A18: Operating Margin (T12) | B18: 0.66826787 | D18: C1 | E18: 3 | F18: 2 | G18: 41 | H18: 37 | I18: 4 | J18: 1258 | K18: 1896 | L18: 1794 | M18: 14 | N18: 23 | O18: 1765 | P18: 1699 | Q18: 1770 | R18: 1944 | S18: 1707 | T18: 1706 | U18: 1828 | V18: 1828 | W18: 1750 | X18: 1750 | Y18: -0.0039224232 | Z18: 0.073004695 | AA18: inferred | AB18: Talise
D19: C1R | E19: 3 | F19: 2 | G19: 18 | H19: 16 | I19: 2 | J19: 1258 | K19: 2023 | L19: 2013 | M19: 9 | N19: 7 | O19: 1943 | P19: 1978 | Q19: 1792 | R19: 1862 | S19: 2140 | T19: 1943 | U19: 2129 | V19: 2129 | W19: 1958 | X19: 1941 | Y19: 0.14972323 | Z19: 0.23689179 | AA19: inferred | AB19: Talise
D20: C2 | E20: 3 | F20: 2 | G20: 20 | H20: 18 | I20: 2 | J20: 1364 | K20: 2130 | L20: 1995 | M20: 8 | N20: 10 | O20: 1983 | P20: 1999 | Q20: 1777 | R20: 2041 | S20: 2049 | T20: 2049 | U20: 2057 | V20: 2057 | W20: 2012 | X20: 1961 | Y20: 0.078940467 | Z20: 0.16543909 | AA20: inferred | AB20: Marin
D21: TOTAL / AVG | G21: 715 | H21: 643 | I21: 72 | J21: 947 | K21: 1457 | L21: 1445 | M21: 318 | N21: 325 | O21: 1375 | U21: 1391 | V21: 1391 | W21: 1370 | X21: 1343 | Y21: -0.040394429 | Z21: 0.041621377
D22: New-lease = lease start ≤ move-in (renewals excluded). HD T90/T365 = executed (off-market) asking/effective; HD90 YoY compares the trailing 90 days to the same window a year ago.
A24: ⚑ UNDERWRITING FLAGS
A25: • Jan 2023–Dec 2023 sourced from a summary-level statement; sub-line detail (concessions, loss-to-lease, RUBS, etc.) is not itemized for those months and reads as 0 in those codes.
A26: • 'trash/doortodoor' ($90/mo, RUBS-style recovery) -- confirm whether it nets against the trash expense or books as Other Income (RT).
A27: • Seasonality: executed asking rents peak in Jul and trough in Dec (~10% spread across the HelloData history).
A28: • HelloData asking-rent YoY (same calendar month): -5.8% average across 25 month-pair(s).
A29: • Loss-to-Lease moved from $-72,859 (Jan 2023) to $89,986 (Dec 2025) -- a $162,846 swing; rents are catching up to market.
A30: • Annualized EGR: T3 $12,656,543 vs T12 $13,325,549 (-5.0%) -- recent run-rate is below the trailing year.
A31: • Annualized NOI: T3 $8,469,822 vs T12 $8,905,036 (-4.9%).
A32: • Year-over-year EGR (same calendar month): Jan 2024 -0%, Feb 2024 +2%, Mar 2024 +1%, Apr 2024 +0%, May 2024 +1%, Jun 2024 +2%, Jul 2024 +3%, Aug 2024 +1%, Sep 2024 +3%, Oct 2024 +4%, Nov 2024 +2%, Dec 2024 +5%, Jan 2025 -3%, Feb 2025 -2%, Mar 2025 +1%, Apr 2025 +2%, May 2025 +2%, Jun 2025 +0%, Jul 2025 +1%, Aug 2025 -0%, Sep 2025 -5%, Oct 2025 -7%, Nov 2025 -8%, Dec 2025 -10% (avg -0.2%). On a lease-up this reflects occupancy ramp more than rent growth — see the Lease Trend tab for per-unit market-rent movement.
A34: HOW TO USE → paste into the TMG acquisition model
A35: 1. Review 'T12 Categorized' col A (amber). Every GL line appears once with all months flowing across; edit a code via the dropdown to re-map. Category (col B) and OS Summary roll up automatically. Overlapping months are sourced from the freshest statement so nothing double-counts.
A36: 2. 'OS Summary' is the standardized chart of accounts (live SUMIFS, most recent 12 months). Copy A1:Q77 → model 'OS Summary Dump' A1 (Paste Special → Values).
... A40: 6. The unit mix (with new-lease + HD T90/T365/YoY market-rent indicators) is on this Dashboard; check 'Lease Trend' (seasonality / market-rent trajectory) and 'Reconciliation' (contract-rent ↔ AGPR tie-out) before underwriting. Paste targets only — do NOT populate the model itself from here.

Sheet T12 Categorized
A1: Code | B1: Category | C1: Line Item (raw GL) | D1: 44927 | E1: 44958 | F1: 44986 | G1: 45017 | H1: 45047 | I1: 45078 | J1: 45108 | K1: 45139 | L1: 45170 | M1: 45200 | N1: 45231 | O1: 45261 | P1: 45292 | Q1: 45323 | R1: 45352 | S1: 45383 | T1: 45413 | U1: 45444 | V1: 45474 | W1: 45505 | X1: 45536 | Y1: 45566 | Z1: 45597 | AA1: 45627 | AB1: 45658 | AC1: 45689 | AD1: 45717 | AE1: 45748 | AF1: 45778 | AG1: 45809 | AH1: 45839 | AI1: 45870 | AJ1: 45901 | AK1: 45931 | AL1: 45962 | AM1: 45992 | AN1: T12 Total
C2: Stitched from: Bella T12 2023 (Jan 2023–Dec 2023) · Bella T12 2024 (Jan 2024–Dec 2024) · Bella T12 2025 (Jan 2025–Dec 2025). Each month is sourced from the freshest statement covering it; blank cells = that line not itemized in the statement owning that month.
C3: INCOME
A4: Rentinc | B4: =IFERROR(VLOOKUP($A4,Codes!$A:$B,2,FALSE()),"") | C4: Market Rent | D4: 1202135 | E4: 1202135 | F4: 1203860 | G4: 1203860 | H4: 1203860 | I4: 1203860 | J4: 1203860 | K4: 1203860 | L4: 1203860 | M4: 1203860 | N4: 1203860 | O4: 1203860 | P4: 1203860 | Q4: 1203860 | R4: 1203860 | S4: 1203860 | T4: 1203860 | U4: 1203860 | V4: 1203860 | W4: 1203860 | X4: 1203860 | Y4: 1203860 | Z4: 1203860 | AA4: 1203860 | AB4: 1203860 | AC4: 1203536.6 | AD4: 1203860 | AE4: 1203860 | AF4: 1203860 | AG4: 1210063 | AH4: 1210063 | AI4: 1219673 | AJ4: 1219673 | AK4: 1068808 | AL4: 993633 | AM4: 949933 | AN4: =SUM(AB4:AM4)
A5: ltl | B5: =IFERROR(VLOOKUP($A5,Codes!$A:$B,2,FALSE()),"") | C5: Gain / Loss To Lease | D5: -72859.49 | E5: -6765.71 | F5: -28066.12 | G5: -45208.78 | H5: -165653.61 | I5: -86227.22 | J5: -81434.07 | K5: -81536.9 | L5: -82079.39 | M5: -83739.02 | N5: -86749.96 | O5: -91437.55 | P5: -96136.61 | Q5: -92712.74 | R5: -97016.32 | S5: -102520.66 | T5: -98174.24 | U5: -96977.6 | V5: -97226.32 | W5: -100400.38 | X5: -102203.79 | Y5: -101963.66 | Z5: -103217.57 | AA5: -93282.6 | AB5: -111910.07 | AC5: -119197.7 | AD5: -119723.97 | AE5: -122944.21 | AF5: -121684.6 | AG5: -129818.96 | AH5: -132527.69 | AI5: -144836.41 | AJ5: -146457.7 | AK5: -5111.86 | AL5: 60499.02 | AM5: 89986.12 | AN5: =SUM(AB5:AM5)
A6: conc | B6: =IFERROR(VLOOKUP($A6,Codes!$A:$B,2,FALSE()),"") | C6: Res. Rent Concessions | D6: -1319.01 | E6: -230.3 | F6: -227.26 | G6: 672.41 | H6: -497.9 | I6: -575.57 | J6: -2759.4 | K6: -12085.85 | L6: -1593.22 | M6: -6592.23 | N6: -12726.4 | O6: -18420.97 | P6: -8071.87 | Q6: -12416.89 | R6: -5909.94 | S6: 26398.7 | T6: 0 | U6: 0 | V6: 0 | W6: 0 | X6: 0 | Y6: 0 | Z6: 0 | AA6: 0 | AN6: =SUM(AB6:AM6)
A7: conc | B7: =IFERROR(VLOOKUP($A7,Codes!$A:$B,2,FALSE()),"") | C7: One-Time Concessions | D7: 0 | E7: 0 | F7: 713.72 | G7: 0 | H7: 0 | I7: 0 | J7: 0 | K7: 0 | L7: 0 | M7: 0 | N7: 0 | O7: 0 | P7: 250 | Q7: 0 | R7: 0 | S7: -26004.53 | T7: -1968.24 | U7: -7674.86 | V7: -15018.95 | W7: -1968.92 | X7: -3434.02 | Y7: 3279.09 | Z7: -3967.32 | AA7: -1492.6 | AB7: 1023.94 | AC7: 2266 | AD7: 1680 | AE7: -325 | AF7: -589 | AG7: 883 | AH7: -1241 | AI7: -30 | AJ7: -2389.33 | AK7: -8809.13 | AL7: -8744.08 | AM7: -5805.06 | AN7: =SUM(AB7:AM7)
A8: vac | B8: =IFERROR(VLOOKUP($A8,Codes!$A:$B,2,FALSE()),"") | C8: Vacancy Loss | D8: -80881.93 | E8: -134644.72 | F8: -180138.43 | G8: -212318.84 | H8: -124265.31 | I8: -95331.65 | J8: -121495.95 | K8: -120108.53 | L8: -96474.17 | M8: -108619.53 | N8: -111081.02 | O8: -79539.11 | P8: -80089.2 | Q8: -78903.74 | R8: -72275.01 | S8: -70834.23 | T8: -84106.2 | U8: -79407.72 | V8: -65222.16 | W8: -66261.6 | X8: -65786.32 | Y8: -83792.81 | Z8: -78065.14 | AA8: -68751.46 | AB8: -81128.24 | AC8: -74193.14 | AD8: -73650.77 | AE8: -68216.19 | AF8: -75005.87 | AG8: -71531.57 | AH8: -65223.88 | AI8: -76573.08 | AJ8: -89133.35 | AK8: -81831.06 | AL8: -103704.55 | AM8: -88770.86 | AN8: =SUM(AB8:AM8)
A9: nr | B9: =IFERROR(VLOOKUP($A9,Codes!$A:$B,2,FALSE()),"") | C9: Employee Units | D9: -2103.6 | E9: -2791.55 | F9: -4816.34 | G9: -4903.07 | H9: -4920.22 | I9: -4557.59 | J9: -4529 | K9: -5197.95 | L9: -5338.8 | M9: -5009.54 | N9: -5078.8 | O9: -5078.8 | P9: -6942.86 | Q9: -6132.01 | R9: -6558.4 | S9: -6558.4 | T9: -6558.4 | U9: -6558.4 | V9: -6558.4 | W9: -5164.02 | X9: -5269.55 | Y9: -6738.61 | Z9: -5783.07 | AA9: -6561.8 | AB9: 333.8 | AC9: -3853.41 | AD9: -4400.4 | AE9: -2944.8 | AF9: -2944.8 | AG9: -16635.21 | AH9: -7081.2 | AI9: -7927.2 | AJ9: -7648.18 | AK9: -7572.2 | AL9: -7788.24 | AM9: -7255.35 | AN9: =SUM(AB9:AM9)
A10: nr | B10: =IFERROR(VLOOKUP($A10,Codes!$A:$B,2,FALSE()),"") | C10: Model & Storage Units | D10: -1475 | E10: -1475 | F10: -1475 | G10: -1475 | H10: -1475 | I10: -1475 | J10: -1475 | K10: -1475 | L10: -1475 | M10: -1475 | N10: -1475 | O10: -1475 | P10: -1475 | Q10: -1475 | R10: -1475 | S10: -1475 | T10: -1475 | U10: -1475 | V10: -1475 | W10: -1475 | X10: 0 | Y10: 0 | Z10: 0 | AA10: 0 | AN10: =SUM(AB10:AM10)
A11: Rentinc | B11: =IFERROR(VLOOKUP($A11,Codes!$A:$B,2,FALSE()),"") | C11: Guest Suite | D11: 0 | E11: 0 | F11: -1955 | G11: -1955 | H11: -1955 | I11: -1955 | J11: -1875 | K11: -1875 | L11: -1875 | M11: -1875 | N11: -1875 | O11: -1875 | P11: -1875 | Q11: -1875 | R11: -1875 | S11: -1875 | T11: -1875 | U11: -1875 | V11: -1875 | W11: -1875 | X11: -1875 | Y11: -1875 | Z11: -1875 | AA11: -1875 | AB11: -1875 | AC11: -1875 | AD11: -1875 | AE11: -1875 | AF11: -1875 | AG11: -1890 | AH11: -1890 | AI11: -1900 | AJ11: -1900 | AK11: -1957 | AL11: 0 | AM11: 0 | AN11: =SUM(AB11:AM11)
A12: cl | B12: =IFERROR(VLOOKUP($A12,Codes!$A:$B,2,FALSE()),"") | C12: Bad Debt - Rent | D12: -24054.96 | E12: -38106.75 | F12: 33120.5 | G12: 75977.5 | H12: 87475.26 | I12: -4649.34 | J12: -6723.15 | K12: 9881.98 | L12: -9233.24 | M12: -4365.53 | N12: 11429.75 | O12: -14437.34 | P12: -8447.76 | Q12: -9974.99 | R12: -13746.79 | S12: -11077.77 | T12: 159.07 | U12: -6102.47 | V12: -6908.49 | W12: -8388.75 | X12: -10543.92 | Y12: -15175.14 | Z12: -1356.96 | AA12: -12193.47 | AB12: -13671 | AC12: -15889.14 | AD12: -2668.89 | AE12: -2694.81 | AF12: -3900.28 | AG12: -10686.8 | AH12: -5557.97 | AI12: -13284.54 | AJ12: -8921.83 | AK12: -15370.77 | AL12: -18576.97 | AM12: -10406.52 | AN12: =SUM(AB12:AM12)
A13: cl | B13: =IFERROR(VLOOKUP($A13,Codes!$A:$B,2,FALSE()),"") | C13: Bad Debt Recovery - Rent | D13: 120 | E13: 137.51 | F13: -19044.76 | G13: -54.01 | H13: 2143.14 | I13: -1380.87 | J13: -486.37 | K13: 263.59 | L13: 274.27 | M13: 130.93 | N13: 1410.62 | O13: 4264.53 | P13: -3853.07 | Q13: 154.15 | R13: 85.84 | S13: 152.23 | T13: 80.76 | U13: 6381 | V13: -5871.88 | W13: 184.94 | X13: 746.14 | Y13: 157.56 | Z13: 205.13 | AA13: 310.38 | AB13: 0 | AC13: 0 | AD13: 0 | AE13: -1000 | AF13: -140.36 | AG13: 0.01 | AH13: 0 | AI13: 0 | AJ13: 1603.65 | AK13: 0 | AL13: 890.22 | AM13: 0 | AN13: =SUM(AB13:AM13)
A14: OI | B14: =IFERROR(VLOOKUP($A14,Codes!$A:$B,2,FALSE()),"") | C14: Administrative Fees | D14: 7608.2 | E14: 3325 | F14: 6505 | G14: 5945.39 | H14: 6600 | I14: 2489.99 | J14: 3475 | K14: 4625 | L14: 2250 | M14: 3721.36 | N14: 8425 | O14: 6050 | P14: 8499.89 | Q14: 12200 | R14: 4500 | S14: 1850 | T14: 1000 | U14: 3875 | V14: 1425 | W14: 2700 | X14: 150 | Y14: 2800 | Z14: 550 | AA14: 3814.2 | AB14: 3200 | AC14: 2775 | AD14: 5750 | AE14: 5850 | AF14: 6975 | AG14: 6625 | AH14: 4525 | AI14: 7351 | AJ14: 3900 | AK14: 3250 | AL14: 1775 | AM14: 4825 | AN14: =SUM(AB14:AM14)
A15: OI | B15: =IFERROR(VLOOKUP($A15,Codes!$A:$B,2,FALSE()),"") | C15: Application Fees | D15: 3705.12 | E15: 2622.66 | F15: 4200 | G15: 2310 | H15: 3410 | I15: 1530 | J15: 2970 | K15: 3537.34 | L15: 1595 | M15: 2255 | N15: 3025 | O15: 2860 | P15: 3465 | Q15: 4125 | R15: 2200 | S15: 2145 | T15: 1320 | U15: 4565 | V15: 2640 | W15: 2305 | X15: 2805 | Y15: 2701.38 | Z15: 4070 | AA15: 4180 | AB15: 3628.62 | AC15: 1375 | AD15: 4015 | AE15: 3685 | AF15: 3520 | AG15: 2748.62 | AH15: 3465 | AI15: 2750 | AJ15: 1925 | AK15: 1760 | AL15: 2795 | AM15: 4080 | AN15: =SUM(AB15:AM15)
A16: cable | B16: =IFERROR(VLOOKUP($A16,Codes!$A:$B,2,FALSE()),"") | C16: Cable TV Commissions | D16: 0 | E16: 16902.07 | F16: 0 | G16: 0 | H16: 17242.21 | I16: 0 | J16: 0 | K16: 16924.83 | L16: 0 | M16: 0 | N16: 16112.48 | O16: 0 | P16: 0 | Q16: 16338.6 | R16: 0 | S16: 0 | T16: 0 | U16: 0 | V16: 0 | W16: 0 | X16: 0 | Y16: 32776.73 | Z16: 16811.3 | AA16: 0 | AB16: 0 | AC16: 32437.08 | AD16: 0 | AE16: 0 | AF16: -8183.37 | AG16: 7784.9 | AH16: 0 | AI16: 15244.46 | AJ16: 0 | AK16: 0 | AL16: 13971.32 | AM16: 0 | AN16: =SUM(AB16:AM16)
A17: OI | B17: =IFERROR(VLOOKUP($A17,Codes!$A:$B,2,FALSE()),"") | C17: Club Room Rental Fees | D17: 0 | E17: 0 | F17: 0 | G17: 0 | H17: 0 | I17: 0 | J17: 0 | K17: 0 | L17: 0 | M17: 0 | N17: 300 | O17: 0 | P17: -100 | Q17: 0 | R17: 0 | S17: 0 | T17: 100 | U17: 400 | V17: -100 | W17: 0 | X17: 0 | Y17: 0 | Z17: 0 | AA17: 0 | AB17: 0 | AC17: 0 | AD17: 150 | AE17: 400 | AF17: 200 | AG17: 350 | AH17: 50 | AI17: 175 | AJ17: 500 | AK17: 200 | AL17: 250 | AM17: 0 | AN17: =SUM(AB17:AM17)
A18: OI | B18: =IFERROR(VLOOKUP($A18,Codes!$A:$B,2,FALSE()),"") | C18: Damages | D18: 2656.13 | E18: 6402.3 | F18: 15395.63 | G18: 5202.16 | H18: 3438.92 | I18: 4228.08 | J18: 3335.25 | K18: 6299.72 | L18: 2150.23 | M18: 4979.48 | N18: 4278.51 | O18: 1715.35 | P18: 8915.82 | Q18: 3895.72 | R18: 6687.06 | S18: 3911.98 | T18: 6903.33 | U18: 1316.19 | V18: 3704.53 | W18: 2540.16 | X18: 3468.08 | Y18: 2790.87 | Z18: 4376.22 | AA18: 4017.94 | AB18: 4488.89 | AC18: 2377.48 | AD18: 7307.5 | AE18: 8587.54 | AF18: 5723.99 | AG18: 5525.06 | AH18: 5526.19 | AI18: 5169.02 | AJ18: 4593.44 | AK18: 5256.41 | AL18: 2539.26 | AM18: 4669.66 | AN18: =SUM(AB18:AM18)
A19: park | B19: =IFERROR(VLOOKUP($A19,Codes!$A:$B,2,FALSE()),"") | C19: Garage Income | D19: 6650.25 | E19: 7247.74 | F19: 6602.92 | G19: 7030.08 | H19: 6912.52 | I19: 7071.33 | J19: 6646.91 | K19: 6375.57 | L19: 6529.01 | M19: 6484.16 | N19: 6739.17 | O19: 6883.23 | P19: 7217.27 | Q19: 7419.66 | R19: 7505.32 | S19: 7212.86 | T19: 7270.48 | U19: 7734.98 | V19: 7577.25 | W19: 7743.55 | X19: 7549.81 | Y19: 7506.13 | Z19: 7454.4 | AA19: 7611.95 | AB19: 7643.72 | AC19: 7472.01 | AD19: 7246.15 | AE19: 7055.12 | AF19: 7234.2 | AG19: 7166.13 | AH19: 7056.78 | AI19: 6979 | AJ19: 7445.2 | AK19: 6786.31 | AL19: 6411.47 | AM19: 6128.82 | AN19: =SUM(AB19:AM19)
A20: OI | B20: =IFERROR(VLOOKUP($A20,Codes!$A:$B,2,FALSE()),"") | C20: Insufficient Notice Fees | D20: 0 | E20: 0 | F20: 1536.25 | G20: 0 | H20: 0 | I20: 0 | J20: 799.15 | K20: 5112.88 | L20: 1864.23 | M20: 5314.51 | N20: 646.1 | O20: 277.56 | P20: 7745.47 | Q20: 8493.98 | R20: 2463.35 | S20: 4303.93 | T20: 1266.89 | U20: 858.04 | V20: 4595.27 | W20: 3527.97 | X20: 4872.42 | Y20: 2844.99 | Z20: 3215.15 | AA20: 3064.67 | AB20: 6510.85 | AC20: 6278.01 | AD20: 4157.39 | AE20: 6430.7 | AF20: 9404.49 | AG20: 8752.65 | AH20: 2522.45 | AI20: 3071.61 | AJ20: 4745.03 | AK20: 4249.6 | AL20: 6754.05 | AM20: 2285.83 | AN20: =SUM(AB20:AM20)
A21: OI | B21: =IFERROR(VLOOKUP($A21,Codes!$A:$B,2,FALSE()),"") | C21: Interest Income | P21: 0 | Q21: 0 | R21: 72.39 | S21: 50.58 | T21: 27.61 | U21: 0 | V21: 1514.39 | W21: 1370.51 | X21: 3044.09 | Y21: 3035.7 | Z21: 754.63 | AA21: 1365.89 | AB21: 1473.43 | AC21: 1562.08 | AD21: 1814.32 | AE21: 2047.99 | AF21: 800.22 | AG21: 888.04 | AH21: 1544.03 | AI21: 882.89 | AJ21: 1156.09 | AK21: 1420.31 | AL21: 506.43 | AM21: 603.88 | AN21: =SUM(AB21:AM21)
A22: OI | B22: =IFERROR(VLOOKUP($A22,Codes!$A:$B,2,FALSE()),"") | C22: Late Charge Fees | D22: 18149.66 | E22: 13280.24 | F22: 7850.16 | G22: 11855 | H22: 12873.76 | I22: 14147.52 | J22: 15209.02 | K22: 14717.58 | L22: 19229.76 | M22: 16035 | N22: 15040 | O22: 15986 | P22: 16350 | Q22: 16810 | R22: 12795 | S22: 13825.41 | T22: 13564.64 | U22: 17721.64 | V22: 12895 | W22: 15750 | X22: 17393.15 | Y22: 10201.22 | Z22: 17541.93 | AA22: 17489.81 | AB22: 12210 | AC22: 13380.84 | AD22: 15245 | AE22: 11615.72 | AF22: 14420.88 | AG22: 15769.99 | AH22: 12322.55 | AI22: 14727.77 | AJ22: 16195 | AK22: 15120 | AL22: 15185.95 | AM22: 11582.38 | AN22: =SUM(AB22:AM22)
A23: OI | B23: =IFERROR(VLOOKUP($A23,Codes!$A:$B,2,FALSE()),"") | C23: Lease Cancellation Fee | D23: 12702.36 | E23: 5992 | F23: 6084.33 | G23: 0 | H23: 4167.99 | I23: 3404.65 | J23: 10524.15 | K23: 5740.25 | L23: 2822.54 | M23: 1245.87 | N23: 7525.65 | O23: 2806 | P23: 18049.56 | Q23: 14855.24 | R23: 7297.98 | S23: 3532.07 | T23: 10265.51 | U23: 9089.95 | V23: 21343.51 | W23: 2110.29 | X23: 17060.67 | Y23: 8898.7 | Z23: 5856.33 | AA23: 7151.58 | AB23: 5306.5 | AC23: 7090.94 | AD23: 6408.01 | AE23: 11138.04 | AF23: 23243.23 | AG23: 4860.59 | AH23: 14324.01 | AI23: 8839.3 | AJ23: 11698.5 | AK23: 652.1 | AL23: 1669.69 | AM23: 4915.2 | AN23: =SUM(AB23:AM23)
A24: OI | B24: =IFERROR(VLOOKUP($A24,Codes!$A:$B,2,FALSE()),"") | C24: Legal Fees | D24: 3310.74 | E24: 3236.26 | F24: 3908 | G24: 3252 | H24: 4025.12 | I24: 4843 | J24: 5839.11 | K24: 6939.87 | L24: 7021.9 | M24: 5785.5 | N24: 5943 | O24: 4749.46 | P24: 8035.96 | Q24: 7677.84 | R24: 3866 | S24: 5102.04 | T24: 6667.72 | U24: 5493 | V24: 5721.82 | W24: 8195.45 | X24: 8376.88 | Y24: 4166 | Z24: 11187.73 | AA24: 9120.2 | AB24: 4847.21 | AC24: 10247 | AD24: 8343.31 | AE24: 6890.42 | AF24: 10641.88 | AG24: 8273.8 | AH24: 6320.71 | AI24: 9453.87 | AJ24: 6435.01 | AK24: 9299 | AL24: 10309.19 | AM24: 6425.66 | AN24: =SUM(AB24:AM24)
A25: OI | B25: =IFERROR(VLOOKUP($A25,Codes!$A:$B,2,FALSE()),"") | C25: Locks / Key Income | D25: 100 | E25: 150 | F25: 50 | G25: 0 | H25: 50 | I25: 170 | J25: 50 | K25: 55 | L25: 180 | M25: 550 | N25: 75 | O25: 150 | P25: 585 | Q25: 290 | R25: 465 | S25: 305 | T25: 570 | U25: 210 | V25: 110 | W25: 10 | X25: 110 | Y25: 150 | Z25: 160 | AA25: 50 | AB25: 150 | AC25: 180 | AD25: 5 | AE25: 245 | AF25: 210 | AG25: 270 | AH25: 540 | AI25: 180 | AJ25: 297.73 | AK25: 320 | AL25: 60 | AM25: 250 | AN25: =SUM(AB25:AM25)
A26: Rentinc | B26: =IFERROR(VLOOKUP($A26,Codes!$A:$B,2,FALSE()),"") | C26: Month-to-Month Premiums | D26: 2.76 | E26: 4.1 | F26: 290.77 | G26: 4.86 | H26: 3.44 | I26: 8.77 | J26: 8.13 | K26: 12.18 | L26: 11.49 | M26: 220.75 | N26: 13.56 | O26: 13.28 | P26: 18.87 | Q26: 16.56 | R26: 12.29 | S26: 8.05 | T26: 10.1 | U26: 11.4 | V26: 11.55 | W26: 6.1 | X26: 5.77 | Y26: 816.39 | Z26: 5.59 | AA26: 76.67 | AB26: 0.38 | AC26: 6.25 | AD26: 10.68 | AE26: 10.02 | AF26: 17.35 | AG26: 18.44 | AH26: 21.22 | AI26: 20.64 | AJ26: 9.64 | AK26: 11.18 | AL26: 11.8 | AM26: 4.31 | AN26: =SUM(AB26:AM26)
A27: OI | B27: =IFERROR(VLOOKUP($A27,Codes!$A:$B,2,FALSE()),"") | C27: NSF Fees | D27: 650 | E27: 300 | F27: 400 | G27: 550 | H27: 700 | I27: 250 | J27: 850 | K27: 500 | L27: 600 | M27: 850 | N27: -50 | O27: 450 | P27: 400 | Q27: 550 | R27: 400 | S27: 850 | T27: 500 | U27: 950 | V27: 450 | W27: 950 | X27: 675 | Y27: 500 | Z27: 900 | AA27: 750 | AB27: 600 | AC27: 650 | AD27: 650 | AE27: 300 | AF27: 500 | AG27: 1100 | AH27: 300 | AI27: 700 | AJ27: 1050 | AK27: 750 | AL27: 550 | AM27: 500 | AN27: =SUM(AB27:AM27)
A28: OI | B28: =IFERROR(VLOOKUP($A28,Codes!$A:$B,2,FALSE()),"") | C28: Package Concierge/Locker Income | D28: 600.2 | E28: 625.07 | F28: 639.2 | G28: 656.4 | H28: 650.39 | I28: 656 | J28: 644.85 | K28: 653.04 | L28: 656.78 | M28: 652.54 | N28: 657.17 | O28: 664.04 | P28: 667.82 | Q28: 665.83 | R28: 664.38 | S28: 665.52 | T28: 665.7 | U28: 662.69 | V28: 670.19 | W28: 671.39 | X28: 672.62 | Y28: 665.12 | Z28: 667.26 | AA28: 666.1 | AB28: 656.78 | AC28: 660.54 | AD28: 668.25 | AE28: 667.31 | AF28: 667.36 | AG28: 667.52 | AH28: 668.24 | AI28: 660.05 | AJ28: 655.35 | AK28: 651.04 | AL28: 934.79 | AM28: 715.62 | AN28: =SUM(AB28:AM28)
A29: park | B29: =IFERROR(VLOOKUP($A29,Codes!$A:$B,2,FALSE()),"") | C29: Parking / Carport Income | D29: 1731.28 | E29: 1796.25 | F29: 1751.84 | G29: 7067.58 | H29: 1899.03 | I29: 1879.5 | J29: -1319.79 | K29: 1807.42 | L29: 1810 | M29: 1904.68 | N29: 5379.71 | O29: 1871.29 | P29: 3903.78 | Q29: 1859.83 | R29: 1639.35 | S29: 1742.17 | T29: 3247.66 | U29: 1796.67 | V29: 1946.56 | W29: -189.28 | X29: 3628.97 | Y29: 1578.49 | Z29: 3818 | AA29: 1598.54 | AB29: 3035.66 | AC29: 1311.96 | AD29: 1408.44 | AE29: 3198.33 | AF29: 1278.07 | AG29: 1312.83 | AH29: 1212.26 | AI29: 2736.59 | AJ29: 1195.49 | AK29: 896.77 | AL29: 10825.85 | AM29: 594.19 | AN29: =SUM(AB29:AM29)
A30: OI | B30: =IFERROR(VLOOKUP($A30,Codes!$A:$B,2,FALSE()),"") | C30: Pet Fees - Non-Refundable | D30: 1800 | E30: 1900 | F30: 2200 | G30: -100 | H30: 1200 | I30: 917 | J30: 1200 | K30: 1230.97 | L30: 1200 | M30: 300 | N30: 0 | O30: 900 | P30: 1200 | Q30: 1800 | R30: 2100 | S30: 600 | T30: 300 | U30: 1211 | V30: 1500 | W30: 900 | X30: 600 | Y30: 2219.35 | Z30: 600 | AA30: 550 | AB30: 880 | AC30: 38.39 | AD30: 1800 | AE30: 1230 | AF30: 930 | AG30: 3944.67 | AH30: -70 | AI30: 1530 | AJ30: 630 | AK30: 1831 | AL30: 375 | AM30: 1594.52 | AN30: =SUM(AB30:AM30)
A31: OI | B31: =IFERROR(VLOOKUP($A31,Codes!$A:$B,2,FALSE()),"") | C31: Pet Rent | D31: 3995.99 | E31: 3938.12 | F31: 3922.53 | G31: 3693.79 | H31: 3496.39 | I31: 3537.77 | J31: 3540.33 | K31: 3426.03 | L31: 3387.33 | M31: 3203.44 | N31: 2954.37 | O31: 2975.8 | P31: 2861.36 | Q31: 3002.26 | R31: 3104.85 | S31: 3110.57 | T31: 3024.14 | U31: 3025.35 | V31: 3149.11 | W31: 2780.64 | X31: 2972.82 | Y31: 2939.72 | Z31: 2966.85 | AA31: 3060.74 | AB31: 3036.48 | AC31: 2822.39 | AD31: 2665.2 | AE31: 2800.78 | AF31: 2717.48 | AG31: 2581 | AH31: 2796.8 | AI31: 2570.2 | AJ31: 2691.42 | AK31: 2704.67 | AL31: 2702.91 | AM31: 3073.11 | AN31: =SUM(AB31:AM31)
A32: OI | B32: =IFERROR(VLOOKUP($A32,Codes!$A:$B,2,FALSE()),"") | C32: Renter's Insurance Fees | D32: 83.76 | E32: -2071.23 | F32: -5027.84 | G32: 6244.57 | H32: 119.1 | I32: 394.24 | J32: -299.32 | K32: 244.2 | L32: -153.49 | M32: 3766.34 | N32: -992.22 | O32: -6476.8 | P32: -1648.29 | Q32: -1809.07 | R32: -2536.45 | S32: 5128.25 | T32: -3682.22 | U32: -128.61 | V32: 213.68 | W32: 743.22 | X32: 405.06 | Y32: 5173.2 | Z32: 354.66 | AA32: 463.5 | AB32: 582.48 | AC32: 497.88 | AD32: 766.02 | AE32: 915 | AF32: 629.39 | AG32: 518.46 | AH32: 509.1 | AI32: 432.66 | AJ32: 289.86 | AK32: 471.3 | AL32: 140.28 | AM32: 57.06 | AN32: =SUM(AB32:AM32)
A33: OI | B33: =IFERROR(VLOOKUP($A33,Codes!$A:$B,2,FALSE()),"") | C33: Transfer Fee | D33: 500 | E33: 2750 | F33: 750 | G33: 250 | H33: 1250 | I33: 1750 | J33: 750 | K33: 2250 | L33: 1250 | M33: 2000 | N33: 250 | O33: 2500 | P33: 1250 | Q33: 1250 | R33: 1500 | S33: 1000 | T33: 1000 | U33: -250 | V33: 500 | W33: 750 | X33: 1750 | Y33: 1750 | Z33: 2250 | AA33: 1500 | AB33: 1500 | AC33: 1500 | AD33: 1500 | AE33: 500 | AF33: 500 | AG33: 4750 | AH33: 2000 | AI33: 1000 | AJ33: 750 | AK33: 750 | AL33: 2250 | AM33: 1500 | AN33: =SUM(AB33:AM33)
... A41: OI | B41: =IFERROR(VLOOKUP($A41,Codes!$A:$B,2,FALSE()),"") | C41: Miscellaneous Income | D41: 24 | E41: 30 | F41: 88 | G41: 24 | H41: 27 | I41: 29 | J41: 6522.16 | K41: 56 | L41: 26 | M41: 0 | N41: 17 | O41: 23 | P41: 0 | Q41: 81 | R41: 40 | S41: 20 | T41: 19 | U41: 0 | V41: 36 | W41: 3841.56 | X41: -1959.62 | Y41: 17 | Z41: 16 | AA41: 15 | AB41: 15 | AC41: 14 | AD41: 16 | AE41: 19 | AF41: 16 | AG41: 11 | AH41: 12 | AI41: 16.7 | AJ41: 17 | AK41: 0 | AL41: 18 | AM41: 0 | AN41: =SUM(AB41:AM41)
A42: OI | B42: =IFERROR(VLOOKUP($A42,Codes!$A:$B,2,FALSE()),"") | C42: Smart Home Income | AB42: 0 | AC42: 0 | AD42: 0 | AE42: 0 | AF42: 0 | AG42: 0 | AH42: 0 | AI42: 0 | AJ42: 0 | AK42: 0 | AL42: 0 | AM42: 198.73 | AN42: =SUM(AB42:AM42)
A43: OI | B43: =IFERROR(VLOOKUP($A43,Codes!$A:$B,2,FALSE()),"") | C43: Guest Suite Income | AB43: 0 | AC43: 0 | AD43: 0 | AE43: 0 | AF43: 448 | AG43: 0 | AH43: 150 | AI43: 844 | AJ43: 0 | AK43: 0 | AL43: 245 | AM43: 0 | AN43: =SUM(AB43:AM43)
A44: RF | B44: =IFERROR(VLOOKUP($A44,Codes!$A:$B,2,FALSE()),"") | C44: Electric Rebill | AB44: 0 | AC44: 0 | AD44: 0 | AE44: 0 | AF44: 0 | AG44: 0 | AH44: 0 | AI44: 0 | AJ44: 0 | AK44: 0 | AL44: 0 | AM44: 571.29 | AN44: =SUM(AB44:AM44)
A45: Rentinc | B45: =IFERROR(VLOOKUP($A45,Codes!$A:$B,2,FALSE()),"") | C45: Prior Period Rent Adjustment | D45: 0 | E45: 0 | F45: -104.26 | G45: 0 | H45: 0 | I45: 0 | J45: 0 | K45: 0 | L45: 0 | M45: 0 | N45: 0 | O45: 0 | AN45: =SUM(AB45:AM45)
A46: nr | B46: =IFERROR(VLOOKUP($A46,Codes!$A:$B,2,FALSE()),"") | C46: Down Unit Loss | D46: 0 | E46: -1955 | F46: 0 | G46: -1125 | H46: -1875 | I46: -1875 | J46: 0 | K46: 0 | L46: 0 | M46: 0 | N46: 0 | O46: 0 | AN46: =SUM(AB46:AM46)
A47: conc | B47: =IFERROR(VLOOKUP($A47,Codes!$A:$B,2,FALSE()),"") | C47: Recurring Concessions | D47: 0 | E47: 0 | F47: -1 | G47: 0 | H47: 0 | I47: 0 | J47: 0 | K47: 0 | L47: 0 | M47: 0 | N47: 0 | O47: 0 | AN47: =SUM(AB47:AM47)
A48: cl | B48: =IFERROR(VLOOKUP($A48,Codes!$A:$B,2,FALSE()),"") | C48: Bad Debt - Payment Plan | D48: 0 | E48: 0 | F48: 0 | G48: 0 | H48: 0 | I48: 0 | J48: 0 | K48: 0 | L48: 0 | M48: 198.66 | N48: 0 | O48: 0 | AN48: =SUM(AB48:AM48)
C49: OPERATING EXPENSES
A50: Pay | B50: =IFERROR(VLOOKUP($A50,Codes!$A:$B,2,FALSE()),"") | C50: Management - Salaries | D50: 7634.31 | E50: 10741.53 | F50: 10750.61 | G50: 10615.32 | H50: 12553.19 | I50: 10151.67 | J50: 11085.69 | K50: 12276.09 | L50: 11196.28 | M50: 11630.98 | N50: 13427.62 | O50: 8273.07 | P50: 14050.22 | Q50: 7485.73 | R50: 11406.04 | S50: 15199.67 | T50: 14037.59 | U50: 12026.83 | V50: -21519.78 | W50: 15455.04 | X50: 13666.02 | Y50: 13212.37 | Z50: 10251.7 | AA50: 11089.03 | AB50: 12026.76 | AC50: 12650.55 | AD50: 10685.49 | AE50: 14248.43 | AF50: 10611.14 | AG50: -14289.22 | AH50: 8026.12 | AI50: 6537.94 | AJ50: 7883.89 | AK50: 14114.48 | AL50: 7661.8 | AM50: 6706.59 | AN50: =SUM(AB50:AM50)
A51: Pay | B51: =IFERROR(VLOOKUP($A51,Codes!$A:$B,2,FALSE()),"") | C51: Assistant Management - Salaries | D51: 9778.55 | E51: 4625.91 | F51: 5501.11 | G51: 5178.44 | H51: 4511.75 | I51: 5334.47 | J51: 4456.3 | K51: 6760.74 | L51: 4983.77 | M51: 5857.78 | N51: 3873.84 | O51: 6815.09 | P51: 7825.29 | Q51: 772.75 | R51: 4826.65 | S51: 2635.18 | T51: 6301.82 | U51: 5280.91 | V51: 39659.95 | W51: 4455.1 | X51: 5745.9 | Y51: 5894.27 | Z51: 5588.98 | AA51: 5214.83 | AB51: 5455.94 | AC51: 5205.21 | AD51: 5210.13 | AE51: 3821.82 | AF51: 5107.97 | AG51: 29930.18 | AH51: 9188.14 | AI51: 9188.99 | AJ51: 8988.18 | AK51: 10751.02 | AL51: 8693.41 | AM51: 7900.12 | AN51: =SUM(AB51:AM51)
A52: Pay | B52: =IFERROR(VLOOKUP($A52,Codes!$A:$B,2,FALSE()),"") | C52: Leasing - Salaries | D52: 8314.07 | E52: 11291.88 | F52: 12720.65 | G52: 11259.99 | H52: 13079.11 | I52: 12474.47 | J52: 12055.05 | K52: 13064.82 | L52: 12265.64 | M52: 12433.16 | N52: 14058.06 | O52: 15561.92 | P52: 15910.21 | Q52: 7065.1 | R52: 13187.6 | S52: 12559.01 | T52: 14477.98 | U52: 13387.09 | V52: 12859.94 | W52: 13351.2 | X52: 13396.4 | Y52: 15287.42 | Z52: 13264.05 | AA52: 13591.77 | AB52: 13629.74 | AC52: 12493.19 | AD52: 11340.92 | AE52: 10053.33 | AF52: 12419.09 | AG52: 16194.77 | AH52: 13267.57 | AI52: 13081.52 | AJ52: 12836.98 | AK52: 18703.75 | AL52: 12153.7 | AM52: 12573.42 | AN52: =SUM(AB52:AM52)
A53: PBo | B53: =IFERROR(VLOOKUP($A53,Codes!$A:$B,2,FALSE()),"") | C53: Bonuses | D53: 5384.19 | E53: 14367.02 | F53: 6236.25 | G53: 8148.46 | H53: 11080.26 | I53: -2651.18 | J53: 11561.48 | K53: 0 | L53: 7464.86 | M53: 5839.86 | N53: 6530.75 | O53: 7049.9 | P53: 6729.88 | Q53: 8936.49 | R53: 11036.59 | S53: 10105.8 | T53: 9197.88 | U53: 11797.94 | V53: 11494.46 | W53: 12316.08 | X53: 12771.24 | Y53: 14182.52 | Z53: 10956.45 | AA53: 9647.53 | AB53: 8492.27 | AC53: 10348.76 | AD53: 9225.73 | AE53: 10774.1 | AF53: 9109.41 | AG53: 11462.26 | AH53: 10948.64 | AI53: 10435.48 | AJ53: 10940.26 | AK53: 9661.33 | AL53: 10952.86 | AM53: 7370.04 | AN53: =SUM(AB53:AM53)
A54: PBo | B54: =IFERROR(VLOOKUP($A54,Codes!$A:$B,2,FALSE()),"") | C54: Quarterly Bonuses | D54: 0 | E54: 0 | F54: 0 | G54: 0 | H54: 0 | I54: 9966 | J54: 0 | K54: 8181.26 | L54: 0 | M54: 0 | N54: 5750.25 | O54: 0 | P54: 2296.01 | Q54: 0 | R54: 0 | S54: 0 | T54: 6702.98 | U54: 0 | V54: 5031.95 | W54: 0 | X54: 0 | Y54: 4074.57 | Z54: -4074.57 | AA54: 0 | AB54: 0 | AC54: 3340.59 | AD54: 0 | AE54: 4277.88 | AF54: 0 | AG54: 0 | AH54: 0 | AI54: 3982.84 | AJ54: 0 | AK54: 4007.35 | AL54: 0 | AM54: 0 | AN54: =SUM(AB54:AM54)
A55: Pay | B55: =IFERROR(VLOOKUP($A55,Codes!$A:$B,2,FALSE()),"") | C55: Maintenance - Salaries | D55: 23379.59 | E55: 23723.12 | F55: 26927.91 | G55: 28068.53 | H55: 34758.95 | I55: 29918.38 | J55: 27867.22 | K55: 29236 | L55: 32019.38 | M55: 31157.74 | N55: 23515.78 | O55: 33851.75 | P55: 37221.06 | Q55: 16213.05 | R55: 29022.11 | S55: 27900.54 | T55: 33842.41 | U55: 30510.98 | V55: 32061.31 | W55: 31492.54 | X55: 27973.16 | Y55: 32856.77 | Z55: 27762.88 | AA55: 27514.82 | AB55: 27529.7 | AC55: 28512.5 | AD55: 28500.89 | AE55: 30185.24 | AF55: 28131.46 | AG55: 30739.78 | AH55: 30610.35 | AI55: 31078.41 | AJ55: 29214.71 | AK55: 45712.83 | AL55: 31644.07 | AM55: 25612.61 | AN55: =SUM(AB55:AM55)
A56: PB | B56: =IFERROR(VLOOKUP($A56,Codes!$A:$B,2,FALSE()),"") | C56: 401k Contributions | D56: 288.99 | E56: 390.48 | F56: 551.46 | G56: 507.73 | H56: 517.56 | I56: 612.96 | J56: 692.75 | K56: 933.76 | L56: 731.8 | M56: 780.53 | N56: 648.77 | O56: 878.76 | P56: 1010.72 | Q56: 698.98 | R56: 942.48 | S56: 918.87 | T56: 880.25 | U56: 1083.67 | V56: 1115.74 | W56: 1142.18 | X56: 970.5 | Y56: 739.53 | Z56: 876.26 | AA56: 885.48 | AB56: 1070.64 | AC56: 910.86 | AD56: 947.06 | AE56: 816.76 | AF56: 923.78 | AG56: 950.05 | AH56: 981.27 | AI56: 1088.46 | AJ56: 1079.6 | AK56: 1573.73 | AL56: 1177.48 | AM56: 1090.12 | AN56: =SUM(AB56:AM56)
A57: PB | B57: =IFERROR(VLOOKUP($A57,Codes!$A:$B,2,FALSE()),"") | C57: Employee Burden | D57: 9819.07 | E57: 11768.82 | F57: 10345.45 | G57: 10945.66 | H57: 10790.34 | I57: 10825.38 | J57: 11673.62 | K57: 11938.86 | L57: 11025.5 | M57: 11196.9 | N57: 9635.59 | O57: 12641.12 | P57: 16048.42 | Q57: 8546.62 | R57: 11755.6 | S57: 15501.78 | T57: 13856.38 | U57: 14260.13 | V57: 15060.04 | W57: 15078.99 | X57: 13259.71 | Y57: 10409.74 | Z57: 2987.54 | AA57: 11675.55 | AB57: 14129.69 | AC57: 12419.12 | AD57: 12077.83 | AE57: 11059.68 | AF57: 11858.62 | AG57: 12250.58 | AH57: 12279.89 | AI57: 12806.91 | AJ57: 12520.03 | AK57: 17338.61 | AL57: 12382.51 | AM57: 10841.01 | AN57: =SUM(AB57:AM57)
A58: PB | B58: =IFERROR(VLOOKUP($A58,Codes!$A:$B,2,FALSE()),"") | C58: Group Insurance | D58: 6371.68 | E58: 6301.02 | F58: 6300 | G58: 7000 | H58: 7000 | I58: 7000 | J58: 7000 | K58: 6300 | L58: 6300 | M58: 6921.19 | N58: 6456.53 | O58: 6066.55 | P58: 6462 | Q58: 7180 | R58: 7193.67 | S58: 7180 | T58: 7180.98 | U58: 7180 | V58: 7180 | W58: 7180 | X58: 6411.49 | Y58: 5744 | Z58: 5660.43 | AA58: 5681.63 | AB58: 7180 | AC58: 7180 | AD58: 6947.04 | AE58: 7092.16 | AF58: 7238.84 | AG58: 7570.05 | AH58: 7381.86 | AI58: 7430 | AJ58: 7362.7 | AK58: 7369.17 | AL58: 7452.5 | AM58: 7430 | AN58: =SUM(AB58:AM58)
A59: inter/exte | B59: =IFERROR(VLOOKUP($A59,Codes!$A:$B,2,FALSE()),"") | C59: Access Gate Expense | D59: 0 | E59: 0 | F59: 0 | G59: 90 | H59: 132.9 | I59: 526.66 | J59: 5.85 | K59: 363.75 | L59: 148.7 | M59: 32.81 | N59: 41.9 | O59: 183.8 | P59: -86.9 | Q59: 300.94 | R59: 328.62 | S59: 0 | T59: 0 | U59: 0 | V59: 2202.26 | W59: 0 | X59: 157.5 | Y59: 0 | Z59: 0 | AA59: 0 | AB59: 33.58 | AC59: 171.67 | AD59: 0 | AE59: 0 | AF59: 0 | AG59: 0 | AH59: 0 | AI59: 0 | AJ59: 0 | AK59: -156.82 | AL59: 0 | AM59: 0 | AN59: =SUM(AB59:AM59)
A60: inter/exte | B60: =IFERROR(VLOOKUP($A60,Codes!$A:$B,2,FALSE()),"") | C60: Appliance Repairs | D60: 5119.42 | E60: 2622.84 | F60: 4354.14 | G60: 3355.54 | H60: 4002.22 | I60: -15443.52 | J60: 220.71 | K60: 972.47 | L60: 367.17 | M60: 317.95 | N60: 122.42 | O60: 270.03 | P60: 581.16 | Q60: 200.5 | R60: 37.27 | S60: 227.61 | T60: 285.49 | U60: 304.18 | V60: 608.56 | W60: 223.21 | X60: 697.35 | Y60: 330.77 | Z60: 146.5 | AA60: 108.69 | AB60: 563.77 | AC60: 556.81 | AD60: 754.09 | AE60: 149.46 | AF60: 982.11 | AG60: 685.56 | AH60: 158.68 | AI60: 559.61 | AJ60: 139.56 | AK60: 1313.25 | AL60: 767.35 | AM60: 778.32 | AN60: =SUM(AB60:AM60)
A61: inter/exte | B61: =IFERROR(VLOOKUP($A61,Codes!$A:$B,2,FALSE()),"") | C61: Building - Interior | D61: 850.88 | E61: 0 | F61: 114.52 | G61: 1050.14 | H61: 442.95 | I61: 252.73 | J61: 916.05 | K61: 193.18 | L61: 529.52 | M61: 510.39 | N61: 85.7 | O61: 165.16 | P61: 0 | Q61: 13.53 | R61: 445.1 | S61: 141.42 | T61: 32.59 | U61: 160.35 | V61: 309.57 | W61: 435.07 | X61: 0 | Y61: 155.87 | Z61: 71.74 | AA61: 58.46 | AB61: 203.69 | AC61: 507.4 | AD61: 0 | AE61: 63.58 | AF61: 174.43 | AG61: 293.41 | AH61: 544.39 | AI61: 111.39 | AJ61: -77.52 | AK61: 43.8 | AL61: 175.26 | AM61: 43.25 | AN61: =SUM(AB61:AM61)
... A138: ret | B138: =IFERROR(VLOOKUP($A138,Codes!$A:$B,2,FALSE()),"") | C138: Ad Valorem Property Taxes | D138: 68710.63 | E138: 68710.63 | F138: 89317 | G138: 75579.38 | H138: 75579.42 | I138: 75579.42 | J138: 75579.42 | K138: 75579.42 | L138: 75579.42 | M138: 75579.42 | N138: 20547.73 | O138: 70576.54 | P138: 74105.36 | Q138: 74105.36 | R138: 74105.36 | S138: 74105.36 | T138: 74105.36 | U138: 74105.36 | V138: 74105.36 | W138: 74105.36 | X138: 63857.6 | Y138: 72966.72 | Z138: 72966.72 | AA138: 72966.69 | AB138: 78913.67 | AC138: 78913.67 | AD138: 78913.67 | AE138: 78913.67 | AF138: 78913.67 | AG138: 78913.67 | AH138: 78913.67 | AI138: 78913.67 | AJ138: 78913.67 | AK138: 45446.65 | AL138: 75566.97 | AM138: 75566.97 | AN138: =SUM(AB138:AM138)
A139: ret | B139: =IFERROR(VLOOKUP($A139,Codes!$A:$B,2,FALSE()),"") | C139: Sales and Use Taxes | D139: -1780.14 | E139: 1401.87 | F139: -193 | G139: 3034 | H139: 360.54 | I139: 2367.18 | J139: 2520.58 | K139: 1104.11 | L139: -1268.75 | M139: 729.65 | N139: 161.32 | O139: -161.7 | P139: 1289.67 | Q139: 3.26 | R139: 1349.53 | S139: 2695.39 | T139: 942.88 | U139: 982.05 | V139: 1004.29 | W139: -571.41 | X139: -979.21 | Y139: -316.28 | Z139: -2069.73 | AA139: 2195.33 | AN139: =SUM(AB139:AM139)
A140: ins | B140: =IFERROR(VLOOKUP($A140,Codes!$A:$B,2,FALSE()),"") | C140: Property Insurance | D140: 20071.48 | E140: 20071.48 | F140: 20071.49 | G140: 28450.76 | H140: 28450.82 | I140: 28450.82 | J140: 28450.82 | K140: 28450.82 | L140: 28450.82 | M140: 28450.82 | N140: 28450.82 | O140: 28450.82 | P140: 28450.82 | Q140: 28450.82 | R140: 28450.82 | S140: 26735.62 | T140: 26735.68 | U140: 26735.62 | V140: 26735.62 | W140: 26735.62 | X140: 26735.62 | Y140: 26735.62 | Z140: 26735.62 | AA140: 26735.62 | AB140: 26735.62 | AC140: 26735.62 | AD140: 26735.62 | AE140: 28915.07 | AF140: 20382.53 | AG140: 24648.8 | AH140: 24648.8 | AI140: 24648.8 | AJ140: 24648.8 | AK140: 24648.8 | AL140: 24648.8 | AM140: 24648.82 | AN140: =SUM(AB140:AM140)
A141: cont | B141: =IFERROR(VLOOKUP($A141,Codes!$A:$B,2,FALSE()),"") | C141: Fire Alarm Contract | D141: 248 | E141: 10.32 | F141: 0 | G141: 258.32 | H141: 840 | I141: 0 | J141: 124 | K141: 173.08 | L141: 0 | M141: 124 | N141: -124 | O141: 0 | AB141: 0 | AC141: 0 | AD141: 0 | AE141: 0 | AF141: 0 | AG141: 0 | AH141: 0 | AI141: 0 | AJ141: 0 | AK141: 871.2 | AL141: 0 | AM141: 0 | AN141: =SUM(AB141:AM141)
A142: adv | B142: =IFERROR(VLOOKUP($A142,Codes!$A:$B,2,FALSE()),"") | C142: Other Leasing& Marketing - Surveys | AB142: 0 | AC142: 0 | AD142: 0 | AE142: 0 | AF142: 756.75 | AG142: 1135.11 | AH142: 315.31 | AI142: 315.31 | AJ142: 315.31 | AK142: -2837.79 | AL142: 0 | AM142: 0 | AN142: =SUM(AB142:AM142)
A143: GA | B143: =IFERROR(VLOOKUP($A143,Codes!$A:$B,2,FALSE()),"") | C143: Administrative / Accounting Fees | AB143: 0 | AC143: 0 | AD143: 0 | AE143: 0 | AF143: 238.17 | AG143: 238.17 | AH143: 303.7 | AI143: -780.04 | AJ143: 0 | AK143: 0 | AL143: 0 | AM143: 0 | AN143: =SUM(AB143:AM143)
A144: GA | B144: =IFERROR(VLOOKUP($A144,Codes!$A:$B,2,FALSE()),"") | C144: Tax Preparation Fees | D144: 0 | E144: 0 | F144: 250 | G144: -250 | H144: 250 | I144: -250 | J144: 0 | K144: 0 | L144: 500 | M144: 0 | N144: 0 | O144: 0 | AB144: 0 | AC144: 0 | AD144: 0 | AE144: 0 | AF144: 270.4 | AG144: 0 | AH144: 0 | AI144: 0 | AJ144: 0 | AK144: 0 | AL144: 0 | AM144: 0 | AN144: =SUM(AB144:AM144)
A145: ins | B145: =IFERROR(VLOOKUP($A145,Codes!$A:$B,2,FALSE()),"") | C145: Environmental Liability Insurance | AB145: 0 | AC145: 0 | AD145: 0 | AE145: 0 | AF145: 0 | AG145: 427.94 | AH145: 494.34 | AI145: 213.97 | AJ145: 213.97 | AK145: 213.97 | AL145: 213.97 | AM145: 213.97 | AN145: =SUM(AB145:AM145)
A146: Pay | B146: =IFERROR(VLOOKUP($A146,Codes!$A:$B,2,FALSE()),"") | C146: Grounds - Salaries | D146: 0 | E146: 0 | F146: 0 | G146: 0 | H146: 0 | I146: 0 | J146: 0 | K146: 0 | L146: 0 | M146: 829.54 | N146: 1521.93 | O146: 450 | AN146: =SUM(AB146:AM146)
A147: GA | B147: =IFERROR(VLOOKUP($A147,Codes!$A:$B,2,FALSE()),"") | C147: Legal Fees | D147: 0 | E147: 0 | F147: 0 | G147: 0 | H147: 0.93 | I147: 1120.65 | J147: 1081.55 | K147: 0 | L147: 0 | M147: 0 | N147: 0 | O147: 0 | AN147: =SUM(AB147:AM147)
A148: GA | B148: =IFERROR(VLOOKUP($A148,Codes!$A:$B,2,FALSE()),"") | C148: Mileage Expense | D148: 0 | E148: 0 | F148: 0 | G148: 0 | H148: 0 | I148: 0 | J148: 0 | K148: 0 | L148: 206.98 | M148: -0.01 | N148: 0 | O148: 0 | AN148: =SUM(AB148:AM148)
C149: NON-OPERATING EXPENSES
A150: onoe | B150: =IFERROR(VLOOKUP($A150,Codes!$A:$B,2,FALSE()),"") | C150: Administrative / Supervision Fees | D150: 0 | E150: 0 | F150: 6860.09 | G150: 0 | H150: 7873.84 | I150: -14733.93 | J150: 0 | K150: 6524.56 | L150: 7015.96 | M150: 0 | N150: 0 | O150: 0 | P150: 0 | Q150: 0 | R150: 0 | S150: 68.9 | T150: 63.6 | U150: 0 | V150: 0 | W150: 0 | X150: 0 | Y150: 0 | Z150: 0 | AA150: 0 | AN150: =SUM(AB150:AM150)
A151: onoe | B151: =IFERROR(VLOOKUP($A151,Codes!$A:$B,2,FALSE()),"") | C151: Partnership / Owner Expense - Other 2nd | D151: 0 | E151: 973.3 | F151: 486.65 | G151: 486.65 | H151: 486.65 | I151: 498.25 | J151: 0 | K151: 996.5 | L151: 498.25 | M151: 498.25 | N151: 498.25 | O151: 0 | P151: 996.5 | Q151: 16995.53 | R151: 863.44 | S151: -935.97 | T151: -991.77 | U151: 607.04 | V151: 23727.65 | W151: -5497.32 | X151: 3294.01 | Y151: 1888.13 | Z151: 509.85 | AA151: 509.85 | AB151: 4057.82 | AC151: 509.85 | AD151: 265.13 | AE151: 1174.68 | AF151: 1019.7 | AG151: 0 | AH151: 533.01 | AI151: 5847.21 | AJ151: 533.01 | AK151: 1302.73 | AL151: 539.01 | AM151: 539.01 | AN151: =SUM(AB151:AM151)
A152: intex | B152: =IFERROR(VLOOKUP($A152,Codes!$A:$B,2,FALSE()),"") | C152: Interest Expense - 1st Mortgage | D152: 164621.68 | E152: 148690.55 | F152: 164621.68 | G152: 159312.12 | H152: 164620.87 | I152: 159311.31 | J152: 164621.68 | K152: 164621.68 | L152: 159311.31 | M152: 164621.68 | N152: 159311.31 | O152: 164621.68 | P152: 164621.68 | Q152: 154000.93 | R152: 164621.68 | S152: 159311.31 | T152: 164621.68 | U152: 159311.31 | V152: 164621.68 | W152: 164621.68 | X152: 159311.31 | Y152: 164621.68 | Z152: 161311.31 | AA152: 0 | AN152: =SUM(AB152:AM152)
A153: intex | B153: =IFERROR(VLOOKUP($A153,Codes!$A:$B,2,FALSE()),"") | C153: Interest Expense - 2nd Mortgage | D153: 45398.53 | E153: 40934.35 | F153: 45223.16 | G153: 43687.8 | H153: 45058.56 | I153: 43527.85 | J153: 44892.6 | K153: 44812.13 | L153: 43288.38 | M153: 44374.15 | N153: 43125.14 | O153: 44744.79 | P153: 44392.57 | Q153: 41451.29 | R153: 44215.14 | S153: 42708.23 | T153: 44042.24 | U153: 42540.21 | V153: 43867.9 | W153: 43743.4 | X153: 42328.18 | Y153: 43606.68 | Z153: 43116.94 | AA153: 0 | AN153: =SUM(AB153:AM153)
A154: intex | B154: =IFERROR(VLOOKUP($A154,Codes!$A:$B,2,FALSE()),"") | C154: Interest Expense - 3rd Mortgage | D154: 56420.22 | E154: 50898.39 | F154: 56256.73 | G154: 54375 | H154: 56109.21 | I154: 54231.56 | J154: 55960.29 | K154: 55889.64 | L154: 54018.04 | M154: 55738.62 | N154: 53871.19 | O154: 55586.18 | P154: 55513.72 | Q154: 51864.08 | R154: 55350.51 | S154: 53493.79 | T154: 55194.37 | U154: 53341.96 | V154: 55036.74 | W154: 54961.64 | X154: 53115.64 | Y154: 54801.8 | Z154: 53960.22 | AA154: 0 | AN154: =SUM(AB154:AM154)
A155: intex | B155: =IFERROR(VLOOKUP($A155,Codes!$A:$B,2,FALSE()),"") | C155: Interest Expense - Other | P155: 0 | Q155: 0 | R155: 0 | S155: 0 | T155: 0 | U155: 0 | V155: 0 | W155: 0 | X155: 0 | Y155: 0 | Z155: 0 | AA155: 703769.29 | AB155: 532793.85 | AC155: 466306.66 | AD155: 518577.15 | AE155: 500352.59 | AF155: 518414.65 | AG155: 498614.94 | AH155: 515861.85 | AI155: 517626.55 | AJ155: 502010.81 | AK155: 514912.08 | AL155: 489989.59 | AM155: 490619.86 | AN155: =SUM(AB155:AM155)
A156: prin | B156: =IFERROR(VLOOKUP($A156,Codes!$A:$B,2,FALSE()),"") | C156: Amortization | D156: 12538.5 | E156: 12538.5 | F156: 12538.5 | G156: 12538.5 | H156: 12538.5 | I156: 12538.5 | J156: 12538.5 | K156: 12538.5 | L156: 12538.5 | M156: 12538.5 | N156: 12538.5 | O156: 12538.5 | P156: 12538.5 | Q156: 12538.5 | R156: 12538.5 | S156: 12538.5 | T156: 12538.5 | U156: 12538.5 | V156: 12538.5 | W156: 12538.5 | X156: 12538.5 | Y156: 12538.5 | Z156: 12538.48 | AA156: 10033.38 | AB156: 10033.38 | AC156: 10033.38 | AD156: 10033.38 | AE156: 10033.38 | AF156: 10033.38 | AG156: 10033.38 | AH156: 10033.38 | AI156: 10033.38 | AJ156: 10033.38 | AK156: 10033.38 | AL156: 10033.38 | AM156: 10033.38 | AN156: =SUM(AB156:AM156)
A157: onoe | B157: =IFERROR(VLOOKUP($A157,Codes!$A:$B,2,FALSE()),"") | C157: Tax Escrow | D157: -73369.7 | E157: -73369.7 | F157: -73369.7 | G157: 338894.04 | H157: -73369.7 | I157: -74119.45 | J157: -74119.45 | K157: -64866.28 | L157: -64866.28 | M157: -64866.28 | N157: 358592.95 | O157: -64866.28 | P157: -64866.28 | Q157: -64866.28 | R157: -64866.28 | S157: -64866.28 | T157: 358592.95 | U157: -72146.18 | V157: -72146.18 | W157: -73005.51 | X157: -73005.51 | Y157: -73005.51 | Z157: 72927.8 | AA157: 161642.13 | AB157: -72966.75 | AC157: -72966.75 | AD157: -72966.75 | AE157: -72966.75 | AF157: -72966.75 | AG157: -54971.68 | AH157: -72966.74 | AI157: -31902.37 | AJ157: -31902.37 | AK157: 421499.43 | AL157: -31902.37 | AM157: -31902.37 | AN157: =SUM(AB157:AM157)
A158: onoe | B158: =IFERROR(VLOOKUP($A158,Codes!$A:$B,2,FALSE()),"") | C158: Insurance Escrow | P158: 0 | Q158: 0 | R158: 0 | S158: 0 | T158: 0 | U158: 0 | V158: 0 | W158: 0 | X158: 0 | Y158: 0 | Z158: -213884.97 | AA158: 0 | AB158: -26735.62 | AC158: -26735.62 | AD158: -26735.62 | AE158: -26735.62 | AF158: 269050 | AG158: -44730.69 | AH158: -26735.63 | AI158: -24648.84 | AJ158: -24648.84 | AK158: -24648.84 | AL158: -24648.84 | AM158: -24648.84 | AN158: =SUM(AB158:AM158)
A159: onoe | B159: =IFERROR(VLOOKUP($A159,Codes!$A:$B,2,FALSE()),"") | C159: Replacement / Rehab Escrow | D159: -15230 | E159: 128359.54 | F159: -15230 | G159: 63841.9 | H159: -15230 | I159: -15230 | J159: -15230 | K159: -15230 | L159: -15230 | M159: 49069.16 | N159: 53991.76 | O159: -15230 | P159: -15230 | Q159: -15230 | R159: 23307.08 | S159: -15230 | T159: -15230 | U159: -15230 | V159: 20575.1 | W159: -15230 | X159: 4670.82 | Y159: -15230 | Z159: -275098 | AA159: 213853.04 | AB159: -8938 | AC159: -8938 | AD159: -8938 | AE159: -8938 | AF159: -8938 | AG159: -8938 | AH159: -8938 | AI159: -8938 | AJ159: -8938 | AK159: -8938 | AL159: -8938 | AM159: 268935.68 | AN159: =SUM(AB159:AM159)
A160: onoe | B160: =IFERROR(VLOOKUP($A160,Codes!$A:$B,2,FALSE()),"") | C160: Accounts Receivable | D160: 6055.93 | E160: -4241.95 | F160: -72.47 | G160: -6521.37 | H160: 22185.6 | I160: -5969.26 | J160: -11637.84 | K160: 8739.38 | L160: -16241.24 | M160: 11516.85 | N160: -15836.98 | O160: 499.54 | P160: 13915.29 | Q160: -14225.59 | R160: 16599.75 | S160: 913.16 | T160: 3944.55 | U160: 1798.85 | V160: -8743.67 | W160: -7363.47 | X160: -1034.9 | Y160: 21148.49 | Z160: -25791.47 | AA160: -5596.64 | AB160: 19810.04 | AC160: 2312.05 | AD160: -13089.6 | AE160: 12963.37 | AF160: -10209.19 | AG160: -6855.43 | AH160: 6675.12 | AI160: 4110.39 | AJ160: 13604.54 | AK160: -18046.45 | AL160: 304 | AM160: 22629.6 | AN160: =SUM(AB160:AM160)
A161: onoe | B161: =IFERROR(VLOOKUP($A161,Codes!$A:$B,2,FALSE()),"") | C161: A/R - Other | D161: 144774.65 | E161: 0 | F161: 0 | G161: 0 | H161: 0 | I161: 0 | J161: 0 | K161: 0 | L161: 10594.63 | M161: 0 | N161: 0 | O161: 0 | P161: 0 | Q161: 0 | R161: -38537.08 | S161: 0 | T161: -514.5 | U161: 38794.33 | V161: -150.33 | W161: 407.58 | X161: 0 | Y161: 0 | Z161: 0 | AA161: 0 | AB161: -2364.21 | AC161: 908.61 | AD161: 1455.6 | AE161: 0 | AF161: 0 | AG161: 0 | AH161: 0 | AI161: -453.98 | AJ161: 0 | AK161: -3066.02 | AL161: 277873.68 | AM161: -277873.68 | AN161: =SUM(AB161:AM161)
A162: onoe | B162: =IFERROR(VLOOKUP($A162,Codes!$A:$B,2,FALSE()),"") | C162: Intra-Company A/R - A/P | D162: 0 | E162: -0.02 | F162: 0.02 | G162: 0 | H162: 0 | I162: 0 | J162: 0 | K162: 0 | L162: 0 | M162: 0 | N162: 0 | O162: 0 | P162: 0 | Q162: 0 | R162: 0 | S162: 0 | T162: 0 | U162: 0 | V162: 0 | W162: 0 | X162: 0 | Y162: 0 | Z162: 0.03 | AA162: -0.03 | AB162: 0 | AC162: 0 | AD162: 0 | AE162: 0 | AF162: 10224.94 | AG162: -10224.94 | AH162: 0 | AI162: 0 | AJ162: 0 | AK162: 0 | AL162: 0 | AM162: 0 | AN162: =SUM(AB162:AM162)
A163: onoe | B163: =IFERROR(VLOOKUP($A163,Codes!$A:$B,2,FALSE()),"") | C163: Accrued Receivables | D163: -67444.7 | E163: -89451.67 | F163: -2555.72 | G163: 4289.5 | H163: -4644.78 | I163: 13911.73 | J163: 516.15 | K163: 8350.99 | L163: -8307.61 | M163: 1003.49 | N163: 2719.43 | O163: -10791.95 | P163: -148.71 | Q163: -11448.07 | R163: -9757.51 | S163: 4130.9 | T163: -2659.49 | U163: 8749.81 | V163: 6385.08 | W163: 3298.96 | X163: 26.3 | Y163: -1834.03 | Z163: -977.48 | AA163: -12624.22 | AB163: 706.32 | AC163: -17202.85 | AD163: -3494.61 | AE163: -7168.46 | AF163: 6917.65 | AG163: 6114.27 | AH163: -10316.76 | AI163: -3473.12 | AJ163: 18625.12 | AK163: -7455.88 | AL163: -3249.83 | AM163: 4254.22 | AN163: =SUM(AB163:AM163)
A164: onoe | B164: =IFERROR(VLOOKUP($A164,Codes!$A:$B,2,FALSE()),"") | C164: Prepaid Insurance | D164: 20071.48 | E164: 20071.48 | F164: 20071.49 | G164: -312959.02 | H164: 28450.82 | I164: 28450.82 | J164: 28450.82 | K164: 28450.82 | L164: 28450.82 | M164: 28450.82 | N164: 28450.82 | O164: 28450.82 | P164: 28450.82 | Q164: 28450.82 | R164: 28450.82 | S164: 0 | T164: -267356.2 | U164: 26735.62 | V164: 26735.62 | W164: 26735.62 | X164: 26735.62 | Y164: 26735.62 | Z164: 26735.62 | AA164: 26735.62 | AB164: 26735.62 | AC164: 26735.62 | AD164: 26735.62 | AE164: 0 | AF164: -246488.02 | AG164: 24648.8 | AH164: 17587.79 | AI164: 24862.77 | AJ164: 24862.77 | AK164: 24862.77 | AL164: 24862.77 | AM164: 24862.79 | AN164: =SUM(AB164:AM164)
A165: onoe | B165: =IFERROR(VLOOKUP($A165,Codes!$A:$B,2,FALSE()),"") | C165: Prepaid Real Property Taxes | P165: 0 | Q165: 0 | R165: 0 | S165: 0 | T165: 0 | U165: 0 | V165: 0 | W165: 0 | X165: 0 | Y165: 0 | Z165: -72966.69 | AA165: 72966.69 | AN165: =SUM(AB165:AM165)
A166: onoe | B166: =IFERROR(VLOOKUP($A166,Codes!$A:$B,2,FALSE()),"") | C166: Prepaid - Other | D166: 0 | E166: 0 | F166: 0 | G166: 0 | H166: -7000 | I166: 7000 | J166: -507.08 | K166: 85.68 | L166: 421.4 | M166: 0 | N166: -6487.95 | O166: 6066.55 | P166: 421.4 | Q166: -421.4 | R166: -196.38 | S166: 454.45 | T166: 20.42 | U166: 20.42 | V166: 20.42 | W166: 20.42 | X166: -191.22 | Y166: -5532.41 | Z166: 2415.37 | AA166: 72.41 | AB166: 3317.5 | AC166: -1506.82 | AD166: 426.36 | AE166: -7421.52 | AF166: 6009.02 | AG166: 2145.2 | AH166: 38.64 | AI166: 38.64 | AJ166: 38.64 | AK166: 38.64 | AL166: 38.64 | AM166: -136.86 | AN166: =SUM(AB166:AM166)
A167: capx | B167: =IFERROR(VLOOKUP($A167,Codes!$A:$B,2,FALSE()),"") | C167: Maj. Repairs - Landscape | D167: 0 | E167: 0 | F167: 0 | G167: -5575 | H167: -19820 | I167: -2820 | J167: -2820 | K167: 0 | L167: 0 | M167: 0 | N167: -900 | O167: -7156 | P167: 0 | Q167: -17718.25 | R167: -17718.25 | S167: -2520 | T167: -23464.75 | U167: 15198.75 | V167: 0 | W167: -22058.32 | X167: 0 | Y167: -5966 | Z167: -19454.75 | AA167: -1190.43 | AB167: -4140 | AC167: 0 | AD167: 0 | AE167: -20730 | AF167: -5206 | AG167: 0 | AH167: -1190 | AI167: 0 | AJ167: -378.97 | AK167: -6715.83 | AL167: -1736 | AM167: -990 | AN167: =SUM(AB167:AM167)
A168: capx | B168: =IFERROR(VLOOKUP($A168,Codes!$A:$B,2,FALSE()),"") | C168: Major Repairs - Roof | D168: -489 | E168: -4449.39 | F168: -2770.78 | G168: -784.39 | H168: 0 | I168: 0 | J168: 0 | K168: 0 | L168: 0 | M168: 0 | N168: 0 | O168: 0 | P168: -1446.39 | Q168: 0 | R168: 0 | S168: -7431.78 | T168: -2894.78 | U168: 0 | V168: 0 | W168: -1326.39 | X168: 0 | Y168: 0 | Z168: 0 | AA168: 0 | AB168: 0 | AC168: 0 | AD168: 0 | AE168: -1735.78 | AF168: 0 | AG168: 0 | AH168: -904.39 | AI168: 0 | AJ168: -1130.39 | AK168: -451 | AL168: -2554.39 | AM168: -756.4 | AN168: =SUM(AB168:AM168)
A169: capx | B169: =IFERROR(VLOOKUP($A169,Codes!$A:$B,2,FALSE()),"") | C169: Major Repairs - Model / Office | D169: 0 | E169: -7006.38 | F169: -70779.07 | G169: -108483.71 | H169: -86938 | I169: -25301.1 | J169: -85283.4 | K169: -14054.41 | L169: -81535.42 | M169: -47035.19 | N169: -11366.01 | O169: -3420.72 | P169: -2061.67 | Q169: -74194.13 | R169: 50000 | S169: 136.61 | T169: 0 | U169: -950 | V169: -34800 | W169: -10212.77 | X169: -14609.69 | Y169: -2746.55 | Z169: -14080.49 | AA169: -32244.59 | AB169: -7000 | AC169: 446.13 | AD169: 1708.01 | AE169: -167.3 | AF169: 0 | AG169: 0 | AH169: 0 | AI169: 0 | AJ169: 0 | AK169: -47.5 | AL169: 0 | AM169: -7000 | AN169: =SUM(AB169:AM169)
A170: capx | B170: =IFERROR(VLOOKUP($A170,Codes!$A:$B,2,FALSE()),"") | C170: Major Repairs - Electrical | D170: 0 | E170: 0 | F170: 0 | G170: 0 | H170: 0 | I170: 0 | J170: 0 | K170: 0 | L170: 0 | M170: 0 | N170: 0 | O170: -398.58 | P170: 0 | Q170: 0 | R170: 0 | S170: 0 | T170: 0 | U170: 0 | V170: 0 | W170: -615 | X170: 0 | Y170: 0 | Z170: 0 | AA170: 0 | AN170: =SUM(AB170:AM170)
A171: capx | B171: =IFERROR(VLOOKUP($A171,Codes!$A:$B,2,FALSE()),"") | C171: Major Repairs - Garage / Carport | D171: 0 | E171: 0 | F171: 0 | G171: -975 | H171: 0 | I171: 0 | J171: 0 | K171: 0 | L171: 0 | M171: 0 | N171: 0 | O171: 0 | P171: 0 | Q171: 0 | R171: 0 | S171: 0 | T171: 0 | U171: -2808 | V171: 0 | W171: -1000 | X171: 0 | Y171: 0 | Z171: 0 | AA171: 0 | AB171: 0 | AC171: 0 | AD171: 0 | AE171: 0 | AF171: -2196.48 | AG171: -2255.24 | AH171: 0 | AI171: 0 | AJ171: -503.55 | AK171: -9735.64 | AL171: -2162.75 | AM171: -4924.61 | AN171: =SUM(AB171:AM171)
A172: capx | B172: =IFERROR(VLOOKUP($A172,Codes!$A:$B,2,FALSE()),"") | C172: Major Repairs - Common Areas | D172: 0 | E172: -7392.29 | F172: 0 | G172: -444.3 | H172: 0 | I172: -11438.53 | J172: -1733.47 | K172: -10063.11 | L172: -7293.23 | M172: -14869.82 | N172: -14736 | O172: -99931.64 | P172: -51961.99 | Q172: 36297.3 | R172: -1816.36 | S172: -36125.54 | T172: -10678.93 | U172: -46237.02 | V172: -7534.62 | W172: -3801.01 | X172: -4961.38 | Y172: -631.25 | Z172: -11491.1 | AA172: -379.34 | AB172: -23946.95 | AC172: 17435 | AD172: -5762.83 | AE172: -13439 | AF172: -30215.02 | AG172: -8357.03 | AH172: -15438.88 | AI172: -18124.58 | AJ172: 2926.52 | AK172: 89740.3 | AL172: -3495 | AM172: 0 | AN172: =SUM(AB172:AM172)
A173: capx | B173: =IFERROR(VLOOKUP($A173,Codes!$A:$B,2,FALSE()),"") | C173: Renovation Costs | D173: -74055.5 | E173: -4779.17 | F173: 0 | G173: 0 | H173: 0 | I173: 0 | J173: 0 | K173: 0 | L173: 0 | M173: 0 | N173: 255 | O173: -1759.46 | P173: -2335 | Q173: 0 | R173: 0 | S173: 0 | T173: 0 | U173: 0 | V173: 0 | W173: 0 | X173: 0 | Y173: 0 | Z173: 0 | AA173: 0 | AN173: =SUM(AB173:AM173)
A174: capx | B174: =IFERROR(VLOOKUP($A174,Codes!$A:$B,2,FALSE()),"") | C174: Signage | D174: -33851.64 | E174: 0 | F174: 0 | G174: 0 | H174: 0 | I174: 0 | J174: 0 | K174: 0 | L174: 0 | M174: 0 | N174: 0 | O174: -46923 | P174: 0 | Q174: 15279.96 | R174: 0 | S174: -3421.46 | T174: 9735.62 | U174: 0 | V174: -6842.92 | W174: -3421.46 | X174: -6842.92 | Y174: 0 | Z174: -6842.92 | AA174: 0 | AB174: -27870.27 | AC174: -24980.41 | AD174: 0.02 | AE174: -22163.75 | AF174: 0 | AG174: 0 | AH174: 0 | AI174: 0 | AJ174: 0 | AK174: 0 | AL174: -107.34 | AM174: 0 | AN174: =SUM(AB174:AM174)
A175: capx | B175: =IFERROR(VLOOKUP($A175,Codes!$A:$B,2,FALSE()),"") | C175: Vehicles | D175: 0 | E175: -8191.95 | F175: 0 | G175: 0 | H175: 0 | I175: 0 | J175: 0 | K175: 0 | L175: 0 | M175: 0 | N175: 0 | O175: -218.23 | P175: 0 | Q175: 0 | R175: -1152.78 | S175: -1305.19 | T175: 0 | U175: 0 | V175: -638.2 | W175: -17441.77 | X175: 0 | Y175: -756.35 | Z175: 0 | AA175: -150 | AB175: 0 | AC175: 150 | AD175: 0 | AE175: -1407.12 | AF175: 0 | AG175: 0 | AH175: -114.21 | AI175: -1322.12 | AJ175: 0 | AK175: 0 | AL175: 0 | AM175: 0 | AN175: =SUM(AB175:AM175)
A176: capx | B176: =IFERROR(VLOOKUP($A176,Codes!$A:$B,2,FALSE()),"") | C176: Appliances | D176: -9273.82 | E176: -5081.18 | F176: -4729.68 | G176: -4482.48 | H176: -3629.66 | I176: -24206.41 | J176: -8075.27 | K176: -1176.19 | L176: -2521.15 | M176: -7681.26 | N176: -4296.61 | O176: -8925.79 | P176: -13403.75 | Q176: -4028.16 | R176: -7788.16 | S176: -4329.17 | T176: -10935.49 | U176: -3671.86 | V176: -11464.77 | W176: -1331.52 | X176: -9744.15 | Y176: -6155.75 | Z176: -6534.9 | AA176: -8234.33 | AB176: -7252.2 | AC176: -9201.76 | AD176: -12780.58 | AE176: -6401.98 | AF176: -11332 | AG176: -11183.19 | AH176: -5962.59 | AI176: -5481.67 | AJ176: 1113.65 | AK176: 69323.23 | AL176: 0 | AM176: 0 | AN176: =SUM(AB176:AM176)
A177: capx | B177: =IFERROR(VLOOKUP($A177,Codes!$A:$B,2,FALSE()),"") | C177: Appliances - Water Heaters | D177: -2749.73 | E177: -1890.73 | F177: -5306.7 | G177: -2777.85 | H177: -2363.57 | I177: -1757.22 | J177: -1890.67 | K177: 0 | L177: -3781.59 | M177: -1890.75 | N177: -4258.79 | O177: -4903.78 | P177: -5754.19 | Q177: -3112.94 | R177: -8621.69 | S177: -4384.99 | T177: -5004.52 | U177: -4464.47 | V177: -4490.77 | W177: -966.12 | X177: -4290.44 | Y177: -203.03 | Z177: -4280.16 | AA177: -2382.53 | AB177: -3835.8 | AC177: -1760.33 | AD177: -4083.34 | AE177: -7017.72 | AF177: -1121.85 | AG177: -2971.69 | AH177: -3908.82 | AI177: -210.84 | AJ177: -3037.85 | AK177: -3202.74 | AL177: -1458 | AM177: -5494.88 | AN177: =SUM(AB177:AM177)
A178: capx | B178: =IFERROR(VLOOKUP($A178,Codes!$A:$B,2,FALSE()),"") | C178: Building - Interior | D178: -15341.36 | E178: -47186.14 | F178: -27751.15 | G178: -68345.81 | H178: -600.62 | I178: -23585.2 | J178: -13171.41 | K178: -23847.6 | L178: -16917.06 | M178: -14220.82 | N178: -18842.23 | O178: -5576.3 | P178: -20160.48 | Q178: -21117.4 | R178: -24421.7 | S178: -21305.99 | T178: -8883.39 | U178: -12070.45 | V178: -11887.64 | W178: -12560.48 | X178: -11039.03 | Y178: -15132.31 | Z178: -20890.58 | AA178: -21726.25 | AB178: -11742.97 | AC178: -25860.7 | AD178: -15845 | AE178: -11210.01 | AF178: -15933.6 | AG178: -21445.6 | AH178: -16952.25 | AI178: -30349.99 | AJ178: 20189.33 | AK178: 96192.19 | AL178: -12822.39 | AM178: -11170.68 | AN178: =SUM(AB178:AM178)
A179: capx | B179: =IFERROR(VLOOKUP($A179,Codes!$A:$B,2,FALSE()),"") | C179: Carpets | D179: -29178.74 | E179: -23197.06 | F179: -27750.09 | G179: -27328.23 | H179: -23801.01 | I179: -20856.42 | J179: -28732.46 | K179: -20369.55 | L179: -21320.97 | M179: -26255.35 | N179: -11376.38 | O179: -14238.27 | P179: -27664.49 | Q179: -27578.83 | R179: -21318.02 | S179: -20452.82 | T179: -9101.36 | U179: -22698.95 | V179: -21689.88 | W179: -18569.1 | X179: -17633.12 | Y179: -20522.6 | Z179: -11176.25 | AA179: -17583.3 | AB179: -32358.38 | AC179: -18033.74 | AD179: -12503.8 | AE179: -11000.32 | AF179: -13906.33 | AG179: -15732.34 | AH179: -13395.91 | AI179: -12969.87 | AJ179: -15069.38 | AK179: -6998.68 | AL179: -10140.14 | AM179: -17796.66 | AN179: =SUM(AB179:AM179)
A180: capx | B180: =IFERROR(VLOOKUP($A180,Codes!$A:$B,2,FALSE()),"") | C180: Floor / Tile | D180: -2258.32 | E180: 0 | F180: -670.42 | G180: -1961.27 | H180: -2290.4 | I180: -16168.55 | J180: -198.38 | K180: 0 | L180: -270 | M180: 0 | N180: 0 | O180: 0 | P180: -380 | Q180: -3256.04 | R180: 0 | S180: 0 | T180: 0 | U180: 0 | V180: -1872.01 | W180: 0 | X180: -2833.83 | Y180: 0 | Z180: 0 | AA180: 0 | AB180: 0 | AC180: 0 | AD180: -1233.5 | AE180: 0 | AF180: 0 | AG180: 0 | AH180: -2259.35 | AI180: -5944.84 | AJ180: 4959.15 | AK180: 0 | AL180: 0 | AM180: 0 | AN180: =SUM(AB180:AM180)
A181: capx | B181: =IFERROR(VLOOKUP($A181,Codes!$A:$B,2,FALSE()),"") | C181: Electrical | D181: 0 | E181: 0 | F181: 0 | G181: 0 | H181: 0 | I181: 0 | J181: 0 | K181: -296.81 | L181: 0 | M181: -292.03 | N181: 0 | O181: 0 | P181: -84.78 | Q181: -78.26 | R181: 0 | S181: 0 | T181: 0 | U181: 0 | V181: 0 | W181: 0 | X181: 0 | Y181: 0 | Z181: 0 | AA181: 0 | AN181: =SUM(AB181:AM181)
A182: capx | B182: =IFERROR(VLOOKUP($A182,Codes!$A:$B,2,FALSE()),"") | C182: HVAC | D182: 0 | E182: -1103 | F182: -4373.14 | G182: -984.47 | H182: -16791.34 | I182: -4664.03 | J182: -11331.5 | K182: -9501.64 | L182: -15654.56 | M182: -1386.52 | N182: -9567.31 | O182: -625 | P182: -3497.47 | Q182: -69.06 | R182: -1124.21 | S182: -5601.68 | T182: -4290.44 | U182: -3245.85 | V182: -23439.74 | W182: 173.75 | X182: -7923.07 | Y182: -1096.09 | Z182: -3264.77 | AA182: -7405.74 | AB182: 0 | AC182: -405.49 | AD182: -6787.44 | AE182: -4011.69 | AF182: -5771.59 | AG182: -9330.75 | AH182: -5674.54 | AI182: -17544.88 | AJ182: -9991.38 | AK182: -6180.67 | AL182: -2877.88 | AM182: -5560 | AN182: =SUM(AB182:AM182)
A183: capx | B183: =IFERROR(VLOOKUP($A183,Codes!$A:$B,2,FALSE()),"") | C183: Mini Blinds / Drapes | D183: -876.31 | E183: -250.7 | F183: -2097.89 | G183: -227.24 | H183: -1485.09 | I183: -573.86 | J183: -528.37 | K183: -1133.46 | L183: -804.02 | M183: -1476.5 | N183: -1773.5 | O183: -374.13 | P183: -1628.06 | Q183: -1967.54 | R183: -264.99 | S183: -579.36 | T183: -791.08 | U183: -883.55 | V183: -315.56 | W183: -2458.39 | X183: -258.06 | Y183: -1117.49 | Z183: -693.95 | AA183: -1146.52 | AB183: -1105.06 | AC183: -1771.8 | AD183: -1756.28 | AE183: -2809.82 | AF183: 302.95 | AG183: -1057.02 | AH183: -715.23 | AI183: -2305.21 | AJ183: 0 | AK183: 0 | AL183: 0 | AM183: 0 | AN183: =SUM(AB183:AM183)
...

Sheet OS Summary
B1: Bella Mirage
B2: Operating Statement — Standardized (live rollup)
B3: Adjusted Amounts ($ totals) — most recent 12 months · model paste target (A1:Q77)
C4: Annual | D4: Annual | E4: Annual | F4: Monthly | G4: Monthly | H4: Monthly | I4: Monthly | J4: Monthly | K4: Monthly | L4: Monthly | M4: Monthly | N4: Monthly | O4: Monthly | P4: Monthly | Q4: Monthly
F5: 45658 | G5: 45689 | H5: 45717 | I5: 45748 | J5: 45778 | K5: 45809 | L5: 45839 | M5: 45870 | N5: 45901 | O5: 45931 | P5: 45962 | Q5: 45992
A6: Code | B6: Effective Gross Revenue
A7: Rentinc | B7: Rental Income | F7: =SUMIFS('T12 Categorized'!AB:AB,'T12 Categorized'!$A:$A,$A7) | G7: =SUMIFS('T12 Categorized'!AC:AC,'T12 Categorized'!$A:$A,$A7) | H7: =SUMIFS('T12 Categorized'!AD:AD,'T12 Categorized'!$A:$A,$A7) | I7: =SUMIFS('T12 Categorized'!AE:AE,'T12 Categorized'!$A:$A,$A7) | J7: =SUMIFS('T12 Categorized'!AF:AF,'T12 Categorized'!$A:$A,$A7) | K7: =SUMIFS('T12 Categorized'!AG:AG,'T12 Categorized'!$A:$A,$A7) | L7: =SUMIFS('T12 Categorized'!AH:AH,'T12 Categorized'!$A:$A,$A7) | M7: =SUMIFS('T12 Categorized'!AI:AI,'T12 Categorized'!$A:$A,$A7) | N7: =SUMIFS('T12 Categorized'!AJ:AJ,'T12 Categorized'!$A:$A,$A7) | O7: =SUMIFS('T12 Categorized'!AK:AK,'T12 Categorized'!$A:$A,$A7) | P7: =SUMIFS('T12 Categorized'!AL:AL,'T12 Categorized'!$A:$A,$A7) | Q7: =SUMIFS('T12 Categorized'!AM:AM,'T12 Categorized'!$A:$A,$A7)
A8: OI | B8: Other Income | F8: =SUMIFS('T12 Categorized'!AB:AB,'T12 Categorized'!$A:$A,$A8) | G8: =SUMIFS('T12 Categorized'!AC:AC,'T12 Categorized'!$A:$A,$A8) | H8: =SUMIFS('T12 Categorized'!AD:AD,'T12 Categorized'!$A:$A,$A8) | I8: =SUMIFS('T12 Categorized'!AE:AE,'T12 Categorized'!$A:$A,$A8) | J8: =SUMIFS('T12 Categorized'!AF:AF,'T12 Categorized'!$A:$A,$A8) | K8: =SUMIFS('T12 Categorized'!AG:AG,'T12 Categorized'!$A:$A,$A8) | L8: =SUMIFS('T12 Categorized'!AH:AH,'T12 Categorized'!$A:$A,$A8) | M8: =SUMIFS('T12 Categorized'!AI:AI,'T12 Categorized'!$A:$A,$A8) | N8: =SUMIFS('T12 Categorized'!AJ:AJ,'T12 Categorized'!$A:$A,$A8) | O8: =SUMIFS('T12 Categorized'!AK:AK,'T12 Categorized'!$A:$A,$A8) | P8: =SUMIFS('T12 Categorized'!AL:AL,'T12 Categorized'!$A:$A,$A8) | Q8: =SUMIFS('T12 Categorized'!AM:AM,'T12 Categorized'!$A:$A,$A8)
A9: RWS | B9: Rubs Water / Sewage | F9: =SUMIFS('T12 Categorized'!AB:AB,'T12 Categorized'!$A:$A,$A9) | G9: =SUMIFS('T12 Categorized'!AC:AC,'T12 Categorized'!$A:$A,$A9) | H9: =SUMIFS('T12 Categorized'!AD:AD,'T12 Categorized'!$A:$A,$A9) | I9: =SUMIFS('T12 Categorized'!AE:AE,'T12 Categorized'!$A:$A,$A9) | J9: =SUMIFS('T12 Categorized'!AF:AF,'T12 Categorized'!$A:$A,$A9) | K9: =SUMIFS('T12 Categorized'!AG:AG,'T12 Categorized'!$A:$A,$A9) | L9: =SUMIFS('T12 Categorized'!AH:AH,'T12 Categorized'!$A:$A,$A9) | M9: =SUMIFS('T12 Categorized'!AI:AI,'T12 Categorized'!$A:$A,$A9) | N9: =SUMIFS('T12 Categorized'!AJ:AJ,'T12 Categorized'!$A:$A,$A9) | O9: =SUMIFS('T12 Categorized'!AK:AK,'T12 Categorized'!$A:$A,$A9) | P9: =SUMIFS('T12 Categorized'!AL:AL,'T12 Categorized'!$A:$A,$A9) | Q9: =SUMIFS('T12 Categorized'!AM:AM,'T12 Categorized'!$A:$A,$A9)
A10: RT | B10: Rubs Trash | F10: =SUMIFS('T12 Categorized'!AB:AB,'T12 Categorized'!$A:$A,$A10) | G10: =SUMIFS('T12 Categorized'!AC:AC,'T12 Categorized'!$A:$A,$A10) | H10: =SUMIFS('T12 Categorized'!AD:AD,'T12 Categorized'!$A:$A,$A10) | I10: =SUMIFS('T12 Categorized'!AE:AE,'T12 Categorized'!$A:$A,$A10) | J10: =SUMIFS('T12 Categorized'!AF:AF,'T12 Categorized'!$A:$A,$A10) | K10: =SUMIFS('T12 Categorized'!AG:AG,'T12 Categorized'!$A:$A,$A10) | L10: =SUMIFS('T12 Categorized'!AH:AH,'T12 Categorized'!$A:$A,$A10) | M10: =SUMIFS('T12 Categorized'!AI:AI,'T12 Categorized'!$A:$A,$A10) | N10: =SUMIFS('T12 Categorized'!AJ:AJ,'T12 Categorized'!$A:$A,$A10) | O10: =SUMIFS('T12 Categorized'!AK:AK,'T12 Categorized'!$A:$A,$A10) | P10: =SUMIFS('T12 Categorized'!AL:AL,'T12 Categorized'!$A:$A,$A10) | Q10: =SUMIFS('T12 Categorized'!AM:AM,'T12 Categorized'!$A:$A,$A10)
A11: RF | B11: Rubs Fees | F11: =SUMIFS('T12 Categorized'!AB:AB,'T12 Categorized'!$A:$A,$A11) | G11: =SUMIFS('T12 Categorized'!AC:AC,'T12 Categorized'!$A:$A,$A11) | H11: =SUMIFS('T12 Categorized'!AD:AD,'T12 Categorized'!$A:$A,$A11) | I11: =SUMIFS('T12 Categorized'!AE:AE,'T12 Categorized'!$A:$A,$A11) | J11: =SUMIFS('T12 Categorized'!AF:AF,'T12 Categorized'!$A:$A,$A11) | K11: =SUMIFS('T12 Categorized'!AG:AG,'T12 Categorized'!$A:$A,$A11) | L11: =SUMIFS('T12 Categorized'!AH:AH,'T12 Categorized'!$A:$A,$A11) | M11: =SUMIFS('T12 Categorized'!AI:AI,'T12 Categorized'!$A:$A,$A11) | N11: =SUMIFS('T12 Categorized'!AJ:AJ,'T12 Categorized'!$A:$A,$A11) | O11: =SUMIFS('T12 Categorized'!AK:AK,'T12 Categorized'!$A:$A,$A11) | P11: =SUMIFS('T12 Categorized'!AL:AL,'T12 Categorized'!$A:$A,$A11) | Q11: =SUMIFS('T12 Categorized'!AM:AM,'T12 Categorized'!$A:$A,$A11)
A12: park | B12: Garage / Parking | F12: =SUMIFS('T12 Categorized'!AB:AB,'T12 Categorized'!$A:$A,$A12) | G12: =SUMIFS('T12 Categorized'!AC:AC,'T12 Categorized'!$A:$A,$A12) | H12: =SUMIFS('T12 Categorized'!AD:AD,'T12 Categorized'!$A:$A,$A12) | I12: =SUMIFS('T12 Categorized'!AE:AE,'T12 Categorized'!$A:$A,$A12) | J12: =SUMIFS('T12 Categorized'!AF:AF,'T12 Categorized'!$A:$A,$A12) | K12: =SUMIFS('T12 Categorized'!AG:AG,'T12 Categorized'!$A:$A,$A12) | L12: =SUMIFS('T12 Categorized'!AH:AH,'T12 Categorized'!$A:$A,$A12) | M12: =SUMIFS('T12 Categorized'!AI:AI,'T12 Categorized'!$A:$A,$A12) | N12: =SUMIFS('T12 Categorized'!AJ:AJ,'T12 Categorized'!$A:$A,$A12) | O12: =SUMIFS('T12 Categorized'!AK:AK,'T12 Categorized'!$A:$A,$A12) | P12: =SUMIFS('T12 Categorized'!AL:AL,'T12 Categorized'!$A:$A,$A12) | Q12: =SUMIFS('T12 Categorized'!AM:AM,'T12 Categorized'!$A:$A,$A12)
A13: CI | B13: Corporate Income | F13: =SUMIFS('T12 Categorized'!AB:AB,'T12 Categorized'!$A:$A,$A13) | G13: =SUMIFS('T12 Categorized'!AC:AC,'T12 Categorized'!$A:$A,$A13) | H13: =SUMIFS('T12 Categorized'!AD:AD,'T12 Categorized'!$A:$A,$A13) | I13: =SUMIFS('T12 Categorized'!AE:AE,'T12 Categorized'!$A:$A,$A13) | J13: =SUMIFS('T12 Categorized'!AF:AF,'T12 Categorized'!$A:$A,$A13) | K13: =SUMIFS('T12 Categorized'!AG:AG,'T12 Categorized'!$A:$A,$A13) | L13: =SUMIFS('T12 Categorized'!AH:AH,'T12 Categorized'!$A:$A,$A13) | M13: =SUMIFS('T12 Categorized'!AI:AI,'T12 Categorized'!$A:$A,$A13) | N13: =SUMIFS('T12 Categorized'!AJ:AJ,'T12 Categorized'!$A:$A,$A13) | O13: =SUMIFS('T12 Categorized'!AK:AK,'T12 Categorized'!$A:$A,$A13) | P13: =SUMIFS('T12 Categorized'!AL:AL,'T12 Categorized'!$A:$A,$A13) | Q13: =SUMIFS('T12 Categorized'!AM:AM,'T12 Categorized'!$A:$A,$A13)
A14: cable | B14: Cable Income | F14: =SUMIFS('T12 Categorized'!AB:AB,'T12 Categorized'!$A:$A,$A14) | G14: =SUMIFS('T12 Categorized'!AC:AC,'T12 Categorized'!$A:$A,$A14) | H14: =SUMIFS('T12 Categorized'!AD:AD,'T12 Categorized'!$A:$A,$A14) | I14: =SUMIFS('T12 Categorized'!AE:AE,'T12 Categorized'!$A:$A,$A14) | J14: =SUMIFS('T12 Categorized'!AF:AF,'T12 Categorized'!$A:$A,$A14) | K14: =SUMIFS('T12 Categorized'!AG:AG,'T12 Categorized'!$A:$A,$A14) | L14: =SUMIFS('T12 Categorized'!AH:AH,'T12 Categorized'!$A:$A,$A14) | M14: =SUMIFS('T12 Categorized'!AI:AI,'T12 Categorized'!$A:$A,$A14) | N14: =SUMIFS('T12 Categorized'!AJ:AJ,'T12 Categorized'!$A:$A,$A14) | O14: =SUMIFS('T12 Categorized'!AK:AK,'T12 Categorized'!$A:$A,$A14) | P14: =SUMIFS('T12 Categorized'!AL:AL,'T12 Categorized'!$A:$A,$A14) | Q14: =SUMIFS('T12 Categorized'!AM:AM,'T12 Categorized'!$A:$A,$A14)
A15: ltl | B15: (Loss to Lease) / Gain to Lease | F15: =SUMIFS('T12 Categorized'!AB:AB,'T12 Categorized'!$A:$A,$A15) | G15: =SUMIFS('T12 Categorized'!AC:AC,'T12 Categorized'!$A:$A,$A15) | H15: =SUMIFS('T12 Categorized'!AD:AD,'T12 Categorized'!$A:$A,$A15) | I15: =SUMIFS('T12 Categorized'!AE:AE,'T12 Categorized'!$A:$A,$A15) | J15: =SUMIFS('T12 Categorized'!AF:AF,'T12 Categorized'!$A:$A,$A15) | K15: =SUMIFS('T12 Categorized'!AG:AG,'T12 Categorized'!$A:$A,$A15) | L15: =SUMIFS('T12 Categorized'!AH:AH,'T12 Categorized'!$A:$A,$A15) | M15: =SUMIFS('T12 Categorized'!AI:AI,'T12 Categorized'!$A:$A,$A15) | N15: =SUMIFS('T12 Categorized'!AJ:AJ,'T12 Categorized'!$A:$A,$A15) | O15: =SUMIFS('T12 Categorized'!AK:AK,'T12 Categorized'!$A:$A,$A15) | P15: =SUMIFS('T12 Categorized'!AL:AL,'T12 Categorized'!$A:$A,$A15) | Q15: =SUMIFS('T12 Categorized'!AM:AM,'T12 Categorized'!$A:$A,$A15)
A16: vac | B16: Vacancy | F16: =SUMIFS('T12 Categorized'!AB:AB,'T12 Categorized'!$A:$A,$A16) | G16: =SUMIFS('T12 Categorized'!AC:AC,'T12 Categorized'!$A:$A,$A16) | H16: =SUMIFS('T12 Categorized'!AD:AD,'T12 Categorized'!$A:$A,$A16) | I16: =SUMIFS('T12 Categorized'!AE:AE,'T12 Categorized'!$A:$A,$A16) | J16: =SUMIFS('T12 Categorized'!AF:AF,'T12 Categorized'!$A:$A,$A16) | K16: =SUMIFS('T12 Categorized'!AG:AG,'T12 Categorized'!$A:$A,$A16) | L16: =SUMIFS('T12 Categorized'!AH:AH,'T12 Categorized'!$A:$A,$A16) | M16: =SUMIFS('T12 Categorized'!AI:AI,'T12 Categorized'!$A:$A,$A16) | N16: =SUMIFS('T12 Categorized'!AJ:AJ,'T12 Categorized'!$A:$A,$A16) | O16: =SUMIFS('T12 Categorized'!AK:AK,'T12 Categorized'!$A:$A,$A16) | P16: =SUMIFS('T12 Categorized'!AL:AL,'T12 Categorized'!$A:$A,$A16) | Q16: =SUMIFS('T12 Categorized'!AM:AM,'T12 Categorized'!$A:$A,$A16)
A17: cl | B17: Collection Loss / Bad Debt | F17: =SUMIFS('T12 Categorized'!AB:AB,'T12 Categorized'!$A:$A,$A17) | G17: =SUMIFS('T12 Categorized'!AC:AC,'T12 Categorized'!$A:$A,$A17) | H17: =SUMIFS('T12 Categorized'!AD:AD,'T12 Categorized'!$A:$A,$A17) | I17: =SUMIFS('T12 Categorized'!AE:AE,'T12 Categorized'!$A:$A,$A17) | J17: =SUMIFS('T12 Categorized'!AF:AF,'T12 Categorized'!$A:$A,$A17) | K17: =SUMIFS('T12 Categorized'!AG:AG,'T12 Categorized'!$A:$A,$A17) | L17: =SUMIFS('T12 Categorized'!AH:AH,'T12 Categorized'!$A:$A,$A17) | M17: =SUMIFS('T12 Categorized'!AI:AI,'T12 Categorized'!$A:$A,$A17) | N17: =SUMIFS('T12 Categorized'!AJ:AJ,'T12 Categorized'!$A:$A,$A17) | O17: =SUMIFS('T12 Categorized'!AK:AK,'T12 Categorized'!$A:$A,$A17) | P17: =SUMIFS('T12 Categorized'!AL:AL,'T12 Categorized'!$A:$A,$A17) | Q17: =SUMIFS('T12 Categorized'!AM:AM,'T12 Categorized'!$A:$A,$A17)
A18: nr | B18: Non-Revenue Units | F18: =SUMIFS('T12 Categorized'!AB:AB,'T12 Categorized'!$A:$A,$A18) | G18: =SUMIFS('T12 Categorized'!AC:AC,'T12 Categorized'!$A:$A,$A18) | H18: =SUMIFS('T12 Categorized'!AD:AD,'T12 Categorized'!$A:$A,$A18) | I18: =SUMIFS('T12 Categorized'!AE:AE,'T12 Categorized'!$A:$A,$A18) | J18: =SUMIFS('T12 Categorized'!AF:AF,'T12 Categorized'!$A:$A,$A18) | K18: =SUMIFS('T12 Categorized'!AG:AG,'T12 Categorized'!$A:$A,$A18) | L18: =SUMIFS('T12 Categorized'!AH:AH,'T12 Categorized'!$A:$A,$A18) | M18: =SUMIFS('T12 Categorized'!AI:AI,'T12 Categorized'!$A:$A,$A18) | N18: =SUMIFS('T12 Categorized'!AJ:AJ,'T12 Categorized'!$A:$A,$A18) | O18: =SUMIFS('T12 Categorized'!AK:AK,'T12 Categorized'!$A:$A,$A18) | P18: =SUMIFS('T12 Categorized'!AL:AL,'T12 Categorized'!$A:$A,$A18) | Q18: =SUMIFS('T12 Categorized'!AM:AM,'T12 Categorized'!$A:$A,$A18)
A19: conc | B19: Concessions | F19: =SUMIFS('T12 Categorized'!AB:AB,'T12 Categorized'!$A:$A,$A19) | G19: =SUMIFS('T12 Categorized'!AC:AC,'T12 Categorized'!$A:$A,$A19) | H19: =SUMIFS('T12 Categorized'!AD:AD,'T12 Categorized'!$A:$A,$A19) | I19: =SUMIFS('T12 Categorized'!AE:AE,'T12 Categorized'!$A:$A,$A19) | J19: =SUMIFS('T12 Categorized'!AF:AF,'T12 Categorized'!$A:$A,$A19) | K19: =SUMIFS('T12 Categorized'!AG:AG,'T12 Categorized'!$A:$A,$A19) | L19: =SUMIFS('T12 Categorized'!AH:AH,'T12 Categorized'!$A:$A,$A19) | M19: =SUMIFS('T12 Categorized'!AI:AI,'T12 Categorized'!$A:$A,$A19) | N19: =SUMIFS('T12 Categorized'!AJ:AJ,'T12 Categorized'!$A:$A,$A19) | O19: =SUMIFS('T12 Categorized'!AK:AK,'T12 Categorized'!$A:$A,$A19) | P19: =SUMIFS('T12 Categorized'!AL:AL,'T12 Categorized'!$A:$A,$A19) | Q19: =SUMIFS('T12 Categorized'!AM:AM,'T12 Categorized'!$A:$A,$A19)
B20: Effective Gross Revenue | F20: =SUM(F7:F19) | G20: =SUM(G7:G19) | H20: =SUM(H7:H19) | I20: =SUM(I7:I19) | J20: =SUM(J7:J19) | K20: =SUM(K7:K19) | L20: =SUM(L7:L19) | M20: =SUM(M7:M19) | ... Q20: =SUM(Q7:Q19)
B22: Operating Expenses
A23: Pay | B23: Payroll | F23: =SUMIFS('T12 Categorized'!AB:AB,'T12 Categorized'!$A:$A,$A23) | G23: =SUMIFS('T12 Categorized'!AC:AC,'T12 Categorized'!$A:$A,$A23) | H23: =SUMIFS('T12 Categorized'!AD:AD,'T12 Categorized'!$A:$A,$A23) | I23: =SUMIFS('T12 Categorized'!AE:AE,'T12 Categorized'!$A:$A,$A23) | J23: =SUMIFS('T12 Categorized'!AF:AF,'T12 Categorized'!$A:$A,$A23) | K23: =SUMIFS('T12 Categorized'!AG:AG,'T12 Categorized'!$A:$A,$A23) | L23: =SUMIFS('T12 Categorized'!AH:AH,'T12 Categorized'!$A:$A,$A23) | M23: =SUMIFS('T12 Categorized'!AI:AI,'T12 Categorized'!$A:$A,$A23) | N23: =SUMIFS('T12 Categorized'!AJ:AJ,'T12 Categorized'!$A:$A,$A23) | O23: =SUMIFS('T12 Categorized'!AK:AK,'T12 Categorized'!$A:$A,$A23) | P23: =SUMIFS('T12 Categorized'!AL:AL,'T12 Categorized'!$A:$A,$A23) | Q23: =SUMIFS('T12 Categorized'!AM:AM,'T12 Categorized'!$A:$A,$A23)
A24: PB | B24: Payroll Burden | F24: =SUMIFS('T12 Categorized'!AB:AB,'T12 Categorized'!$A:$A,$A24) | G24: =SUMIFS('T12 Categorized'!AC:AC,'T12 Categorized'!$A:$A,$A24) | H24: =SUMIFS('T12 Categorized'!AD:AD,'T12 Categorized'!$A:$A,$A24) | I24: =SUMIFS('T12 Categorized'!AE:AE,'T12 Categorized'!$A:$A,$A24) | J24: =SUMIFS('T12 Categorized'!AF:AF,'T12 Categorized'!$A:$A,$A24) | K24: =SUMIFS('T12 Categorized'!AG:AG,'T12 Categorized'!$A:$A,$A24) | L24: =SUMIFS('T12 Categorized'!AH:AH,'T12 Categorized'!$A:$A,$A24) | M24: =SUMIFS('T12 Categorized'!AI:AI,'T12 Categorized'!$A:$A,$A24) | N24: =SUMIFS('T12 Categorized'!AJ:AJ,'T12 Categorized'!$A:$A,$A24) | O24: =SUMIFS('T12 Categorized'!AK:AK,'T12 Categorized'!$A:$A,$A24) | P24: =SUMIFS('T12 Categorized'!AL:AL,'T12 Categorized'!$A:$A,$A24) | Q24: =SUMIFS('T12 Categorized'!AM:AM,'T12 Categorized'!$A:$A,$A24)
A25: PBo | B25: Payroll Bonuses | F25: =SUMIFS('T12 Categorized'!AB:AB,'T12 Categorized'!$A:$A,$A25) | G25: =SUMIFS('T12 Categorized'!AC:AC,'T12 Categorized'!$A:$A,$A25) | H25: =SUMIFS('T12 Categorized'!AD:AD,'T12 Categorized'!$A:$A,$A25) | I25: =SUMIFS('T12 Categorized'!AE:AE,'T12 Categorized'!$A:$A,$A25) | J25: =SUMIFS('T12 Categorized'!AF:AF,'T12 Categorized'!$A:$A,$A25) | K25: =SUMIFS('T12 Categorized'!AG:AG,'T12 Categorized'!$A:$A,$A25) | L25: =SUMIFS('T12 Categorized'!AH:AH,'T12 Categorized'!$A:$A,$A25) | M25: =SUMIFS('T12 Categorized'!AI:AI,'T12 Categorized'!$A:$A,$A25) | N25: =SUMIFS('T12 Categorized'!AJ:AJ,'T12 Categorized'!$A:$A,$A25) | O25: =SUMIFS('T12 Categorized'!AK:AK,'T12 Categorized'!$A:$A,$A25) | P25: =SUMIFS('T12 Categorized'!AL:AL,'T12 Categorized'!$A:$A,$A25) | Q25: =SUMIFS('T12 Categorized'!AM:AM,'T12 Categorized'!$A:$A,$A25)
A26: adv | B26: Marketing / Advertising | F26: =SUMIFS('T12 Categorized'!AB:AB,'T12 Categorized'!$A:$A,$A26) | G26: =SUMIFS('T12 Categorized'!AC:AC,'T12 Categorized'!$A:$A,$A26) | H26: =SUMIFS('T12 Categorized'!AD:AD,'T12 Categorized'!$A:$A,$A26) | I26: =SUMIFS('T12 Categorized'!AE:AE,'T12 Categorized'!$A:$A,$A26) | J26: =SUMIFS('T12 Categorized'!AF:AF,'T12 Categorized'!$A:$A,$A26) | K26: =SUMIFS('T12 Categorized'!AG:AG,'T12 Categorized'!$A:$A,$A26) | L26: =SUMIFS('T12 Categorized'!AH:AH,'T12 Categorized'!$A:$A,$A26) | M26: =SUMIFS('T12 Categorized'!AI:AI,'T12 Categorized'!$A:$A,$A26) | N26: =SUMIFS('T12 Categorized'!AJ:AJ,'T12 Categorized'!$A:$A,$A26) | O26: =SUMIFS('T12 Categorized'!AK:AK,'T12 Categorized'!$A:$A,$A26) | P26: =SUMIFS('T12 Categorized'!AL:AL,'T12 Categorized'!$A:$A,$A26) | Q26: =SUMIFS('T12 Categorized'!AM:AM,'T12 Categorized'!$A:$A,$A26)
A27: GA | B27: General & Administrative | F27: =SUMIFS('T12 Categorized'!AB:AB,'T12 Categorized'!$A:$A,$A27) | G27: =SUMIFS('T12 Categorized'!AC:AC,'T12 Categorized'!$A:$A,$A27) | H27: =SUMIFS('T12 Categorized'!AD:AD,'T12 Categorized'!$A:$A,$A27) | I27: =SUMIFS('T12 Categorized'!AE:AE,'T12 Categorized'!$A:$A,$A27) | J27: =SUMIFS('T12 Categorized'!AF:AF,'T12 Categorized'!$A:$A,$A27) | K27: =SUMIFS('T12 Categorized'!AG:AG,'T12 Categorized'!$A:$A,$A27) | L27: =SUMIFS('T12 Categorized'!AH:AH,'T12 Categorized'!$A:$A,$A27) | M27: =SUMIFS('T12 Categorized'!AI:AI,'T12 Categorized'!$A:$A,$A27) | N27: =SUMIFS('T12 Categorized'!AJ:AJ,'T12 Categorized'!$A:$A,$A27) | O27: =SUMIFS('T12 Categorized'!AK:AK,'T12 Categorized'!$A:$A,$A27) | P27: =SUMIFS('T12 Categorized'!AL:AL,'T12 Categorized'!$A:$A,$A27) | Q27: =SUMIFS('T12 Categorized'!AM:AM,'T12 Categorized'!$A:$A,$A27)
A28: turn | B28: Turnover | F28: =SUMIFS('T12 Categorized'!AB:AB,'T12 Categorized'!$A:$A,$A28) | G28: =SUMIFS('T12 Categorized'!AC:AC,'T12 Categorized'!$A:$A,$A28) | H28: =SUMIFS('T12 Categorized'!AD:AD,'T12 Categorized'!$A:$A,$A28) | I28: =SUMIFS('T12 Categorized'!AE:AE,'T12 Categorized'!$A:$A,$A28) | J28: =SUMIFS('T12 Categorized'!AF:AF,'T12 Categorized'!$A:$A,$A28) | K28: =SUMIFS('T12 Categorized'!AG:AG,'T12 Categorized'!$A:$A,$A28) | L28: =SUMIFS('T12 Categorized'!AH:AH,'T12 Categorized'!$A:$A,$A28) | M28: =SUMIFS('T12 Categorized'!AI:AI,'T12 Categorized'!$A:$A,$A28) | N28: =SUMIFS('T12 Categorized'!AJ:AJ,'T12 Categorized'!$A:$A,$A28) | O28: =SUMIFS('T12 Categorized'!AK:AK,'T12 Categorized'!$A:$A,$A28) | P28: =SUMIFS('T12 Categorized'!AL:AL,'T12 Categorized'!$A:$A,$A28) | Q28: =SUMIFS('T12 Categorized'!AM:AM,'T12 Categorized'!$A:$A,$A28)
A29: inter/exte | B29: R&M Interior / Exterior | F29: =SUMIFS('T12 Categorized'!AB:AB,'T12 Categorized'!$A:$A,$A29) | G29: =SUMIFS('T12 Categorized'!AC:AC,'T12 Categorized'!$A:$A,$A29) | H29: =SUMIFS('T12 Categorized'!AD:AD,'T12 Categorized'!$A:$A,$A29) | I29: =SUMIFS('T12 Categorized'!AE:AE,'T12 Categorized'!$A:$A,$A29) | J29: =SUMIFS('T12 Categorized'!AF:AF,'T12 Categorized'!$A:$A,$A29) | K29: =SUMIFS('T12 Categorized'!AG:AG,'T12 Categorized'!$A:$A,$A29) | L29: =SUMIFS('T12 Categorized'!AH:AH,'T12 Categorized'!$A:$A,$A29) | M29: =SUMIFS('T12 Categorized'!AI:AI,'T12 Categorized'!$A:$A,$A29) | N29: =SUMIFS('T12 Categorized'!AJ:AJ,'T12 Categorized'!$A:$A,$A29) | O29: =SUMIFS('T12 Categorized'!AK:AK,'T12 Categorized'!$A:$A,$A29) | P29: =SUMIFS('T12 Categorized'!AL:AL,'T12 Categorized'!$A:$A,$A29) | Q29: =SUMIFS('T12 Categorized'!AM:AM,'T12 Categorized'!$A:$A,$A29)
A30: cont | B30: Contract | F30: =SUMIFS('T12 Categorized'!AB:AB,'T12 Categorized'!$A:$A,$A30) | G30: =SUMIFS('T12 Categorized'!AC:AC,'T12 Categorized'!$A:$A,$A30) | H30: =SUMIFS('T12 Categorized'!AD:AD,'T12 Categorized'!$A:$A,$A30) | I30: =SUMIFS('T12 Categorized'!AE:AE,'T12 Categorized'!$A:$A,$A30) | J30: =SUMIFS('T12 Categorized'!AF:AF,'T12 Categorized'!$A:$A,$A30) | K30: =SUMIFS('T12 Categorized'!AG:AG,'T12 Categorized'!$A:$A,$A30) | L30: =SUMIFS('T12 Categorized'!AH:AH,'T12 Categorized'!$A:$A,$A30) | M30: =SUMIFS('T12 Categorized'!AI:AI,'T12 Categorized'!$A:$A,$A30) | N30: =SUMIFS('T12 Categorized'!AJ:AJ,'T12 Categorized'!$A:$A,$A30) | O30: =SUMIFS('T12 Categorized'!AK:AK,'T12 Categorized'!$A:$A,$A30) | P30: =SUMIFS('T12 Categorized'!AL:AL,'T12 Categorized'!$A:$A,$A30) | Q30: =SUMIFS('T12 Categorized'!AM:AM,'T12 Categorized'!$A:$A,$A30)
A31: Safe | B31: Life Safety / Elevators | F31: =SUMIFS('T12 Categorized'!AB:AB,'T12 Categorized'!$A:$A,$A31) | G31: =SUMIFS('T12 Categorized'!AC:AC,'T12 Categorized'!$A:$A,$A31) | H31: =SUMIFS('T12 Categorized'!AD:AD,'T12 Categorized'!$A:$A,$A31) | I31: =SUMIFS('T12 Categorized'!AE:AE,'T12 Categorized'!$A:$A,$A31) | J31: =SUMIFS('T12 Categorized'!AF:AF,'T12 Categorized'!$A:$A,$A31) | K31: =SUMIFS('T12 Categorized'!AG:AG,'T12 Categorized'!$A:$A,$A31) | L31: =SUMIFS('T12 Categorized'!AH:AH,'T12 Categorized'!$A:$A,$A31) | M31: =SUMIFS('T12 Categorized'!AI:AI,'T12 Categorized'!$A:$A,$A31) | N31: =SUMIFS('T12 Categorized'!AJ:AJ,'T12 Categorized'!$A:$A,$A31) | O31: =SUMIFS('T12 Categorized'!AK:AK,'T12 Categorized'!$A:$A,$A31) | P31: =SUMIFS('T12 Categorized'!AL:AL,'T12 Categorized'!$A:$A,$A31) | Q31: =SUMIFS('T12 Categorized'!AM:AM,'T12 Categorized'!$A:$A,$A31)
A32: HAF | B32: Homeowners Association Fees | F32: =SUMIFS('T12 Categorized'!AB:AB,'T12 Categorized'!$A:$A,$A32) | G32: =SUMIFS('T12 Categorized'!AC:AC,'T12 Categorized'!$A:$A,$A32) | H32: =SUMIFS('T12 Categorized'!AD:AD,'T12 Categorized'!$A:$A,$A32) | I32: =SUMIFS('T12 Categorized'!AE:AE,'T12 Categorized'!$A:$A,$A32) | J32: =SUMIFS('T12 Categorized'!AF:AF,'T12 Categorized'!$A:$A,$A32) | K32: =SUMIFS('T12 Categorized'!AG:AG,'T12 Categorized'!$A:$A,$A32) | L32: =SUMIFS('T12 Categorized'!AH:AH,'T12 Categorized'!$A:$A,$A32) | M32: =SUMIFS('T12 Categorized'!AI:AI,'T12 Categorized'!$A:$A,$A32) | N32: =SUMIFS('T12 Categorized'!AJ:AJ,'T12 Categorized'!$A:$A,$A32) | O32: =SUMIFS('T12 Categorized'!AK:AK,'T12 Categorized'!$A:$A,$A32) | P32: =SUMIFS('T12 Categorized'!AL:AL,'T12 Categorized'!$A:$A,$A32) | Q32: =SUMIFS('T12 Categorized'!AM:AM,'T12 Categorized'!$A:$A,$A32)
A33: UT | B33: Utilities Trash | F33: =SUMIFS('T12 Categorized'!AB:AB,'T12 Categorized'!$A:$A,$A33) | G33: =SUMIFS('T12 Categorized'!AC:AC,'T12 Categorized'!$A:$A,$A33) | H33: =SUMIFS('T12 Categorized'!AD:AD,'T12 Categorized'!$A:$A,$A33) | I33: =SUMIFS('T12 Categorized'!AE:AE,'T12 Categorized'!$A:$A,$A33) | J33: =SUMIFS('T12 Categorized'!AF:AF,'T12 Categorized'!$A:$A,$A33) | K33: =SUMIFS('T12 Categorized'!AG:AG,'T12 Categorized'!$A:$A,$A33) | L33: =SUMIFS('T12 Categorized'!AH:AH,'T12 Categorized'!$A:$A,$A33) | M33: =SUMIFS('T12 Categorized'!AI:AI,'T12 Categorized'!$A:$A,$A33) | N33: =SUMIFS('T12 Categorized'!AJ:AJ,'T12 Categorized'!$A:$A,$A33) | O33: =SUMIFS('T12 Categorized'!AK:AK,'T12 Categorized'!$A:$A,$A33) | P33: =SUMIFS('T12 Categorized'!AL:AL,'T12 Categorized'!$A:$A,$A33) | Q33: =SUMIFS('T12 Categorized'!AM:AM,'T12 Categorized'!$A:$A,$A33)
A34: UWS | B34: Utilities Water Sewer | F34: =SUMIFS('T12 Categorized'!AB:AB,'T12 Categorized'!$A:$A,$A34) | G34: =SUMIFS('T12 Categorized'!AC:AC,'T12 Categorized'!$A:$A,$A34) | H34: =SUMIFS('T12 Categorized'!AD:AD,'T12 Categorized'!$A:$A,$A34) | I34: =SUMIFS('T12 Categorized'!AE:AE,'T12 Categorized'!$A:$A,$A34) | J34: =SUMIFS('T12 Categorized'!AF:AF,'T12 Categorized'!$A:$A,$A34) | K34: =SUMIFS('T12 Categorized'!AG:AG,'T12 Categorized'!$A:$A,$A34) | L34: =SUMIFS('T12 Categorized'!AH:AH,'T12 Categorized'!$A:$A,$A34) | M34: =SUMIFS('T12 Categorized'!AI:AI,'T12 Categorized'!$A:$A,$A34) | N34: =SUMIFS('T12 Categorized'!AJ:AJ,'T12 Categorized'!$A:$A,$A34) | O34: =SUMIFS('T12 Categorized'!AK:AK,'T12 Categorized'!$A:$A,$A34) | P34: =SUMIFS('T12 Categorized'!AL:AL,'T12 Categorized'!$A:$A,$A34) | Q34: =SUMIFS('T12 Categorized'!AM:AM,'T12 Categorized'!$A:$A,$A34)
... A41: site | B41: R&M Site | F41: =SUMIFS('T12 Categorized'!AB:AB,'T12 Categorized'!$A:$A,$A41) | G41: =SUMIFS('T12 Categorized'!AC:AC,'T12 Categorized'!$A:$A,$A41) | H41: =SUMIFS('T12 Categorized'!AD:AD,'T12 Categorized'!$A:$A,$A41) | I41: =SUMIFS('T12 Categorized'!AE:AE,'T12 Categorized'!$A:$A,$A41) | J41: =SUMIFS('T12 Categorized'!AF:AF,'T12 Categorized'!$A:$A,$A41) | K41: =SUMIFS('T12 Categorized'!AG:AG,'T12 Categorized'!$A:$A,$A41) | L41: =SUMIFS('T12 Categorized'!AH:AH,'T12 Categorized'!$A:$A,$A41) | M41: =SUMIFS('T12 Categorized'!AI:AI,'T12 Categorized'!$A:$A,$A41) | N41: =SUMIFS('T12 Categorized'!AJ:AJ,'T12 Categorized'!$A:$A,$A41) | O41: =SUMIFS('T12 Categorized'!AK:AK,'T12 Categorized'!$A:$A,$A41) | P41: =SUMIFS('T12 Categorized'!AL:AL,'T12 Categorized'!$A:$A,$A41) | Q41: =SUMIFS('T12 Categorized'!AM:AM,'T12 Categorized'!$A:$A,$A41)
B42: Operating Expenses | F42: =SUM(F23:F41) | G42: =SUM(G23:G41) | H42: =SUM(H23:H41) | I42: =SUM(I23:I41) | J42: =SUM(J23:J41) | K42: =SUM(K23:K41) | L42: =SUM(L23:L41) | M42: =SUM(M23:M41) | ... Q42: =SUM(Q23:Q41)
B44: Net Operating Income | F44: =F20-F42 | G44: =G20-G42 | H44: =H20-H42 | I44: =I20-I42 | J44: =J20-J42 | K44: =K20-K42 | L44: =L20-L42 | M44: =M20-M42 | ... Q44: =Q20-Q42
B46: Non-Operating Revenue
A47: dispro | B47: Disposition Proceeds | F47: =SUMIFS('T12 Categorized'!AB:AB,'T12 Categorized'!$A:$A,$A47) | G47: =SUMIFS('T12 Categorized'!AC:AC,'T12 Categorized'!$A:$A,$A47) | H47: =SUMIFS('T12 Categorized'!AD:AD,'T12 Categorized'!$A:$A,$A47) | I47: =SUMIFS('T12 Categorized'!AE:AE,'T12 Categorized'!$A:$A,$A47) | J47: =SUMIFS('T12 Categorized'!AF:AF,'T12 Categorized'!$A:$A,$A47) | K47: =SUMIFS('T12 Categorized'!AG:AG,'T12 Categorized'!$A:$A,$A47) | L47: =SUMIFS('T12 Categorized'!AH:AH,'T12 Categorized'!$A:$A,$A47) | M47: =SUMIFS('T12 Categorized'!AI:AI,'T12 Categorized'!$A:$A,$A47) | N47: =SUMIFS('T12 Categorized'!AJ:AJ,'T12 Categorized'!$A:$A,$A47) | O47: =SUMIFS('T12 Categorized'!AK:AK,'T12 Categorized'!$A:$A,$A47) | P47: =SUMIFS('T12 Categorized'!AL:AL,'T12 Categorized'!$A:$A,$A47) | Q47: =SUMIFS('T12 Categorized'!AM:AM,'T12 Categorized'!$A:$A,$A47)
B48: Non-Operating Revenue | F48: =SUM(F47:F47) | G48: =SUM(G47:G47) | H48: =SUM(H47:H47) | I48: =SUM(I47:I47) | J48: =SUM(J47:J47) | K48: =SUM(K47:K47) | L48: =SUM(L47:L47) | M48: =SUM(M47:M47) | ... Q48: =SUM(Q47:Q47)
B50: Non-Operating Expenses
A51: rd | B51: Replacement Reserve Deposits | F51: =SUMIFS('T12 Categorized'!AB:AB,'T12 Categorized'!$A:$A,$A51) | G51: =SUMIFS('T12 Categorized'!AC:AC,'T12 Categorized'!$A:$A,$A51) | H51: =SUMIFS('T12 Categorized'!AD:AD,'T12 Categorized'!$A:$A,$A51) | I51: =SUMIFS('T12 Categorized'!AE:AE,'T12 Categorized'!$A:$A,$A51) | J51: =SUMIFS('T12 Categorized'!AF:AF,'T12 Categorized'!$A:$A,$A51) | K51: =SUMIFS('T12 Categorized'!AG:AG,'T12 Categorized'!$A:$A,$A51) | L51: =SUMIFS('T12 Categorized'!AH:AH,'T12 Categorized'!$A:$A,$A51) | M51: =SUMIFS('T12 Categorized'!AI:AI,'T12 Categorized'!$A:$A,$A51) | N51: =SUMIFS('T12 Categorized'!AJ:AJ,'T12 Categorized'!$A:$A,$A51) | O51: =SUMIFS('T12 Categorized'!AK:AK,'T12 Categorized'!$A:$A,$A51) | P51: =SUMIFS('T12 Categorized'!AL:AL,'T12 Categorized'!$A:$A,$A51) | Q51: =SUMIFS('T12 Categorized'!AM:AM,'T12 Categorized'!$A:$A,$A51)
A52: capx | B52: Capital Improvements | F52: =SUMIFS('T12 Categorized'!AB:AB,'T12 Categorized'!$A:$A,$A52) | G52: =SUMIFS('T12 Categorized'!AC:AC,'T12 Categorized'!$A:$A,$A52) | H52: =SUMIFS('T12 Categorized'!AD:AD,'T12 Categorized'!$A:$A,$A52) | I52: =SUMIFS('T12 Categorized'!AE:AE,'T12 Categorized'!$A:$A,$A52) | J52: =SUMIFS('T12 Categorized'!AF:AF,'T12 Categorized'!$A:$A,$A52) | K52: =SUMIFS('T12 Categorized'!AG:AG,'T12 Categorized'!$A:$A,$A52) | L52: =SUMIFS('T12 Categorized'!AH:AH,'T12 Categorized'!$A:$A,$A52) | M52: =SUMIFS('T12 Categorized'!AI:AI,'T12 Categorized'!$A:$A,$A52) | N52: =SUMIFS('T12 Categorized'!AJ:AJ,'T12 Categorized'!$A:$A,$A52) | O52: =SUMIFS('T12 Categorized'!AK:AK,'T12 Categorized'!$A:$A,$A52) | P52: =SUMIFS('T12 Categorized'!AL:AL,'T12 Categorized'!$A:$A,$A52) | Q52: =SUMIFS('T12 Categorized'!AM:AM,'T12 Categorized'!$A:$A,$A52)
A53: aex | B53: Appliance Expenditures | F53: =SUMIFS('T12 Categorized'!AB:AB,'T12 Categorized'!$A:$A,$A53) | G53: =SUMIFS('T12 Categorized'!AC:AC,'T12 Categorized'!$A:$A,$A53) | H53: =SUMIFS('T12 Categorized'!AD:AD,'T12 Categorized'!$A:$A,$A53) | I53: =SUMIFS('T12 Categorized'!AE:AE,'T12 Categorized'!$A:$A,$A53) | J53: =SUMIFS('T12 Categorized'!AF:AF,'T12 Categorized'!$A:$A,$A53) | K53: =SUMIFS('T12 Categorized'!AG:AG,'T12 Categorized'!$A:$A,$A53) | L53: =SUMIFS('T12 Categorized'!AH:AH,'T12 Categorized'!$A:$A,$A53) | M53: =SUMIFS('T12 Categorized'!AI:AI,'T12 Categorized'!$A:$A,$A53) | N53: =SUMIFS('T12 Categorized'!AJ:AJ,'T12 Categorized'!$A:$A,$A53) | O53: =SUMIFS('T12 Categorized'!AK:AK,'T12 Categorized'!$A:$A,$A53) | P53: =SUMIFS('T12 Categorized'!AL:AL,'T12 Categorized'!$A:$A,$A53) | Q53: =SUMIFS('T12 Categorized'!AM:AM,'T12 Categorized'!$A:$A,$A53)
A54: ece | B54: Extraordinary Capital Expenditure | F54: =SUMIFS('T12 Categorized'!AB:AB,'T12 Categorized'!$A:$A,$A54) | G54: =SUMIFS('T12 Categorized'!AC:AC,'T12 Categorized'!$A:$A,$A54) | H54: =SUMIFS('T12 Categorized'!AD:AD,'T12 Categorized'!$A:$A,$A54) | I54: =SUMIFS('T12 Categorized'!AE:AE,'T12 Categorized'!$A:$A,$A54) | J54: =SUMIFS('T12 Categorized'!AF:AF,'T12 Categorized'!$A:$A,$A54) | K54: =SUMIFS('T12 Categorized'!AG:AG,'T12 Categorized'!$A:$A,$A54) | L54: =SUMIFS('T12 Categorized'!AH:AH,'T12 Categorized'!$A:$A,$A54) | M54: =SUMIFS('T12 Categorized'!AI:AI,'T12 Categorized'!$A:$A,$A54) | N54: =SUMIFS('T12 Categorized'!AJ:AJ,'T12 Categorized'!$A:$A,$A54) | O54: =SUMIFS('T12 Categorized'!AK:AK,'T12 Categorized'!$A:$A,$A54) | P54: =SUMIFS('T12 Categorized'!AL:AL,'T12 Categorized'!$A:$A,$A54) | Q54: =SUMIFS('T12 Categorized'!AM:AM,'T12 Categorized'!$A:$A,$A54)
A55: tird | B55: TI&LC Reserve Deposits | F55: =SUMIFS('T12 Categorized'!AB:AB,'T12 Categorized'!$A:$A,$A55) | G55: =SUMIFS('T12 Categorized'!AC:AC,'T12 Categorized'!$A:$A,$A55) | H55: =SUMIFS('T12 Categorized'!AD:AD,'T12 Categorized'!$A:$A,$A55) | I55: =SUMIFS('T12 Categorized'!AE:AE,'T12 Categorized'!$A:$A,$A55) | J55: =SUMIFS('T12 Categorized'!AF:AF,'T12 Categorized'!$A:$A,$A55) | K55: =SUMIFS('T12 Categorized'!AG:AG,'T12 Categorized'!$A:$A,$A55) | L55: =SUMIFS('T12 Categorized'!AH:AH,'T12 Categorized'!$A:$A,$A55) | M55: =SUMIFS('T12 Categorized'!AI:AI,'T12 Categorized'!$A:$A,$A55) | N55: =SUMIFS('T12 Categorized'!AJ:AJ,'T12 Categorized'!$A:$A,$A55) | O55: =SUMIFS('T12 Categorized'!AK:AK,'T12 Categorized'!$A:$A,$A55) | P55: =SUMIFS('T12 Categorized'!AL:AL,'T12 Categorized'!$A:$A,$A55) | Q55: =SUMIFS('T12 Categorized'!AM:AM,'T12 Categorized'!$A:$A,$A55)
A56: tirw | B56: TI&LC Reserve Withdrawls | F56: =SUMIFS('T12 Categorized'!AB:AB,'T12 Categorized'!$A:$A,$A56) | G56: =SUMIFS('T12 Categorized'!AC:AC,'T12 Categorized'!$A:$A,$A56) | H56: =SUMIFS('T12 Categorized'!AD:AD,'T12 Categorized'!$A:$A,$A56) | I56: =SUMIFS('T12 Categorized'!AE:AE,'T12 Categorized'!$A:$A,$A56) | J56: =SUMIFS('T12 Categorized'!AF:AF,'T12 Categorized'!$A:$A,$A56) | K56: =SUMIFS('T12 Categorized'!AG:AG,'T12 Categorized'!$A:$A,$A56) | L56: =SUMIFS('T12 Categorized'!AH:AH,'T12 Categorized'!$A:$A,$A56) | M56: =SUMIFS('T12 Categorized'!AI:AI,'T12 Categorized'!$A:$A,$A56) | N56: =SUMIFS('T12 Categorized'!AJ:AJ,'T12 Categorized'!$A:$A,$A56) | O56: =SUMIFS('T12 Categorized'!AK:AK,'T12 Categorized'!$A:$A,$A56) | P56: =SUMIFS('T12 Categorized'!AL:AL,'T12 Categorized'!$A:$A,$A56) | Q56: =SUMIFS('T12 Categorized'!AM:AM,'T12 Categorized'!$A:$A,$A56)
A57: tiae | B57: TI&LC Actual Expenditures | F57: =SUMIFS('T12 Categorized'!AB:AB,'T12 Categorized'!$A:$A,$A57) | G57: =SUMIFS('T12 Categorized'!AC:AC,'T12 Categorized'!$A:$A,$A57) | H57: =SUMIFS('T12 Categorized'!AD:AD,'T12 Categorized'!$A:$A,$A57) | I57: =SUMIFS('T12 Categorized'!AE:AE,'T12 Categorized'!$A:$A,$A57) | J57: =SUMIFS('T12 Categorized'!AF:AF,'T12 Categorized'!$A:$A,$A57) | K57: =SUMIFS('T12 Categorized'!AG:AG,'T12 Categorized'!$A:$A,$A57) | L57: =SUMIFS('T12 Categorized'!AH:AH,'T12 Categorized'!$A:$A,$A57) | M57: =SUMIFS('T12 Categorized'!AI:AI,'T12 Categorized'!$A:$A,$A57) | N57: =SUMIFS('T12 Categorized'!AJ:AJ,'T12 Categorized'!$A:$A,$A57) | O57: =SUMIFS('T12 Categorized'!AK:AK,'T12 Categorized'!$A:$A,$A57) | P57: =SUMIFS('T12 Categorized'!AL:AL,'T12 Categorized'!$A:$A,$A57) | Q57: =SUMIFS('T12 Categorized'!AM:AM,'T12 Categorized'!$A:$A,$A57)
A58: intex | B58: Interest | F58: =SUMIFS('T12 Categorized'!AB:AB,'T12 Categorized'!$A:$A,$A58) | G58: =SUMIFS('T12 Categorized'!AC:AC,'T12 Categorized'!$A:$A,$A58) | H58: =SUMIFS('T12 Categorized'!AD:AD,'T12 Categorized'!$A:$A,$A58) | I58: =SUMIFS('T12 Categorized'!AE:AE,'T12 Categorized'!$A:$A,$A58) | J58: =SUMIFS('T12 Categorized'!AF:AF,'T12 Categorized'!$A:$A,$A58) | K58: =SUMIFS('T12 Categorized'!AG:AG,'T12 Categorized'!$A:$A,$A58) | L58: =SUMIFS('T12 Categorized'!AH:AH,'T12 Categorized'!$A:$A,$A58) | M58: =SUMIFS('T12 Categorized'!AI:AI,'T12 Categorized'!$A:$A,$A58) | N58: =SUMIFS('T12 Categorized'!AJ:AJ,'T12 Categorized'!$A:$A,$A58) | O58: =SUMIFS('T12 Categorized'!AK:AK,'T12 Categorized'!$A:$A,$A58) | P58: =SUMIFS('T12 Categorized'!AL:AL,'T12 Categorized'!$A:$A,$A58) | Q58: =SUMIFS('T12 Categorized'!AM:AM,'T12 Categorized'!$A:$A,$A58)
A59: prin | B59: Principal | F59: =SUMIFS('T12 Categorized'!AB:AB,'T12 Categorized'!$A:$A,$A59) | G59: =SUMIFS('T12 Categorized'!AC:AC,'T12 Categorized'!$A:$A,$A59) | H59: =SUMIFS('T12 Categorized'!AD:AD,'T12 Categorized'!$A:$A,$A59) | I59: =SUMIFS('T12 Categorized'!AE:AE,'T12 Categorized'!$A:$A,$A59) | J59: =SUMIFS('T12 Categorized'!AF:AF,'T12 Categorized'!$A:$A,$A59) | K59: =SUMIFS('T12 Categorized'!AG:AG,'T12 Categorized'!$A:$A,$A59) | L59: =SUMIFS('T12 Categorized'!AH:AH,'T12 Categorized'!$A:$A,$A59) | M59: =SUMIFS('T12 Categorized'!AI:AI,'T12 Categorized'!$A:$A,$A59) | N59: =SUMIFS('T12 Categorized'!AJ:AJ,'T12 Categorized'!$A:$A,$A59) | O59: =SUMIFS('T12 Categorized'!AK:AK,'T12 Categorized'!$A:$A,$A59) | P59: =SUMIFS('T12 Categorized'!AL:AL,'T12 Categorized'!$A:$A,$A59) | Q59: =SUMIFS('T12 Categorized'!AM:AM,'T12 Categorized'!$A:$A,$A59)
A60: draw | B60: Loan Draws | F60: =SUMIFS('T12 Categorized'!AB:AB,'T12 Categorized'!$A:$A,$A60) | G60: =SUMIFS('T12 Categorized'!AC:AC,'T12 Categorized'!$A:$A,$A60) | H60: =SUMIFS('T12 Categorized'!AD:AD,'T12 Categorized'!$A:$A,$A60) | I60: =SUMIFS('T12 Categorized'!AE:AE,'T12 Categorized'!$A:$A,$A60) | J60: =SUMIFS('T12 Categorized'!AF:AF,'T12 Categorized'!$A:$A,$A60) | K60: =SUMIFS('T12 Categorized'!AG:AG,'T12 Categorized'!$A:$A,$A60) | L60: =SUMIFS('T12 Categorized'!AH:AH,'T12 Categorized'!$A:$A,$A60) | M60: =SUMIFS('T12 Categorized'!AI:AI,'T12 Categorized'!$A:$A,$A60) | N60: =SUMIFS('T12 Categorized'!AJ:AJ,'T12 Categorized'!$A:$A,$A60) | O60: =SUMIFS('T12 Categorized'!AK:AK,'T12 Categorized'!$A:$A,$A60) | P60: =SUMIFS('T12 Categorized'!AL:AL,'T12 Categorized'!$A:$A,$A60) | Q60: =SUMIFS('T12 Categorized'!AM:AM,'T12 Categorized'!$A:$A,$A60)
A61: repay | B61: Loan Repayments | F61: =SUMIFS('T12 Categorized'!AB:AB,'T12 Categorized'!$A:$A,$A61) | G61: =SUMIFS('T12 Categorized'!AC:AC,'T12 Categorized'!$A:$A,$A61) | H61: =SUMIFS('T12 Categorized'!AD:AD,'T12 Categorized'!$A:$A,$A61) | I61: =SUMIFS('T12 Categorized'!AE:AE,'T12 Categorized'!$A:$A,$A61) | J61: =SUMIFS('T12 Categorized'!AF:AF,'T12 Categorized'!$A:$A,$A61) | K61: =SUMIFS('T12 Categorized'!AG:AG,'T12 Categorized'!$A:$A,$A61) | L61: =SUMIFS('T12 Categorized'!AH:AH,'T12 Categorized'!$A:$A,$A61) | M61: =SUMIFS('T12 Categorized'!AI:AI,'T12 Categorized'!$A:$A,$A61) | N61: =SUMIFS('T12 Categorized'!AJ:AJ,'T12 Categorized'!$A:$A,$A61) | O61: =SUMIFS('T12 Categorized'!AK:AK,'T12 Categorized'!$A:$A,$A61) | P61: =SUMIFS('T12 Categorized'!AL:AL,'T12 Categorized'!$A:$A,$A61) | Q61: =SUMIFS('T12 Categorized'!AM:AM,'T12 Categorized'!$A:$A,$A61)
A62: othdf | B62: Other Debt Fees | F62: =SUMIFS('T12 Categorized'!AB:AB,'T12 Categorized'!$A:$A,$A62) | G62: =SUMIFS('T12 Categorized'!AC:AC,'T12 Categorized'!$A:$A,$A62) | H62: =SUMIFS('T12 Categorized'!AD:AD,'T12 Categorized'!$A:$A,$A62) | I62: =SUMIFS('T12 Categorized'!AE:AE,'T12 Categorized'!$A:$A,$A62) | J62: =SUMIFS('T12 Categorized'!AF:AF,'T12 Categorized'!$A:$A,$A62) | K62: =SUMIFS('T12 Categorized'!AG:AG,'T12 Categorized'!$A:$A,$A62) | L62: =SUMIFS('T12 Categorized'!AH:AH,'T12 Categorized'!$A:$A,$A62) | M62: =SUMIFS('T12 Categorized'!AI:AI,'T12 Categorized'!$A:$A,$A62) | N62: =SUMIFS('T12 Categorized'!AJ:AJ,'T12 Categorized'!$A:$A,$A62) | O62: =SUMIFS('T12 Categorized'!AK:AK,'T12 Categorized'!$A:$A,$A62) | P62: =SUMIFS('T12 Categorized'!AL:AL,'T12 Categorized'!$A:$A,$A62) | Q62: =SUMIFS('T12 Categorized'!AM:AM,'T12 Categorized'!$A:$A,$A62)
... A72: onoe | B72: Other Non-Operating Expense | F72: =SUMIFS('T12 Categorized'!AB:AB,'T12 Categorized'!$A:$A,$A72) | G72: =SUMIFS('T12 Categorized'!AC:AC,'T12 Categorized'!$A:$A,$A72) | H72: =SUMIFS('T12 Categorized'!AD:AD,'T12 Categorized'!$A:$A,$A72) | I72: =SUMIFS('T12 Categorized'!AE:AE,'T12 Categorized'!$A:$A,$A72) | J72: =SUMIFS('T12 Categorized'!AF:AF,'T12 Categorized'!$A:$A,$A72) | K72: =SUMIFS('T12 Categorized'!AG:AG,'T12 Categorized'!$A:$A,$A72) | L72: =SUMIFS('T12 Categorized'!AH:AH,'T12 Categorized'!$A:$A,$A72) | M72: =SUMIFS('T12 Categorized'!AI:AI,'T12 Categorized'!$A:$A,$A72) | N72: =SUMIFS('T12 Categorized'!AJ:AJ,'T12 Categorized'!$A:$A,$A72) | O72: =SUMIFS('T12 Categorized'!AK:AK,'T12 Categorized'!$A:$A,$A72) | P72: =SUMIFS('T12 Categorized'!AL:AL,'T12 Categorized'!$A:$A,$A72) | Q72: =SUMIFS('T12 Categorized'!AM:AM,'T12 Categorized'!$A:$A,$A72)
B73: Non-Operating Expenses | F73: =SUM(F51:F72) | G73: =SUM(G51:G72) | H73: =SUM(H51:H72) | I73: =SUM(I51:I72) | J73: =SUM(J51:J72) | K73: =SUM(K51:K72) | L73: =SUM(L51:L72) | M73: =SUM(M51:M72) | ... Q73: =SUM(Q51:Q72)
B75: Net Income | F75: =F44+F48-F73 | G75: =G44+G48-G73 | H75: =H44+H48-H73 | I75: =I44+I48-I73 | J75: =J44+J48-J73 | K75: =K44+K48-K73 | L75: =L44+L48-L73 | M75: =M44+M48-M73 | ... Q75: =Q44+Q48-Q73
B77: Generated 06/19/2026 — live SUMIFS over 'T12 Categorized' code column

Sheet Rent Roll (One-Line)
A1: Unit No. | B1: Floor Plan | C1: Net sf | D1: Bed | E1: Bath | F1: Lease Type | G1: Occupancy Status | H1: Market Rent | I1: Contractual Rent | J1: Net Effective Rent | K1: Lease Start Date | L1: Lease Expiration | M1: Move In Date | O1: Scheduled Charges by Code (monthly $)
O2: rent | P2: techfee | Q2: garage | R2: empdisc | S2: conc/renew | T2: petrent | U2: package | V2: carport | W2: conc/other | X2: eviction | Y2: trash/doortodoor | Z2: mtm
A3: 0111 | B3: A2 | C3: 777 | D3: 1 | E3: 1 | F3: Market | G3: Occupied | H3: 1127 | I3: 1185 | J3: 1185 | K3: 09/13/2025 | L3: 09/12/2026 | M3: 09/13/2025 | O3: 1185 | U3: 1
A4: 0112 | B4: A2R | C4: 777 | D4: 1 | E4: 1 | F4: Market | G4: Occupied | H4: 1327 | I4: 1258 | J4: 1258 | K4: 06/09/2025 | L4: 08/08/2026 | M4: 06/09/2025 | O4: 1258 | U4: 1
A5: 0113 | B5: A2 | C5: 777 | D5: 1 | E5: 1 | F5: Market | G5: Occupied | H5: 1187 | I5: 1091 | J5: 1091 | K5: 01/20/2026 | L5: 04/12/2027 | M5: 01/20/2026 | O5: 1091 | P5: 35 | U5: 3
A6: 0114 | B6: A2 | C6: 777 | D6: 1 | E6: 1 | F6: Market | G6: Occupied | H6: 1127 | I6: 1222 | J6: 1222 | K6: 08/30/2025 | L6: 09/29/2026 | M6: 08/30/2025 | O6: 1222 | U6: 1
A7: 0115 | B7: A2R | C7: 777 | D7: 1 | E7: 1 | F7: Market | G7: Occupied | H7: 1327 | I7: 1262 | J7: 1262 | K7: 01/16/2026 | L7: 04/22/2027 | M7: 01/16/2026 | O7: 1262 | P7: 35 | U7: 3
A8: 0116 | B8: A2 | C8: 777 | D8: 1 | E8: 1 | F8: Market | G8: Occupied | H8: 1127 | I8: 1230 | J8: 1230 | K8: 05/15/2026 | L8: 07/14/2027 | M8: 04/15/2025 | O8: 1230 | P8: 35 | S8: -300 | U8: 3
A9: 0117 | B9: A2R | C9: 777 | D9: 1 | E9: 1 | F9: Market | G9: Occupied | H9: 1327 | I9: 1242 | J9: 1242 | K9: 02/06/2026 | L9: 05/06/2027 | M9: 02/06/2026 | O9: 1242 | P9: 35 | U9: 3
A10: 0118 | B10: A2 | C10: 777 | D10: 1 | E10: 1 | F10: Market | G10: Occupied | H10: 1167 | I10: 1352 | J10: 1352 | K10: 08/19/2025 | L10: 11/18/2026 | M10: 01/19/2022 | O10: 1352 | U10: 1
A11: 0121 | B11: A2 | C11: 777 | D11: 1 | E11: 1 | F11: Market | G11: Vacant | H11: 1167 | I11: 0 | J11: 0
A12: 0122 | B12: A2 | C12: 777 | D12: 1 | E12: 1 | F12: Market | G12: Occupied | H12: 1107 | I12: 1260 | J12: 1260 | K12: 01/09/2026 | L12: 01/15/2027 | M12: 09/02/2023 | O12: 1260 | U12: 3
A13: 0123 | B13: A2R | C13: 777 | D13: 1 | E13: 1 | F13: Market | G13: Vacant | H13: 1307 | I13: 0 | J13: 0
A14: 0124 | B14: A2 | C14: 777 | D14: 1 | E14: 1 | F14: Market | G14: Occupied | H14: 1107 | I14: 1130 | J14: 1130 | K14: 05/08/2026 | L14: 08/07/2027 | M14: 02/15/2025 | O14: 1130 | P14: 35 | S14: -300 | U14: 3
A15: 0125 | B15: A2 | C15: 777 | D15: 1 | E15: 1 | F15: Market | G15: Occupied | H15: 1107 | I15: 1346 | J15: 1346 | K15: 08/20/2025 | L15: 08/26/2026 | M15: 05/13/2022 | O15: 1346 | U15: 1
A16: 0126 | B16: A2 | C16: 777 | D16: 1 | E16: 1 | F16: Market | G16: Occupied | H16: 1107 | I16: 1202 | J16: 1202 | K16: 08/23/2025 | L16: 09/22/2026 | M16: 08/23/2025 | O16: 1202 | U16: 1
A17: 0127 | B17: A2R | C17: 777 | D17: 1 | E17: 1 | F17: Market | G17: Occupied | H17: 1307 | I17: 1443 | J17: 1443 | K17: 08/19/2025 | L17: 08/25/2026 | M17: 05/19/2023 | O17: 1443 | U17: 1
A18: 0128 | B18: A2 | C18: 777 | D18: 1 | E18: 1 | F18: Market | G18: Occupied | H18: 1107 | I18: 1243 | J18: 1243 | K18: 12/03/2025 | L18: 03/02/2027 | M18: 12/03/2025 | O18: 1243 | U18: 1
A19: 0132 | B19: A2R | C19: 777 | D19: 1 | E19: 1 | F19: Market | G19: Occupied | H19: 1307 | I19: 1353 | J19: 1353 | K19: 03/27/2025 | L19: 06/26/2026 | M19: 03/27/2025 | O19: 1353 | T19: 30 | U19: 1
A20: 0133 | B20: A2R | C20: 777 | D20: 1 | E20: 1 | F20: Market | G20: Occupied | H20: 1307 | I20: 1435 | J20: 1435 | K20: 04/20/2026 | L20: 07/19/2027 | M20: 10/20/2023 | O20: 1435 | P20: 35 | U20: 3
A21: 0136 | B21: A2R | C21: 777 | D21: 1 | E21: 1 | F21: Market | G21: Occupied | H21: 1307 | I21: 1139 | J21: 1139 | K21: 11/28/2025 | L21: 02/20/2027 | M21: 11/28/2025 | O21: 1139 | U21: 3
A22: 0137 | B22: A2 | C22: 777 | D22: 1 | E22: 1 | F22: Market | G22: Occupied | H22: 1107 | I22: 1186 | J22: 1186 | K22: 06/15/2025 | L22: 08/14/2026 | M22: 06/15/2025 | O22: 1186 | U22: 1
A23: 0211 | B23: B4 | C23: 1187 | D23: 2 | E23: 2 | F23: Market | G23: Occupied | H23: 1691 | I23: 1743 | J23: 1743 | K23: 09/18/2025 | L23: 09/17/2026 | M23: 08/18/2020 | O23: 1743 | T23: 40 | U23: 1
A24: 0212 | B24: B1 | C24: 947 | D24: 2 | E24: 2 | F24: Market | G24: Occupied | H24: 1427 | I24: 1465 | J24: 1465 | K24: 06/23/2025 | L24: 09/22/2026 | M24: 06/23/2025 | O24: 1465 | U24: 1
A25: 0213 | B25: B1 | C25: 947 | D25: 2 | E25: 2 | F25: Market | G25: Occupied | H25: 1427 | I25: 1464 | J25: 1464 | K25: 02/17/2026 | L25: 03/23/2027 | M25: 11/17/2023 | O25: 1464 | U25: 3
A26: 0214 | B26: B4 | C26: 1187 | D26: 2 | E26: 2 | F26: Market | G26: Occupied | H26: 1691 | I26: 1527 | J26: 1527 | K26: 05/05/2025 | L26: 08/04/2026 | M26: 05/05/2025 | O26: 1527 | Q26: 125 | U26: 1
A27: 0215 | B27: B4 | C27: 1187 | D27: 2 | E27: 2 | F27: Market | G27: Occupied | H27: 1691 | I27: 1456 | J27: 1456 | K27: 11/22/2025 | L27: 01/21/2027 | M27: 11/22/2025 | O27: 1456 | U27: 3
A28: 0216 | B28: B1R | C28: 947 | D28: 2 | E28: 2 | F28: Market | G28: Occupied | H28: 1552 | I28: 1738 | J28: 1738 | K28: 05/06/2025 | L28: 06/05/2026 | M28: 02/01/2024 | O28: 1738 | T28: 40 | U28: 1
A29: 0217 | B29: B1R | C29: 947 | D29: 2 | E29: 2 | F29: Market | G29: Occupied | H29: 1552 | I29: 1467 | J29: 1467 | K29: 10/08/2025 | L29: 10/07/2026 | M29: 10/08/2025 | O29: 1467 | U29: 1
A30: 0218 | B30: B4 | C30: 1187 | D30: 2 | E30: 2 | F30: Market | G30: Occupied | H30: 1691 | I30: 1723 | J30: 1723 | K30: 05/02/2025 | L30: 07/26/2026 | M30: 01/27/2024 | O30: 1723 | U30: 1
A31: 0221 | B31: B4 | C31: 1187 | D31: 2 | E31: 2 | F31: Market | G31: Occupied | H31: 1596 | I31: 1396 | J31: 1396 | K31: 07/16/2025 | L31: 10/15/2026 | M31: 07/16/2025 | O31: 1396 | U31: 1
A32: 0222 | B32: B1 | C32: 947 | D32: 2 | E32: 2 | F32: Market | G32: Occupied | H32: 1332 | I32: 1437 | J32: 1437 | K32: 07/09/2025 | L32: 07/08/2026 | M32: 03/09/2023 | O32: 1437 | T32: 30 | U32: 1
A33: 0223 | B33: B1 | C33: 947 | D33: 2 | E33: 2 | F33: Market | G33: Occupied | H33: 1332 | I33: 1410 | J33: 1410 | K33: 11/12/2025 | L33: 11/11/2026 | M33: 06/28/2018 | O33: 1410 | U33: 1
A34: 0224 | B34: B4 | C34: 1187 | D34: 2 | E34: 2 | F34: Market | G34: Occupied | H34: 1596 | I34: 1458 | J34: 1458 | K34: 03/26/2026 | L34: 05/25/2027 | M34: 12/28/2024 | O34: 1458 | P34: 35 | U34: 3
A35: 0225 | B35: B4 | C35: 1187 | D35: 2 | E35: 2 | F35: Market | G35: Occupied | H35: 1636 | I35: 1538 | J35: 1538 | K35: 04/25/2025 | L35: 07/24/2026 | M35: 04/25/2025 | O35: 1538 | Q35: 100 | U35: 1
A36: 0226 | B36: B1 | C36: 947 | D36: 2 | E36: 2 | F36: Market | G36: Occupied | H36: 1332 | I36: 1673 | J36: 1673 | K36: 10/31/2025 | L36: 10/30/2026 | M36: 05/24/2022 | O36: 1673 | Q36: 100 | U36: 1
A37: 0227 | B37: B1 | C37: 947 | D37: 2 | E37: 2 | F37: Market | G37: Occupied | H37: 1332 | I37: 1466 | J37: 1466 | K37: 07/07/2025 | L37: 07/06/2026 | M37: 07/07/2024 | O37: 1466 | Q37: 75 | U37: 1
A38: 0228 | B38: B4R | C38: 1187 | D38: 2 | E38: 2 | F38: Market | G38: Occupied | H38: 1796 | I38: 1515 | J38: 1515 | K38: 02/14/2026 | L38: 03/06/2027 | M38: 11/14/2024 | O38: 1515 | T38: 45 | U38: 3
A39: 0232 | B39: B1 | C39: 947 | D39: 2 | E39: 2 | F39: Market | G39: Occupied | H39: 1332 | I39: 1247 | J39: 1247 | K39: 10/04/2025 | L39: 11/03/2026 | M39: 10/04/2025 | O39: 1247 | U39: 1
A40: 0233 | B40: B1R | C40: 947 | D40: 2 | E40: 2 | F40: Market | G40: Vacant | H40: 1532 | I40: 0 | J40: 0
A41: 0236 | B41: B1 | C41: 947 | D41: 2 | E41: 2 | F41: Market | G41: Occupied | H41: 1332 | I41: 1384 | J41: 1384 | K41: 10/25/2025 | L41: 11/24/2026 | M41: 10/25/2019 | O41: 1384 | Q41: 100 | U41: 1
A42: 0237 | B42: B1R | C42: 947 | D42: 2 | E42: 2 | F42: Market | G42: Occupied | H42: 1532 | I42: 1422 | J42: 1422 | K42: 04/16/2025 | L42: 07/14/2026 | M42: 04/16/2025 | O42: 1422 | U42: 1
A43: 0321 | B43: B2 | C43: 1040 | D43: 2 | E43: 2 | F43: Market | G43: Occupied | H43: 1536 | I43: 1519 | J43: 1519 | K43: 08/08/2025 | L43: 11/07/2026 | M43: 08/08/2025 | O43: 1519 | U43: 1
A44: 0411 | B44: B4 | C44: 1187 | D44: 2 | E44: 2 | F44: Market | G44: Occupied | H44: 1656 | I44: 1665 | J44: 1665 | K44: 09/08/2025 | L44: 10/07/2026 | M44: 06/08/2024 | O44: 1665 | Q44: 100 | U44: 1
A45: 0412 | B45: B1R | C45: 947 | D45: 2 | E45: 2 | F45: Market | G45: Occupied | H45: 1552 | I45: 1571 | J45: 1571 | K45: 06/19/2025 | L45: 07/18/2026 | M45: 06/19/2025 | O45: 1571 | U45: 1
A46: 0413 | B46: B1 | C46: 947 | D46: 2 | E46: 2 | F46: Market | G46: Occupied | H46: 1392 | I46: 1381 | J46: 1381 | K46: 10/24/2025 | L46: 01/23/2027 | M46: 10/24/2025 | O46: 1381 | U46: 1 | V46: 50
A47: 0414 | B47: B4 | C47: 1187 | D47: 2 | E47: 2 | F47: Market | G47: Occupied | H47: 1616 | I47: 1570 | J47: 1570 | K47: 08/27/2025 | L47: 09/24/2026 | M47: 08/22/2025 | O47: 1570 | U47: 1
A48: 0415 | B48: B4R | C48: 1187 | D48: 2 | E48: 2 | F48: Market | G48: Occupied | H48: 1816 | I48: 1746 | J48: 1746 | K48: 05/30/2025 | L48: 07/29/2026 | M48: 05/30/2025 | O48: 1746 | U48: 1
A49: 0416 | B49: B1 | C49: 947 | D49: 2 | E49: 2 | F49: Market | G49: Occupied | H49: 1352 | I49: 1262 | J49: 1262 | K49: 07/14/2025 | L49: 10/13/2026 | M49: 07/14/2025 | O49: 1262 | T49: 30 | U49: 1
A50: 0417 | B50: B1R | C50: 947 | D50: 2 | E50: 2 | F50: Market | G50: Vacant | H50: 1552 | I50: 0 | J50: 0
A51: 0418 | B51: B4 | C51: 1187 | D51: 2 | E51: 2 | F51: Market | G51: Occupied | H51: 1616 | I51: 1517 | J51: 1517 | K51: 10/01/2025 | L51: 12/31/2026 | M51: 03/24/2015 | O51: 1517 | U51: 1
A52: 0421 | B52: B4 | C52: 1187 | D52: 2 | E52: 2 | F52: Market | G52: Occupied | H52: 1636 | I52: 1472 | J52: 1472 | K52: 04/22/2026 | L52: 05/21/2027 | M52: 01/24/2025 | O52: 1472 | P52: 35 | S52: -300 | U52: 3
A53: 0422 | B53: B1R | C53: 947 | D53: 2 | E53: 2 | F53: Market | G53: Occupied | H53: 1532 | I53: 1621 | J53: 1621 | K53: 06/29/2025 | L53: 09/28/2026 | M53: 06/29/2025 | O53: 1621 | Q53: 75 | U53: 1
A54: 0423 | B54: B1 | C54: 947 | D54: 2 | E54: 2 | F54: Market | G54: Occupied | H54: 1332 | I54: 1203 | J54: 1203 | K54: 02/14/2026 | L54: 03/06/2027 | M54: 02/14/2026 | O54: 1203 | P54: 35 | U54: 3
A55: 0424 | B55: B4 | C55: 1187 | D55: 2 | E55: 2 | F55: Market | G55: Vacant | H55: 1596 | I55: 0 | J55: 0
A56: 0425 | B56: B4 | C56: 1187 | D56: 2 | E56: 2 | F56: Market | G56: Occupied | H56: 1596 | I56: 1505 | J56: 1505 | K56: 05/25/2026 | L56: 06/24/2027 | M56: 09/18/2016 | O56: 1505 | P56: 35 | U56: 3
A57: 0426 | B57: B1 | C57: 947 | D57: 2 | E57: 2 | F57: Market | G57: Occupied | H57: 1372 | I57: 1331 | J57: 1331 | K57: 04/08/2026 | L57: 05/07/2027 | M57: 01/30/2025 | O57: 1331 | P57: 35 | U57: 3
A58: 0427 | B58: B1R | C58: 947 | D58: 2 | E58: 2 | F58: Market | G58: Occupied | H58: 1532 | I58: 1606 | J58: 1606 | K58: 03/15/2026 | L58: 09/14/2026 | M58: 03/15/2026 | O58: 1606 | P58: 35 | U58: 3 | V58: 65
A59: 0428 | B59: B4 | C59: 1187 | D59: 2 | E59: 2 | F59: Market | G59: Occupied | H59: 1646 | I59: 1493 | J59: 1493 | K59: 07/12/2025 | L59: 08/11/2026 | M59: 07/12/2025 | O59: 1493 | U59: 1
A60: 0432 | B60: B1 | C60: 947 | D60: 2 | E60: 2 | F60: Market | G60: Vacant | H60: 1332 | I60: 0 | J60: 0
A61: 0433 | B61: B1R | C61: 947 | D61: 2 | E61: 2 | F61: Market | G61: Occupied | H61: 1532 | I61: 1474 | J61: 1474 | K61: 10/18/2025 | L61: 10/17/2026 | M61: 10/18/2025 | O61: 1474 | U61: 1
A62: 0436 | B62: B1 | C62: 947 | D62: 2 | E62: 2 | F62: Market | G62: Occupied | H62: 1332 | I62: 1307 | J62: 1307 | K62: 09/21/2025 | L62: 09/27/2026 | M62: 06/29/2015 | O62: 1307 | U62: 1
A63: 0437 | B63: B1R | C63: 947 | D63: 2 | E63: 2 | F63: Market | G63: Occupied | H63: 1532 | I63: 1394 | J63: 1394 | K63: 05/16/2026 | L63: 07/14/2027 | M63: 05/16/2026 | O63: 1394 | P63: 35 | U63: 3
A64: 0511 | B64: C1R | C64: 1258 | D64: 3 | E64: 2 | F64: Market | G64: Occupied | H64: 2070 | I64: 1961 | J64: 1961 | K64: 01/01/2026 | L64: 12/31/2026 | M64: 12/10/2022 | O64: 1961 | Q64: 250 | R64: -784.4 | U64: 1
A65: 0512 | B65: B4R | C65: 1187 | D65: 2 | E65: 2 | F65: Market | G65: Occupied | H65: 1976 | I65: 2143 | J65: 2143 | K65: 09/11/2025 | L65: 12/10/2026 | M65: 06/11/2024 | O65: 2143 | U65: 1
A66: 0513 | B66: A2 | C66: 777 | D66: 1 | E66: 1 | F66: Market | G66: Occupied | H66: 1307 | I66: 1420 | J66: 1420 | K66: 11/23/2025 | L66: 11/15/2026 | M66: 05/30/2023 | O66: 1420 | U66: 1
A67: 0514 | B67: B1 | C67: 947 | D67: 2 | E67: 2 | F67: Market | G67: Occupied | H67: 1487 | I67: 1378 | J67: 1378 | K67: 02/25/2026 | L67: 03/24/2027 | M67: 01/31/2025 | O67: 1378 | U67: 3
A68: 0521 | B68: C1R | C68: 1258 | D68: 3 | E68: 2 | F68: Market | G68: Occupied | H68: 1975 | I68: 1872 | J68: 1872 | K68: 06/13/2025 | L68: 09/05/2026 | M68: 06/13/2025 | O68: 1872 | U68: 1
A69: 0522 | B69: B4R | C69: 1187 | D69: 2 | E69: 2 | F69: Market | G69: Vacant | H69: 1796 | I69: 0 | J69: 0
A70: 0523 | B70: A2R | C70: 777 | D70: 1 | E70: 1 | F70: Market | G70: Occupied | H70: 1327 | I70: 1262 | J70: 1262 | K70: 01/06/2026 | L70: 04/05/2027 | M70: 01/06/2026 | O70: 1262 | T70: 45 | U70: 3
A71: 0524 | B71: B1 | C71: 947 | D71: 2 | E71: 2 | F71: Market | G71: Occupied | H71: 1352 | I71: 1207 | J71: 1207 | K71: 05/21/2026 | L71: 07/20/2027 | M71: 05/21/2026 | O71: 1207 | P71: 35 | U71: 3
A72: 0531 | B72: C1R | C72: 1258 | D72: 3 | E72: 2 | F72: Market | G72: Occupied | H72: 1975 | I72: 1792 | J72: 1792 | K72: 03/26/2026 | L72: 06/25/2027 | M72: 03/26/2026 | O72: 1792 | P72: 35 | U72: 3
A73: 0532 | B73: B4R | C73: 1187 | D73: 2 | E73: 2 | F73: Market | G73: Occupied | H73: 1796 | I73: 1530 | J73: 1530 | K73: 01/26/2026 | L73: 04/25/2027 | M73: 01/26/2026 | O73: 1530 | P73: 35 | U73: 3
A74: 0533 | B74: A2 | C74: 777 | D74: 1 | E74: 1 | F74: Market | G74: Occupied | H74: 1127 | I74: 1166 | J74: 1166 | K74: 03/15/2025 | L74: 06/14/2026 | M74: 03/15/2025 | O74: 1166 | U74: 1
A75: 0534 | B75: B1R | C75: 947 | D75: 2 | E75: 2 | F75: Market | G75: Occupied | H75: 1552 | I75: 1265 | J75: 1265 | K75: 12/23/2025 | L75: 03/15/2027 | M75: 12/23/2025 | O75: 1265 | P75: 35 | Q75: 125 | U75: 3
A76: 0611 | B76: C1R | C76: 1258 | D76: 3 | E76: 2 | F76: Market | G76: Occupied | H76: 1970 | I76: 1862 | J76: 1862 | K76: 01/16/2026 | L76: 04/15/2027 | M76: 01/16/2026 | O76: 1862 | U76: 3
A77: 0612 | B77: A1R | C77: 739 | D77: 1 | E77: 1 | F77: Market | G77: Occupied | H77: 1287 | I77: 1404 | J77: 1404 | K77: 12/27/2025 | L77: 03/26/2027 | M77: 11/20/2023 | O77: 1404 | U77: 1
A78: 0613 | B78: A1 | C78: 739 | D78: 1 | E78: 1 | F78: Market | G78: Occupied | H78: 1122 | I78: 1055 | J78: 1055 | K78: 05/26/2026 | L78: 08/25/2027 | M78: 05/26/2026 | O78: 1055 | P78: 35 | U78: 3
A79: 0614 | B79: C1 | C79: 1258 | D79: 3 | E79: 2 | F79: Market | G79: Occupied | H79: 1830 | I79: 1686 | J79: 1686 | K79: 08/28/2025 | L79: 11/27/2026 | M79: 02/28/2023 | O79: 1686 | U79: 1
A80: 0615 | B80: C1 | C80: 1258 | D80: 3 | E80: 2 | F80: Market | G80: Occupied | H80: 1835 | I80: 1830 | J80: 1830 | K80: 04/17/2026 | L80: 06/16/2027 | M80: 02/17/2025 | O80: 1830 | P80: 35 | U80: 3
A81: 0616 | B81: A1 | C81: 739 | D81: 1 | E81: 1 | F81: Market | G81: Occupied | H81: 1127 | I81: 1273 | J81: 1273 | K81: 06/02/2025 | L81: 05/31/2026 | M81: 05/25/2017 | O81: 1273 | U81: 1
A82: 0617 | B82: A1 | C82: 739 | D82: 1 | E82: 1 | F82: Market | G82: Occupied | H82: 1122 | I82: 1218 | J82: 1218 | K82: 10/25/2025 | L82: 12/17/2026 | M82: 10/01/2024 | O82: 1218 | U82: 1
A83: 0618 | B83: C1 | C83: 1258 | D83: 3 | E83: 2 | F83: Market | G83: Occupied | H83: 1870 | I83: 1708 | J83: 1708 | K83: 06/16/2025 | L83: 09/15/2026 | M83: 04/23/2018 | O83: 1708 | Q83: 100 | U83: 1
A84: 0621 | B84: C1R | C84: 1258 | D84: 3 | E84: 2 | F84: Market | G84: Occupied | H84: 1975 | I84: 1978 | J84: 1978 | K84: 04/04/2026 | L84: 06/10/2027 | M84: 04/04/2026 | O84: 1978 | P84: 35 | U84: 3
A85: 0622 | B85: A1 | C85: 739 | D85: 1 | E85: 1 | F85: Market | G85: Occupied | H85: 1067 | I85: 1049 | J85: 1049 | K85: 06/05/2025 | L85: 08/04/2026 | M85: 06/05/2025 | O85: 1049 | U85: 1
A86: 0623 | B86: A1R | C86: 739 | D86: 1 | E86: 1 | F86: Market | G86: Occupied | H86: 1302 | I86: 1334 | J86: 1334 | K86: 05/10/2026 | L86: 08/09/2027 | M86: 12/03/2023 | O86: 1334 | P86: 35 | U86: 3
A87: 0624 | B87: C1R | C87: 1258 | D87: 3 | E87: 2 | F87: Market | G87: Occupied | H87: 2010 | I87: 1958 | J87: 1958 | K87: 10/23/2025 | L87: 11/22/2026 | M87: 09/30/2023 | O87: 1958 | U87: 1
A88: 0625 | B88: C1 | C88: 1258 | D88: 3 | E88: 2 | F88: Market | G88: Occupied | H88: 1775 | I88: 1699 | J88: 1699 | K88: 05/16/2026 | L88: 08/15/2027 | M88: 05/16/2026 | O88: 1699 | P88: 35 | U88: 3
A89: 0626 | B89: A1 | C89: 739 | D89: 1 | E89: 1 | F89: Market | G89: Occupied | H89: 1067 | I89: 1166 | J89: 1166 | K89: 12/11/2025 | L89: 12/10/2026 | M89: 12/11/2025 | O89: 1166 | U89: 1
A90: 0627 | B90: A1R | C90: 739 | D90: 1 | E90: 1 | F90: Market | G90: Occupied | H90: 1302 | I90: 1358 | J90: 1358 | K90: 10/20/2025 | L90: 12/19/2026 | M90: 07/13/2024 | O90: 1358 | U90: 1
A91: 0628 | B91: C1R | C91: 1258 | D91: 3 | E91: 2 | F91: Market | G91: Occupied | H91: 2010 | I91: 1791 | J91: 1791 | K91: 04/13/2026 | L91: 05/12/2027 | M91: 03/13/2025 | O91: 1791 | P91: 35 | U91: 3
A92: 0632 | B92: A1 | C92: 739 | D92: 1 | E92: 1 | F92: Market | G92: Occupied | H92: 1067 | I92: 1206 | J92: 1206 | K92: 06/03/2025 | L92: 06/02/2026 | M92: 06/03/2023 | O92: 1206 | U92: 1
A93: 0633 | B93: A1 | C93: 739 | D93: 1 | E93: 1 | F93: Market | G93: Occupied | H93: 1102 | I93: 1164 | J93: 1164 | K93: 03/07/2026 | L93: 04/06/2027 | M93: 01/28/2020 | O93: 1164 | P93: 35 | U93: 3
A94: 0636 | B94: A1 | C94: 739 | D94: 1 | E94: 1 | F94: Market | G94: Occupied | H94: 1067 | I94: 1239 | J94: 1239 | K94: 07/29/2025 | L94: 07/28/2026 | M94: 08/15/2018 | O94: 1239 | Q94: 100 | U94: 1
A95: 0637 | B95: A1R | C95: 739 | D95: 1 | E95: 1 | F95: Market | G95: Occupied | H95: 1302 | I95: 1395 | J95: 1395 | K95: 12/11/2025 | L95: 03/10/2027 | M95: 06/03/2023 | O95: 1395 | U95: 1
A96: 0721 | B96: B2R | C96: 1040 | D96: 2 | E96: 2 | F96: Market | G96: Occupied | H96: 1786 | I96: 1813 | J96: 1813 | K96: 05/01/2026 | L96: 07/31/2027 | M96: 05/01/2026 | O96: 1813 | P96: 35 | U96: 3
A97: 0722 | B97: B2 | C97: 1040 | D97: 2 | E97: 2 | F97: Market | G97: Occupied | H97: 1586 | I97: 1568 | J97: 1568 | K97: 07/19/2025 | L97: 10/18/2026 | M97: 04/19/2024 | O97: 1568 | U97: 1
A98: 0811 | B98: C1R | C98: 1258 | D98: 3 | E98: 2 | F98: Market | G98: Occupied | H98: 2145 | I98: 2140 | J98: 2140 | K98: 01/09/2026 | L98: 04/08/2027 | M98: 01/09/2026 | O98: 2140 | P98: 35 | U98: 3
A99: 0812 | B99: A1 | C99: 739 | D99: 1 | E99: 1 | F99: Market | G99: Occupied | H99: 1137 | I99: 1284 | J99: 1284 | K99: 09/03/2025 | L99: 12/02/2026 | M99: 09/03/2025 | O99: 1284 | U99: 1
A100: 0813 | B100: A1 | C100: 739 | D100: 1 | E100: 1 | F100: Market | G100: Vacant | H100: 1127 | I100: 0 | J100: 0
...

Sheet Lease Trend
A1: Lease Trend & Operating History (monthly)
A2: True market rent from HelloData executed leases (mix-weighted by floor plan) + new-lease signings; loss-to-lease backed into from T12 AGPR; concessions compared T12 vs HelloData. Months flow left-to-right; renewals excluded from market reads.
A4: Month → | B4: Jan 2023 | C4: Feb 2023 | D4: Mar 2023 | E4: Apr 2023 | F4: May 2023 | G4: Jun 2023 | H4: Jul 2023 | I4: Aug 2023 | J4: Sep 2023 | K4: Oct 2023 | L4: Nov 2023 | M4: Dec 2023 | N4: Jan 2024 | O4: Feb 2024 | P4: Mar 2024 | Q4: Apr 2024 | R4: May 2024 | S4: Jun 2024 | T4: Jul 2024 | U4: Aug 2024 | V4: Sep 2024 | W4: Oct 2024 | X4: Nov 2024 | Y4: Dec 2024 | Z4: Jan 2025 | AA4: Feb 2025 | AB4: Mar 2025 | AC4: Apr 2025 | AD4: May 2025 | AE4: Jun 2025 | AF4: Jul 2025 | AG4: Aug 2025 | AH4: Sep 2025 | AI4: Oct 2025 | AJ4: Nov 2025 | AK4: Dec 2025 | AL4: Jan 2026 | AM4: Feb 2026 | AN4: Mar 2026 | AO4: Apr 2026 | AP4: May 2026 | AQ4: Jun 2026
A5: MARKET RENT — HelloData executed (mix-weighted) + new-lease signings
A6: HD Market Rent / unit (asking) | G6: 1619 | H6: 1586 | I6: 1444 | J6: 1531 | K6: 1487 | L6: 1434 | M6: 1434 | N6: 1476 | O6: 1518 | P6: 1522 | Q6: 1510 | R6: 1587 | S6: 1440 | T6: 1496 | U6: 1444 | V6: 1496 | W6: 1495 | X6: 1423 | Y6: 1370 | Z6: 1397 | AA6: 1512 | AB6: 1462 | AC6: 1447 | AD6: 1371 | AE6: 1420 | AF6: 1377 | AG6: 1393 | AH6: 1252 | AI6: 1301 | AJ6: 1334 | AK6: 1252 | AL6: 1373 | AM6: 1328 | AN6: 1323 | AO6: 1391 | AP6: 1312 | AQ6: 1346
A7: HD Effective Rent / unit | G7: 1557 | H7: 1546 | I7: 1393 | J7: 1487 | K7: 1363 | L7: 1315 | M7: 1314 | N7: 1353 | O7: 1403 | P7: 1407 | Q7: 1394 | R7: 1456 | S7: 1398 | T7: 1496 | U7: 1444 | V7: 1496 | W7: 1495 | X7: 1319 | Y7: 1260 | Z7: 1286 | AA7: 1390 | AB7: 1343 | AC7: 1334 | AD7: 1264 | AE7: 1306 | AF7: 1269 | AG7: 1335 | AH7: 1148 | AI7: 1200 | AJ7: 1334 | AK7: 1252 | AL7: 1373 | AM7: 1328 | AN7: 1323 | AO7: 1391 | AP7: 1312 | AQ7: 1346
A8: HD Concession % (1 − eff/ask) | G8: 0.03835641 | H8: 0.024987032 | I8: 0.03505407 | J8: 0.028593679 | K8: 0.083317394 | L8: 0.083364716 | M8: 0.083268291 | N8: 0.083355593 | O8: 0.075944519 | P8: 0.075310491 | Q8: 0.076701026 | R8: 0.082317368 | S8: 0.029065269 | X8: 0.072707408 | Y8: 0.080452643 | Z8: 0.079746802 | AA8: 0.081098451 | AB8: 0.080843259 | AC8: 0.078739642 | AD8: 0.078294258 | AE8: 0.08045396 | AF8: 0.078942763 | AG8: 0.041826303 | AH8: 0.083246955 | AI8: 0.07778538
A9: HD Executed Leases (#) | G9: 4 | H9: 18 | I9: 20 | J9: 14 | K9: 19 | L9: 20 | M9: 32 | N9: 21 | O9: 37 | P9: 28 | Q9: 18 | R9: 17 | S9: 46 | T9: 20 | U9: 21 | V9: 19 | W9: 28 | X9: 33 | Y9: 42 | Z9: 33 | AA9: 16 | AB9: 41 | AC9: 28 | AD9: 41 | AE9: 30 | AF9: 32 | AG9: 22 | AH9: 14 | AI9: 20 | AJ9: 32 | AK9: 33 | AL9: 30 | AM9: 15 | AN9: 35 | AO9: 23 | AP9: 44 | AQ9: 20
A10: New-Lease Contract / unit (rent roll) | AB10: 1523 | AC10: 1449 | AD10: 1438 | AE10: 1409 | AF10: 1392 | AG10: 1335 | AH10: 1306 | AI10: 1322 | AJ10: 1317 | AK10: 1273 | AL10: 1277 | AM10: 1289 | AN10: 1328 | AO10: 1404 | AP10: 1325
A11: New Leases (#) | AB11: 11 | AC11: 13 | AD11: 20 | AE11: 25 | AF11: 23 | AG11: 26 | AH11: 14 | AI11: 20 | AJ11: 20 | AK11: 30 | AL11: 22 | AM11: 18 | AN11: 36 | AO11: 16 | AP11: 24
A13: OCCUPANCY & RENT POSITION — from financial statements
A14: Physical Occupancy % (T12: 1 − vac/AGPR) | B14: 0.92837733 | C14: 0.88736179 | D14: 0.84656343 | E14: 0.8164445 | F14: 0.88008229 | G14: 0.91455338 | H14: 0.89157559 | I14: 0.89280429 | J14: 0.91385597 | K14: 0.90288533 | L14: 0.90039797 | M14: 0.92837932 | N14: 0.92757793 | O14: 0.92886998 | P14: 0.93459162 | Q14: 0.93557434 | R14: 0.92380448 | S14: 0.92813903 | T14: 0.94096314 | U14: 0.93984917 | V14: 0.94018267 | W14: 0.92388269 | X14: 0.92895244 | Y14: 0.93799354 | Z14: 0.92557556 | AA14: 0.93145941 | AB14: 0.93194799 | AC14: 0.9367813 | AD14: 0.93057055 | AE14: 0.9336671 | AF14: 0.93936422 | AG14: 0.92863361 | AH14: 0.91680083 | AI14: 0.92292815 | AJ14: 0.90162201 | AK14: 0.91463712
A15: Contract Rent / unit — AGPR (T12) | B15: 1579 | C15: 1672 | D15: 1642 | E15: 1618 | F15: 1449 | G15: 1560 | H15: 1567 | I15: 1567 | J15: 1566 | K15: 1564 | L15: 1560 | M15: 1553 | N15: 1547 | O15: 1551 | P15: 1545 | Q15: 1538 | R15: 1544 | S15: 1545 | T15: 1545 | U15: 1541 | V15: 1538 | W15: 1540 | X15: 1537 | Y15: 1551 | Z15: 1525 | AA15: 1514 | AB15: 1514 | AC15: 1509 | AD15: 1511 | AE15: 1508 | AF15: 1504 | AG15: 1501 | AH15: 1498 | AI15: 1485 | AJ15: 1474 | AK15: 1454
A16: Market Rent / unit — GPR basis (T12, ref only) | B16: 1681 | C16: 1681 | D16: 1681 | E16: 1681 | F16: 1681 | G16: 1681 | H16: 1681 | I16: 1681 | J16: 1681 | K16: 1681 | L16: 1681 | M16: 1681 | N16: 1681 | O16: 1681 | P16: 1681 | Q16: 1681 | R16: 1681 | S16: 1681 | T16: 1681 | U16: 1681 | V16: 1681 | W16: 1682 | X16: 1681 | Y16: 1681 | Z16: 1681 | AA16: 1681 | AB16: 1681 | AC16: 1681 | AD16: 1681 | AE16: 1690 | AF16: 1690 | AG16: 1703 | AH16: 1703 | AI16: 1492 | AJ16: 1390 | AK16: 1329
A17: Loss-to-Lease / unit (HD mkt − AGPR) | G17: 59 | H17: 19 | I17: -123 | J17: -35 | K17: -77 | L17: -125 | M17: -120 | N17: -70 | O17: -33 | P17: -24 | Q17: -28 | R17: 43 | S17: -106 | T17: -49 | U17: -97 | V17: -42 | W17: -45 | X17: -114 | Y17: -181 | Z17: -128 | AA17: -2 | AB17: -52 | AC17: -62 | AD17: -140 | AE17: -88 | AF17: -127 | AG17: -108 | AH17: -246 | AI17: -184 | AJ17: -140 | AK17: -203
A18: Loss-to-Lease % (vs HD market) | G18: 0.036157319 | H18: 0.011822877 | I18: -0.085212791 | J18: -0.022968153 | K18: -0.051937952 | L18: -0.087406347 | M18: -0.083379825 | N18: -0.047614074 | O18: -0.021987283 | P18: -0.015693913 | Q18: -0.018547235 | R18: 0.027068346 | S18: -0.073447144 | T18: -0.032881524 | U18: -0.067191587 | V18: -0.027859254 | W18: -0.03008898 | X18: -0.080304295 | Y18: -0.13199367 | Z18: -0.091395964 | AA18: -0.0011371998 | AB18: -0.0356488 | AC18: -0.042611363 | AD18: -0.10199534 | AE18: -0.061873515 | AF18: -0.092345131 | AG18: -0.077337433 | AH18: -0.19685966 | AI18: -0.1412781 | AJ18: -0.10513887 | AK18: -0.16193725
A20: CONCESSIONS — T12 (portfolio) vs HelloData (new-lease)
A21: T12 Concessions ($/mo) | B21: -1319 | C21: -230 | D21: 485 | E21: 672 | F21: -498 | G21: -576 | H21: -2759 | I21: -12086 | J21: -1593 | K21: -6592 | L21: -12726 | M21: -18421 | N21: -7822 | O21: -12417 | P21: -5910 | Q21: 394 | R21: -1968 | S21: -7675 | T21: -15019 | U21: -1969 | V21: -3434 | W21: 3279 | X21: -3967 | Y21: -1493 | Z21: 1024 | AA21: 2266 | AB21: 1680 | AC21: -325 | AD21: -589 | AE21: 883 | AF21: -1241 | AG21: -30 | AH21: -2389 | AI21: -8809 | AJ21: -8744 | AK21: -5805
A22: T12 Concessions % of AGPR | B22: 0.0011680115 | C22: 0.00019265947 | D22: -0.00041350043 | E22: -0.000581317 | F22: 0.00048048027 | G22: 0.00051588862 | H22: 0.0024625208 | I22: 0.010786505 | J22: 0.0014226232 | K22: 0.0058939885 | L22: 0.011411267 | M22: 0.016587089 | N22: 0.0070730641 | O22: 0.011193559 | P22: 0.0053484541 | Q22: -0.00035850832 | R22: 0.0017831154 | S22: 0.0069454565 | T22: 0.013594637 | U22: 0.0017873426 | V22: 0.003122441 | W22: -0.0029787224 | X22: 0.003610682 | Y22: 0.0013461654 | Z22: -0.0009393296 | AA22: -0.0020933603 | AB22: -0.0015522904 | AC22: 0.00030119064 | AD22: 0.00054520996 | AE22: -0.00081882653 | AF22: 0.0011537033 | AG22: 2.7960108e-05 | AH22: 0.002230257 | AI22: 0.0082967999 | AJ22: 0.0082949592 | AK22: 0.0055821995
A23: HD Concession % (new-lease) | G23: 0.03835641 | H23: 0.024987032 | I23: 0.03505407 | J23: 0.028593679 | K23: 0.083317394 | L23: 0.083364716 | M23: 0.083268291 | N23: 0.083355593 | O23: 0.075944519 | P23: 0.075310491 | Q23: 0.076701026 | R23: 0.082317368 | S23: 0.029065269 | X23: 0.072707408 | Y23: 0.080452643 | Z23: 0.079746802 | AA23: 0.081098451 | AB23: 0.080843259 | AC23: 0.078739642 | AD23: 0.078294258 | AE23: 0.08045396 | AF23: 0.078942763 | AG23: 0.041826303 | AH23: 0.083246955 | AI23: 0.07778538
A25: OPERATING TREND — from stitched T12
A26: Effective Gross Revenue | B26: 1143514 | C26: 1145572 | D26: 1121077 | E26: 1120083 | F26: 1116882 | G26: 1092100 | H26: 1094124 | I26: 1113985 | J26: 1116213 | K26: 1103979 | L26: 1131526 | M26: 1102587 | N26: 1141431 | O26: 1170076 | P26: 1131084 | Q26: 1123026 | R26: 1123158 | S26: 1118430 | T26: 1123281 | U26: 1127132 | V26: 1153725 | W26: 1148946 | X26: 1149839 | Y26: 1161354 | Z26: 1111397 | AA26: 1144483 | AB26: 1138198 | AC26: 1147377 | AD26: 1146827 | AE26: 1118878 | AF26: 1137450 | AG26: 1126264 | AH26: 1090538 | AI26: 1069938 | AJ26: 1053659 | AK26: 1040538
A27: Operating Expenses | B27: 343089 | C27: 317955 | D27: 348099 | E27: 366590 | F27: 349311 | G27: 310720 | H27: 354213 | I27: 367003 | J27: 327477 | K27: 360559 | L27: 267608 | M27: 346324 | N27: 387583 | O27: 338045 | P27: 325176 | Q27: 373255 | R27: 361992 | S27: 355862 | T27: 379859 | U27: 364264 | V27: 356243 | W27: 382298 | X27: 342206 | Y27: 343551 | Z27: 361414 | AA27: 368963 | AB27: 387322 | AC27: 426049 | AD27: 350329 | AE27: 391397 | AF27: 370729 | AG27: 366505 | AH27: 351125 | AI27: 347675 | AJ27: 350663 | AK27: 348342
A28: Net Operating Income | B28: 800425 | C28: 827618 | D28: 772978 | E28: 753493 | F28: 767571 | G28: 781380 | H28: 739911 | I28: 746982 | J28: 788736 | K28: 743421 | L28: 863918 | M28: 756263 | N28: 753848 | O28: 832030 | P28: 805908 | Q28: 749772 | R28: 761167 | S28: 762568 | T28: 743422 | U28: 762868 | V28: 797483 | W28: 766648 | X28: 807633 | Y28: 817803 | Z28: 749984 | AA28: 775520 | AB28: 750876 | AC28: 721328 | AD28: 796498 | AE28: 727481 | AF28: 766721 | AG28: 759759 | AH28: 739413 | AI28: 722263 | AJ28: 702996 | AK28: 692196
A30: TRAILING ANNUALIZATIONS
B31: T12 | C31: T6 | D31: T3
A32: EGR (annualized) | B32: 13325549 | C32: 13036777 | D32: 12656543
A33: Operating Expenses | B33: 4420513 | C33: 4270078 | D33: 4186721
A34: NOI | B34: 8905036 | C34: 8766699 | D34: 8469822
A36: Observations
A37: • Seasonality: executed asking rents peak in Jul and trough in Dec (~10% spread across the HelloData history).
A38: • HelloData asking-rent YoY (same calendar month): -5.8% average across 25 month-pair(s).
A39: • Concessions by source: the T12 books concessions across the WHOLE portfolio (~0.3% of AGPR here), while HelloData's is per NEW lease (~6.9% here). The portfolio figure ≈ new-lease concession × the share of units on a recently-signed lease — here ~44% of in-place leases are new (lease-up), so the two run close (little dilution). On a stabilized deal with ~40–50% annual turnover, expect the T12 figure nearer half the new-lease rate.
A42: Trailing-90-Day Executed by Floor Plan (HelloData)
A43: Base Plan | B43: T90 Asking | C43: T90 Effective | D43: Concession % | E43: Exec (n)
A44: A1 | B44: 1079 | C44: 1079 | D44: =IF(OR(B44="",B44=0),"-",1-C44/B44) | E44: 14
A45: A1R | B45: 1178 | C45: 1178 | D45: =IF(OR(B45="",B45=0),"-",1-C45/B45) | E45: 2
A46: A2 | B46: 1160 | C46: 1160 | D46: =IF(OR(B46="",B46=0),"-",1-C46/B46) | E46: 29
A47: A2R | B47: 1234 | C47: 1234 | D47: =IF(OR(B47="",B47=0),"-",1-C47/B47) | E47: 9
A48: B1 | B48: 1340 | C48: 1340 | D48: =IF(OR(B48="",B48=0),"-",1-C48/B48) | E48: 12
A49: B1R | B49: 1383 | C49: 1383 | D49: =IF(OR(B49="",B49=0),"-",1-C49/B49) | E49: 3
A50: B2 | B50: 1579 | C50: 1579 | D50: =IF(OR(B50="",B50=0),"-",1-C50/B50) | E50: 2
A51: B2R | B51: 1813 | C51: 1813 | D51: =IF(OR(B51="",B51=0),"-",1-C51/B51) | E51: 1
A52: B3 | B52: 1780 | C52: 1780 | D52: =IF(OR(B52="",B52=0),"-",1-C52/B52) | E52: 1
A53: B4 | B53: 1630 | C53: 1630 | D53: =IF(OR(B53="",B53=0),"-",1-C53/B53) | E53: 6
A54: B4.2 | B54: 1766 | C54: 1766 | D54: =IF(OR(B54="",B54=0),"-",1-C54/B54) | E54: 3
A55: B4R | B55: 1618 | C55: 1618 | D55: =IF(OR(B55="",B55=0),"-",1-C55/B55) | E55: 2
... A58: C2 | B58: 2057 | C58: 2057 | D58: =IF(OR(B58="",B58=0),"-",1-C58/B58) | E58: 1
A60: Last 5 New Leases by Floor Plan (rent roll)
A61: Floor Plan | B61: Unit | C61: Lease Start | D61: Contract Rent | E61: Rent PSF (mo.)
A62: A1 | B62: 0613 | C62: 05/26/2026 | D62: 1055 | E62: 1.43
A63: A1 | B63: 4112 | C63: 05/21/2026 | D63: 1092 | E63: 1.48
A64: A1 | B64: 4916 | C64: 05/18/2026 | D64: 1167 | E64: 1.58
A65: A1 | B65: 4113 | C65: 05/02/2026 | D65: 1119 | E65: 1.51
A66: A1 | B66: 0816 | C66: 04/15/2026 | D66: 1008 | E66: 1.36
A67: A1R | B67: 2432 | C67: 03/28/2026 | D67: 1218 | E67: 1.65
A68: A1R | B68: 2413 | C68: 12/12/2025 | D68: 1134 | E68: 1.53
A69: A1R | B69: 0823 | C69: 11/29/2025 | D69: 1102 | E69: 1.49
A70: A1R | B70: 0817 | C70: 11/07/2025 | D70: 1408 | E70: 1.91
A71: A1R | B71: 2426 | C71: 07/15/2025 | D71: 1215 | E71: 1.64
A72: A2 | B72: 2716 | C72: 05/26/2026 | D72: 1066 | E72: 1.37
A73: A2 | B73: 3326 | C73: 05/15/2026 | D73: 1180 | E73: 1.52
... A133: C2 | B133: 3514 | C133: 10/03/2025 | D133: 2049 | E133: 1.5

Sheet HelloData
A1: Property Name | B1: Floorplan | C1: Unit | D1: Floor | E1: Bedrooms | F1: Bathrooms | G1: Partial Bathrooms | H1: SF | I1: Available On | J1: Deposit | K1: Term | L1: AMI Level | M1: Last Asking Rent | N1: Asking Rent PSF | O1: Last Effective Rent | P1: Effective Rent PSF | Q1: On Market Date | R1: Off Market Date | S1: Days on Market | T1: Days Vacant | U1: Floorplan Mapped
A2: Bella Mirage | B2: Brook | C2: 3127 | D2: 3 | E2: 1 | F2: 1 | H2: 739 | I2: 7/20/2026 | J2: 300 | K2: 12 | L2: 50% | M2: 987 | N2: 1.34 | O2: 987 | P2: 1.34 | Q2: 2026-05-08 | R2: 2026-05-20 | S2: 13 | T2: 0 | U2: Brook
A3: Bella Mirage | B3: Brook | C3: 0816 | E3: 1 | F3: 1 | H3: 739 | I3: 1/15/2025 | J3: 200 | K3: 13 | L3: 50% | M3: 1270 | N3: 1.72 | O3: 1270 | P3: 1.72 | Q3: 2024-10-05 | R3: 2024-10-31 | S3: 27 | T3: 0 | U3: Brook
A4: Bella Mirage | B4: Brook | C4: 0816 | E4: 1 | F4: 1 | H4: 739 | I4: 4/15/2026 | J4: 300 | K4: 12 | L4: 50% | M4: 1004 | N4: 1.36 | O4: 1004 | P4: 1.36 | Q4: 2026-02-14 | R4: 2026-02-22 | S4: 9 | T4: 0 | U4: Brook
A5: Bella Mirage | B5: Brook | C5: 0826 | D5: 2 | E5: 1 | F5: 1 | H5: 739 | I5: 7/21/2023 | L5: 50% | M5: 1358 | N5: 1.84 | O5: 1296 | P5: 1.75 | R5: 2023-06-20 | U5: Brook
A6: Bella Mirage | B6: Brook | C6: 0826 | D6: 2 | E6: 1 | F6: 1 | H6: 739 | I6: 8/4/2025 | J6: 200 | K6: 12 | L6: 50% | M6: 1101 | N6: 1.49 | O6: 1009 | P6: 1.37 | Q6: 2025-05-21 | R6: 2025-05-24 | S6: 4 | T6: 0 | U6: Brook
A7: Bella Mirage | B7: Brook | C7: 0826 | D7: 2 | E7: 1 | F7: 1 | H7: 739 | I7: 8/18/2026 | J7: 300 | K7: 13 | L7: 50% | M7: 1005 | N7: 1.36 | O7: 1005 | P7: 1.36 | Q7: 2026-06-02 | R7: 2026-06-03 | S7: 2 | T7: 0 | U7: Brook
A8: Bella Mirage | B8: Brook | C8: 2423 | D8: 2 | E8: 1 | F8: 1 | H8: 739 | I8: 11/1/2024 | J8: 200 | K8: 12 | L8: 50% | M8: 1154 | N8: 1.56 | O8: 1154 | P8: 1.56 | Q8: 2024-08-19 | R8: 2024-08-25 | S8: 7 | T8: 0 | U8: Brook
A9: Bella Mirage | B9: Brook | C9: 2423 | D9: 2 | E9: 1 | F9: 1 | H9: 739 | I9: 12/15/2025 | J9: 300 | K9: 13 | L9: 50% | M9: 1005 | N9: 1.36 | O9: 1005 | P9: 1.36 | Q9: 2025-11-08 | R9: 2025-12-01 | S9: 24 | T9: 0 | U9: Brook
A10: Bella Mirage | B10: Brook | C10: 2427 | D10: 2 | E10: 1 | F10: 1 | H10: 739 | I10: 3/3/2025 | J10: 200 | K10: 14 | L10: 50% | M10: 1116 | N10: 1.51 | O10: 1036 | P10: 1.4 | Q10: 2024-12-28 | R10: 2025-04-14 | S10: 108 | T10: 43 | U10: Brook
A11: Bella Mirage | B11: Brook | C11: 2427 | D11: 2 | E11: 1 | F11: 1 | H11: 739 | I11: 8/4/2026 | J11: 300 | K11: 12 | L11: 50% | M11: 1012 | N11: 1.37 | O11: 1012 | P11: 1.37 | Q11: 2026-04-28 | R11: 2026-04-29 | S11: 2 | T11: 0 | U11: Brook
A12: Bella Mirage | B12: Brook | C12: 3117 | D12: 3 | E12: 1 | F12: 1 | H12: 739 | I12: 12/10/2023 | L12: 50% | M12: 1204 | N12: 1.63 | O12: 1104 | P12: 1.49 | Q12: 2023-12-03 | R12: 2023-12-11 | S12: 9 | T12: 2 | U12: Brook
A13: Bella Mirage | B13: Brook | C13: 3117 | D13: 3 | E13: 1 | F13: 1 | H13: 739 | I13: 3/19/2026 | J13: 300 | K13: 13 | L13: 50% | M13: 1019 | N13: 1.38 | O13: 1019 | P13: 1.38 | Q13: 2026-01-21 | R13: 2026-02-27 | S13: 38 | T13: 0 | U13: Brook
A14: Bella Mirage | B14: Brook | C14: 4126 | D14: 4 | E14: 1 | F14: 1 | H14: 739 | I14: 7/31/2023 | L14: 50% | M14: 1442 | N14: 1.95 | O14: 1380 | P14: 1.87 | Q14: 2023-07-02 | R14: 2023-07-07 | S14: 6 | T14: 0 | U14: Brook
A15: Bella Mirage | B15: Brook | C15: 4126 | D15: 4 | E15: 1 | F15: 1 | H15: 739 | I15: 9/14/2024 | J15: 200 | K15: 12 | L15: 50% | M15: 1268 | N15: 1.72 | O15: 1268 | P15: 1.72 | Q15: 2024-06-10 | R15: 2024-06-24 | S15: 15 | T15: 0 | U15: Brook
A16: Bella Mirage | B16: Brook | C16: 4126 | D16: 4 | E16: 1 | F16: 1 | H16: 739 | I16: 9/27/2025 | J16: 300 | K16: 12 | L16: 50% | M16: 1188 | N16: 1.61 | O16: 1089 | P16: 1.47 | Q16: 2025-08-19 | R16: 2025-09-22 | S16: 35 | T16: 0 | U16: Brook
A17: Bella Mirage | B17: Brook | C17: 4126 | D17: 4 | E17: 1 | F17: 1 | H17: 739 | I17: 4/11/2026 | J17: 300 | K17: 12 | L17: 50% | M17: 1027 | N17: 1.39 | O17: 1027 | P17: 1.39 | Q17: 2026-02-04 | R17: 2026-05-20 | S17: 106 | T17: 40 | U17: Brook
A18: Bella Mirage | B18: Brook | C18: 2433 | D18: 2 | E18: 1 | F18: 1 | H18: 739 | I18: 6/20/2023 | L18: 50% | M18: 1370 | N18: 1.85 | O18: 1308 | P18: 1.77 | Q18: 2023-06-20 | R18: 2023-06-29 | S18: 10 | T18: 10 | U18: Brook
A19: Bella Mirage | B19: Brook | C19: 2433 | D19: 2 | E19: 1 | F19: 1 | H19: 739 | I19: 6/21/2026 | J19: 300 | K19: 13 | L19: 50% | M19: 1027 | N19: 1.39 | O19: 1027 | P19: 1.39 | Q19: 2026-04-02 | R19: 2026-05-20 | S19: 49 | T19: 0 | U19: Brook
A20: Bella Mirage | B20: Brook | C20: 0813 | E20: 1 | F20: 1 | H20: 739 | I20: 5/25/2026 | J20: 300 | K20: 12 | L20: 50% | M20: 1032 | N20: 1.4 | O20: 1032 | P20: 1.4 | Q20: 2026-05-16 | R20: 2026-05-20 | S20: 5 | T20: 0 | U20: Brook
A21: Bella Mirage | B21: Brook | C21: 4123 | D21: 4 | E21: 1 | F21: 1 | H21: 739 | I21: 9/7/2023 | L21: 50% | M21: 1232 | N21: 1.67 | O21: 1129 | P21: 1.53 | Q21: 2023-08-16 | R21: 2023-10-26 | S21: 72 | T21: 50 | U21: Brook
A22: Bella Mirage | B22: Brook | C22: 4123 | D22: 4 | E22: 1 | F22: 1 | H22: 739 | I22: 1/3/2025 | J22: 200 | K22: 12 | L22: 50% | M22: 1300 | N22: 1.76 | O22: 1192 | P22: 1.61 | Q22: 2024-10-25 | R22: 2024-11-13 | S22: 20 | T22: 0 | U22: Brook
A23: Bella Mirage | B23: Brook | C23: 4123 | D23: 4 | E23: 1 | F23: 1 | H23: 739 | I23: 4/16/2026 | J23: 300 | K23: 12 | L23: 50% | M23: 1042 | N23: 1.41 | O23: 1042 | P23: 1.41 | Q23: 2026-02-25 | R23: 2026-05-17 | S23: 82 | T23: 32 | U23: Brook
A24: Bella Mirage | B24: Brook | C24: 0613 | E24: 1 | F24: 1 | H24: 739 | I24: 4/12/2024 | J24: 200 | K24: 13 | L24: 50% | M24: 1245 | N24: 1.68 | O24: 1149 | P24: 1.55 | Q24: 2024-02-16 | R24: 2024-02-20 | S24: 5 | T24: 0 | U24: Brook
A25: Bella Mirage | B25: Brook | C25: 0613 | E25: 1 | F25: 1 | H25: 739 | I25: 5/26/2026 | J25: 300 | K25: 12 | L25: 50% | M25: 1050 | N25: 1.42 | O25: 1050 | P25: 1.42 | Q25: 2026-02-24 | R25: 2026-03-09 | S25: 14 | T25: 0 | U25: Brook
A26: Bella Mirage | B26: Brook | C26: 4937 | E26: 1 | F26: 1 | H26: 739 | I26: 4/28/2024 | J26: 200 | K26: 13 | L26: 50% | M26: 1402 | N26: 1.9 | O26: 1294 | P26: 1.75 | Q26: 2024-02-12 | R26: 2024-05-22 | S26: 101 | T26: 25 | U26: Brook
A27: Bella Mirage | B27: Brook | C27: 4937 | E27: 1 | F27: 1 | H27: 739 | I27: 3/5/2026 | J27: 300 | K27: 12 | L27: 50% | M27: 1073 | N27: 1.45 | O27: 1073 | P27: 1.45 | Q27: 2025-12-16 | R27: 2026-06-03 | S27: 170 | T27: 91 | U27: Brook
A28: Bella Mirage | B28: Brook | C28: 4922 | D28: 2 | E28: 1 | F28: 1 | H28: 739 | I28: 5/2/2024 | J28: 200 | K28: 14 | L28: 50% | M28: 1198 | N28: 1.62 | O28: 1198 | P28: 1.62 | Q28: 2024-02-22 | R28: 2024-06-15 | S28: 115 | T28: 45 | U28: Brook
A29: Bella Mirage | B29: Brook | C29: 4922 | D29: 2 | E29: 1 | F29: 1 | H29: 739 | I29: 10/2/2025 | J29: 300 | K29: 12 | L29: 50% | M29: 1079 | N29: 1.46 | O29: 1079 | P29: 1.46 | Q29: 2025-09-12 | R29: 2025-12-04 | S29: 84 | T29: 64 | U29: Brook
A30: Bella Mirage | B30: Brook | C30: 0836 | D30: 3 | E30: 1 | F30: 1 | H30: 739 | I30: 2/26/2025 | J30: 200 | K30: 12 | L30: 50% | M30: 1090 | N30: 1.47 | O30: 999 | P30: 1.35 | Q30: 2024-12-14 | R30: 2024-12-20 | S30: 7 | T30: 0 | U30: Brook
A31: Bella Mirage | B31: Brook | C31: 3612 | D31: 3 | E31: 1 | F31: 1 | H31: 739 | I31: 6/22/2026 | J31: 300 | K31: 13 | L31: 50% | M31: 1092 | N31: 1.48 | O31: 1092 | P31: 1.48 | Q31: 2026-03-28 | R31: 2026-05-20 | S31: 54 | T31: 0 | U31: Brook
A32: Bella Mirage | B32: Brook | C32: 3613 | E32: 1 | F32: 1 | H32: 739 | I32: 9/7/2024 | J32: 200 | K32: 12 | L32: 50% | M32: 1310 | N32: 1.77 | O32: 1310 | P32: 1.77 | Q32: 2024-03-19 | R32: 2024-08-09 | S32: 144 | T32: 0 | U32: Brook
A33: Bella Mirage | B33: Brook | C33: 3613 | E33: 1 | F33: 1 | H33: 739 | I33: 8/8/2025 | J33: 200 | K33: 13 | L33: 50% | M33: 1093 | N33: 1.48 | O33: 1009 | P33: 1.37 | Q33: 2025-07-06 | R33: 2025-07-31 | S33: 26 | T33: 0 | U33: Brook
A34: Bella Mirage | B34: Brook | C34: 3636 | D34: 3 | E34: 1 | F34: 1 | H34: 739 | I34: 8/20/2023 | L34: 50% | M34: 1357 | N34: 1.84 | O34: 1294 | P34: 1.75 | Q34: 2023-07-27 | R34: 2023-09-20 | S34: 56 | T34: 32 | U34: Brook
A35: Bella Mirage | B35: Brook | C35: 3636 | D35: 3 | E35: 1 | F35: 1 | H35: 739 | I35: 1/10/2025 | J35: 200 | K35: 12 | L35: 50% | M35: 1302 | N35: 1.76 | O35: 1194 | P35: 1.62 | Q35: 2024-10-29 | R35: 2025-02-16 | S35: 111 | T35: 38 | U35: Brook
A36: Bella Mirage | B36: Brook | C36: 3636 | D36: 3 | E36: 1 | F36: 1 | H36: 739 | I36: 7/7/2025 | J36: 200 | K36: 12 | L36: 50% | M36: 1225 | N36: 1.66 | O36: 1123 | P36: 1.52 | Q36: 2025-06-09 | R36: 2025-07-23 | S36: 45 | T36: 17 | U36: Brook
A37: Bella Mirage | B37: Brook | C37: 3636 | D37: 3 | E37: 1 | F37: 1 | H37: 739 | I37: 8/3/2026 | J37: 300 | K37: 12 | L37: 50% | M37: 1097 | N37: 1.48 | O37: 1097 | P37: 1.48 | Q37: 2026-05-07 | R37: 2026-05-13 | S37: 7 | T37: 0 | U37: Brook
A38: Bella Mirage | B38: Brook | C38: 4127 | D38: 4 | E38: 1 | F38: 1 | H38: 739 | I38: 10/28/2023 | L38: 50% | M38: 1254 | N38: 1.7 | O38: 1150 | P38: 1.56 | Q38: 2023-10-26 | R38: 2023-11-18 | S38: 24 | T38: 22 | U38: Brook
A39: Bella Mirage | B39: Brook | C39: 4127 | D39: 4 | E39: 1 | F39: 1 | H39: 739 | I39: 1/7/2025 | J39: 200 | K39: 13 | L39: 50% | M39: 1208 | N39: 1.63 | O39: 1115 | P39: 1.51 | Q39: 2024-12-04 | R39: 2024-12-15 | S39: 12 | T39: 0 | U39: Brook
A40: Bella Mirage | B40: Brook | C40: 4127 | D40: 4 | E40: 1 | F40: 1 | H40: 739 | I40: 2/20/2026 | J40: 300 | K40: 15 | L40: 50% | M40: 1102 | N40: 1.49 | O40: 1102 | P40: 1.49 | Q40: 2026-01-06 | R40: 2026-03-18 | S40: 72 | T40: 27 | U40: Brook
A41: Bella Mirage | B41: Brook | C41: 0823 | D41: 2 | E41: 1 | F41: 1 | H41: 739 | I41: 4/30/2024 | J41: 200 | K41: 12 | L41: 50% | M41: 1362 | N41: 1.84 | O41: 1248 | P41: 1.69 | Q41: 2024-04-02 | R41: 2024-06-08 | S41: 68 | T41: 40 | U41: Brook
A42: Bella Mirage | B42: Brook | C42: 0823 | D42: 2 | E42: 1 | F42: 1 | H42: 739 | I42: 8/26/2025 | J42: 300 | K42: 12 | L42: 50% | M42: 1102 | N42: 1.49 | O42: 1102 | P42: 1.49 | Q42: 2025-06-09 | R42: 2025-11-16 | S42: 161 | T42: 83 | U42: Brook
A43: Bella Mirage | B43: Brook | C43: 4912 | E43: 1 | F43: 1 | H43: 739 | I43: 6/17/2023 | L43: 50% | M43: 1262 | N43: 1.71 | O43: 1157 | P43: 1.57 | R43: 2023-10-24 | U43: Brook
A44: Bella Mirage | B44: Brook | C44: 4912 | E44: 1 | F44: 1 | H44: 739 | I44: 7/26/2025 | J44: 300 | K44: 12 | L44: 50% | M44: 1106 | N44: 1.5 | O44: 1106 | P44: 1.5 | Q44: 2025-05-20 | R44: 2025-12-29 | S44: 224 | T44: 157 | U44: Brook
A45: Bella Mirage | B45: Brook | C45: 0622 | D45: 2 | E45: 1 | F45: 1 | H45: 739 | I45: 5/19/2025 | J45: 200 | K45: 12 | L45: 50% | M45: 1209 | N45: 1.64 | O45: 1108 | P45: 1.5 | Q45: 2025-01-19 | R45: 2025-02-05 | S45: 18 | T45: 0 | U45: Brook
A46: Bella Mirage | B46: Brook | C46: 0622 | D46: 2 | E46: 1 | F46: 1 | H46: 739 | I46: 5/13/2025 | J46: 200 | K46: 13 | L46: 50% | M46: 1112 | N46: 1.5 | O46: 1026 | P46: 1.39 | Q46: 2025-05-18 | R46: 2025-05-24 | S46: 7 | T46: 7 | U46: Brook
A47: Bella Mirage | B47: Brook | C47: 3137 | E47: 1 | F47: 1 | H47: 739 | I47: 8/6/2024 | J47: 200 | K47: 12 | L47: 50% | M47: 1085 | N47: 1.47 | O47: 1085 | P47: 1.47 | Q47: 2024-05-20 | R47: 2024-06-16 | S47: 28 | T47: 0 | U47: Brook
A48: Bella Mirage | B48: Brook | C48: 3137 | E48: 1 | F48: 1 | H48: 739 | I48: 11/20/2025 | J48: 300 | K48: 12 | L48: 50% | M48: 1116 | N48: 1.51 | O48: 1023 | P48: 1.38 | Q48: 2025-09-02 | R48: 2025-10-05 | S48: 34 | T48: 0 | U48: Brook
A49: Bella Mirage | B49: Brook | C49: 4113 | D49: 4 | E49: 1 | F49: 1 | H49: 739 | I49: 4/20/2025 | J49: 200 | K49: 12 | L49: 50% | M49: 1204 | N49: 1.63 | O49: 1104 | P49: 1.49 | Q49: 2025-03-06 | R49: 2025-03-10 | S49: 5 | T49: 0 | U49: Brook
A50: Bella Mirage | B50: Brook | C50: 4113 | D50: 4 | E50: 1 | F50: 1 | H50: 739 | I50: 5/2/2026 | J50: 300 | K50: 12 | L50: 50% | M50: 1119 | N50: 1.51 | O50: 1119 | P50: 1.51 | Q50: 2026-01-27 | R50: 2026-03-03 | S50: 36 | T50: 0 | U50: Brook
A51: Bella Mirage | B51: Brook | C51: 3136 | D51: 3 | E51: 1 | F51: 1 | H51: 739 | I51: 12/15/2024 | J51: 200 | K51: 12 | L51: 60% | M51: 1315 | N51: 1.78 | O51: 1205 | P51: 1.63 | Q51: 2024-09-26 | R51: 2024-12-15 | S51: 81 | T51: 1 | U51: Brook
A52: Bella Mirage | B52: Brook | C52: 3136 | D52: 3 | E52: 1 | F52: 1 | H52: 739 | I52: 3/27/2026 | J52: 300 | K52: 12 | L52: 60% | M52: 1123 | N52: 1.52 | O52: 1123 | P52: 1.52 | Q52: 2026-03-18 | R52: 2026-05-20 | S52: 64 | T52: 55 | U52: Brook
A53: Bella Mirage | B53: Brook | C53: 4112 | D53: 4 | E53: 1 | F53: 1 | H53: 739 | I53: 10/14/2023 | L53: 60% | M53: 1247 | N53: 1.69 | O53: 1143 | P53: 1.55 | Q53: 2023-10-14 | R53: 2023-11-03 | S53: 21 | T53: 21 | U53: Brook
A54: Bella Mirage | B54: Brook | C54: 4112 | D54: 4 | E54: 1 | F54: 1 | H54: 739 | I54: 2/13/2026 | J54: 300 | K54: 12 | L54: 60% | M54: 1128 | N54: 1.53 | O54: 1128 | P54: 1.53 | Q54: 2026-01-07 | R54: 2026-05-16 | S54: 130 | T54: 93 | U54: Brook
A55: Bella Mirage | B55: Brook | C55: 2413 | E55: 1 | F55: 1 | H55: 739 | I55: 6/22/2023 | L55: 60% | M55: 1316 | N55: 1.78 | O55: 1254 | P55: 1.7 | Q55: 2023-06-22 | R55: 2023-08-25 | S55: 65 | T55: 65 | U55: Brook
A56: Bella Mirage | B56: Brook | C56: 2413 | E56: 1 | F56: 1 | H56: 739 | I56: 9/16/2024 | J56: 200 | K56: 13 | L56: 60% | M56: 1374 | N56: 1.86 | O56: 1374 | P56: 1.86 | Q56: 2024-08-01 | R56: 2024-08-24 | S56: 24 | T56: 0 | U56: Brook
A57: Bella Mirage | B57: Brook | C57: 2413 | E57: 1 | F57: 1 | H57: 739 | I57: 9/11/2025 | J57: 300 | K57: 12 | L57: 60% | M57: 1134 | N57: 1.53 | O57: 1134 | P57: 1.53 | Q57: 2025-07-08 | R57: 2025-12-07 | S57: 153 | T57: 88 | U57: Brook
A58: Bella Mirage | B58: Brook | C58: 3637 | E58: 1 | F58: 1 | H58: 739 | I58: 9/11/2025 | J58: 300 | K58: 12 | L58: 60% | M58: 1218 | N58: 1.65 | O58: 1116 | P58: 1.51 | Q58: 2025-08-28 | R58: 2025-10-03 | S58: 37 | T58: 23 | U58: Brook
A59: Bella Mirage | B59: Brook | C59: 4122 | D59: 4 | E59: 1 | F59: 1 | H59: 739 | I59: 1/29/2025 | J59: 200 | K59: 12 | L59: 60% | M59: 1284 | N59: 1.74 | O59: 1177 | P59: 1.59 | Q59: 2024-11-07 | R59: 2025-01-26 | S59: 81 | T59: 0 | U59: Brook
A60: Bella Mirage | B60: Brook | C60: 4122 | D60: 4 | E60: 1 | F60: 1 | H60: 739 | I60: 2/8/2026 | J60: 300 | K60: 12 | L60: 60% | M60: 1136 | N60: 1.54 | O60: 1136 | P60: 1.54 | Q60: 2025-12-24 | R60: 2026-02-04 | S60: 43 | T60: 0 | U60: Brook
A61: Bella Mirage | B61: Brook | C61: 4923 | D61: 4 | E61: 1 | F61: 1 | H61: 739 | I61: 3/21/2025 | J61: 200 | K61: 12 | L61: 60% | M61: 1141 | N61: 1.54 | O61: 1046 | P61: 1.42 | Q61: 2024-11-24 | R61: 2025-07-29 | S61: 248 | T61: 131 | U61: Brook
A62: Bella Mirage | B62: Brook | C62: 3122 | E62: 1 | F62: 1 | H62: 739 | I62: 9/4/2024 | J62: 200 | K62: 12 | L62: 60% | M62: 1283 | N62: 1.74 | O62: 1176 | P62: 1.59 | Q62: 2024-06-22 | R62: 2024-11-13 | S62: 145 | T62: 71 | U62: Brook
A63: Bella Mirage | B63: Brook | C63: 0626 | D63: 2 | E63: 1 | F63: 1 | H63: 739 | I63: 11/5/2024 | J63: 200 | K63: 12 | L63: 60% | M63: 1184 | N63: 1.6 | O63: 1184 | P63: 1.6 | Q63: 2024-08-19 | R63: 2024-09-24 | S63: 37 | T63: 0 | U63: Brook
A64: Bella Mirage | B64: Brook | C64: 0626 | D64: 2 | E64: 1 | F64: 1 | H64: 739 | I64: 12/11/2025 | J64: 300 | K64: 12 | L64: 60% | M64: 1166 | N64: 1.58 | O64: 1069 | P64: 1.45 | Q64: 2025-09-11 | R64: 2025-10-25 | S64: 45 | T64: 0 | U64: Brook
A65: Bella Mirage | B65: Brook | C65: 4116 | D65: 4 | E65: 1 | F65: 1 | H65: 739 | I65: 1/5/2024 | J65: 200 | K65: 15 | L65: 60% | M65: 1325 | N65: 1.79 | O65: 1237 | P65: 1.67 | Q65: 2023-11-14 | R65: 2024-02-20 | S65: 99 | T65: 47 | U65: Brook
A66: Bella Mirage | B66: Brook | C66: 4116 | D66: 4 | E66: 1 | F66: 1 | H66: 739 | I66: 7/24/2024 | J66: 200 | K66: 12 | L66: 60% | M66: 1300 | N66: 1.76 | O66: 1300 | P66: 1.76 | Q66: 2024-06-01 | R66: 2024-06-20 | S66: 20 | T66: 0 | U66: Brook
A67: Bella Mirage | B67: Brook | C67: 4116 | D67: 4 | E67: 1 | F67: 1 | H67: 739 | I67: 7/18/2025 | J67: 200 | K67: 12 | L67: 60% | M67: 1165 | N67: 1.58 | O67: 1068 | P67: 1.45 | Q67: 2025-05-23 | R67: 2025-07-30 | S67: 69 | T67: 13 | U67: Brook
A68: Bella Mirage | B68: Brook | C68: 3627 | D68: 2 | E68: 1 | F68: 1 | H68: 739 | I68: 6/26/2024 | J68: 200 | K68: 14 | L68: 60% | M68: 1249 | N68: 1.69 | O68: 1249 | P68: 1.69 | Q68: 2023-12-15 | R68: 2024-08-22 | S68: 252 | T68: 58 | U68: Brook
A69: Bella Mirage | B69: Brook | C69: 3627 | D69: 2 | E69: 1 | F69: 1 | H69: 739 | I69: 6/9/2025 | J69: 200 | K69: 13 | L69: 60% | M69: 1250 | N69: 1.69 | O69: 1154 | P69: 1.56 | Q69: 2025-03-29 | R69: 2025-08-03 | S69: 128 | T69: 56 | U69: Brook
A70: Bella Mirage | B70: Brook | C70: 3627 | D70: 2 | E70: 1 | F70: 1 | H70: 739 | I70: 11/26/2025 | J70: 300 | K70: 12 | L70: 60% | M70: 1172 | N70: 1.59 | O70: 1172 | P70: 1.59 | Q70: 2025-11-04 | R70: 2026-03-17 | S70: 134 | T70: 112 | U70: Brook
A71: Bella Mirage | B71: Brook | C71: 3616 | E71: 1 | F71: 1 | H71: 739 | I71: 8/19/2023 | L71: 60% | M71: 1292 | N71: 1.75 | O71: 1184 | P71: 1.6 | Q71: 2023-07-28 | R71: 2023-10-26 | S71: 91 | T71: 69 | U71: Brook
A72: Bella Mirage | B72: Brook | C72: 3616 | E72: 1 | F72: 1 | H72: 739 | I72: 1/15/2025 | J72: 200 | K72: 14 | L72: 60% | M72: 1260 | N72: 1.71 | O72: 1170 | P72: 1.58 | Q72: 2024-10-25 | R72: 2025-04-23 | S72: 181 | T72: 99 | U72: Brook
A73: Bella Mirage | B73: Brook | C73: 3616 | E73: 1 | F73: 1 | H73: 739 | I73: 2/19/2026 | J73: 300 | K73: 13 | L73: 60% | M73: 1174 | N73: 1.59 | O73: 1174 | P73: 1.59 | Q73: 2026-01-04 | R73: 2026-02-19 | S73: 47 | T73: 1 | U73: Brook
A74: Bella Mirage | B74: Brook | C74: 3626 | D74: 3 | E74: 1 | F74: 1 | H74: 739 | I74: 8/26/2023 | L74: 60% | M74: 1178 | N74: 1.59 | O74: 1080 | P74: 1.46 | Q74: 2023-08-23 | R74: 2023-10-31 | S74: 70 | T74: 67 | U74: Brook
A75: Bella Mirage | B75: Brook | C75: 3626 | D75: 3 | E75: 1 | F75: 1 | H75: 739 | I75: 2/6/2025 | J75: 200 | K75: 12 | L75: 60% | M75: 1343 | N75: 1.82 | O75: 1231 | P75: 1.67 | Q75: 2024-12-18 | R75: 2025-02-17 | S75: 62 | T75: 12 | U75: Brook
A76: Bella Mirage | B76: Brook | C76: 3626 | D76: 3 | E76: 1 | F76: 1 | H76: 739 | I76: 12/1/2025 | J76: 300 | K76: 12 | L76: 60% | M76: 1179 | N76: 1.6 | O76: 1081 | P76: 1.46 | Q76: 2025-08-26 | R76: 2025-09-14 | S76: 20 | T76: 0 | U76: Brook
A77: Bella Mirage | B77: Brook | C77: 2412 | E77: 1 | F77: 1 | H77: 739 | I77: 3/19/2024 | J77: 200 | K77: 15 | L77: 60% | M77: 1318 | N77: 1.78 | O77: 1230 | P77: 1.66 | Q77: 2024-03-12 | R77: 2024-03-13 | S77: 2 | T77: 0 | U77: Brook
A78: Bella Mirage | B78: Brook | C78: 2412 | E78: 1 | F78: 1 | H78: 739 | I78: 11/22/2024 | J78: 200 | K78: 12 | L78: 60% | M78: 1178 | N78: 1.59 | O78: 1080 | P78: 1.46 | Q78: 2024-11-10 | R78: 2024-12-22 | S78: 43 | T78: 31 | U78: Brook
A79: Bella Mirage | B79: Brook | C79: 4916 | D79: 4 | E79: 1 | F79: 1 | H79: 739 | I79: 5/8/2024 | J79: 200 | K79: 14 | L79: 60% | M79: 1316 | N79: 1.78 | O79: 1316 | P79: 1.78 | Q79: 2024-04-16 | R79: 2024-07-05 | S79: 81 | T79: 59 | U79: Brook
A80: Bella Mirage | B80: Brook | C80: 4916 | D80: 4 | E80: 1 | F80: 1 | H80: 739 | I80: 12/17/2024 | J80: 200 | K80: 13 | L80: 60% | M80: 1419 | N80: 1.92 | O80: 1310 | P80: 1.77 | Q80: 2024-12-04 | R80: 2025-05-09 | S80: 157 | T80: 144 | U80: Brook
A81: Bella Mirage | B81: Brook | C81: 4916 | D81: 4 | E81: 1 | F81: 1 | H81: 739 | I81: 5/9/2026 | J81: 300 | K81: 12 | L81: 60% | M81: 1178 | N81: 1.59 | O81: 1178 | P81: 1.59 | Q81: 2026-04-07 | R81: 2026-05-14 | S81: 38 | T81: 6 | U81: Brook
A82: Bella Mirage | B82: Brook | C82: 3623 | D82: 2 | E82: 1 | F82: 1 | H82: 739 | I82: 6/1/2025 | J82: 200 | K82: 12 | L82: 60% | M82: 1180 | N82: 1.6 | O82: 1082 | P82: 1.46 | Q82: 2025-05-18 | R82: 2025-06-08 | S82: 22 | T82: 8 | U82: Brook
A83: Bella Mirage | B83: Brook | C83: 3113 | E83: 1 | F83: 1 | H83: 739 | I83: 1/17/2025 | J83: 200 | K83: 13 | L83: 60% | M83: 1187 | N83: 1.61 | O83: 1096 | P83: 1.48 | Q83: 2024-11-02 | R83: 2025-03-04 | S83: 123 | T83: 47 | U83: Brook
A84: Bella Mirage | B84: Brook | C84: 2436 | D84: 3 | E84: 1 | F84: 1 | H84: 739 | I84: 11/15/2024 | J84: 200 | K84: 12 | L84: 60% | M84: 1187 | N84: 1.61 | O84: 1088 | P84: 1.47 | Q84: 2024-11-08 | R84: 2024-11-22 | S84: 15 | T84: 8 | U84: Brook
A85: Bella Mirage | B85: Brook | C85: 3413 | D85: 3 | E85: 1 | F85: 1 | H85: 739 | I85: 10/15/2024 | J85: 200 | K85: 13 | L85: 60% | M85: 1299 | N85: 1.76 | O85: 1299 | P85: 1.76 | Q85: 2024-08-29 | R85: 2024-09-06 | S85: 9 | T85: 0 | U85: Brook
A86: Bella Mirage | B86: Brook | C86: 3413 | D86: 3 | E86: 1 | F86: 1 | H86: 739 | I86: 6/4/2026 | J86: 300 | K86: 13 | L86: 60% | M86: 1187 | N86: 1.61 | O86: 1187 | P86: 1.61 | Q86: 2026-05-13 | R86: 2026-05-20 | S86: 8 | T86: 0 | U86: Brook
A87: Bella Mirage | B87: Brook | C87: 4926 | E87: 1 | F87: 1 | H87: 739 | I87: 6/25/2023 | L87: 60% | M87: 1284 | N87: 1.74 | O87: 1222 | P87: 1.65 | R87: 2023-07-24 | U87: Brook
A88: Bella Mirage | B88: Brook | C88: 4926 | E88: 1 | F88: 1 | H88: 739 | I88: 8/2/2024 | J88: 200 | K88: 15 | L88: 60% | M88: 1239 | N88: 1.68 | O88: 1239 | P88: 1.68 | Q88: 2024-05-01 | R88: 2024-09-04 | S88: 127 | T88: 34 | U88: Brook
A89: Bella Mirage | B89: Brook | C89: 4926 | E89: 1 | F89: 1 | H89: 739 | I89: 9/9/2025 | J89: 300 | K89: 12 | L89: 60% | M89: 1188 | N89: 1.61 | O89: 1089 | P89: 1.47 | Q89: 2025-07-21 | R89: 2025-09-21 | S89: 63 | T89: 13 | U89: Brook
A90: Bella Mirage | B90: Brook | C90: 4136 | D90: 4 | E90: 1 | F90: 1 | H90: 739 | I90: 2/23/2025 | J90: 200 | K90: 12 | L90: 60% | M90: 1190 | N90: 1.61 | O90: 1091 | P90: 1.48 | Q90: 2024-11-19 | R90: 2024-12-27 | S90: 39 | T90: 0 | U90: Brook
A91: Bella Mirage | B91: Brook | C91: 4933 | E91: 1 | F91: 1 | H91: 739 | I91: 11/9/2024 | J91: 200 | K91: 13 | L91: 60% | M91: 1190 | N91: 1.61 | O91: 1098 | P91: 1.49 | Q91: 2024-11-02 | R91: 2025-01-04 | S91: 64 | T91: 57 | U91: Brook
A92: Bella Mirage | B92: Brook | C92: 4933 | E92: 1 | F92: 1 | H92: 739 | I92: 8/21/2025 | J92: 300 | K92: 12 | L92: 60% | M92: 1191 | N92: 1.61 | O92: 1092 | P92: 1.48 | Q92: 2025-08-07 | R92: 2025-09-16 | S92: 41 | T92: 27 | U92: Brook
A93: Bella Mirage | B93: Brook | C93: 2416 | E93: 1 | F93: 1 | H93: 739 | I93: 8/28/2024 | J93: 200 | K93: 12 | L93: 60% | M93: 1155 | N93: 1.56 | O93: 1155 | P93: 1.56 | Q93: 2024-06-14 | R93: 2024-06-16 | S93: 3 | T93: 0 | U93: Brook
A94: Bella Mirage | B94: Brook | C94: 2416 | E94: 1 | F94: 1 | H94: 739 | I94: 10/2/2025 | J94: 300 | K94: 12 | L94: 60% | M94: 1196 | N94: 1.62 | O94: 1096 | P94: 1.48 | Q94: 2025-09-11 | R94: 2025-10-11 | S94: 31 | T94: 10 | U94: Brook
A95: Bella Mirage | B95: Brook | C95: 4932 | E95: 1 | F95: 1 | H95: 739 | I95: 1/29/2024 | J95: 200 | K95: 14 | L95: 60% | M95: 1309 | N95: 1.77 | O95: 1216 | P95: 1.65 | Q95: 2023-11-30 | R95: 2024-03-28 | S95: 120 | T95: 60 | U95: Brook
A96: Bella Mirage | B96: Brook | C96: 4932 | E96: 1 | F96: 1 | H96: 739 | I96: 7/9/2025 | J96: 200 | K96: 13 | L96: 60% | M96: 1200 | N96: 1.62 | O96: 1200 | P96: 1.62 | Q96: 2025-05-02 | R96: 2025-08-15 | S96: 106 | T96: 38 | U96: Brook
A97: Bella Mirage | B97: Brook | C97: 4913 | D97: 4 | E97: 1 | F97: 1 | H97: 739 | I97: 4/4/2024 | J97: 200 | K97: 13 | L97: 60% | M97: 1363 | N97: 1.84 | O97: 1258 | P97: 1.7 | Q97: 2024-02-27 | R97: 2024-05-22 | S97: 86 | T97: 49 | U97: Brook
A98: Bella Mirage | B98: Brook | C98: 4913 | D98: 4 | E98: 1 | F98: 1 | H98: 739 | I98: 9/8/2025 | J98: 300 | K98: 12 | L98: 60% | M98: 1211 | N98: 1.64 | O98: 1110 | P98: 1.5 | Q98: 2025-06-02 | R98: 2025-09-25 | S98: 116 | T98: 18 | U98: Brook
A99: Bella Mirage | B99: Brook | C99: 3112 | E99: 1 | F99: 1 | H99: 739 | I99: 6/17/2023 | L99: 60% | M99: 1293 | N99: 1.75 | O99: 1230 | P99: 1.66 | R99: 2023-08-09 | U99: Brook
A100: Bella Mirage | B100: Brook | C100: 3112 | E100: 1 | F100: 1 | H100: 739 | I100: 11/29/2025 | J100: 300 | K100: 13 | L100: 60% | M100: 1208 | N100: 1.63 | O100: 1208 | P100: 1.63 | Q100: 2025-09-03 | R100: 2025-12-13 | S100: 102 | T100: 15 | U100: Brook
...

Sheet Reconciliation
A1: Reconciliation — Rent Roll ↔ T12
A2: Latest T12 month: Dec 2025. 'In Contract Rent?' flags which charges roll into contract rent.
A4: Control Tie-Outs (rent roll vs latest T12 month)
A5: Measure | B5: Rent Roll | C5: T12 (latest mo. / ann.) | D5: Variance | E5: Var % | F5: Note
A6: Gross Market Rent (asking), monthly | B6: 1041569 | C6: 949937.31 | D6: =B6-C6 | E6: =IF(C6=0,"-",D6/C6) | F6: RR Market column ↔ T12 GPR — both are seller-set ASKING rents and are NOT a market-rent signal (either can be set at will). True market rent = latest new-lease contract rents + HelloData executed asking; see the unit mix and Lease Trend tabs. Shown here only as a data-integrity check that the two files describe the same property/period.
A7: Contract Rent incl. amenity (occupied), monthly | B7: 928798.28 | C7: 943897.22 | D7: =B7-C7 | E7: =IF(C7=0,"-",D7/C7) | F7: RR contract (Rent+Amenity) ↔ T12 contract net of vacancy (Rentinc+LtL+Vac+NonRev)
A8: T1 AGPR, annualized | B8: 11145579 | C8: 12479081 | D8: =B8-C8 | E8: =IF(C8=0,"-",D8/C8) | F8: RR contract ×12 ↔ T12 latest-month AGPR ×12 (Rentinc+LtL). Amenity rent is IN contract rent — it is not a separate T12 line, and including it ties RR contract closer to AGPR.
A9: Other Income (recurring), monthly | B9: 11259.54 | C9: 112852.62 | D9: =B9-C9 | E9: =IF(C9=0,"-",D9/C9) | F9: RR ancillary charges ↔ T12 other-income codes
A11: Charge-Code Map (rent roll scheduled, monthly)
A12: Charge Code | B12: Mapped Code | C12: Yardi Type | D12: Monthly $ | E12: In Contract Rent?
A13: rent | B13: Rentinc | D13: 928798.28 | E13: Yes
A14: techfee | B14: OI | D14: 7420 | E14: No
A15: garage | B15: park | D15: 7075 | E15: No
A16: empdisc | B16: OI | D16: -5486 | E16: No
A17: conc/renew | B17: OI | D17: -3300 | E17: No
A18: petrent | B18: OI | D18: 3120 | E18: No
A19: package | B19: OI | D19: 1215 | E19: No
A20: carport | B20: park | D20: 1195 | E20: No
A21: conc/other | B21: OI | D21: -300 | E21: No
A22: eviction | B22: OI | D22: 228.54 | E22: No
A23: trash/doortodoor | B23: RT | D23: 90 | E23: No
A24: mtm | B24: OI | D24: 2 | E24: No
A26: Correlated Cross-Checks (rent-roll counts/charges ↔ T12 income)
A27: Parking | B27: RR: 84 units billed parking, $8,270/mo (avg $98/space) ↔ T12 parking income $9,469/mo — 115% of RR-scheduled parking appears on the T12.
A28: Utility recapture (RUBS) | B28: T12 utility expense $57,364/mo (UWS+UC+UF+UT) ↔ RUBS/billback income $62,000/mo (RWS+RT+RF) = 108% recaptured · water/sewer alone 83% ($25,713/$31,030)
A30: ⚑ Flags for Underwriting
A31: • 'trash/doortodoor' ($90/mo, RUBS-style recovery) -- confirm whether it nets against the trash expense or books as Other Income (RT).

Sheet Codes
A1: Standardized Code Legend
A2: Source list for the 'T12 Categorized' dropdown. Col A drives VLOOKUP & SUMIFS.
A4: Code | B4: Category | C4: Section
A5: Rentinc | B5: Rental Income | C5: rev
A6: OI | B6: Other Income | C6: rev
A7: RWS | B7: Rubs Water / Sewage | C7: rev
A8: RT | B8: Rubs Trash | C8: rev
A9: RF | B9: Rubs Fees | C9: rev
A10: park | B10: Garage / Parking | C10: rev
A11: CI | B11: Corporate Income | C11: rev
A12: cable | B12: Cable Income | C12: rev
A13: ltl | B13: (Loss to Lease) / Gain to Lease | C13: rev
A14: vac | B14: Vacancy | C14: rev
A15: cl | B15: Collection Loss / Bad Debt | C15: rev
... A59: onoe | B59: Other Non-Operating Expense | C59: nonop-exp
