Workbook
Name CodeList: Codes!$A$5:$A$59

Sheet Dashboard
A1: Aura Beacon Island — Underwriting Intake
A2: Generated June 23, 2026 · RR-T12 Processor intake · Operating period May 2025 – Apr 2026 (12 mo)
A3: Data vintage · Rent roll as-of 05/23/2026 · Latest financial statement thru Apr 2026
A4: SNAPSHOT | D4: UNIT MIX — mix-weighted market-rent indicators
A5: Units | B5: 290 | D5: Floor Plan | E5: Bed | F5: Bath | G5: Units | H5: Occ | I5: Vac | J5: Avg SF | K5: Avg Market Rent (per RR — not a mkt signal) | L5: Avg Contract Rent | M5: New Leases | N5: Renew Leases | O5: Avg New-Lease (last 5) | P5: New #1 | Q5: New #2 | R5: New #3 | S5: New #4 | T5: New #5 | U5: HD T90 Asking | V5: HD T90 Effective | W5: HD T365 Asking | X5: HD T365 Effective | Y5: HD90 YoY Asking | Z5: HD90 YoY Effective | AA5: Bed/Bath Src | AB5: HD Plan (website)
A6: Occupied / Vacant / Non-Rev | B6: 272 / 18 / 0 | D6: A1-abi | E6: 1 | F6: 1 | G6: 14 | H6: 12 | I6: 2 | J6: 690 | K6: 1577 | L6: 1433 | M6: 4 | N6: 8 | O6: 1374 | P6: 1350 | Q6: 1350 | R6: 1299 | S6: 1499 | U6: 1505 | V6: 1336 | W6: 1440 | X6: 1256 | Y6: 0.014150943 | Z6: -0.099561995 | AA6: HelloData | AB6: A1
A7: Occupancy % | B7: 0.93793103 | D7: A2-abi | E7: 1 | F7: 1 | G7: 29 | H7: 26 | I7: 3 | J7: 698 | K7: 1712 | L7: 1503 | M7: 16 | N7: 10 | O7: 1449 | P7: 1660 | Q7: 1399 | R7: 1399 | S7: 1399 | T7: 1387 | U7: 1590 | V7: 1448 | W7: 1510 | X7: 1309 | Y7: -0.053769841 | Z7: -0.0071991772 | AA7: HelloData | AB7: A2
A8: Total Rentable SF | B8: 266411 | D8: A3-abi | E8: 1 | F8: 1 | G8: 46 | H8: 42 | I8: 4 | J8: 719 | K8: 1592 | L8: 1490 | M8: 24 | N8: 18 | O8: 1575 | P8: 1550 | Q8: 1550 | R8: 1595 | S8: 1630 | T8: 1550 | U8: 1549 | V8: 1357 | W8: 1493 | X8: 1284 | Y8: -0.017195431 | Z8: 0.045776819 | AA8: HelloData | AB8: A3
A9: New / Renewal leases | B9: 0 / 0 | D9: A3.8-abi | E9: 1 | F9: 1 | G9: 2 | H9: 2 | I9: 0 | J9: 739 | K9: 1565 | L9: 1460 | M9: 0 | N9: 2 | AA9: HelloData | AB9: A3
A10: — Market Rent Indicators (true signal) — | D10: A4-abi | E10: 1 | F10: 1 | G10: 18 | H10: 18 | I10: 0 | J10: 736 | K10: 1687 | L10: 1522 | M10: 8 | N10: 10 | O10: 1386 | P10: 1384 | Q10: 1304 | R10: 1395 | S10: 1395 | T10: 1450 | W10: 1417 | X10: 1178 | AA10: HelloData | AB10: A4
A11: HelloData asking, T90 (mix-wtd) | B11: 1832 | D11: A5-abi | E11: 1 | F11: 1 | G11: 21 | H11: 21 | I11: 0 | J11: 762 | K11: 1601 | L11: 1567 | M11: 10 | N11: 11 | O11: 1613 | P11: 2272 | Q11: 1565 | R11: 1398 | S11: 1433 | T11: 1398 | U11: 1565 | V11: 1339 | W11: 1466 | X11: 1225 | Y11: -0.039877301 | Z11: -0.027596224 | AA11: HelloData | AB11: A5
A12: HelloData effective, T90 (mix-wtd) | B12: 1623 | D12: A5.3-abi | E12: 1 | F12: 1 | G12: 3 | H12: 3 | I12: 0 | J12: 762 | K12: 1605 | L12: 1500 | M12: 2 | N12: 1 | O12: 1495 | P12: 1385 | Q12: 1605 | U12: 1590 | V12: 1418 | W12: 1517 | X12: 1398 | AA12: HelloData | AB12: A5
A13: New-lease contract, T90 (avg) | B13: 1823 | D13: A6-abi | E13: 1 | F13: 1 | G13: 26 | H13: 24 | I13: 2 | J13: 803 | K13: 1755 | L13: 1709 | M13: 12 | N13: 12 | O13: 1608 | P13: 1600 | Q13: 1599 | R13: 1510 | S13: 1510 | T13: 1820 | U13: 1717 | V13: 1469 | W13: 1698 | X13: 1451 | Y13: -0.015296367 | Z13: -0.058936579 | AA13: HelloData | AB13: A6
A14: — T12 Annualized (most recent 12 mo.) — | D14: A7-abi | E14: 1 | F14: 1 | G14: 18 | H14: 17 | I14: 1 | J14: 941 | K14: 1857 | L14: 1841 | M14: 12 | N14: 5 | O14: 1795 | P14: 1860 | Q14: 1800 | R14: 1769 | S14: 1895 | T14: 1650 | U14: 1845 | V14: 1712 | W14: 1818 | X14: 1598 | Y14: 0.0033990483 | Z14: 0.0094339623 | AA14: HelloData | AB14: A7
A15: Effective Gross Revenue (T12) | B15: 6032933 | D15: B1-abi | E15: 2 | F15: 2 | G15: 48 | H15: 46 | I15: 2 | J15: 1082 | K15: 2254 | L15: 2165 | M15: 24 | N15: 22 | O15: 2606 | P15: 4170 | Q15: 2165 | R15: 2305 | S15: 2130 | T15: 2260 | U15: 2200 | V15: 2014 | W15: 2103 | X15: 1842 | Y15: 0.022463207 | Z15: 0.023981019 | AA15: HelloData | AB15: B1
A16: Operating Expenses (T12) | B16: 2631211.9 | D16: B1.7-abi | E16: 2 | F16: 2 | G16: 2 | H16: 2 | I16: 0 | J16: 1082 | K16: 2238 | L16: 2044 | M16: 2 | N16: 0 | O16: 2044 | P16: 1899 | Q16: 2190 | W16: 1884 | X16: 1519 | AA16: HelloData | AB16: B1
A17: Net Operating Income (T12) | B17: 3401721.1 | D17: B2-abi | E17: 2 | F17: 2 | G17: 27 | H17: 26 | I17: 1 | J17: 1109 | K17: 2127 | L17: 2089 | M17: 12 | N17: 14 | O17: 2123 | P17: 2035 | Q17: 2115 | R17: 2080 | S17: 2035 | T17: 2350 | U17: 2105 | V17: 1815 | W17: 2060 | X17: 1839 | Y17: -0.070640177 | Z17: -0.084898131 | AA17: HelloData | AB17: B2
A18: Operating Margin (T12) | B18: 0.56385859 | D18: B2.3-abi | E18: 2 | F18: 2 | G18: 2 | H18: 2 | I18: 0 | J18: 1155 | K18: 2328 | L18: 2298 | M18: 1 | N18: 1 | O18: 2350 | P18: 2350 | W18: 2335 | X18: 1973 | AA18: HelloData | AB18: B2
D19: B3-abi | E19: 2 | F19: 2 | G19: 18 | H19: 18 | I19: 0 | J19: 1213 | K19: 2172 | L19: 2135 | M19: 9 | N19: 9 | O19: 2142 | P19: 2175 | Q19: 2130 | R19: 2175 | S19: 2130 | T19: 2099 | U19: 2145 | V19: 1836 | W19: 2128 | X19: 1773 | Y19: -0.0069444444 | Z19: 0.0062100457 | AA19: HelloData | AB19: B3
D20: TH-abi | E20: 2 | F20: 2 | G20: 2 | H20: 2 | I20: 0 | J20: 1381 | K20: 3410 | L20: 3022 | M20: 1 | N20: 1 | O20: 3410 | P20: 3410 | U20: 3395 | V20: 2908 | W20: 3395 | X20: 2889 | Y20: 0 | Z20: 0.013240418 | AA20: HelloData(unit) | AB20: TH1
D21: TH.1-abi | E21: 2 | F21: 2 | G21: 1 | H21: 0 | I21: 1 | J21: 1461 | K21: 3785 | L21: 0 | M21: 0 | N21: 0 | AA21: HelloData(unit) | AB21: TH1
D22: C1-abi | E22: 3 | F22: 2 | G22: 11 | H22: 9 | I22: 2 | J22: 1564 | K22: 2898 | L22: 2739 | M22: 2 | N22: 7 | O22: 2778 | P22: 2905 | Q22: 2650 | W22: 2762 | X22: 2299 | AA22: HelloData | AB22: C1
D23: C1.2-abi | E23: 3 | F23: 2 | G23: 1 | H23: 1 | I23: 0 | J23: 1564 | K23: 2925 | L23: 2550 | M23: 1 | N23: 0 | O23: 2550 | P23: 2550 | W23: 2535 | X23: 2044 | AA23: HelloData | AB23: C1
D24: TH.2-abi | G24: 1 | H24: 1 | I24: 0 | J24: 1427 | K24: 3955 | L24: 3955 | M24: 0 | N24: 1 | AA24: unknown
D25: TOTAL / AVG | G25: 290 | H25: 272 | I25: 18 | J25: 919 | K25: 1928 | L25: 1826 | M25: 140 | N25: 132 | O25: 1877 | U25: 1832 | V25: 1623 | W25: 1795 | X25: 1547 | Y25: -0.017189554 | Z25: -0.0098067061
D26: New-lease = lease start ≤ move-in (renewals excluded). HD T90/T365 = executed (off-market) asking/effective; HD90 YoY compares the trailing 90 days to the same window a year ago.
A28: ⚑ UNDERWRITING FLAGS
A29: • HelloData reflects the website 'Total Monthly', which can bundle mandatory fees. HD market rent here is shown NET of $15.00/mo (explicit override). See 'Reconciliation → HelloData Asking: Fee Netting' for the full derivation.
A30: • New-Lease Contract / unit history draws on 2 rent rolls (current 05/23/2026 + older 02/26/2024); older rolls supply signings that have since turned over. The dashboard and unit mix use the current rent roll only.
A31: • Seasonality: executed asking rents peak in Apr and trough in Nov (~15% spread across the HelloData history).
A32: • HelloData asking-rent YoY (same calendar month): -1.7% average across 25 month-pair(s).
A33: • Annualized EGR: T3 $5,989,462 vs T12 $6,032,933 (-0.7%) -- recent run-rate is below the trailing year.
A34: • Annualized NOI: T3 $3,479,043 vs T12 $3,401,721 (+2.3%).
A36: HOW TO USE → paste into the TMG acquisition model
A37: 1. Review 'T12 Categorized' col A (amber). Every GL line appears once with all months flowing across; edit a code via the dropdown to re-map. Category (col B) and OS Summary roll up automatically.
A38: 2. 'OS Summary' is the standardized chart of accounts (live SUMIFS, most recent 12 months). Copy A1:Q77 → model 'OS Summary Dump' A1 (Paste Special → Values).
A39: 3. 'T12 Categorized' → copy Code, Category, Line Item + the most recent 12 month columns (NOT the Total column) → model 'T12 Dump' A2.
A40: 4. 'Rent Roll (One-Line) 05-23-26' (newest rent roll) → copy the core columns A2:M(last) → model 'RR Dump' A2. (The per-unit charge-code columns to the right of the gap are reference detail, not a model paste target.)
... A42: 6. The unit mix (with new-lease + HD T90/T365/YoY market-rent indicators) is on this Dashboard; check 'Lease Trend' (seasonality / market-rent trajectory) and 'Reconciliation' (contract-rent ↔ AGPR tie-out) before underwriting. Paste targets only — do NOT populate the model itself from here.

Sheet T12 Categorized
A1: Code | B1: Category | C1: Line Item (raw GL) | D1: 45778 | E1: 45809 | F1: 45839 | G1: 45870 | H1: 45901 | I1: 45931 | J1: 45962 | K1: 45992 | L1: 46023 | M1: 46054 | N1: 46082 | O1: 46113 | P1: Total
C2: INCOME
A3: Rentinc | B3: =IFERROR(VLOOKUP($A3,Codes!$A:$B,2,FALSE()),"") -> Rental Income | C3: Gross Mkt Rent Potential | D3: 559150 | E3: 559150 | F3: 559150 | G3: 559150 | H3: 559150 | I3: 559150 | J3: 559150 | K3: 559150 | L3: 559150 | M3: 559150 | N3: 559150 | O3: 559150 | P3: =SUM(D3:O3) -> 6709800
A4: ltl | B4: =IFERROR(VLOOKUP($A4,Codes!$A:$B,2,FALSE()),"") -> (Loss to Lease) / Gain to Lease | C4: Gain/Loss To Lease | D4: -27581 | E4: -27745 | F4: -26926 | G4: -25054 | H4: -24168 | I4: -23750 | J4: -24711 | K4: -24276 | L4: -24152 | M4: -27423 | N4: -28527 | O4: -28582 | P4: =SUM(D4:O4) -> -312895
A5: vac | B5: =IFERROR(VLOOKUP($A5,Codes!$A:$B,2,FALSE()),"") -> Vacancy | C5: Vacancy | D5: -32059.41 | E5: -39950.81 | F5: -32160.7 | G5: -36295.85 | H5: -45481.47 | I5: -33225.96 | J5: -39789.69 | K5: -54891.16 | L5: -63024.55 | M5: -51062.94 | N5: -37121.02 | O5: -36993.26 | P5: =SUM(D5:O5) -> -502056.82
A6: nr | B6: =IFERROR(VLOOKUP($A6,Codes!$A:$B,2,FALSE()),"") -> Non-Revenue Units | C6: Models | D6: -2340 | E6: -2340 | F6: -2340 | G6: -2340 | H6: -2340 | I6: -2340 | J6: -2340 | K6: -2340 | L6: -2340 | M6: -2340 | N6: -2340 | O6: -2340 | P6: =SUM(D6:O6) -> -28080
A7: nr | B7: =IFERROR(VLOOKUP($A7,Codes!$A:$B,2,FALSE()),"") -> Non-Revenue Units | C7: Employee Units | D7: -780 | E7: -780 | F7: -780 | G7: -780 | H7: -780 | I7: -780 | J7: -780 | K7: -780 | L7: -780 | M7: -780 | N7: -780 | O7: 0 | P7: =SUM(D7:O7) -> -8580
A8: conc | B8: =IFERROR(VLOOKUP($A8,Codes!$A:$B,2,FALSE()),"") -> Concessions | C8: Non-Recurring Concessions | D8: -51396.97 | E8: -36344.5 | F8: -41734.5 | G8: -40560 | H8: -23142 | I8: -21379.5 | J8: -23729 | K8: -23776 | L8: -29613.92 | M8: -31630 | N8: -41571.5 | O8: -45133.5 | P8: =SUM(D8:O8) -> -410011.39
A9: cl | B9: =IFERROR(VLOOKUP($A9,Codes!$A:$B,2,FALSE()),"") -> Collection Loss / Bad Debt | C9: Less: Writeoffs | D9: 0 | E9: -1848.4 | F9: 0 | G9: 0 | H9: 0 | I9: -228 | J9: 0 | K9: 0 | L9: -590.33 | M9: -35.6 | N9: 0 | O9: 0 | P9: =SUM(D9:O9) -> -2702.33
A10: cl | B10: =IFERROR(VLOOKUP($A10,Codes!$A:$B,2,FALSE()),"") -> Collection Loss / Bad Debt | C10: Write Off Rent Recovery | D10: 578.27 | E10: 1879.47 | F10: 769.11 | G10: 435.61 | H10: 1925.3 | I10: 589.48 | J10: 717.3 | K10: 655.42 | L10: 599.36 | M10: 779.74 | N10: 317.12 | O10: 794.2 | P10: =SUM(D10:O10) -> 10040.38
A11: park | B11: =IFERROR(VLOOKUP($A11,Codes!$A:$B,2,FALSE()),"") -> Garage / Parking | C11: Garage | D11: 17933.17 | E11: 17644.06 | F11: 17812.97 | G11: 17705.81 | H11: 17039.62 | I11: 18121.15 | J11: 19020.19 | K11: 18158.39 | L11: 18462.74 | M11: 17206.53 | N11: 18794.28 | O11: 17540.68 | P11: =SUM(D11:O11) -> 215439.59
A12: park | B12: =IFERROR(VLOOKUP($A12,Codes!$A:$B,2,FALSE()),"") -> Garage / Parking | C12: Carport | D12: 2127.33 | E12: 2102.45 | F12: 2038.51 | G12: 2079.53 | H12: 2420.92 | I12: 2363.18 | J12: 2017.34 | K12: 1968.54 | L12: 2014.68 | M12: 1888.53 | N12: 2091.97 | O12: 2092.55 | P12: =SUM(D12:O12) -> 25205.53
A13: park | B13: =IFERROR(VLOOKUP($A13,Codes!$A:$B,2,FALSE()),"") -> Garage / Parking | C13: Storage | D13: 145 | E13: 203.06 | F13: 165.65 | G13: 145 | H13: 145 | I13: 172.1 | J13: 183.83 | K13: 160 | L13: 160 | M13: 160 | N13: 160 | O13: 160 | P13: =SUM(D13:O13) -> 1959.64
A14: Rentinc | B14: =IFERROR(VLOOKUP($A14,Codes!$A:$B,2,FALSE()),"") -> Rental Income | C14: Mtm Premium | D14: 1212.9 | E14: 1133.33 | F14: 1122.58 | G14: 464.52 | H14: 400 | I14: 619.35 | J14: 200 | K14: 670.97 | L14: 516.13 | M14: 557.14 | N14: 982.26 | O14: 736.66 | P14: =SUM(D14:O14) -> 8615.84
... A33: RF | B33: =IFERROR(VLOOKUP($A33,Codes!$A:$B,2,FALSE()),"") -> Rubs Fees | C33: Reimbursed Pest Control | D33: 1291.59 | E33: 1301.26 | F33: 1340.74 | G33: 1341.46 | H33: 1310.48 | I33: 1317.11 | J33: 1313.62 | K33: 1331.48 | L33: 1302.91 | M33: 1236.96 | N33: 1214.7 | O33: 1329.41 | P33: =SUM(D33:O33) -> 15631.72
C34: OPERATING EXPENSES
A35: Pay | B35: =IFERROR(VLOOKUP($A35,Codes!$A:$B,2,FALSE()),"") -> Payroll | C35: Manager | D35: 11183.45 | E35: 6763.32 | F35: 6417.17 | G35: 7455.63 | H35: 7109.48 | I35: 10144.98 | J35: 6763.33 | K35: 7455.62 | L35: 6417.17 | M35: 7455.63 | N35: 7548.71 | O35: 11183.46 | P35: =SUM(D35:O35) -> 95897.95
A36: Pay | B36: =IFERROR(VLOOKUP($A36,Codes!$A:$B,2,FALSE()),"") -> Payroll | C36: Assistant Manager | D36: 4985.05 | E36: 3181.73 | F36: 3484.61 | G36: 3459.09 | H36: 3496.35 | I36: 1821.58 | J36: 2674.18 | K36: 3445.1 | L36: 3233.37 | M36: 3364.43 | N36: 3195.15 | O36: 20.29 | P36: =SUM(D36:O36) -> 36360.93
A37: Pay | B37: =IFERROR(VLOOKUP($A37,Codes!$A:$B,2,FALSE()),"") -> Payroll | C37: Leasing Consultant | D37: 4815.47 | E37: 3201.04 | F37: 2469.79 | G37: 2622.8 | H37: 3183.66 | I37: 4160.93 | J37: 3024.4 | K37: 2801.38 | L37: 3131.45 | M37: 3080.91 | N37: 3225.07 | O37: 2285.55 | P37: =SUM(D37:O37) -> 38002.45
A38: Pay | B38: =IFERROR(VLOOKUP($A38,Codes!$A:$B,2,FALSE()),"") -> Payroll | C38: Divisional Maint Mgr | D38: 0 | E38: 0 | F38: 0 | G38: 249.68 | H38: 0 | I38: 0 | J38: 0 | K38: 0 | L38: 0 | M38: 0 | N38: 0 | O38: 0 | P38: =SUM(D38:O38) -> 249.68
A39: Pay | B39: =IFERROR(VLOOKUP($A39,Codes!$A:$B,2,FALSE()),"") -> Payroll | C39: Maintenance Manager | D39: 8573.27 | E39: 5709.81 | F39: 5306.73 | G39: 9256.24 | H39: 5620.23 | I39: 8255.05 | J39: 5721.34 | K39: 5443.68 | L39: 5105.94 | M39: 5492.05 | N39: 5945.75 | O39: 8045.39 | P39: =SUM(D39:O39) -> 78475.48
A40: Pay | B40: =IFERROR(VLOOKUP($A40,Codes!$A:$B,2,FALSE()),"") -> Payroll | C40: Asst Maintenance Mgr | D40: 424.39 | E40: 0 | F40: 264.7 | G40: 713.81 | H40: 1.35 | I40: 0 | J40: 0 | K40: 0 | L40: 0 | M40: 0 | N40: 0 | O40: 0 | P40: =SUM(D40:O40) -> 1404.25
A41: Pay | B41: =IFERROR(VLOOKUP($A41,Codes!$A:$B,2,FALSE()),"") -> Payroll | C41: Maintenance Technician | D41: 7238.87 | E41: 4407.65 | F41: 3360.95 | G41: 0 | H41: 2692.2 | I41: 6805.36 | J41: 4405.9 | K41: 4379.48 | L41: 4196.6 | M41: 4537.2 | N41: 4324 | O41: 6688.79 | P41: =SUM(D41:O41) -> 53037
A42: Pay | B42: =IFERROR(VLOOKUP($A42,Codes!$A:$B,2,FALSE()),"") -> Payroll | C42: Porter/Grounds Person | D42: 4058.81 | E42: 2560.33 | F42: 2541.82 | G42: 1573.42 | H42: 2356.5 | I42: 1740.96 | J42: 3101.56 | K42: 3122.56 | L42: 3108.76 | M42: 3017.86 | N42: 2971.06 | O42: 4372.44 | P42: =SUM(D42:O42) -> 34526.08
A43: Pay | B43: =IFERROR(VLOOKUP($A43,Codes!$A:$B,2,FALSE()),"") -> Payroll | C43: Housekeeper | D43: 4448.69 | E43: 2567.02 | F43: 2456.43 | G43: 2764.12 | H43: 1488.14 | I43: 4444.05 | J43: 2180.93 | K43: 2847.61 | L43: 2373.07 | M43: 2949.66 | N43: 2963.83 | O43: 4169.19 | P43: =SUM(D43:O43) -> 35652.74
A44: PBo | B44: =IFERROR(VLOOKUP($A44,Codes!$A:$B,2,FALSE()),"") -> Payroll Bonuses | C44: Bonuses | D44: 5804.95 | E44: 2953.87 | F44: 2444.96 | G44: 4250.44 | H44: 7587 | I44: 3435.35 | J44: 1055.26 | K44: 4772.8 | L44: 7182.49 | M44: 2932.09 | N44: 11664.54 | O44: 5933.22 | P44: =SUM(D44:O44) -> 60016.97
A45: PB | B45: =IFERROR(VLOOKUP($A45,Codes!$A:$B,2,FALSE()),"") -> Payroll Burden | C45: Payroll Taxes - Administrative | D45: 1870.45 | E45: 1208.23 | F45: 1157.02 | G45: 1404.62 | H45: 1235.74 | I45: 1444.62 | J45: 1245.42 | K45: 1278.47 | L45: 1553.4 | M45: 1726.13 | N45: 1549.35 | O45: 1804.01 | P45: =SUM(D45:O45) -> 17477.46
A46: PB | B46: =IFERROR(VLOOKUP($A46,Codes!$A:$B,2,FALSE()),"") -> Payroll Burden | C46: Payroll Taxes - Maintenance | D46: 1898.48 | E46: 1177.76 | F46: 1304.91 | G46: 1421.7 | H46: 1056.7 | I46: 1899.14 | J46: 1349.98 | K46: 1332.07 | L46: 1554.69 | M46: 1835.24 | N46: 1678.04 | O46: 2104.93 | P46: =SUM(D46:O46) -> 18613.64
... A137: ret | B137: =IFERROR(VLOOKUP($A137,Codes!$A:$B,2,FALSE()),"") -> Real Estate Taxes | C137: Homeowners Association Fees | D137: 0 | E137: 0 | F137: 0 | G137: 0 | H137: 0 | I137: 57792.2 | J137: 0 | K137: 0 | L137: 0 | M137: 0 | N137: 0 | O137: 0 | P137: =SUM(D137:O137) -> 57792.2
A139: Outliers & Notable Patterns (amber month cells = > 3.5× that line's median)
A140: • Plumbing Supplies: Aug 2025 = $5,655 (55.4× the line's median) — one-off / reclass worth checking.
A141: • Marketing Dues & Subscriptions: Dec 2025 = $4,639 (10.9× the line's median) — one-off / reclass worth checking.
A142: • Internet Listing Service (ILS): May 2025 = $5,290 (7.0× the line's median) — one-off / reclass worth checking.
A143: • Training & Education: May 2025 = $2,708 (5.3× the line's median) — one-off / reclass worth checking.
A144: • Fire/Life Safety: May 2025 = $8,341 (4.9× the line's median) — one-off / reclass worth checking.
A145: • Locator/Broker Fees: Jul 2025 = $9,580 (4.7× the line's median) — one-off / reclass worth checking.
A146: • Water Irrigation: Jul 2025 = $5,908 (4.2× the line's median) — one-off / reclass worth checking.
A147: • Temp Help - Maintenance: Jun 2025 = $11,823 (4.1× the line's median) — one-off / reclass worth checking.

Sheet OS Summary
B1: Aura Beacon Island
B2: Operating Statement — Standardized (live rollup)
B3: Adjusted Amounts ($ totals) — model paste target (A1:Q77)
C4: Annual | D4: Annual | E4: Annual | F4: Monthly | G4: Monthly | H4: Monthly | I4: Monthly | J4: Monthly | K4: Monthly | L4: Monthly | M4: Monthly | N4: Monthly | O4: Monthly | P4: Monthly | Q4: Monthly
F5: 45778 | G5: 45809 | H5: 45839 | I5: 45870 | J5: 45901 | K5: 45931 | L5: 45962 | M5: 45992 | N5: 46023 | O5: 46054 | P5: 46082 | Q5: 46113
A6: Code | B6: Effective Gross Revenue
A7: Rentinc | B7: Rental Income | F7: =SUMIFS('T12 Categorized'!D:D,'T12 Categorized'!$A:$A,$A7) -> 560362.9 | G7: =SUMIFS('T12 Categorized'!E:E,'T12 Categorized'!$A:$A,$A7) -> 560283.33 | H7: =SUMIFS('T12 Categorized'!F:F,'T12 Categorized'!$A:$A,$A7) -> 560272.58 | I7: =SUMIFS('T12 Categorized'!G:G,'T12 Categorized'!$A:$A,$A7) -> 559614.52 | J7: =SUMIFS('T12 Categorized'!H:H,'T12 Categorized'!$A:$A,$A7) -> 559550 | K7: =SUMIFS('T12 Categorized'!I:I,'T12 Categorized'!$A:$A,$A7) -> 559769.35 | L7: =SUMIFS('T12 Categorized'!J:J,'T12 Categorized'!$A:$A,$A7) -> 559350 | M7: =SUMIFS('T12 Categorized'!K:K,'T12 Categorized'!$A:$A,$A7) -> 559820.97 | N7: =SUMIFS('T12 Categorized'!L:L,'T12 Categorized'!$A:$A,$A7) -> 559666.13 | O7: =SUMIFS('T12 Categorized'!M:M,'T12 Categorized'!$A:$A,$A7) -> 559707.14 | P7: =SUMIFS('T12 Categorized'!N:N,'T12 Categorized'!$A:$A,$A7) -> 560132.26 | Q7: =SUMIFS('T12 Categorized'!O:O,'T12 Categorized'!$A:$A,$A7) -> 559886.66
A8: OI | B8: Other Income | F8: =SUMIFS('T12 Categorized'!D:D,'T12 Categorized'!$A:$A,$A8) -> 8089.05 | G8: =SUMIFS('T12 Categorized'!E:E,'T12 Categorized'!$A:$A,$A8) -> 13543.97 | H8: =SUMIFS('T12 Categorized'!F:F,'T12 Categorized'!$A:$A,$A8) -> 2301.9 | I8: =SUMIFS('T12 Categorized'!G:G,'T12 Categorized'!$A:$A,$A8) -> 7760.52 | J8: =SUMIFS('T12 Categorized'!H:H,'T12 Categorized'!$A:$A,$A8) -> 16194.51 | K8: =SUMIFS('T12 Categorized'!I:I,'T12 Categorized'!$A:$A,$A8) -> 15595.09 | L8: =SUMIFS('T12 Categorized'!J:J,'T12 Categorized'!$A:$A,$A8) -> 21356.58 | M8: =SUMIFS('T12 Categorized'!K:K,'T12 Categorized'!$A:$A,$A8) -> 6500.52 | N8: =SUMIFS('T12 Categorized'!L:L,'T12 Categorized'!$A:$A,$A8) -> 11917.51 | O8: =SUMIFS('T12 Categorized'!M:M,'T12 Categorized'!$A:$A,$A8) -> 10691.33 | P8: =SUMIFS('T12 Categorized'!N:N,'T12 Categorized'!$A:$A,$A8) -> 17428.26 | Q8: =SUMIFS('T12 Categorized'!O:O,'T12 Categorized'!$A:$A,$A8) -> 23681.5
A9: RWS | B9: Rubs Water / Sewage | F9: =SUMIFS('T12 Categorized'!D:D,'T12 Categorized'!$A:$A,$A9) -> 6959.11 | G9: =SUMIFS('T12 Categorized'!E:E,'T12 Categorized'!$A:$A,$A9) -> 7143.5 | H9: =SUMIFS('T12 Categorized'!F:F,'T12 Categorized'!$A:$A,$A9) -> 7380.64 | I9: =SUMIFS('T12 Categorized'!G:G,'T12 Categorized'!$A:$A,$A9) -> 7337.77 | J9: =SUMIFS('T12 Categorized'!H:H,'T12 Categorized'!$A:$A,$A9) -> 7228.83 | K9: =SUMIFS('T12 Categorized'!I:I,'T12 Categorized'!$A:$A,$A9) -> 7292.49 | L9: =SUMIFS('T12 Categorized'!J:J,'T12 Categorized'!$A:$A,$A9) -> 6808.47 | M9: =SUMIFS('T12 Categorized'!K:K,'T12 Categorized'!$A:$A,$A9) -> 6969.01 | N9: =SUMIFS('T12 Categorized'!L:L,'T12 Categorized'!$A:$A,$A9) -> 6428.92 | O9: =SUMIFS('T12 Categorized'!M:M,'T12 Categorized'!$A:$A,$A9) -> 6438.11 | P9: =SUMIFS('T12 Categorized'!N:N,'T12 Categorized'!$A:$A,$A9) -> 6786.85 | Q9: =SUMIFS('T12 Categorized'!O:O,'T12 Categorized'!$A:$A,$A9) -> 6531.75
A10: RT | B10: Rubs Trash | F10: =SUMIFS('T12 Categorized'!D:D,'T12 Categorized'!$A:$A,$A10) -> 7588.49 | G10: =SUMIFS('T12 Categorized'!E:E,'T12 Categorized'!$A:$A,$A10) -> 7495.05 | H10: =SUMIFS('T12 Categorized'!F:F,'T12 Categorized'!$A:$A,$A10) -> 7663.84 | I10: =SUMIFS('T12 Categorized'!G:G,'T12 Categorized'!$A:$A,$A10) -> 7618.37 | J10: =SUMIFS('T12 Categorized'!H:H,'T12 Categorized'!$A:$A,$A10) -> 7467.65 | K10: =SUMIFS('T12 Categorized'!I:I,'T12 Categorized'!$A:$A,$A10) -> 7585.84 | L10: =SUMIFS('T12 Categorized'!J:J,'T12 Categorized'!$A:$A,$A10) -> 7579.56 | M10: =SUMIFS('T12 Categorized'!K:K,'T12 Categorized'!$A:$A,$A10) -> 6915.2 | N10: =SUMIFS('T12 Categorized'!L:L,'T12 Categorized'!$A:$A,$A10) -> 7073.64 | O10: =SUMIFS('T12 Categorized'!M:M,'T12 Categorized'!$A:$A,$A10) -> 6874.17 | P10: =SUMIFS('T12 Categorized'!N:N,'T12 Categorized'!$A:$A,$A10) -> 7143.6 | Q10: =SUMIFS('T12 Categorized'!O:O,'T12 Categorized'!$A:$A,$A10) -> 7132.04
A11: RF | B11: Rubs Fees | F11: =SUMIFS('T12 Categorized'!D:D,'T12 Categorized'!$A:$A,$A11) -> 1537.67 | G11: =SUMIFS('T12 Categorized'!E:E,'T12 Categorized'!$A:$A,$A11) -> 1543.28 | H11: =SUMIFS('T12 Categorized'!F:F,'T12 Categorized'!$A:$A,$A11) -> 1471.98 | I11: =SUMIFS('T12 Categorized'!G:G,'T12 Categorized'!$A:$A,$A11) -> 1528.12 | J11: =SUMIFS('T12 Categorized'!H:H,'T12 Categorized'!$A:$A,$A11) -> 1318.6 | K11: =SUMIFS('T12 Categorized'!I:I,'T12 Categorized'!$A:$A,$A11) -> 1411.99 | L11: =SUMIFS('T12 Categorized'!J:J,'T12 Categorized'!$A:$A,$A11) -> 1434.13 | M11: =SUMIFS('T12 Categorized'!K:K,'T12 Categorized'!$A:$A,$A11) -> 1736.61 | N11: =SUMIFS('T12 Categorized'!L:L,'T12 Categorized'!$A:$A,$A11) -> 1383.14 | O11: =SUMIFS('T12 Categorized'!M:M,'T12 Categorized'!$A:$A,$A11) -> 1258.28 | P11: =SUMIFS('T12 Categorized'!N:N,'T12 Categorized'!$A:$A,$A11) -> 1310.28 | Q11: =SUMIFS('T12 Categorized'!O:O,'T12 Categorized'!$A:$A,$A11) -> 1480.36
A12: park | B12: Garage / Parking | F12: =SUMIFS('T12 Categorized'!D:D,'T12 Categorized'!$A:$A,$A12) -> 20205.5 | G12: =SUMIFS('T12 Categorized'!E:E,'T12 Categorized'!$A:$A,$A12) -> 19949.57 | H12: =SUMIFS('T12 Categorized'!F:F,'T12 Categorized'!$A:$A,$A12) -> 20017.13 | I12: =SUMIFS('T12 Categorized'!G:G,'T12 Categorized'!$A:$A,$A12) -> 19930.34 | J12: =SUMIFS('T12 Categorized'!H:H,'T12 Categorized'!$A:$A,$A12) -> 19605.54 | K12: =SUMIFS('T12 Categorized'!I:I,'T12 Categorized'!$A:$A,$A12) -> 20656.43 | L12: =SUMIFS('T12 Categorized'!J:J,'T12 Categorized'!$A:$A,$A12) -> 21221.36 | M12: =SUMIFS('T12 Categorized'!K:K,'T12 Categorized'!$A:$A,$A12) -> 20286.93 | N12: =SUMIFS('T12 Categorized'!L:L,'T12 Categorized'!$A:$A,$A12) -> 20637.42 | O12: =SUMIFS('T12 Categorized'!M:M,'T12 Categorized'!$A:$A,$A12) -> 19255.06 | P12: =SUMIFS('T12 Categorized'!N:N,'T12 Categorized'!$A:$A,$A12) -> 21046.25 | Q12: =SUMIFS('T12 Categorized'!O:O,'T12 Categorized'!$A:$A,$A12) -> 19793.23
A13: CI | B13: Corporate Income | F13: =SUMIFS('T12 Categorized'!D:D,'T12 Categorized'!$A:$A,$A13) -> 0 | G13: =SUMIFS('T12 Categorized'!E:E,'T12 Categorized'!$A:$A,$A13) -> 0 | H13: =SUMIFS('T12 Categorized'!F:F,'T12 Categorized'!$A:$A,$A13) -> 0 | I13: =SUMIFS('T12 Categorized'!G:G,'T12 Categorized'!$A:$A,$A13) -> 0 | J13: =SUMIFS('T12 Categorized'!H:H,'T12 Categorized'!$A:$A,$A13) -> 0 | K13: =SUMIFS('T12 Categorized'!I:I,'T12 Categorized'!$A:$A,$A13) -> 0 | L13: =SUMIFS('T12 Categorized'!J:J,'T12 Categorized'!$A:$A,$A13) -> 0 | M13: =SUMIFS('T12 Categorized'!K:K,'T12 Categorized'!$A:$A,$A13) -> 0 | N13: =SUMIFS('T12 Categorized'!L:L,'T12 Categorized'!$A:$A,$A13) -> 0 | O13: =SUMIFS('T12 Categorized'!M:M,'T12 Categorized'!$A:$A,$A13) -> 0 | P13: =SUMIFS('T12 Categorized'!N:N,'T12 Categorized'!$A:$A,$A13) -> 0 | Q13: =SUMIFS('T12 Categorized'!O:O,'T12 Categorized'!$A:$A,$A13) -> 0
A14: cable | B14: Cable Income | F14: =SUMIFS('T12 Categorized'!D:D,'T12 Categorized'!$A:$A,$A14) -> 0 | G14: =SUMIFS('T12 Categorized'!E:E,'T12 Categorized'!$A:$A,$A14) -> 0 | H14: =SUMIFS('T12 Categorized'!F:F,'T12 Categorized'!$A:$A,$A14) -> 0 | I14: =SUMIFS('T12 Categorized'!G:G,'T12 Categorized'!$A:$A,$A14) -> 0 | J14: =SUMIFS('T12 Categorized'!H:H,'T12 Categorized'!$A:$A,$A14) -> 0 | K14: =SUMIFS('T12 Categorized'!I:I,'T12 Categorized'!$A:$A,$A14) -> 0 | L14: =SUMIFS('T12 Categorized'!J:J,'T12 Categorized'!$A:$A,$A14) -> 0 | M14: =SUMIFS('T12 Categorized'!K:K,'T12 Categorized'!$A:$A,$A14) -> 0 | N14: =SUMIFS('T12 Categorized'!L:L,'T12 Categorized'!$A:$A,$A14) -> 0 | O14: =SUMIFS('T12 Categorized'!M:M,'T12 Categorized'!$A:$A,$A14) -> 0 | P14: =SUMIFS('T12 Categorized'!N:N,'T12 Categorized'!$A:$A,$A14) -> 0 | Q14: =SUMIFS('T12 Categorized'!O:O,'T12 Categorized'!$A:$A,$A14) -> 0
A15: ltl | B15: (Loss to Lease) / Gain to Lease | F15: =SUMIFS('T12 Categorized'!D:D,'T12 Categorized'!$A:$A,$A15) -> -27581 | G15: =SUMIFS('T12 Categorized'!E:E,'T12 Categorized'!$A:$A,$A15) -> -27745 | H15: =SUMIFS('T12 Categorized'!F:F,'T12 Categorized'!$A:$A,$A15) -> -26926 | I15: =SUMIFS('T12 Categorized'!G:G,'T12 Categorized'!$A:$A,$A15) -> -25054 | J15: =SUMIFS('T12 Categorized'!H:H,'T12 Categorized'!$A:$A,$A15) -> -24168 | K15: =SUMIFS('T12 Categorized'!I:I,'T12 Categorized'!$A:$A,$A15) -> -23750 | L15: =SUMIFS('T12 Categorized'!J:J,'T12 Categorized'!$A:$A,$A15) -> -24711 | M15: =SUMIFS('T12 Categorized'!K:K,'T12 Categorized'!$A:$A,$A15) -> -24276 | N15: =SUMIFS('T12 Categorized'!L:L,'T12 Categorized'!$A:$A,$A15) -> -24152 | O15: =SUMIFS('T12 Categorized'!M:M,'T12 Categorized'!$A:$A,$A15) -> -27423 | P15: =SUMIFS('T12 Categorized'!N:N,'T12 Categorized'!$A:$A,$A15) -> -28527 | Q15: =SUMIFS('T12 Categorized'!O:O,'T12 Categorized'!$A:$A,$A15) -> -28582
A16: vac | B16: Vacancy | F16: =SUMIFS('T12 Categorized'!D:D,'T12 Categorized'!$A:$A,$A16) -> -32059.41 | G16: =SUMIFS('T12 Categorized'!E:E,'T12 Categorized'!$A:$A,$A16) -> -39950.81 | H16: =SUMIFS('T12 Categorized'!F:F,'T12 Categorized'!$A:$A,$A16) -> -32160.7 | I16: =SUMIFS('T12 Categorized'!G:G,'T12 Categorized'!$A:$A,$A16) -> -36295.85 | J16: =SUMIFS('T12 Categorized'!H:H,'T12 Categorized'!$A:$A,$A16) -> -45481.47 | K16: =SUMIFS('T12 Categorized'!I:I,'T12 Categorized'!$A:$A,$A16) -> -33225.96 | L16: =SUMIFS('T12 Categorized'!J:J,'T12 Categorized'!$A:$A,$A16) -> -39789.69 | M16: =SUMIFS('T12 Categorized'!K:K,'T12 Categorized'!$A:$A,$A16) -> -54891.16 | N16: =SUMIFS('T12 Categorized'!L:L,'T12 Categorized'!$A:$A,$A16) -> -63024.55 | O16: =SUMIFS('T12 Categorized'!M:M,'T12 Categorized'!$A:$A,$A16) -> -51062.94 | P16: =SUMIFS('T12 Categorized'!N:N,'T12 Categorized'!$A:$A,$A16) -> -37121.02 | Q16: =SUMIFS('T12 Categorized'!O:O,'T12 Categorized'!$A:$A,$A16) -> -36993.26
A17: cl | B17: Collection Loss / Bad Debt | F17: =SUMIFS('T12 Categorized'!D:D,'T12 Categorized'!$A:$A,$A17) -> 578.27 | G17: =SUMIFS('T12 Categorized'!E:E,'T12 Categorized'!$A:$A,$A17) -> 31.07 | H17: =SUMIFS('T12 Categorized'!F:F,'T12 Categorized'!$A:$A,$A17) -> 769.11 | I17: =SUMIFS('T12 Categorized'!G:G,'T12 Categorized'!$A:$A,$A17) -> 435.61 | J17: =SUMIFS('T12 Categorized'!H:H,'T12 Categorized'!$A:$A,$A17) -> 1925.3 | K17: =SUMIFS('T12 Categorized'!I:I,'T12 Categorized'!$A:$A,$A17) -> 361.48 | L17: =SUMIFS('T12 Categorized'!J:J,'T12 Categorized'!$A:$A,$A17) -> 717.3 | M17: =SUMIFS('T12 Categorized'!K:K,'T12 Categorized'!$A:$A,$A17) -> 655.42 | N17: =SUMIFS('T12 Categorized'!L:L,'T12 Categorized'!$A:$A,$A17) -> 9.03 | O17: =SUMIFS('T12 Categorized'!M:M,'T12 Categorized'!$A:$A,$A17) -> 744.14 | P17: =SUMIFS('T12 Categorized'!N:N,'T12 Categorized'!$A:$A,$A17) -> 317.12 | Q17: =SUMIFS('T12 Categorized'!O:O,'T12 Categorized'!$A:$A,$A17) -> 794.2
A18: nr | B18: Non-Revenue Units | F18: =SUMIFS('T12 Categorized'!D:D,'T12 Categorized'!$A:$A,$A18) -> -3120 | G18: =SUMIFS('T12 Categorized'!E:E,'T12 Categorized'!$A:$A,$A18) -> -3120 | H18: =SUMIFS('T12 Categorized'!F:F,'T12 Categorized'!$A:$A,$A18) -> -3120 | I18: =SUMIFS('T12 Categorized'!G:G,'T12 Categorized'!$A:$A,$A18) -> -3120 | J18: =SUMIFS('T12 Categorized'!H:H,'T12 Categorized'!$A:$A,$A18) -> -3120 | K18: =SUMIFS('T12 Categorized'!I:I,'T12 Categorized'!$A:$A,$A18) -> -3120 | L18: =SUMIFS('T12 Categorized'!J:J,'T12 Categorized'!$A:$A,$A18) -> -3120 | M18: =SUMIFS('T12 Categorized'!K:K,'T12 Categorized'!$A:$A,$A18) -> -3120 | N18: =SUMIFS('T12 Categorized'!L:L,'T12 Categorized'!$A:$A,$A18) -> -3120 | O18: =SUMIFS('T12 Categorized'!M:M,'T12 Categorized'!$A:$A,$A18) -> -3120 | P18: =SUMIFS('T12 Categorized'!N:N,'T12 Categorized'!$A:$A,$A18) -> -3120 | Q18: =SUMIFS('T12 Categorized'!O:O,'T12 Categorized'!$A:$A,$A18) -> -2340
A19: conc | B19: Concessions | F19: =SUMIFS('T12 Categorized'!D:D,'T12 Categorized'!$A:$A,$A19) -> -51396.97 | G19: =SUMIFS('T12 Categorized'!E:E,'T12 Categorized'!$A:$A,$A19) -> -36344.5 | H19: =SUMIFS('T12 Categorized'!F:F,'T12 Categorized'!$A:$A,$A19) -> -41734.5 | I19: =SUMIFS('T12 Categorized'!G:G,'T12 Categorized'!$A:$A,$A19) -> -40560 | J19: =SUMIFS('T12 Categorized'!H:H,'T12 Categorized'!$A:$A,$A19) -> -23142 | K19: =SUMIFS('T12 Categorized'!I:I,'T12 Categorized'!$A:$A,$A19) -> -21379.5 | L19: =SUMIFS('T12 Categorized'!J:J,'T12 Categorized'!$A:$A,$A19) -> -23729 | M19: =SUMIFS('T12 Categorized'!K:K,'T12 Categorized'!$A:$A,$A19) -> -23776 | N19: =SUMIFS('T12 Categorized'!L:L,'T12 Categorized'!$A:$A,$A19) -> -29613.92 | O19: =SUMIFS('T12 Categorized'!M:M,'T12 Categorized'!$A:$A,$A19) -> -31630 | P19: =SUMIFS('T12 Categorized'!N:N,'T12 Categorized'!$A:$A,$A19) -> -41571.5 | Q19: =SUMIFS('T12 Categorized'!O:O,'T12 Categorized'!$A:$A,$A19) -> -45133.5
B20: Effective Gross Revenue | F20: =SUM(F7:F19) -> 491163.61 | G20: =SUM(G7:G19) -> 502829.46 | H20: =SUM(H7:H19) -> 495935.98 | I20: =SUM(I7:I19) -> 499195.4 | J20: =SUM(J7:J19) -> 517378.96 | K20: =SUM(K7:K19) -> 531197.21 | L20: =SUM(L7:L19) -> 527117.71 | M20: =SUM(M7:M19) -> 496821.5 | ... Q20: =SUM(Q7:Q19) -> 506250.98
B22: Operating Expenses
A23: Pay | B23: Payroll | F23: =SUMIFS('T12 Categorized'!D:D,'T12 Categorized'!$A:$A,$A23) -> 47514.19 | G23: =SUMIFS('T12 Categorized'!E:E,'T12 Categorized'!$A:$A,$A23) -> 42160.49 | H23: =SUMIFS('T12 Categorized'!F:F,'T12 Categorized'!$A:$A,$A23) -> 35025.93 | I23: =SUMIFS('T12 Categorized'!G:G,'T12 Categorized'!$A:$A,$A23) -> 35609.56 | J23: =SUMIFS('T12 Categorized'!H:H,'T12 Categorized'!$A:$A,$A23) -> 26120.12 | K23: =SUMIFS('T12 Categorized'!I:I,'T12 Categorized'!$A:$A,$A23) -> 43340.74 | L23: =SUMIFS('T12 Categorized'!J:J,'T12 Categorized'!$A:$A,$A23) -> 29301.81 | M23: =SUMIFS('T12 Categorized'!K:K,'T12 Categorized'!$A:$A,$A23) -> 35972.44 | N23: =SUMIFS('T12 Categorized'!L:L,'T12 Categorized'!$A:$A,$A23) -> 29885.56 | O23: =SUMIFS('T12 Categorized'!M:M,'T12 Categorized'!$A:$A,$A23) -> 31936.37 | P23: =SUMIFS('T12 Categorized'!N:N,'T12 Categorized'!$A:$A,$A23) -> 33109.17 | Q23: =SUMIFS('T12 Categorized'!O:O,'T12 Categorized'!$A:$A,$A23) -> 40455.79
A24: PB | B24: Payroll Burden | F24: =SUMIFS('T12 Categorized'!D:D,'T12 Categorized'!$A:$A,$A24) -> 4854.84 | G24: =SUMIFS('T12 Categorized'!E:E,'T12 Categorized'!$A:$A,$A24) -> 3083.18 | H24: =SUMIFS('T12 Categorized'!F:F,'T12 Categorized'!$A:$A,$A24) -> 3169.32 | I24: =SUMIFS('T12 Categorized'!G:G,'T12 Categorized'!$A:$A,$A24) -> 3555.02 | J24: =SUMIFS('T12 Categorized'!H:H,'T12 Categorized'!$A:$A,$A24) -> 2864.74 | K24: =SUMIFS('T12 Categorized'!I:I,'T12 Categorized'!$A:$A,$A24) -> 4025.34 | L24: =SUMIFS('T12 Categorized'!J:J,'T12 Categorized'!$A:$A,$A24) -> 3286.26 | M24: =SUMIFS('T12 Categorized'!K:K,'T12 Categorized'!$A:$A,$A24) -> 3300.42 | N24: =SUMIFS('T12 Categorized'!L:L,'T12 Categorized'!$A:$A,$A24) -> 3831.22 | O24: =SUMIFS('T12 Categorized'!M:M,'T12 Categorized'!$A:$A,$A24) -> 4210.74 | P24: =SUMIFS('T12 Categorized'!N:N,'T12 Categorized'!$A:$A,$A24) -> 3927.4 | Q24: =SUMIFS('T12 Categorized'!O:O,'T12 Categorized'!$A:$A,$A24) -> 4864.51
A25: PBo | B25: Payroll Bonuses | F25: =SUMIFS('T12 Categorized'!D:D,'T12 Categorized'!$A:$A,$A25) -> 5804.95 | G25: =SUMIFS('T12 Categorized'!E:E,'T12 Categorized'!$A:$A,$A25) -> 2953.87 | H25: =SUMIFS('T12 Categorized'!F:F,'T12 Categorized'!$A:$A,$A25) -> 2444.96 | I25: =SUMIFS('T12 Categorized'!G:G,'T12 Categorized'!$A:$A,$A25) -> 4250.44 | J25: =SUMIFS('T12 Categorized'!H:H,'T12 Categorized'!$A:$A,$A25) -> 7587 | K25: =SUMIFS('T12 Categorized'!I:I,'T12 Categorized'!$A:$A,$A25) -> 3435.35 | L25: =SUMIFS('T12 Categorized'!J:J,'T12 Categorized'!$A:$A,$A25) -> 1055.26 | M25: =SUMIFS('T12 Categorized'!K:K,'T12 Categorized'!$A:$A,$A25) -> 4772.8 | N25: =SUMIFS('T12 Categorized'!L:L,'T12 Categorized'!$A:$A,$A25) -> 7182.49 | O25: =SUMIFS('T12 Categorized'!M:M,'T12 Categorized'!$A:$A,$A25) -> 2932.09 | P25: =SUMIFS('T12 Categorized'!N:N,'T12 Categorized'!$A:$A,$A25) -> 11664.54 | Q25: =SUMIFS('T12 Categorized'!O:O,'T12 Categorized'!$A:$A,$A25) -> 5933.22
A26: adv | B26: Marketing / Advertising | F26: =SUMIFS('T12 Categorized'!D:D,'T12 Categorized'!$A:$A,$A26) -> 23263.22 | G26: =SUMIFS('T12 Categorized'!E:E,'T12 Categorized'!$A:$A,$A26) -> 24143.28 | H26: =SUMIFS('T12 Categorized'!F:F,'T12 Categorized'!$A:$A,$A26) -> 32636.04 | I26: =SUMIFS('T12 Categorized'!G:G,'T12 Categorized'!$A:$A,$A26) -> 12131.77 | J26: =SUMIFS('T12 Categorized'!H:H,'T12 Categorized'!$A:$A,$A26) -> 15473.02 | K26: =SUMIFS('T12 Categorized'!I:I,'T12 Categorized'!$A:$A,$A26) -> 14952.05 | L26: =SUMIFS('T12 Categorized'!J:J,'T12 Categorized'!$A:$A,$A26) -> 25697.55 | M26: =SUMIFS('T12 Categorized'!K:K,'T12 Categorized'!$A:$A,$A26) -> 26197.6 | N26: =SUMIFS('T12 Categorized'!L:L,'T12 Categorized'!$A:$A,$A26) -> 10870.19 | O26: =SUMIFS('T12 Categorized'!M:M,'T12 Categorized'!$A:$A,$A26) -> 17144.65 | P26: =SUMIFS('T12 Categorized'!N:N,'T12 Categorized'!$A:$A,$A26) -> 10647.48 | Q26: =SUMIFS('T12 Categorized'!O:O,'T12 Categorized'!$A:$A,$A26) -> 22087.03
A27: GA | B27: General & Administrative | F27: =SUMIFS('T12 Categorized'!D:D,'T12 Categorized'!$A:$A,$A27) -> 11338.36 | G27: =SUMIFS('T12 Categorized'!E:E,'T12 Categorized'!$A:$A,$A27) -> 7288.34 | H27: =SUMIFS('T12 Categorized'!F:F,'T12 Categorized'!$A:$A,$A27) -> 7195.74 | I27: =SUMIFS('T12 Categorized'!G:G,'T12 Categorized'!$A:$A,$A27) -> 9145.64 | J27: =SUMIFS('T12 Categorized'!H:H,'T12 Categorized'!$A:$A,$A27) -> 10112.75 | K27: =SUMIFS('T12 Categorized'!I:I,'T12 Categorized'!$A:$A,$A27) -> 7104.98 | L27: =SUMIFS('T12 Categorized'!J:J,'T12 Categorized'!$A:$A,$A27) -> 7130.14 | M27: =SUMIFS('T12 Categorized'!K:K,'T12 Categorized'!$A:$A,$A27) -> 7674.87 | N27: =SUMIFS('T12 Categorized'!L:L,'T12 Categorized'!$A:$A,$A27) -> 2992.56 | O27: =SUMIFS('T12 Categorized'!M:M,'T12 Categorized'!$A:$A,$A27) -> 9888.61 | P27: =SUMIFS('T12 Categorized'!N:N,'T12 Categorized'!$A:$A,$A27) -> 7589.01 | Q27: =SUMIFS('T12 Categorized'!O:O,'T12 Categorized'!$A:$A,$A27) -> 8156.05
A28: turn | B28: Turnover | F28: =SUMIFS('T12 Categorized'!D:D,'T12 Categorized'!$A:$A,$A28) -> 12238.95 | G28: =SUMIFS('T12 Categorized'!E:E,'T12 Categorized'!$A:$A,$A28) -> 7301.18 | H28: =SUMIFS('T12 Categorized'!F:F,'T12 Categorized'!$A:$A,$A28) -> 9642.41 | I28: =SUMIFS('T12 Categorized'!G:G,'T12 Categorized'!$A:$A,$A28) -> 5349.9 | J28: =SUMIFS('T12 Categorized'!H:H,'T12 Categorized'!$A:$A,$A28) -> 6746.19 | K28: =SUMIFS('T12 Categorized'!I:I,'T12 Categorized'!$A:$A,$A28) -> 3228.24 | L28: =SUMIFS('T12 Categorized'!J:J,'T12 Categorized'!$A:$A,$A28) -> 5587.59 | M28: =SUMIFS('T12 Categorized'!K:K,'T12 Categorized'!$A:$A,$A28) -> 17243.43 | N28: =SUMIFS('T12 Categorized'!L:L,'T12 Categorized'!$A:$A,$A28) -> 6906.11 | O28: =SUMIFS('T12 Categorized'!M:M,'T12 Categorized'!$A:$A,$A28) -> 2769.18 | P28: =SUMIFS('T12 Categorized'!N:N,'T12 Categorized'!$A:$A,$A28) -> 1531.22 | Q28: =SUMIFS('T12 Categorized'!O:O,'T12 Categorized'!$A:$A,$A28) -> 31.18
A29: inter/exte | B29: R&M Interior / Exterior | F29: =SUMIFS('T12 Categorized'!D:D,'T12 Categorized'!$A:$A,$A29) -> 3379.41 | G29: =SUMIFS('T12 Categorized'!E:E,'T12 Categorized'!$A:$A,$A29) -> 5455.23 | H29: =SUMIFS('T12 Categorized'!F:F,'T12 Categorized'!$A:$A,$A29) -> 3778.63 | I29: =SUMIFS('T12 Categorized'!G:G,'T12 Categorized'!$A:$A,$A29) -> 9758.59 | J29: =SUMIFS('T12 Categorized'!H:H,'T12 Categorized'!$A:$A,$A29) -> 8594.46 | K29: =SUMIFS('T12 Categorized'!I:I,'T12 Categorized'!$A:$A,$A29) -> 2430.39 | L29: =SUMIFS('T12 Categorized'!J:J,'T12 Categorized'!$A:$A,$A29) -> 5048.7 | M29: =SUMIFS('T12 Categorized'!K:K,'T12 Categorized'!$A:$A,$A29) -> 7339.77 | N29: =SUMIFS('T12 Categorized'!L:L,'T12 Categorized'!$A:$A,$A29) -> 1253.01 | O29: =SUMIFS('T12 Categorized'!M:M,'T12 Categorized'!$A:$A,$A29) -> 2514.4 | P29: =SUMIFS('T12 Categorized'!N:N,'T12 Categorized'!$A:$A,$A29) -> 4046.05 | Q29: =SUMIFS('T12 Categorized'!O:O,'T12 Categorized'!$A:$A,$A29) -> 12926.31
A30: cont | B30: Contract | F30: =SUMIFS('T12 Categorized'!D:D,'T12 Categorized'!$A:$A,$A30) -> 17519.13 | G30: =SUMIFS('T12 Categorized'!E:E,'T12 Categorized'!$A:$A,$A30) -> 9670.21 | H30: =SUMIFS('T12 Categorized'!F:F,'T12 Categorized'!$A:$A,$A30) -> 13327.98 | I30: =SUMIFS('T12 Categorized'!G:G,'T12 Categorized'!$A:$A,$A30) -> 9633.86 | J30: =SUMIFS('T12 Categorized'!H:H,'T12 Categorized'!$A:$A,$A30) -> 8978.45 | K30: =SUMIFS('T12 Categorized'!I:I,'T12 Categorized'!$A:$A,$A30) -> 10643.63 | L30: =SUMIFS('T12 Categorized'!J:J,'T12 Categorized'!$A:$A,$A30) -> 15811.07 | M30: =SUMIFS('T12 Categorized'!K:K,'T12 Categorized'!$A:$A,$A30) -> 6689.05 | N30: =SUMIFS('T12 Categorized'!L:L,'T12 Categorized'!$A:$A,$A30) -> 15053.13 | O30: =SUMIFS('T12 Categorized'!M:M,'T12 Categorized'!$A:$A,$A30) -> 8712.8 | P30: =SUMIFS('T12 Categorized'!N:N,'T12 Categorized'!$A:$A,$A30) -> -320.19 | Q30: =SUMIFS('T12 Categorized'!O:O,'T12 Categorized'!$A:$A,$A30) -> 18318.41
A31: Safe | B31: Life Safety / Elevators | F31: =SUMIFS('T12 Categorized'!D:D,'T12 Categorized'!$A:$A,$A31) -> 0 | G31: =SUMIFS('T12 Categorized'!E:E,'T12 Categorized'!$A:$A,$A31) -> 0 | H31: =SUMIFS('T12 Categorized'!F:F,'T12 Categorized'!$A:$A,$A31) -> 0 | I31: =SUMIFS('T12 Categorized'!G:G,'T12 Categorized'!$A:$A,$A31) -> 0 | J31: =SUMIFS('T12 Categorized'!H:H,'T12 Categorized'!$A:$A,$A31) -> 0 | K31: =SUMIFS('T12 Categorized'!I:I,'T12 Categorized'!$A:$A,$A31) -> 0 | L31: =SUMIFS('T12 Categorized'!J:J,'T12 Categorized'!$A:$A,$A31) -> 0 | M31: =SUMIFS('T12 Categorized'!K:K,'T12 Categorized'!$A:$A,$A31) -> 0 | N31: =SUMIFS('T12 Categorized'!L:L,'T12 Categorized'!$A:$A,$A31) -> 0 | O31: =SUMIFS('T12 Categorized'!M:M,'T12 Categorized'!$A:$A,$A31) -> 0 | P31: =SUMIFS('T12 Categorized'!N:N,'T12 Categorized'!$A:$A,$A31) -> 0 | Q31: =SUMIFS('T12 Categorized'!O:O,'T12 Categorized'!$A:$A,$A31) -> 0
A32: HAF | B32: Homeowners Association Fees | F32: =SUMIFS('T12 Categorized'!D:D,'T12 Categorized'!$A:$A,$A32) -> 0 | G32: =SUMIFS('T12 Categorized'!E:E,'T12 Categorized'!$A:$A,$A32) -> 0 | H32: =SUMIFS('T12 Categorized'!F:F,'T12 Categorized'!$A:$A,$A32) -> 0 | I32: =SUMIFS('T12 Categorized'!G:G,'T12 Categorized'!$A:$A,$A32) -> 0 | J32: =SUMIFS('T12 Categorized'!H:H,'T12 Categorized'!$A:$A,$A32) -> 0 | K32: =SUMIFS('T12 Categorized'!I:I,'T12 Categorized'!$A:$A,$A32) -> 0 | L32: =SUMIFS('T12 Categorized'!J:J,'T12 Categorized'!$A:$A,$A32) -> 0 | M32: =SUMIFS('T12 Categorized'!K:K,'T12 Categorized'!$A:$A,$A32) -> 0 | N32: =SUMIFS('T12 Categorized'!L:L,'T12 Categorized'!$A:$A,$A32) -> 0 | O32: =SUMIFS('T12 Categorized'!M:M,'T12 Categorized'!$A:$A,$A32) -> 0 | P32: =SUMIFS('T12 Categorized'!N:N,'T12 Categorized'!$A:$A,$A32) -> 0 | Q32: =SUMIFS('T12 Categorized'!O:O,'T12 Categorized'!$A:$A,$A32) -> 0
A33: UT | B33: Utilities Trash | F33: =SUMIFS('T12 Categorized'!D:D,'T12 Categorized'!$A:$A,$A33) -> 0 | G33: =SUMIFS('T12 Categorized'!E:E,'T12 Categorized'!$A:$A,$A33) -> 0 | H33: =SUMIFS('T12 Categorized'!F:F,'T12 Categorized'!$A:$A,$A33) -> 0 | I33: =SUMIFS('T12 Categorized'!G:G,'T12 Categorized'!$A:$A,$A33) -> 0 | J33: =SUMIFS('T12 Categorized'!H:H,'T12 Categorized'!$A:$A,$A33) -> 0 | K33: =SUMIFS('T12 Categorized'!I:I,'T12 Categorized'!$A:$A,$A33) -> 0 | L33: =SUMIFS('T12 Categorized'!J:J,'T12 Categorized'!$A:$A,$A33) -> 0 | M33: =SUMIFS('T12 Categorized'!K:K,'T12 Categorized'!$A:$A,$A33) -> 0 | N33: =SUMIFS('T12 Categorized'!L:L,'T12 Categorized'!$A:$A,$A33) -> 0 | O33: =SUMIFS('T12 Categorized'!M:M,'T12 Categorized'!$A:$A,$A33) -> 0 | P33: =SUMIFS('T12 Categorized'!N:N,'T12 Categorized'!$A:$A,$A33) -> 0 | Q33: =SUMIFS('T12 Categorized'!O:O,'T12 Categorized'!$A:$A,$A33) -> 0
A34: UWS | B34: Utilities Water Sewer | F34: =SUMIFS('T12 Categorized'!D:D,'T12 Categorized'!$A:$A,$A34) -> 10217.44 | G34: =SUMIFS('T12 Categorized'!E:E,'T12 Categorized'!$A:$A,$A34) -> 7301.1 | H34: =SUMIFS('T12 Categorized'!F:F,'T12 Categorized'!$A:$A,$A34) -> 12860.31 | I34: =SUMIFS('T12 Categorized'!G:G,'T12 Categorized'!$A:$A,$A34) -> 7486.59 | J34: =SUMIFS('T12 Categorized'!H:H,'T12 Categorized'!$A:$A,$A34) -> 7214.04 | K34: =SUMIFS('T12 Categorized'!I:I,'T12 Categorized'!$A:$A,$A34) -> 8255.49 | L34: =SUMIFS('T12 Categorized'!J:J,'T12 Categorized'!$A:$A,$A34) -> 11805.66 | M34: =SUMIFS('T12 Categorized'!K:K,'T12 Categorized'!$A:$A,$A34) -> 7754.67 | N34: =SUMIFS('T12 Categorized'!L:L,'T12 Categorized'!$A:$A,$A34) -> 6103.57 | O34: =SUMIFS('T12 Categorized'!M:M,'T12 Categorized'!$A:$A,$A34) -> 4639.58 | P34: =SUMIFS('T12 Categorized'!N:N,'T12 Categorized'!$A:$A,$A34) -> 6046.19 | Q34: =SUMIFS('T12 Categorized'!O:O,'T12 Categorized'!$A:$A,$A34) -> 7377.36
... A41: site | B41: R&M Site | F41: =SUMIFS('T12 Categorized'!D:D,'T12 Categorized'!$A:$A,$A41) -> 0 | G41: =SUMIFS('T12 Categorized'!E:E,'T12 Categorized'!$A:$A,$A41) -> 0 | H41: =SUMIFS('T12 Categorized'!F:F,'T12 Categorized'!$A:$A,$A41) -> 0 | I41: =SUMIFS('T12 Categorized'!G:G,'T12 Categorized'!$A:$A,$A41) -> 0 | J41: =SUMIFS('T12 Categorized'!H:H,'T12 Categorized'!$A:$A,$A41) -> 0 | K41: =SUMIFS('T12 Categorized'!I:I,'T12 Categorized'!$A:$A,$A41) -> 0 | L41: =SUMIFS('T12 Categorized'!J:J,'T12 Categorized'!$A:$A,$A41) -> 0 | M41: =SUMIFS('T12 Categorized'!K:K,'T12 Categorized'!$A:$A,$A41) -> 0 | N41: =SUMIFS('T12 Categorized'!L:L,'T12 Categorized'!$A:$A,$A41) -> 0 | O41: =SUMIFS('T12 Categorized'!M:M,'T12 Categorized'!$A:$A,$A41) -> 0 | P41: =SUMIFS('T12 Categorized'!N:N,'T12 Categorized'!$A:$A,$A41) -> 0 | Q41: =SUMIFS('T12 Categorized'!O:O,'T12 Categorized'!$A:$A,$A41) -> 0
B42: Operating Expenses | F42: =SUM(F23:F41) -> 255793.11 | G42: =SUM(G23:G41) -> 230838.97 | H42: =SUM(H23:H41) -> 242080.33 | I42: =SUM(I23:I41) -> 217832.77 | J42: =SUM(J23:J41) -> 211739.01 | K42: =SUM(K23:K41) -> 281110.25 | L42: =SUM(L23:L41) -> 122488.29 | M42: =SUM(M23:M41) -> 224522.55 | ... Q42: =SUM(Q23:Q41) -> 237340.05
B44: Net Operating Income | F44: =F20-F42 -> 235370.5 | G44: =G20-G42 -> 271990.49 | H44: =H20-H42 -> 253855.65 | I44: =I20-I42 -> 281362.63 | J44: =J20-J42 -> 305639.95 | K44: =K20-K42 -> 250086.96 | L44: =L20-L42 -> 404629.42 | M44: =M20-M42 -> 272298.95 | ... Q44: =Q20-Q42 -> 268910.93
B46: Non-Operating Revenue
A47: dispro | B47: Disposition Proceeds | F47: =SUMIFS('T12 Categorized'!D:D,'T12 Categorized'!$A:$A,$A47) -> 0 | G47: =SUMIFS('T12 Categorized'!E:E,'T12 Categorized'!$A:$A,$A47) -> 0 | H47: =SUMIFS('T12 Categorized'!F:F,'T12 Categorized'!$A:$A,$A47) -> 0 | I47: =SUMIFS('T12 Categorized'!G:G,'T12 Categorized'!$A:$A,$A47) -> 0 | J47: =SUMIFS('T12 Categorized'!H:H,'T12 Categorized'!$A:$A,$A47) -> 0 | K47: =SUMIFS('T12 Categorized'!I:I,'T12 Categorized'!$A:$A,$A47) -> 0 | L47: =SUMIFS('T12 Categorized'!J:J,'T12 Categorized'!$A:$A,$A47) -> 0 | M47: =SUMIFS('T12 Categorized'!K:K,'T12 Categorized'!$A:$A,$A47) -> 0 | N47: =SUMIFS('T12 Categorized'!L:L,'T12 Categorized'!$A:$A,$A47) -> 0 | O47: =SUMIFS('T12 Categorized'!M:M,'T12 Categorized'!$A:$A,$A47) -> 0 | P47: =SUMIFS('T12 Categorized'!N:N,'T12 Categorized'!$A:$A,$A47) -> 0 | Q47: =SUMIFS('T12 Categorized'!O:O,'T12 Categorized'!$A:$A,$A47) -> 0
B48: Non-Operating Revenue | F48: =SUM(F47:F47) -> 0 | G48: =SUM(G47:G47) -> 0 | H48: =SUM(H47:H47) -> 0 | I48: =SUM(I47:I47) -> 0 | J48: =SUM(J47:J47) -> 0 | K48: =SUM(K47:K47) -> 0 | L48: =SUM(L47:L47) -> 0 | M48: =SUM(M47:M47) -> 0 | ... Q48: =SUM(Q47:Q47) -> 0
B50: Non-Operating Expenses
A51: rd | B51: Replacement Reserve Deposits | F51: =SUMIFS('T12 Categorized'!D:D,'T12 Categorized'!$A:$A,$A51) -> 0 | G51: =SUMIFS('T12 Categorized'!E:E,'T12 Categorized'!$A:$A,$A51) -> 0 | H51: =SUMIFS('T12 Categorized'!F:F,'T12 Categorized'!$A:$A,$A51) -> 0 | I51: =SUMIFS('T12 Categorized'!G:G,'T12 Categorized'!$A:$A,$A51) -> 0 | J51: =SUMIFS('T12 Categorized'!H:H,'T12 Categorized'!$A:$A,$A51) -> 0 | K51: =SUMIFS('T12 Categorized'!I:I,'T12 Categorized'!$A:$A,$A51) -> 0 | L51: =SUMIFS('T12 Categorized'!J:J,'T12 Categorized'!$A:$A,$A51) -> 0 | M51: =SUMIFS('T12 Categorized'!K:K,'T12 Categorized'!$A:$A,$A51) -> 0 | N51: =SUMIFS('T12 Categorized'!L:L,'T12 Categorized'!$A:$A,$A51) -> 0 | O51: =SUMIFS('T12 Categorized'!M:M,'T12 Categorized'!$A:$A,$A51) -> 0 | P51: =SUMIFS('T12 Categorized'!N:N,'T12 Categorized'!$A:$A,$A51) -> 0 | Q51: =SUMIFS('T12 Categorized'!O:O,'T12 Categorized'!$A:$A,$A51) -> 0
A52: capx | B52: Capital Improvements | F52: =SUMIFS('T12 Categorized'!D:D,'T12 Categorized'!$A:$A,$A52) -> 0 | G52: =SUMIFS('T12 Categorized'!E:E,'T12 Categorized'!$A:$A,$A52) -> 0 | H52: =SUMIFS('T12 Categorized'!F:F,'T12 Categorized'!$A:$A,$A52) -> 0 | I52: =SUMIFS('T12 Categorized'!G:G,'T12 Categorized'!$A:$A,$A52) -> 0 | J52: =SUMIFS('T12 Categorized'!H:H,'T12 Categorized'!$A:$A,$A52) -> 0 | K52: =SUMIFS('T12 Categorized'!I:I,'T12 Categorized'!$A:$A,$A52) -> 0 | L52: =SUMIFS('T12 Categorized'!J:J,'T12 Categorized'!$A:$A,$A52) -> 0 | M52: =SUMIFS('T12 Categorized'!K:K,'T12 Categorized'!$A:$A,$A52) -> 0 | N52: =SUMIFS('T12 Categorized'!L:L,'T12 Categorized'!$A:$A,$A52) -> 0 | O52: =SUMIFS('T12 Categorized'!M:M,'T12 Categorized'!$A:$A,$A52) -> 0 | P52: =SUMIFS('T12 Categorized'!N:N,'T12 Categorized'!$A:$A,$A52) -> 0 | Q52: =SUMIFS('T12 Categorized'!O:O,'T12 Categorized'!$A:$A,$A52) -> 0
A53: aex | B53: Appliance Expenditures | F53: =SUMIFS('T12 Categorized'!D:D,'T12 Categorized'!$A:$A,$A53) -> 0 | G53: =SUMIFS('T12 Categorized'!E:E,'T12 Categorized'!$A:$A,$A53) -> 0 | H53: =SUMIFS('T12 Categorized'!F:F,'T12 Categorized'!$A:$A,$A53) -> 0 | I53: =SUMIFS('T12 Categorized'!G:G,'T12 Categorized'!$A:$A,$A53) -> 0 | J53: =SUMIFS('T12 Categorized'!H:H,'T12 Categorized'!$A:$A,$A53) -> 0 | K53: =SUMIFS('T12 Categorized'!I:I,'T12 Categorized'!$A:$A,$A53) -> 0 | L53: =SUMIFS('T12 Categorized'!J:J,'T12 Categorized'!$A:$A,$A53) -> 0 | M53: =SUMIFS('T12 Categorized'!K:K,'T12 Categorized'!$A:$A,$A53) -> 0 | N53: =SUMIFS('T12 Categorized'!L:L,'T12 Categorized'!$A:$A,$A53) -> 0 | O53: =SUMIFS('T12 Categorized'!M:M,'T12 Categorized'!$A:$A,$A53) -> 0 | P53: =SUMIFS('T12 Categorized'!N:N,'T12 Categorized'!$A:$A,$A53) -> 0 | Q53: =SUMIFS('T12 Categorized'!O:O,'T12 Categorized'!$A:$A,$A53) -> 0
A54: ece | B54: Extraordinary Capital Expenditure | F54: =SUMIFS('T12 Categorized'!D:D,'T12 Categorized'!$A:$A,$A54) -> 0 | G54: =SUMIFS('T12 Categorized'!E:E,'T12 Categorized'!$A:$A,$A54) -> 0 | H54: =SUMIFS('T12 Categorized'!F:F,'T12 Categorized'!$A:$A,$A54) -> 0 | I54: =SUMIFS('T12 Categorized'!G:G,'T12 Categorized'!$A:$A,$A54) -> 0 | J54: =SUMIFS('T12 Categorized'!H:H,'T12 Categorized'!$A:$A,$A54) -> 0 | K54: =SUMIFS('T12 Categorized'!I:I,'T12 Categorized'!$A:$A,$A54) -> 0 | L54: =SUMIFS('T12 Categorized'!J:J,'T12 Categorized'!$A:$A,$A54) -> 0 | M54: =SUMIFS('T12 Categorized'!K:K,'T12 Categorized'!$A:$A,$A54) -> 0 | N54: =SUMIFS('T12 Categorized'!L:L,'T12 Categorized'!$A:$A,$A54) -> 0 | O54: =SUMIFS('T12 Categorized'!M:M,'T12 Categorized'!$A:$A,$A54) -> 0 | P54: =SUMIFS('T12 Categorized'!N:N,'T12 Categorized'!$A:$A,$A54) -> 0 | Q54: =SUMIFS('T12 Categorized'!O:O,'T12 Categorized'!$A:$A,$A54) -> 0
A55: tird | B55: TI&LC Reserve Deposits | F55: =SUMIFS('T12 Categorized'!D:D,'T12 Categorized'!$A:$A,$A55) -> 0 | G55: =SUMIFS('T12 Categorized'!E:E,'T12 Categorized'!$A:$A,$A55) -> 0 | H55: =SUMIFS('T12 Categorized'!F:F,'T12 Categorized'!$A:$A,$A55) -> 0 | I55: =SUMIFS('T12 Categorized'!G:G,'T12 Categorized'!$A:$A,$A55) -> 0 | J55: =SUMIFS('T12 Categorized'!H:H,'T12 Categorized'!$A:$A,$A55) -> 0 | K55: =SUMIFS('T12 Categorized'!I:I,'T12 Categorized'!$A:$A,$A55) -> 0 | L55: =SUMIFS('T12 Categorized'!J:J,'T12 Categorized'!$A:$A,$A55) -> 0 | M55: =SUMIFS('T12 Categorized'!K:K,'T12 Categorized'!$A:$A,$A55) -> 0 | N55: =SUMIFS('T12 Categorized'!L:L,'T12 Categorized'!$A:$A,$A55) -> 0 | O55: =SUMIFS('T12 Categorized'!M:M,'T12 Categorized'!$A:$A,$A55) -> 0 | P55: =SUMIFS('T12 Categorized'!N:N,'T12 Categorized'!$A:$A,$A55) -> 0 | Q55: =SUMIFS('T12 Categorized'!O:O,'T12 Categorized'!$A:$A,$A55) -> 0
A56: tirw | B56: TI&LC Reserve Withdrawls | F56: =SUMIFS('T12 Categorized'!D:D,'T12 Categorized'!$A:$A,$A56) -> 0 | G56: =SUMIFS('T12 Categorized'!E:E,'T12 Categorized'!$A:$A,$A56) -> 0 | H56: =SUMIFS('T12 Categorized'!F:F,'T12 Categorized'!$A:$A,$A56) -> 0 | I56: =SUMIFS('T12 Categorized'!G:G,'T12 Categorized'!$A:$A,$A56) -> 0 | J56: =SUMIFS('T12 Categorized'!H:H,'T12 Categorized'!$A:$A,$A56) -> 0 | K56: =SUMIFS('T12 Categorized'!I:I,'T12 Categorized'!$A:$A,$A56) -> 0 | L56: =SUMIFS('T12 Categorized'!J:J,'T12 Categorized'!$A:$A,$A56) -> 0 | M56: =SUMIFS('T12 Categorized'!K:K,'T12 Categorized'!$A:$A,$A56) -> 0 | N56: =SUMIFS('T12 Categorized'!L:L,'T12 Categorized'!$A:$A,$A56) -> 0 | O56: =SUMIFS('T12 Categorized'!M:M,'T12 Categorized'!$A:$A,$A56) -> 0 | P56: =SUMIFS('T12 Categorized'!N:N,'T12 Categorized'!$A:$A,$A56) -> 0 | Q56: =SUMIFS('T12 Categorized'!O:O,'T12 Categorized'!$A:$A,$A56) -> 0
A57: tiae | B57: TI&LC Actual Expenditures | F57: =SUMIFS('T12 Categorized'!D:D,'T12 Categorized'!$A:$A,$A57) -> 0 | G57: =SUMIFS('T12 Categorized'!E:E,'T12 Categorized'!$A:$A,$A57) -> 0 | H57: =SUMIFS('T12 Categorized'!F:F,'T12 Categorized'!$A:$A,$A57) -> 0 | I57: =SUMIFS('T12 Categorized'!G:G,'T12 Categorized'!$A:$A,$A57) -> 0 | J57: =SUMIFS('T12 Categorized'!H:H,'T12 Categorized'!$A:$A,$A57) -> 0 | K57: =SUMIFS('T12 Categorized'!I:I,'T12 Categorized'!$A:$A,$A57) -> 0 | L57: =SUMIFS('T12 Categorized'!J:J,'T12 Categorized'!$A:$A,$A57) -> 0 | M57: =SUMIFS('T12 Categorized'!K:K,'T12 Categorized'!$A:$A,$A57) -> 0 | N57: =SUMIFS('T12 Categorized'!L:L,'T12 Categorized'!$A:$A,$A57) -> 0 | O57: =SUMIFS('T12 Categorized'!M:M,'T12 Categorized'!$A:$A,$A57) -> 0 | P57: =SUMIFS('T12 Categorized'!N:N,'T12 Categorized'!$A:$A,$A57) -> 0 | Q57: =SUMIFS('T12 Categorized'!O:O,'T12 Categorized'!$A:$A,$A57) -> 0
A58: intex | B58: Interest | F58: =SUMIFS('T12 Categorized'!D:D,'T12 Categorized'!$A:$A,$A58) -> 0 | G58: =SUMIFS('T12 Categorized'!E:E,'T12 Categorized'!$A:$A,$A58) -> 0 | H58: =SUMIFS('T12 Categorized'!F:F,'T12 Categorized'!$A:$A,$A58) -> 0 | I58: =SUMIFS('T12 Categorized'!G:G,'T12 Categorized'!$A:$A,$A58) -> 0 | J58: =SUMIFS('T12 Categorized'!H:H,'T12 Categorized'!$A:$A,$A58) -> 0 | K58: =SUMIFS('T12 Categorized'!I:I,'T12 Categorized'!$A:$A,$A58) -> 0 | L58: =SUMIFS('T12 Categorized'!J:J,'T12 Categorized'!$A:$A,$A58) -> 0 | M58: =SUMIFS('T12 Categorized'!K:K,'T12 Categorized'!$A:$A,$A58) -> 0 | N58: =SUMIFS('T12 Categorized'!L:L,'T12 Categorized'!$A:$A,$A58) -> 0 | O58: =SUMIFS('T12 Categorized'!M:M,'T12 Categorized'!$A:$A,$A58) -> 0 | P58: =SUMIFS('T12 Categorized'!N:N,'T12 Categorized'!$A:$A,$A58) -> 0 | Q58: =SUMIFS('T12 Categorized'!O:O,'T12 Categorized'!$A:$A,$A58) -> 0
A59: prin | B59: Principal | F59: =SUMIFS('T12 Categorized'!D:D,'T12 Categorized'!$A:$A,$A59) -> 0 | G59: =SUMIFS('T12 Categorized'!E:E,'T12 Categorized'!$A:$A,$A59) -> 0 | H59: =SUMIFS('T12 Categorized'!F:F,'T12 Categorized'!$A:$A,$A59) -> 0 | I59: =SUMIFS('T12 Categorized'!G:G,'T12 Categorized'!$A:$A,$A59) -> 0 | J59: =SUMIFS('T12 Categorized'!H:H,'T12 Categorized'!$A:$A,$A59) -> 0 | K59: =SUMIFS('T12 Categorized'!I:I,'T12 Categorized'!$A:$A,$A59) -> 0 | L59: =SUMIFS('T12 Categorized'!J:J,'T12 Categorized'!$A:$A,$A59) -> 0 | M59: =SUMIFS('T12 Categorized'!K:K,'T12 Categorized'!$A:$A,$A59) -> 0 | N59: =SUMIFS('T12 Categorized'!L:L,'T12 Categorized'!$A:$A,$A59) -> 0 | O59: =SUMIFS('T12 Categorized'!M:M,'T12 Categorized'!$A:$A,$A59) -> 0 | P59: =SUMIFS('T12 Categorized'!N:N,'T12 Categorized'!$A:$A,$A59) -> 0 | Q59: =SUMIFS('T12 Categorized'!O:O,'T12 Categorized'!$A:$A,$A59) -> 0
A60: draw | B60: Loan Draws | F60: =SUMIFS('T12 Categorized'!D:D,'T12 Categorized'!$A:$A,$A60) -> 0 | G60: =SUMIFS('T12 Categorized'!E:E,'T12 Categorized'!$A:$A,$A60) -> 0 | H60: =SUMIFS('T12 Categorized'!F:F,'T12 Categorized'!$A:$A,$A60) -> 0 | I60: =SUMIFS('T12 Categorized'!G:G,'T12 Categorized'!$A:$A,$A60) -> 0 | J60: =SUMIFS('T12 Categorized'!H:H,'T12 Categorized'!$A:$A,$A60) -> 0 | K60: =SUMIFS('T12 Categorized'!I:I,'T12 Categorized'!$A:$A,$A60) -> 0 | L60: =SUMIFS('T12 Categorized'!J:J,'T12 Categorized'!$A:$A,$A60) -> 0 | M60: =SUMIFS('T12 Categorized'!K:K,'T12 Categorized'!$A:$A,$A60) -> 0 | N60: =SUMIFS('T12 Categorized'!L:L,'T12 Categorized'!$A:$A,$A60) -> 0 | O60: =SUMIFS('T12 Categorized'!M:M,'T12 Categorized'!$A:$A,$A60) -> 0 | P60: =SUMIFS('T12 Categorized'!N:N,'T12 Categorized'!$A:$A,$A60) -> 0 | Q60: =SUMIFS('T12 Categorized'!O:O,'T12 Categorized'!$A:$A,$A60) -> 0
A61: repay | B61: Loan Repayments | F61: =SUMIFS('T12 Categorized'!D:D,'T12 Categorized'!$A:$A,$A61) -> 0 | G61: =SUMIFS('T12 Categorized'!E:E,'T12 Categorized'!$A:$A,$A61) -> 0 | H61: =SUMIFS('T12 Categorized'!F:F,'T12 Categorized'!$A:$A,$A61) -> 0 | I61: =SUMIFS('T12 Categorized'!G:G,'T12 Categorized'!$A:$A,$A61) -> 0 | J61: =SUMIFS('T12 Categorized'!H:H,'T12 Categorized'!$A:$A,$A61) -> 0 | K61: =SUMIFS('T12 Categorized'!I:I,'T12 Categorized'!$A:$A,$A61) -> 0 | L61: =SUMIFS('T12 Categorized'!J:J,'T12 Categorized'!$A:$A,$A61) -> 0 | M61: =SUMIFS('T12 Categorized'!K:K,'T12 Categorized'!$A:$A,$A61) -> 0 | N61: =SUMIFS('T12 Categorized'!L:L,'T12 Categorized'!$A:$A,$A61) -> 0 | O61: =SUMIFS('T12 Categorized'!M:M,'T12 Categorized'!$A:$A,$A61) -> 0 | P61: =SUMIFS('T12 Categorized'!N:N,'T12 Categorized'!$A:$A,$A61) -> 0 | Q61: =SUMIFS('T12 Categorized'!O:O,'T12 Categorized'!$A:$A,$A61) -> 0
A62: othdf | B62: Other Debt Fees | F62: =SUMIFS('T12 Categorized'!D:D,'T12 Categorized'!$A:$A,$A62) -> 0 | G62: =SUMIFS('T12 Categorized'!E:E,'T12 Categorized'!$A:$A,$A62) -> 0 | H62: =SUMIFS('T12 Categorized'!F:F,'T12 Categorized'!$A:$A,$A62) -> 0 | I62: =SUMIFS('T12 Categorized'!G:G,'T12 Categorized'!$A:$A,$A62) -> 0 | J62: =SUMIFS('T12 Categorized'!H:H,'T12 Categorized'!$A:$A,$A62) -> 0 | K62: =SUMIFS('T12 Categorized'!I:I,'T12 Categorized'!$A:$A,$A62) -> 0 | L62: =SUMIFS('T12 Categorized'!J:J,'T12 Categorized'!$A:$A,$A62) -> 0 | M62: =SUMIFS('T12 Categorized'!K:K,'T12 Categorized'!$A:$A,$A62) -> 0 | N62: =SUMIFS('T12 Categorized'!L:L,'T12 Categorized'!$A:$A,$A62) -> 0 | O62: =SUMIFS('T12 Categorized'!M:M,'T12 Categorized'!$A:$A,$A62) -> 0 | P62: =SUMIFS('T12 Categorized'!N:N,'T12 Categorized'!$A:$A,$A62) -> 0 | Q62: =SUMIFS('T12 Categorized'!O:O,'T12 Categorized'!$A:$A,$A62) -> 0
... A72: onoe | B72: Other Non-Operating Expense | F72: =SUMIFS('T12 Categorized'!D:D,'T12 Categorized'!$A:$A,$A72) -> 0 | G72: =SUMIFS('T12 Categorized'!E:E,'T12 Categorized'!$A:$A,$A72) -> 0 | H72: =SUMIFS('T12 Categorized'!F:F,'T12 Categorized'!$A:$A,$A72) -> 0 | I72: =SUMIFS('T12 Categorized'!G:G,'T12 Categorized'!$A:$A,$A72) -> 0 | J72: =SUMIFS('T12 Categorized'!H:H,'T12 Categorized'!$A:$A,$A72) -> 0 | K72: =SUMIFS('T12 Categorized'!I:I,'T12 Categorized'!$A:$A,$A72) -> 0 | L72: =SUMIFS('T12 Categorized'!J:J,'T12 Categorized'!$A:$A,$A72) -> 0 | M72: =SUMIFS('T12 Categorized'!K:K,'T12 Categorized'!$A:$A,$A72) -> 0 | N72: =SUMIFS('T12 Categorized'!L:L,'T12 Categorized'!$A:$A,$A72) -> 0 | O72: =SUMIFS('T12 Categorized'!M:M,'T12 Categorized'!$A:$A,$A72) -> 0 | P72: =SUMIFS('T12 Categorized'!N:N,'T12 Categorized'!$A:$A,$A72) -> 0 | Q72: =SUMIFS('T12 Categorized'!O:O,'T12 Categorized'!$A:$A,$A72) -> 0
B73: Non-Operating Expenses | F73: =SUM(F51:F72) -> 0 | G73: =SUM(G51:G72) -> 0 | H73: =SUM(H51:H72) -> 0 | I73: =SUM(I51:I72) -> 0 | J73: =SUM(J51:J72) -> 0 | K73: =SUM(K51:K72) -> 0 | L73: =SUM(L51:L72) -> 0 | M73: =SUM(M51:M72) -> 0 | ... Q73: =SUM(Q51:Q72) -> 0
B75: Net Income | F75: =F44+F48-F73 -> 235370.5 | G75: =G44+G48-G73 -> 271990.49 | H75: =H44+H48-H73 -> 253855.65 | I75: =I44+I48-I73 -> 281362.63 | J75: =J44+J48-J73 -> 305639.95 | K75: =K44+K48-K73 -> 250086.96 | L75: =L44+L48-L73 -> 404629.42 | M75: =M44+M48-M73 -> 272298.95 | ... Q75: =Q44+Q48-Q73 -> 268910.93
B77: Generated 06/23/2026 — live SUMIFS over 'T12 Categorized' code column

Sheet Rent Roll (One-Line) 05-23-26
A1: Unit No. | B1: Floor Plan | C1: Net sf | D1: Bed | E1: Bath | F1: Lease Type | G1: Occupancy Status | H1: Market Rent | I1: Contractual Rent | J1: Net Effective Rent | K1: Lease Start Date | L1: Lease Expiration | M1: Move In Date | O1: Scheduled Charges by Code (monthly $)
O2: rent | P2: upco | Q2: garr | R2: trtra | S2: amfee | T2: cpor | U2: petp | V2: petd | W2: mtom | X2: sdep | Y2: stor | Z2: trvtras | AA2: llock | AB2: vtras
A3: 1102 | B3: C1-abi | C3: 1564 | D3: 3 | E3: 2 | F3: Market | G3: Occupied | H3: 2940 | I3: 2940 | J3: 2940 | L3: 46610 | M3: 45087 | O3: 2940 | Q3: 270 | R3: 25 | S3: 10
A4: 1104 | B4: A3-abi | C4: 719 | D4: 1 | E4: 1 | F4: Market | G4: Occupied | H4: 1630 | I4: 1410 | J4: 1410 | L4: 46277 | M4: 45304 | O4: 1410 | R4: 25 | S4: 10 | U4: 25
A5: 1106 | B5: A3-abi | C5: 719 | D5: 1 | E5: 1 | F5: Market | G5: Occupied | H5: 1630 | I5: 1630 | J5: 1630 | L5: 46485 | M5: 45756 | O5: 1630 | R5: 25 | S5: 10
A6: 1108 | B6: B2-abi | C6: 1109 | D6: 2 | E6: 2 | F6: Market | G6: Occupied | H6: 2115 | I6: 2035 | J6: 2035 | L6: 46348 | M6: 45800 | O6: 2035 | Q6: 200 | R6: 25 | S6: 10
A7: 1109 | B7: A4-abi | C7: 736 | D7: 1 | E7: 1 | F7: Market | G7: Occupied | H7: 1725 | I7: 1568 | J7: 1568 | L7: 46373 | M7: 45340 | O7: 1568 | R7: 25 | S7: 10
A8: 1110 | B8: B2-abi | C8: 1109 | D8: 2 | E8: 2 | F8: Market | G8: Vacant | H8: 2115 | I8: 0 | J8: 0
A9: 1112 | B9: C1-abi | C9: 1564 | D9: 3 | E9: 2 | F9: Market | G9: Occupied | H9: 2940 | I9: 2650 | J9: 2650 | L9: 46298 | M9: 45934 | O9: 2650 | R9: 25 | S9: 10
A10: 1113 | B10: A4-abi | C10: 736 | D10: 1 | E10: 1 | F10: Market | G10: Occupied | H10: 1725 | I10: 1568 | J10: 1568 | L10: 46277 | M10: 45304 | O10: 1568 | R10: 25 | S10: 10 | U10: 25
A11: 1114 | B11: A3-abi | C11: 719 | D11: 1 | E11: 1 | F11: Market | G11: Occupied | H11: 1630 | I11: 1492 | J11: 1492 | L11: 46440 | M11: 45283 | O11: 1492 | R11: 25 | S11: 10
A12: 1116 | B12: B2-abi | C12: 1109 | D12: 2 | E12: 2 | F12: Market | G12: Occupied | H12: 2115 | I12: 2125 | J12: 2125 | L12: 46217 | M12: 45061 | O12: 2125 | Q12: 300 | R12: 25 | S12: 10
A13: 1118 | B13: B2-abi | C13: 1109 | D13: 2 | E13: 2 | F13: Market | G13: Occupied | H13: 2115 | I13: 2085 | J13: 2085 | L13: 46346 | M13: 45159 | O13: 2085 | R13: 25 | S13: 10
A14: 1120 | B14: B1-abi | C14: 1082 | D14: 2 | E14: 2 | F14: Market | G14: Occupied | H14: 2165 | I14: 1974 | J14: 1974 | L14: 46518 | M14: 45589 | O14: 1974 | Q14: 520 | R14: 50 | S14: 20 | U14: 50
A15: 1201 | B15: B1-abi | C15: 1082 | D15: 2 | E15: 2 | F15: Market | G15: Occupied | H15: 2260 | I15: 2095 | J15: 2095 | L15: 46598 | M15: 46053 | O15: 2095 | P15: -1047.5 | R15: 25 | S15: 10 | U15: 25
A16: 1202 | B16: C1-abi | C16: 1564 | D16: 3 | E16: 2 | F16: Market | G16: Occupied | H16: 2860 | I16: 2436 | J16: 2436 | L16: 46404 | M16: 45675 | O16: 2436 | Q16: 160 | R16: 25 | S16: 10 | T16: 65
A17: 1203 | B17: A6-abi | C17: 803 | D17: 1 | E17: 1 | F17: Market | G17: Occupied | H17: 1775 | I17: 1775 | J17: 1775 | L17: 46273 | M17: 45909 | O17: 1775 | R17: 25 | S17: 10
A18: 1204 | B18: A3-abi | C18: 719 | D18: 1 | E18: 1 | F18: Market | G18: Vacant | H18: 1550 | I18: 0 | J18: 0
A19: 1205 | B19: A6-abi | C19: 803 | D19: 1 | E19: 1 | F19: Market | G19: Occupied | H19: 1775 | I19: 1775 | J19: 1775 | L19: 46279 | M19: 45915 | O19: 1775 | Q19: 260 | R19: 25 | S19: 10
A20: 1206 | B20: A3-abi | C20: 719 | D20: 1 | E20: 1 | F20: Market | G20: Occupied | H20: 1550 | I20: 1550 | J20: 1550 | L20: 46248 | M20: 46068 | O20: 1550 | R20: 25 | S20: 10
A21: 1207 | B21: B2-abi | C21: 1109 | D21: 2 | E21: 2 | F21: Market | G21: Occupied | H21: 2210 | I21: 2210 | J21: 2210 | L21: 46283 | M21: 45919 | O21: 2210 | Q21: 200 | R21: 25 | S21: 10
A22: 1208 | B22: B2-abi | C22: 1109 | D22: 2 | E22: 2 | F22: Market | G22: Occupied | H22: 2035 | I22: 2035 | J22: 2035 | L22: 46529 | M22: 46165 | O22: 2035 | R22: 25 | S22: 10 | U22: 25
A23: 1209 | B23: A4-abi | C23: 736 | D23: 1 | E23: 1 | F23: Market | G23: Occupied | H23: 1645 | I23: 1521 | J23: 1521 | L23: 46591 | M23: 45589 | O23: 1521 | R23: 25 | S23: 10
A24: 1210 | B24: B2-abi | C24: 1109 | D24: 2 | E24: 2 | F24: Market | G24: Occupied | H24: 2035 | I24: 1907 | J24: 1907 | L24: 46527 | M24: 45689 | O24: 1907 | Q24: 260 | R24: 25 | S24: 10
A25: 1212 | B25: C1-abi | C25: 1564 | D25: 3 | E25: 2 | F25: Market | G25: Occupied | H25: 2860 | I25: 2902 | J25: 2902 | L25: 46203 | M25: 45474 | O25: 2902 | Q25: 260 | R25: 25 | S25: 10
A26: 1213 | B26: A4-abi | C26: 736 | D26: 1 | E26: 1 | F26: Market | G26: Occupied | H26: 1645 | I26: 1645 | J26: 1645 | L26: 46473 | M26: 45744 | O26: 1645 | R26: 25 | S26: 10
A27: 1214 | B27: A3-abi | C27: 719 | D27: 1 | E27: 1 | F27: Market | G27: Occupied | H27: 1550 | I27: 1550 | J27: 1550 | L27: 46340 | M27: 45519 | O27: 1550 | R27: 25 | S27: 10
A28: 1215 | B28: A2-abi | C28: 698 | D28: 1 | E28: 1 | F28: Market | G28: Occupied | H28: 1660 | I28: 1364 | J28: 1364 | L28: 46385 | M28: 46021 | O28: 1364 | R28: 25 | S28: 10
A29: 1216 | B29: B2-abi | C29: 1109 | D29: 2 | E29: 2 | F29: Market | G29: Occupied | H29: 2035 | I29: 2035 | J29: 2035 | L29: 46224 | M29: 45129 | O29: 2035 | R29: 25 | S29: 10 | U29: 25 | Y29: 40
A30: 1217 | B30: A2-abi | C30: 698 | D30: 1 | E30: 1 | F30: Market | G30: Occupied | H30: 1660 | I30: 1395 | J30: 1395 | L30: 46558 | M30: 45709 | O30: 1395 | R30: 25 | S30: 10
A31: 1218 | B31: B2-abi | C31: 1109 | D31: 2 | E31: 2 | F31: Market | G31: Occupied | H31: 2035 | I31: 2035 | J31: 2035 | L31: 46503 | M31: 46080 | O31: 2035 | P31: -1017.5 | R31: 25 | S31: 10
A32: 1219 | B32: A2-abi | C32: 698 | D32: 1 | E32: 1 | F32: Market | G32: Occupied | H32: 1660 | I32: 1660 | J32: 1660 | L32: 46112 | M32: 45901 | O32: 1660 | R32: 25 | S32: 10
A33: 1220 | B33: B1-abi | C33: 1082 | D33: 2 | E33: 2 | F33: Market | G33: Occupied | H33: 2085 | I33: 1915 | J33: 1915 | L33: 46321 | M33: 45835 | O33: 1915 | Q33: 225 | R33: 25 | S33: 10
A34: 1221 | B34: B1-abi | C34: 1082 | D34: 2 | E34: 2 | F34: Market | G34: Occupied | H34: 2260 | I34: 2260 | J34: 2260 | L34: 46504 | M34: 46081 | O34: 2260 | P34: -1130 | Q34: 230 | R34: 25 | S34: 10
A35: 1301 | B35: B1-abi | C35: 1082 | D35: 2 | E35: 2 | F35: Market | G35: Occupied | H35: 2305 | I35: 2314 | J35: 2314 | L35: 46599 | M35: 45061 | O35: 2314 | Q35: 300 | R35: 25 | S35: 10
A36: 1302 | B36: C1-abi | C36: 1564 | D36: 3 | E36: 2 | F36: Market | G36: Vacant | H36: 2905 | I36: 0 | J36: 0
A37: 1303 | B37: A6-abi | C37: 803 | D37: 1 | E37: 1 | F37: Market | G37: Occupied | H37: 1645 | I37: 1645 | J37: 1645 | L37: 46596 | M37: 45594 | O37: 1645 | R37: 25 | S37: 10
A38: 1304 | B38: A3-abi | C38: 719 | D38: 1 | E38: 1 | F38: Market | G38: Occupied | H38: 1595 | I38: 1435 | J38: 1435 | L38: 46210 | M38: 45238 | O38: 1435 | R38: 25 | S38: 10 | T38: 65
A39: 1305 | B39: A6-abi | C39: 803 | D39: 1 | E39: 1 | F39: Market | G39: Occupied | H39: 1820 | I39: 1770 | J39: 1770 | L39: 46300 | M39: 45113 | O39: 1770 | Q39: 200 | R39: 25 | S39: 10
A40: 1306 | B40: A3-abi | C40: 719 | D40: 1 | E40: 1 | F40: Market | G40: Occupied | H40: 1595 | I40: 1397 | J40: 1397 | L40: 46508 | M40: 45779 | O40: 1397 | R40: 25 | S40: 10
A41: 1307 | B41: B2-abi | C41: 1109 | D41: 2 | E41: 2 | F41: Market | G41: Occupied | H41: 2255 | I41: 2253 | J41: 2253 | L41: 46453 | M41: 45085 | O41: 2253 | R41: 50 | S41: 20 | T41: 130 | U41: 50
A42: 1308 | B42: B2-abi | C42: 1109 | D42: 2 | E42: 2 | F42: Market | G42: Occupied | H42: 2080 | I42: 1980 | J42: 1980 | L42: 46223 | M42: 45220 | O42: 1980 | Q42: 350 | R42: 25 | S42: 10
A43: 1309 | B43: A4-abi | C43: 736 | D43: 1 | E43: 1 | F43: Market | G43: Occupied | H43: 1690 | I43: 1450 | J43: 1450 | L43: 46318 | M43: 45954 | O43: 1450 | R43: 25 | S43: 10
A44: 1310 | B44: B2-abi | C44: 1109 | D44: 2 | E44: 2 | F44: Market | G44: Occupied | H44: 2080 | I44: 2080 | J44: 2080 | L44: 46488 | M44: 45700 | O44: 2080 | Q44: 200 | R44: 25 | S44: 10
A45: 1312 | B45: C1-abi | C45: 1564 | D45: 3 | E45: 2 | F45: Market | G45: Occupied | H45: 2905 | I45: 2905 | J45: 2905 | L45: 46499 | M45: 46076 | O45: 2905 | P45: -1452.5 | Q45: 230 | R45: 25 | S45: 10
A46: 1313 | B46: A4-abi | C46: 736 | D46: 1 | E46: 1 | F46: Market | G46: Occupied | H46: 1690 | I46: 1690 | J46: 1690 | L46: 46701 | M46: 45180 | O46: 1690 | Q46: 350 | R46: 25 | S46: 10
A47: 1314 | B47: A3-abi | C47: 719 | D47: 1 | E47: 1 | F47: Market | G47: Vacant | H47: 1595 | I47: 0 | J47: 0
A48: 1315 | B48: A2-abi | C48: 698 | D48: 1 | E48: 1 | F48: Market | G48: Vacant | H48: 1705 | I48: 0 | J48: 0
A49: 1316 | B49: B2-abi | C49: 1109 | D49: 2 | E49: 2 | F49: Market | G49: Occupied | H49: 2080 | I49: 2080 | J49: 2080 | L49: 46527 | M49: 46104 | O49: 2080 | P49: -1040 | R49: 25 | S49: 10
A50: 1317 | B50: A2-abi | C50: 698 | D50: 1 | E50: 1 | F50: Market | G50: Occupied | H50: 1705 | I50: 1421 | J50: 1421 | L50: 46492 | M50: 45642 | O50: 1421 | Q50: 200 | R50: 25 | S50: 10
A51: 1318 | B51: B2-abi | C51: 1109 | D51: 2 | E51: 2 | F51: Market | G51: Occupied | H51: 2080 | I51: 2030 | J51: 2030 | L51: 46379 | M51: 45375 | O51: 2030 | R51: 25 | S51: 10
A52: 1319 | B52: A2-abi | C52: 698 | D52: 1 | E52: 1 | F52: Market | G52: Occupied | H52: 1705 | I52: 1399 | J52: 1399 | L52: 46533 | M52: 46108 | O52: 1399 | P52: -699.5 | R52: 25 | S52: 10
A53: 1320 | B53: B1-abi | C53: 1082 | D53: 2 | E53: 2 | F53: Market | G53: Occupied | H53: 2130 | I53: 1840 | J53: 1840 | L53: 46410 | M53: 45681 | O53: 1840 | R53: 25 | S53: 10
A54: 1321 | B54: B1-abi | C54: 1082 | D54: 2 | E54: 2 | F54: Market | G54: Occupied | H54: 2305 | I54: 2121 | J54: 2121 | L54: 46460 | M54: 45306 | O54: 2121 | R54: 25 | S54: 10
A55: 2102 | B55: B3-abi | C55: 1213 | D55: 2 | E55: 2 | F55: Market | G55: Occupied | H55: 2210 | I55: 2058 | J55: 2058 | L55: 46079 | M55: 45715 | O55: 2058 | R55: 25 | S55: 10
A56: 2104 | B56: A3-abi | C56: 719 | D56: 1 | E56: 1 | F56: Market | G56: Occupied | H56: 1630 | I56: 1380 | J56: 1380 | L56: 46413 | M56: 45684 | O56: 1380 | R56: 25 | S56: 10
A57: 2106 | B57: A3-abi | C57: 719 | D57: 1 | E57: 1 | F57: Market | G57: Occupied | H57: 1630 | I57: 1431 | J57: 1431 | L57: 46541 | M57: 45264 | O57: 1431 | R57: 25 | S57: 10 | T57: 65
A58: 2108 | B58: A3-abi | C58: 719 | D58: 1 | E58: 1 | F58: Market | G58: Occupied | H58: 1630 | I58: 1469 | J58: 1469 | L58: 46521 | M58: 46096 | O58: 1469 | R58: 25 | S58: 10
A59: 2110 | B59: B3-abi | C59: 1213 | D59: 2 | E59: 2 | F59: Market | G59: Occupied | H59: 2210 | I59: 2210 | J59: 2210 | L59: 46304 | M59: 45940 | O59: 2210 | Q59: 400 | R59: 25 | S59: 10
A60: 2201 | B60: B1-abi | C60: 1082 | D60: 2 | E60: 2 | F60: Market | G60: Occupied | H60: 2260 | I60: 1927 | J60: 1927 | L60: 46491 | M60: 45580 | O60: 1927 | R60: 25 | S60: 10
A61: 2202 | B61: B3-abi | C61: 1213 | D61: 2 | E61: 2 | F61: Market | G61: Occupied | H61: 2130 | I61: 2130 | J61: 2130 | L61: 46353 | M61: 46019 | O61: 2130 | P61: -1065 | R61: 25 | S61: 10 | U61: 50
A62: 2203 | B62: A2-abi | C62: 698 | D62: 1 | E62: 1 | F62: Market | G62: Occupied | H62: 1660 | I62: 1660 | J62: 1660 | L62: 46521 | M62: 46157 | O62: 1660 | Q62: 285 | R62: 25 | S62: 10
A63: 2204 | B63: A3-abi | C63: 719 | D63: 1 | E63: 1 | F63: Market | G63: Occupied | H63: 1550 | I63: 1550 | J63: 1550 | L63: 46538 | M63: 46113 | O63: 1550 | P63: -775 | R63: 25 | S63: 10
A64: 2205 | B64: A2-abi | C64: 698 | D64: 1 | E64: 1 | F64: Market | G64: Occupied | H64: 1660 | I64: 1312 | J64: 1312 | L64: 46458 | M64: 46066 | O64: 1312 | R64: 25 | S64: 10
A65: 2206 | B65: A3-abi | C65: 719 | D65: 1 | E65: 1 | F65: Market | G65: Occupied | H65: 1550 | I65: 1550 | J65: 1550 | L65: 46293 | M65: 45929 | O65: 1550 | R65: 25 | S65: 10
A66: 2207 | B66: A2-abi | C66: 698 | D66: 1 | E66: 1 | F66: Market | G66: Vacant | H66: 1660 | I66: 0 | J66: 0
A67: 2208 | B67: A3-abi | C67: 719 | D67: 1 | E67: 1 | F67: Market | G67: Occupied | H67: 1550 | I67: 1299 | J67: 1299 | L67: 46462 | M67: 46039 | O67: 1299 | P67: -649.5 | R67: 25 | S67: 10
A68: 2209 | B68: B1-abi | C68: 1082 | D68: 2 | E68: 2 | F68: Market | G68: Occupied | H68: 2260 | I68: 1948 | J68: 1948 | L68: 46398 | M68: 45669 | O68: 1948 | R68: 25 | S68: 10
A69: 2210 | B69: B3-abi | C69: 1213 | D69: 2 | E69: 2 | F69: Market | G69: Occupied | H69: 2130 | I69: 2099 | J69: 2099 | L69: 46387 | M69: 45992 | O69: 2099 | P69: -1049.5 | R69: 25 | S69: 10
A70: 2301 | B70: B1-abi | C70: 1082 | D70: 2 | E70: 2 | F70: Market | G70: Occupied | H70: 2305 | I70: 2305 | J70: 2305 | L70: 46279 | M70: 45915 | O70: 2305 | R70: 25 | S70: 10
A71: 2302 | B71: B3-abi | C71: 1213 | D71: 2 | E71: 2 | F71: Market | G71: Occupied | H71: 2175 | I71: 2175 | J71: 2175 | L71: 46521 | M71: 46157 | O71: 2175 | R71: 25 | S71: 10 | T71: 110 | U71: 25 | Y71: 40
A72: 2303 | B72: A2-abi | C72: 698 | D72: 1 | E72: 1 | F72: Market | G72: Vacant | H72: 1705 | I72: 0 | J72: 0
A73: 2304 | B73: A3-abi | C73: 719 | D73: 1 | E73: 1 | F73: Market | G73: Occupied | H73: 1595 | I73: 1419 | J73: 1419 | L73: 46368 | M73: 45611 | O73: 1419 | R73: 25 | S73: 10 | T73: 130
A74: 2305 | B74: A2-abi | C74: 698 | D74: 1 | E74: 1 | F74: Market | G74: Occupied | H74: 1705 | I74: 1705 | J74: 1705 | L74: 46190 | M74: 45278 | O74: 1705 | R74: 25 | S74: 10
A75: 2306 | B75: A3-abi | C75: 719 | D75: 1 | E75: 1 | F75: Market | G75: Occupied | H75: 1595 | I75: 1595 | J75: 1595 | L75: 46265 | M75: 45901 | O75: 1595 | R75: 25 | S75: 10
A76: 2307 | B76: A2-abi | C76: 698 | D76: 1 | E76: 1 | F76: Market | G76: Occupied | H76: 1705 | I76: 1399 | J76: 1399 | L76: 46513 | M76: 46088 | O76: 1399 | S76: 10 | U76: 50 | Z76: 25
A77: 2308 | B77: A3-abi | C77: 719 | D77: 1 | E77: 1 | F77: Market | G77: Occupied | H77: 1595 | I77: 1451 | J77: 1451 | L77: 46443 | M77: 45698 | O77: 1451 | R77: 25 | S77: 10
A78: 2309 | B78: B1-abi | C78: 1082 | D78: 2 | E78: 2 | F78: Market | G78: Occupied | H78: 2305 | I78: 2305 | J78: 2305 | L78: 46359 | M78: 45539 | O78: 2305 | Q78: 260 | R78: 25 | S78: 10
A79: 2310 | B79: B3-abi | C79: 1213 | D79: 2 | E79: 2 | F79: Market | G79: Occupied | H79: 2175 | I79: 2110 | J79: 2110 | L79: 46350 | M79: 45621 | O79: 2110 | R79: 25 | S79: 10 | U79: 50
A80: 3104 | B80: A3-abi | C80: 719 | D80: 1 | E80: 1 | F80: Market | G80: Occupied | H80: 1630 | I80: 1436 | J80: 1436 | L80: 46217 | M80: 45306 | O80: 1436 | R80: 25 | S80: 10 | T80: 65 | Y80: 40
A81: 3106 | B81: A3-abi | C81: 719 | D81: 1 | E81: 1 | F81: Market | G81: Vacant | H81: 1630 | I81: 0 | J81: 0
A82: 3108 | B82: A7-abi | C82: 941 | D82: 1 | E82: 1 | F82: Market | G82: Occupied | H82: 1895 | I82: 1860 | J82: 1860 | L82: 46618 | M82: 46132 | O82: 1860 | P82: -930 | R82: 25 | S82: 10 | U82: 25
A83: 3109 | B83: A4-abi | C83: 736 | D83: 1 | E83: 1 | F83: Market | G83: Occupied | H83: 1725 | I83: 1384 | J83: 1384 | L83: 46459 | M83: 46067 | O83: 1384 | P83: -692 | R83: 25 | S83: 10
A84: 3110 | B84: A7-abi | C84: 941 | D84: 1 | E84: 1 | F84: Market | G84: Occupied | H84: 1895 | I84: 1895 | J84: 1895 | L84: 46446 | M84: 45566 | O84: 1895 | R84: 25 | S84: 10
A85: 3112 | B85: C1.2-abi | C85: 1564 | D85: 3 | E85: 2 | F85: Market | G85: Occupied | H85: 2925 | I85: 2550 | J85: 2550 | L85: 46350 | M85: 45986 | O85: 2550 | R85: 25 | S85: 10
A86: 3114 | B86: A3.8-abi | C86: 739 | D86: 1 | E86: 1 | F86: Market | G86: Occupied | H86: 1605 | I86: 1395 | J86: 1395 | L86: 46519 | M86: 45701 | O86: 1395 | R86: 25 | S86: 10
A87: 3115 | B87: A4-abi | C87: 736 | D87: 1 | E87: 1 | F87: Market | G87: Occupied | H87: 1725 | I87: 1492 | J87: 1492 | L87: 46381 | M87: 45652 | O87: 1492 | R87: 25 | S87: 10 | U87: 25
A88: 3116 | B88: A5-abi | C88: 762 | D88: 1 | E88: 1 | F88: Market | G88: Occupied | H88: 1645 | I88: 1433 | J88: 1433 | L88: 46465 | M88: 46073 | O88: 1433 | P88: -716.5 | R88: 25 | S88: 10
A89: 3118 | B89: A5-abi | C89: 762 | D89: 1 | E89: 1 | F89: Market | G89: Occupied | H89: 1645 | I89: 1645 | J89: 1645 | L89: 46509 | M89: 45780 | O89: 1645 | R89: 25 | S89: 10
A90: 3120 | B90: A1-abi | C90: 690 | D90: 1 | E90: 1 | F90: Market | G90: Occupied | H90: 1615 | I90: 1470 | J90: 1470 | L90: 46622 | M90: 44980 | O90: 1470 | Q90: 250 | R90: 25 | S90: 10
A91: 3122 | B91: B1-abi | C91: 1082 | D91: 2 | E91: 2 | F91: Market | G91: Occupied | H91: 2340 | I91: 2238 | J91: 2238 | L91: 46477 | M91: 45017 | O91: 2238 | Q91: 210 | R91: 25 | S91: 10
A92: 3201 | B92: B1-abi | C92: 1082 | D92: 2 | E92: 2 | F92: Market | G92: Occupied | H92: 2260 | I92: 2260 | J92: 2260 | L92: 46222 | M92: 45402 | O92: 2260 | R92: 25 | S92: 10
A93: 3202 | B93: B1-abi | C93: 1082 | D93: 2 | E93: 2 | F93: Market | G93: Occupied | H93: 2085 | I93: 4170 | J93: 4170 | L93: 46522 | M93: 46158 | O93: 4170 | R93: 50 | S93: 20 | U93: 75 | V93: 700
A94: 3203 | B94: A6-abi | C94: 803 | D94: 1 | E94: 1 | F94: Market | G94: Occupied | H94: 1775 | I94: 1775 | J94: 1775 | L94: 46503 | M94: 45715 | O94: 1775 | R94: 25 | S94: 10
A95: 3204 | B95: A3-abi | C95: 719 | D95: 1 | E95: 1 | F95: Market | G95: Occupied | H95: 1550 | I95: 1550 | J95: 1550 | L95: 46203 | M95: 45839 | O95: 1550 | R95: 25 | S95: 10
A96: 3205 | B96: A6-abi | C96: 803 | D96: 1 | E96: 1 | F96: Market | G96: Occupied | H96: 1775 | I96: 1599 | J96: 1599 | L96: 46531 | M96: 46106 | O96: 1599 | P96: -799.5 | R96: 25 | S96: 10
A97: 3206 | B97: A3-abi | C97: 719 | D97: 1 | E97: 1 | F97: Market | G97: Occupied | H97: 1550 | I97: 1550 | J97: 1550 | L97: 46234 | M97: 45839 | O97: 1550 | R97: 25 | S97: 10
A98: 3208 | B98: A7-abi | C98: 941 | D98: 1 | E98: 1 | F98: Market | G98: Occupied | H98: 1815 | I98: 1815 | J98: 1815 | L98: 46393 | M98: 45998 | O98: 1815 | P98: -907.5 | R98: 25 | S98: 10
A99: 3209 | B99: A4-abi | C99: 736 | D99: 1 | E99: 1 | F99: Market | G99: Occupied | H99: 1645 | I99: 1395 | J99: 1395 | L99: 46545 | M99: 45999 | O99: 1395 | P99: -697.5 | R99: 25 | S99: 10
A100: 3210 | B100: A7-abi | C100: 941 | D100: 1 | E100: 1 | F100: Market | G100: Occupied | H100: 1815 | I100: 1769 | J100: 1769 | L100: 46446 | M100: 46054 | O100: 1769 | Q100: 200 | R100: 25 | S100: 10
...

Sheet Rent Roll (One-Line) 02-26-24
A1: Unit No. | B1: Floor Plan | C1: Net sf | D1: Bed | E1: Bath | F1: Lease Type | G1: Occupancy Status | H1: Market Rent | I1: Contractual Rent | J1: Net Effective Rent | K1: Lease Start Date | L1: Lease Expiration | M1: Move In Date | O1: Scheduled Charges by Code (monthly $)
O2: rent | P2: upco | Q2: garr | R2: vtras | S2: amfee | T2: cpor | U2: petp | V2: empl | W2: edsc | X2: llock | Y2: mtom | Z2: stor
A3: 1102 | B3: C1-abi | C3: 1564 | D3: 3 | E3: 2 | F3: Market | G3: Occupied | H3: 2940 | I3: 2840 | J3: 2840 | L3: 45513 | M3: 45087 | O3: 2840 | Q3: 270 | R3: 25 | S3: 10
A4: 1104 | B4: A3-abi | C4: 719 | D4: 1 | E4: 1 | F4: Market | G4: Occupied | H4: 1630 | I4: 1410 | J4: 1410 | L4: 45728 | M4: 45304 | O4: 1410 | P4: -705 | R4: 25 | S4: 10 | U4: 25
A5: 1106 | B5: A3-abi | C5: 719 | D5: 1 | E5: 1 | F5: Market | G5: Occupied | H5: 1630 | I5: 1450 | J5: 1450 | L5: 45611 | M5: 45185 | O5: 1450 | R5: 25 | S5: 10
A6: 1108 | B6: B2-abi | C6: 1109 | D6: 2 | E6: 2 | F6: Market | G6: Vacant | H6: 2115 | I6: 0 | J6: 0
A7: 1109 | B7: A4-abi | C7: 736 | D7: 1 | E7: 1 | F7: Market | G7: Occupied | H7: 1725 | I7: 1545 | J7: 1545 | L7: 45825 | M7: 45340 | O7: 1545 | R7: 25 | S7: 10
A8: 1110 | B8: B2-abi | C8: 1109 | D8: 2 | E8: 2 | F8: Market | G8: Occupied | H8: 2115 | I8: 2110 | J8: 2110 | L8: 45579 | M8: 45153 | O8: 2110 | R8: 25 | S8: 10
A9: 1112 | B9: C1-abi | C9: 1564 | D9: 3 | E9: 2 | F9: Market | G9: Occupied | H9: 2940 | I9: 2760 | J9: 2760 | L9: 45505 | M9: 45140 | O9: 2760 | R9: 25 | S9: 10 | X9: 29
A10: 1113 | B10: A4-abi | C10: 736 | D10: 1 | E10: 1 | F10: Market | G10: Occupied | H10: 1725 | I10: 1545 | J10: 1545 | L10: 45728 | M10: 45304 | O10: 1545 | P10: -772.5 | R10: 25 | S10: 10 | U10: 25
A11: 1114 | B11: A3-abi | C11: 719 | D11: 1 | E11: 1 | F11: Market | G11: Occupied | H11: 1630 | I11: 1470 | J11: 1470 | L11: 45710 | M11: 45283 | O11: 1470 | P11: -735 | R11: 25 | S11: 10
A12: 1116 | B12: B2-abi | C12: 1109 | D12: 2 | E12: 2 | F12: Market | G12: Occupied | H12: 2115 | I12: 2085 | J12: 2085 | L12: 45487 | M12: 45061 | O12: 2085 | Q12: 300 | R12: 25 | S12: 10
A13: 1118 | B13: B2-abi | C13: 1109 | D13: 2 | E13: 2 | F13: Market | G13: Occupied | H13: 2115 | I13: 2085 | J13: 2085 | L13: 45524 | M13: 45159 | O13: 2085 | R13: 25 | S13: 10
A14: 1120 | B14: B1-abi | C14: 1082 | D14: 2 | E14: 2 | F14: Market | G14: Occupied | H14: 2165 | I14: 2030 | J14: 2030 | L14: 45607 | M14: 45058 | O14: 2030 | Q14: 200 | R14: 25 | S14: 10
A15: 1201 | B15: B1-abi | C15: 1082 | D15: 2 | E15: 2 | F15: Market | G15: Occupied | H15: 2260 | I15: 2260 | J15: 2260 | L15: 45489 | M15: 45094 | O15: 2260 | R15: 25 | S15: 10
A16: 1202 | B16: C1-abi | C16: 1564 | D16: 3 | E16: 2 | F16: Market | G16: Occupied | H16: 2860 | I16: 2860 | J16: 2860 | L16: 45633 | M16: 45177 | O16: 2860 | Q16: 295 | R16: 25 | S16: 10 | U16: 50
A17: 1203 | B17: A6-abi | C17: 803 | D17: 1 | E17: 1 | F17: Market | G17: Occupied | H17: 1775 | I17: 1730 | J17: 1730 | L17: 45505 | M17: 45079 | O17: 1730 | R17: 25 | S17: 10
A18: 1204 | B18: A3-abi | C18: 719 | D18: 1 | E18: 1 | F18: Market | G18: Occupied | H18: 1550 | I18: 1490 | J18: 1490 | L18: 45465 | M18: 45100 | O18: 1490 | R18: 25 | S18: 10
A19: 1205 | B19: A6-abi | C19: 803 | D19: 1 | E19: 1 | F19: Market | G19: Occupied | H19: 1775 | I19: 1750 | J19: 1750 | L19: 45508 | M19: 45082 | O19: 1750 | Q19: 300 | R19: 25 | S19: 10
A20: 1206 | B20: A3-abi | C20: 719 | D20: 1 | E20: 1 | F20: Market | G20: Occupied | H20: 1550 | I20: 1385 | J20: 1385 | L20: 45702 | M20: 45275 | O20: 1385 | P20: -692.5 | R20: 25 | S20: 10
A21: 1207 | B21: B2-abi | C21: 1109 | D21: 2 | E21: 2 | F21: Market | G21: Occupied | H21: 2210 | I21: 2195 | J21: 2195 | L21: 45483 | M21: 45118 | O21: 2195 | R21: 25 | S21: 10 | U21: 25
A22: 1208 | B22: B2-abi | C22: 1109 | D22: 2 | E22: 2 | F22: Market | G22: Occupied | H22: 2035 | I22: 1955 | J22: 1955 | L22: 45610 | M22: 45122 | O22: 1955 | R22: 25 | S22: 10
A23: 1209 | B23: A4-abi | C23: 736 | D23: 1 | E23: 1 | F23: Market | G23: Occupied | H23: 1645 | I23: 1635 | J23: 1635 | L23: 45511 | M23: 45146 | O23: 1635 | Q23: 360 | R23: 25 | S23: 10
A24: 1210 | B24: B2-abi | C24: 1109 | D24: 2 | E24: 2 | F24: Market | G24: Occupied | H24: 2035 | I24: 1990 | J24: 1990 | L24: 45616 | M24: 45128 | O24: 1990 | R24: 25 | S24: 10
A25: 1212 | B25: C1-abi | C25: 1564 | D25: 3 | E25: 2 | F25: Market | G25: Occupied | H25: 2860 | I25: 2860 | J25: 2860 | L25: 45444 | M25: 45079 | O25: 2860 | Q25: 350 | R25: 25 | S25: 10
A26: 1213 | B26: A4-abi | C26: 736 | D26: 1 | E26: 1 | F26: Market | G26: Occupied | H26: 1645 | I26: 1499 | J26: 1499 | L26: 45718 | M26: 45294 | O26: 1499 | P26: -1082 | R26: 25 | S26: 10
A27: 1214 | B27: A3-abi | C27: 719 | D27: 1 | E27: 1 | F27: Market | G27: Occupied | H27: 1550 | I27: 1485 | J27: 1485 | L27: 45512 | M27: 45086 | O27: 1485 | R27: 25 | S27: 10
A28: 1215 | B28: A2-abi | C28: 698 | D28: 1 | E28: 1 | F28: Market | G28: Vacant | H28: 1660 | I28: 0 | J28: 0
A29: 1216 | B29: B2-abi | C29: 1109 | D29: 2 | E29: 2 | F29: Market | G29: Occupied | H29: 2035 | I29: 1980 | J29: 1980 | L29: 45494 | M29: 45129 | O29: 1980 | R29: 25 | S29: 10 | T29: 65
A30: 1217 | B30: A2-abi | C30: 698 | D30: 1 | E30: 1 | F30: Market | G30: Occupied | H30: 1660 | I30: 1480 | J30: 1480 | L30: 45683 | M30: 45257 | O30: 1480 | P30: -740 | R30: 25 | S30: 10
A31: 1218 | B31: B2-abi | C31: 1109 | D31: 2 | E31: 2 | F31: Market | G31: Occupied | H31: 2035 | I31: 2030 | J31: 2030 | L31: 45596 | M31: 45170 | O31: 2030 | R31: 25 | S31: 10 | U31: 25
A32: 1219 | B32: A2-abi | C32: 698 | D32: 1 | E32: 1 | F32: Market | G32: Occupied | H32: 1660 | I32: 1580 | J32: 1580 | L32: 45551 | M32: 45155 | O32: 1580 | R32: 25 | S32: 10
A33: 1220 | B33: B1-abi | C33: 1082 | D33: 2 | E33: 2 | F33: Market | G33: Occupied | H33: 2085 | I33: 2085 | J33: 2085 | L33: 45520 | M33: 45155 | O33: 2085 | R33: 25 | S33: 10
A34: 1221 | B34: B1-abi | C34: 1082 | D34: 2 | E34: 2 | F34: Market | G34: Occupied | H34: 2260 | I34: 1995 | J34: 1995 | L34: 45656 | M34: 45230 | O34: 1995 | R34: 25 | S34: 10
A35: 1301 | B35: B1-abi | C35: 1082 | D35: 2 | E35: 2 | F35: Market | G35: Occupied | H35: 2305 | I35: 2280 | J35: 2280 | L35: 45546 | M35: 45061 | O35: 2280 | Q35: 300 | R35: 25 | S35: 10 | X35: 42
A36: 1302 | B36: C1-abi | C36: 1564 | D36: 3 | E36: 2 | F36: Market | G36: Occupied | H36: 2905 | I36: 2780 | J36: 2780 | L36: 45614 | M36: 45065 | O36: 2780 | Q36: 270 | R36: 25 | S36: 10
A37: 1303 | B37: A6-abi | C37: 803 | D37: 1 | E37: 1 | F37: Market | G37: Occupied | H37: 1645 | I37: 1565 | J37: 1565 | L37: 45528 | M37: 45041 | O37: 1565 | Q37: 250 | R37: 25 | S37: 10
A38: 1304 | B38: A3-abi | C38: 719 | D38: 1 | E38: 1 | F38: Market | G38: Occupied | H38: 1595 | I38: 1435 | J38: 1435 | L38: 45664 | M38: 45238 | O38: 1435 | P38: -717.5 | R38: 25 | S38: 10
A39: 1305 | B39: A6-abi | C39: 803 | D39: 1 | E39: 1 | F39: Market | G39: Occupied | H39: 1820 | I39: 1770 | J39: 1770 | L39: 45540 | M39: 45113 | O39: 1770 | R39: 25 | S39: 10
A40: 1306 | B40: A3-abi | C40: 719 | D40: 1 | E40: 1 | F40: Market | G40: Occupied | H40: 1595 | I40: 1415 | J40: 1415 | L40: 45646 | M40: 45220 | O40: 1415 | R40: 25 | S40: 10 | T40: 65
A41: 1307 | B41: B2-abi | C41: 1109 | D41: 2 | E41: 2 | F41: Market | G41: Occupied | H41: 2255 | I41: 2215 | J41: 2215 | L41: 45450 | M41: 45085 | O41: 2215 | R41: 25 | S41: 10 | T41: 65 | U41: 25
A42: 1308 | B42: B2-abi | C42: 1109 | D42: 2 | E42: 2 | F42: Market | G42: Occupied | H42: 2080 | I42: 1980 | J42: 1980 | L42: 45677 | M42: 45220 | O42: 1980 | Q42: 350 | R42: 25 | S42: 10
A43: 1309 | B43: A4-abi | C43: 736 | D43: 1 | E43: 1 | F43: Market | G43: Occupied | H43: 1690 | I43: 1660 | J43: 1660 | L43: 45645 | M43: 45219 | O43: 1660 | R43: 25 | S43: 10 | U43: 25
A44: 1310 | B44: B2-abi | C44: 1109 | D44: 2 | E44: 2 | F44: Market | G44: Occupied | H44: 2080 | I44: 1995 | J44: 1995 | L44: 45575 | M44: 45180 | O44: 1995 | R44: 25 | S44: 10
A45: 1312 | B45: C1-abi | C45: 1564 | D45: 3 | E45: 2 | F45: Market | G45: Occupied | H45: 2905 | I45: 2585 | J45: 2585 | L45: 45627 | M45: 45201 | O45: 2585 | Q45: 350 | R45: 25 | S45: 10
A46: 1313 | B46: A4-abi | C46: 736 | D46: 1 | E46: 1 | F46: Market | G46: Occupied | H46: 1690 | I46: 1680 | J46: 1680 | L46: 45606 | M46: 45180 | O46: 1680 | Q46: 350 | R46: 25 | S46: 10
A47: 1314 | B47: A3-abi | C47: 719 | D47: 1 | E47: 1 | F47: Market | G47: Occupied | H47: 1595 | I47: 1410 | J47: 1410 | L47: 45689 | M47: 45262 | O47: 1410 | P47: -705 | R47: 25 | S47: 10
A48: 1315 | B48: A2-abi | C48: 698 | D48: 1 | E48: 1 | F48: Market | G48: Occupied | H48: 1705 | I48: 1525 | J48: 1525 | L48: 45665 | M48: 45239 | O48: 1525 | P48: -762.5 | R48: 25 | S48: 10
A49: 1316 | B49: B2-abi | C49: 1109 | D49: 2 | E49: 2 | F49: Market | G49: Occupied | H49: 2080 | I49: 1990 | J49: 1990 | L49: 45443 | M49: 45078 | O49: 1990 | R49: 25 | S49: 10 | U49: 25
A50: 1317 | B50: A2-abi | C50: 698 | D50: 1 | E50: 1 | F50: Market | G50: Occupied | H50: 1705 | I50: 1675 | J50: 1675 | L50: 45511 | M50: 45146 | O50: 1675 | R50: 25 | S50: 10
A51: 1318 | B51: B2-abi | C51: 1109 | D51: 2 | E51: 2 | F51: Market | G51: Vacant | H51: 2080 | I51: 0 | J51: 0
A52: 1319 | B52: A2-abi | C52: 698 | D52: 1 | E52: 1 | F52: Market | G52: Occupied | H52: 1705 | I52: 1465 | J52: 1465 | L52: 45777 | M52: 45230 | O52: 1465 | R52: 25 | S52: 10
A53: 1320 | B53: B1-abi | C53: 1082 | D53: 2 | E53: 2 | F53: Market | G53: Occupied | H53: 2130 | I53: 2005 | J53: 2005 | L53: 45624 | M53: 45198 | O53: 2005 | R53: 25 | S53: 10 | U53: 50
A54: 1321 | B54: B1-abi | C54: 1082 | D54: 2 | E54: 2 | F54: Market | G54: Occupied | H54: 2305 | I54: 2090 | J54: 2090 | L54: 45730 | M54: 45306 | O54: 2090 | P54: -1045 | R54: 25 | S54: 10 | U54: 25
A55: 2102 | B55: B3-abi | C55: 1213 | D55: 2 | E55: 2 | F55: Market | G55: Occupied | H55: 2210 | I55: 2205 | J55: 2205 | L55: 45501 | M55: 45136 | O55: 2205 | R55: 25 | S55: 10 | X55: 42
A56: 2104 | B56: A3-abi | C56: 719 | D56: 1 | E56: 1 | F56: Market | G56: Occupied | H56: 1630 | I56: 1450 | J56: 1450 | L56: 45611 | M56: 45185 | O56: 1450 | R56: 25 | S56: 10
A57: 2106 | B57: A3-abi | C57: 719 | D57: 1 | E57: 1 | F57: Market | G57: Occupied | H57: 1630 | I57: 1410 | J57: 1410 | L57: 45691 | M57: 45264 | O57: 1410 | P57: -705 | R57: 25 | S57: 10 | T57: 65
A58: 2108 | B58: A3-abi | C58: 719 | D58: 1 | E58: 1 | F58: Market | G58: Occupied | H58: 1630 | I58: 1410 | J58: 1410 | L58: 45474 | M58: 45293 | O58: 1410 | R58: 25 | S58: 10
A59: 2110 | B59: B3-abi | C59: 1213 | D59: 2 | E59: 2 | F59: Market | G59: Occupied | H59: 2210 | I59: 2205 | J59: 2205 | L59: 45502 | M59: 45076 | O59: 2205 | R59: 25 | S59: 10 | T59: 130
A60: 2201 | B60: B1-abi | C60: 1082 | D60: 2 | E60: 2 | F60: Market | G60: Occupied | H60: 2260 | I60: 2245 | J60: 2245 | L60: 45444 | M60: 45079 | O60: 2245 | R60: 25 | S60: 10
A61: 2202 | B61: B3-abi | C61: 1213 | D61: 2 | E61: 2 | F61: Market | G61: Occupied | H61: 2130 | I61: 2125 | J61: 2125 | L61: 45574 | M61: 45148 | O61: 2125 | Q61: 360 | R61: 25 | S61: 10
A62: 2203 | B62: A2-abi | C62: 698 | D62: 1 | E62: 1 | F62: Market | G62: Occupied | H62: 1660 | I62: 1630 | J62: 1630 | L62: 45533 | M62: 45107 | O62: 1630 | Q62: 210 | R62: 25 | S62: 10
A63: 2204 | B63: A3-abi | C63: 719 | D63: 1 | E63: 1 | F63: Market | G63: Occupied | H63: 1550 | I63: 1485 | J63: 1485 | L63: 45532 | M63: 45106 | O63: 1485 | R63: 25 | S63: 10
A64: 2205 | B64: A2-abi | C64: 698 | D64: 1 | E64: 1 | F64: Market | G64: Occupied | H64: 1660 | I64: 1630 | J64: 1630 | L64: 45596 | M64: 45170 | O64: 1630 | R64: 25 | S64: 10 | T64: 65 | Z64: 40
A65: 2206 | B65: A3-abi | C65: 719 | D65: 1 | E65: 1 | F65: Market | G65: Occupied | H65: 1550 | I65: 1485 | J65: 1485 | L65: 45471 | M65: 45045 | O65: 1485 | R65: 25 | S65: 10
A66: 2207 | B66: A2-abi | C66: 698 | D66: 1 | E66: 1 | F66: Market | G66: Occupied | H66: 1660 | I66: 1580 | J66: 1580 | L66: 45575 | M66: 45149 | O66: 1580 | R66: 25 | S66: 10
A67: 2208 | B67: A3-abi | C67: 719 | D67: 1 | E67: 1 | F67: Market | G67: Occupied | H67: 1550 | I67: 1485 | J67: 1485 | L67: 45493 | M67: 45067 | O67: 1485 | R67: 25 | S67: 10
A68: 2209 | B68: B1-abi | C68: 1082 | D68: 2 | E68: 2 | F68: Market | G68: Occupied | H68: 2260 | I68: 2190 | J68: 2190 | L68: 45594 | M68: 45229 | O68: 2190 | R68: 25 | S68: 10
A69: 2210 | B69: B3-abi | C69: 1213 | D69: 2 | E69: 2 | F69: Market | G69: Occupied | H69: 2130 | I69: 2115 | J69: 2115 | L69: 45518 | M69: 45061 | O69: 2115 | R69: 25 | S69: 10
A70: 2301 | B70: B1-abi | C70: 1082 | D70: 2 | E70: 2 | F70: Market | G70: Occupied | H70: 2305 | I70: 2090 | J70: 2090 | L70: 45660 | M70: 45295 | O70: 2090 | R70: 25 | S70: 10
A71: 2302 | B71: B3-abi | C71: 1213 | D71: 2 | E71: 2 | F71: Market | G71: Occupied | H71: 2175 | I71: 2170 | J71: 2170 | L71: 45736 | M71: 45312 | O71: 2170 | R71: 25 | S71: 10
A72: 2303 | B72: A2-abi | C72: 698 | D72: 1 | E72: 1 | F72: Market | G72: Occupied | H72: 1705 | I72: 1525 | J72: 1525 | L72: 45625 | M72: 45229 | O72: 1525 | Q72: 295 | R72: 25 | S72: 10
A73: 2304 | B73: A3-abi | C73: 719 | D73: 1 | E73: 1 | F73: Market | G73: Occupied | H73: 1595 | I73: 1485 | J73: 1485 | L73: 45617 | M73: 45129 | O73: 1485 | R73: 25 | S73: 10
A74: 2305 | B74: A2-abi | C74: 698 | D74: 1 | E74: 1 | F74: Market | G74: Occupied | H74: 1705 | I74: 1675 | J74: 1675 | L74: 45460 | M74: 45278 | O74: 1675 | R74: 25 | S74: 10
A75: 2306 | B75: A3-abi | C75: 719 | D75: 1 | E75: 1 | F75: Market | G75: Occupied | H75: 1595 | I75: 1475 | J75: 1475 | L75: 45465 | M75: 45100 | O75: 1475 | R75: 25 | S75: 10 | T75: 65
A76: 2307 | B76: A2-abi | C76: 698 | D76: 1 | E76: 1 | F76: Market | G76: Occupied | H76: 1705 | I76: 1665 | J76: 1665 | L76: 45468 | M76: 45103 | O76: 1665 | R76: 25 | S76: 10 | T76: 65
A77: 2308 | B77: A3-abi | C77: 719 | D77: 1 | E77: 1 | F77: Market | G77: Occupied | H77: 1595 | I77: 1520 | J77: 1520 | L77: 45484 | M77: 45058 | O77: 1520 | Q77: 325 | R77: 25 | S77: 10 | X77: 42
A78: 2309 | B78: B1-abi | C78: 1082 | D78: 2 | E78: 2 | F78: Market | G78: Occupied | H78: 2305 | I78: 2305 | J78: 2305 | L78: 45492 | M78: 45127 | O78: 2305 | R78: 25 | S78: 10 | T78: 65
A79: 2310 | B79: B3-abi | C79: 1213 | D79: 2 | E79: 2 | F79: Market | G79: Occupied | H79: 2175 | I79: 2160 | J79: 2160 | L79: 45565 | M79: 45139 | O79: 2160 | R79: 25 | S79: 10 | T79: 65
A80: 3104 | B80: A3-abi | C80: 719 | D80: 1 | E80: 1 | F80: Market | G80: Occupied | H80: 1630 | I80: 1415 | J80: 1415 | L80: 45791 | M80: 45306 | O80: 1415 | P80: -707.5 | R80: 25 | S80: 10 | T80: 65 | Z80: 40
A81: 3106 | B81: A3-abi | C81: 719 | D81: 1 | E81: 1 | F81: Market | G81: Occupied | H81: 1630 | I81: 1415 | J81: 1415 | L81: 45721 | M81: 45297 | O81: 1415 | P81: -707.5 | R81: 25 | S81: 10
A82: 3108 | B82: A7-abi | C82: 941 | D82: 1 | E82: 1 | F82: Market | G82: Occupied | H82: 1895 | I82: 1895 | J82: 1895 | L82: 45716 | M82: 45229 | O82: 1895 | R82: 25 | S82: 10
A83: 3109 | B83: A4-abi | C83: 736 | D83: 1 | E83: 1 | F83: Market | G83: Vacant | H83: 1725 | I83: 0 | J83: 0
A84: 3110 | B84: A7-abi | C84: 941 | D84: 1 | E84: 1 | F84: Market | G84: Occupied | H84: 1895 | I84: 1895 | J84: 1895 | L84: 45642 | M84: 45216 | O84: 1895 | R84: 25 | S84: 10 | X84: 42
A85: 3112 | B85: C1.2-abi | C85: 1564 | D85: 3 | E85: 2 | F85: Market | G85: Occupied | H85: 2925 | I85: 2920 | J85: 2920 | L85: 45626 | M85: 45200 | O85: 2920 | R85: 25 | S85: 10 | X85: 29
A86: 3114 | B86: A3.8-abi | C86: 739 | D86: 1 | E86: 1 | F86: Market | G86: Vacant | H86: 1605 | I86: 0 | J86: 0
A87: 3115 | B87: A4-abi | C87: 736 | D87: 1 | E87: 1 | F87: Market | G87: Occupied | H87: 1725 | I87: 1595 | J87: 1595 | L87: 45719 | M87: 45234 | O87: 1595 | P87: -797.5 | R87: 25 | S87: 10
A88: 3116 | B88: A5-abi | C88: 762 | D88: 1 | E88: 1 | F88: Market | G88: Occupied | H88: 1645 | I88: 1605 | J88: 1605 | L88: 45527 | M88: 45101 | O88: 1605 | R88: 25 | S88: 10
A89: 3118 | B89: A5-abi | C89: 762 | D89: 1 | E89: 1 | F89: Market | G89: Occupied | H89: 1645 | I89: 1635 | J89: 1635 | L89: 45647 | M89: 45160 | O89: 1635 | R89: 25 | S89: 10
A90: 3120 | B90: A1-abi | C90: 690 | D90: 1 | E90: 1 | F90: Market | G90: Occupied | H90: 1615 | I90: 1470 | J90: 1470 | L90: 45526 | M90: 44980 | O90: 1470 | Q90: 250 | R90: 25 | S90: 10
A91: 3122 | B91: B1-abi | C91: 1082 | D91: 2 | E91: 2 | F91: Market | G91: Occupied | H91: 2340 | I91: 2205 | J91: 2205 | L91: 45565 | M91: 45017 | O91: 2205 | Q91: 210 | R91: 25 | S91: 10
A92: 3201 | B92: B1-abi | C92: 1082 | D92: 2 | E92: 2 | F92: Market | G92: Vacant | H92: 2260 | I92: 0 | J92: 0
A93: 3202 | B93: B1-abi | C93: 1082 | D93: 2 | E93: 2 | F93: Market | G93: Occupied | H93: 2085 | I93: 1990 | J93: 1990 | L93: 45442 | M93: 45016 | O93: 1990 | R93: 25 | S93: 10
A94: 3203 | B94: A6-abi | C94: 803 | D94: 1 | E94: 1 | F94: Market | G94: Occupied | H94: 1775 | I94: 1760 | J94: 1760 | L94: 45691 | M94: 45295 | O94: 1760 | P94: -880 | R94: 25 | S94: 10 | U94: 25
A95: 3204 | B95: A3-abi | C95: 719 | D95: 1 | E95: 1 | F95: Market | G95: Occupied | H95: 1550 | I95: 1520 | J95: 1520 | L95: 45786 | M95: 45301 | O95: 1520 | P95: -760 | R95: 25 | S95: 10
A96: 3205 | B96: A6-abi | C96: 803 | D96: 1 | E96: 1 | F96: Market | G96: Occupied | H96: 1775 | I96: 1750 | J96: 1750 | L96: 45491 | M96: 45126 | O96: 1750 | R96: 25 | S96: 10 | U96: 50
A97: 3206 | B97: A3-abi | C97: 719 | D97: 1 | E97: 1 | F97: Market | G97: Occupied | H97: 1550 | I97: 1520 | J97: 1520 | L97: 45573 | M97: 45147 | O97: 1520 | R97: 25 | S97: 10
A98: 3208 | B98: A7-abi | C98: 941 | D98: 1 | E98: 1 | F98: Market | G98: Occupied | H98: 1815 | I98: 1790 | J98: 1790 | L98: 45571 | M98: 45023 | O98: 1790 | R98: 25 | S98: 10
A99: 3209 | B99: A4-abi | C99: 736 | D99: 1 | E99: 1 | F99: Market | G99: Occupied | H99: 1645 | I99: 1575 | J99: 1575 | L99: 45504 | M99: 45139 | O99: 1575 | R99: 25 | S99: 10
A100: 3210 | B100: A7-abi | C100: 941 | D100: 1 | E100: 1 | F100: Market | G100: Occupied | H100: 1815 | I100: 1790 | J100: 1790 | L100: 45477 | M100: 45051 | O100: 1790 | R100: 25 | S100: 10
...

Sheet Lease Trend
A1: Lease Trend & Operating History (monthly)
A2: True market rent from HelloData executed leases (mix-weighted by floor plan) + new-lease signings; loss-to-lease backed into from T12 AGPR; concessions compared T12 vs HelloData. Months flow left-to-right; renewals excluded from market reads.
A4: Month → | B4: Jan 2023 | C4: Feb 2023 | D4: Mar 2023 | E4: Apr 2023 | F4: May 2023 | G4: Jun 2023 | H4: Jul 2023 | I4: Aug 2023 | J4: Sep 2023 | K4: Oct 2023 | L4: Nov 2023 | M4: Dec 2023 | N4: Jan 2024 | O4: Feb 2024 | P4: Mar 2024 | Q4: Apr 2024 | R4: May 2024 | S4: Jun 2024 | T4: Jul 2024 | U4: Aug 2024 | V4: Sep 2024 | W4: Oct 2024 | X4: Nov 2024 | Y4: Dec 2024 | Z4: Jan 2025 | AA4: Feb 2025 | AB4: Mar 2025 | AC4: Apr 2025 | AD4: May 2025 | AE4: Jun 2025 | AF4: Jul 2025 | AG4: Aug 2025 | AH4: Sep 2025 | AI4: Oct 2025 | AJ4: Nov 2025 | AK4: Dec 2025 | AL4: Jan 2026 | AM4: Feb 2026 | AN4: Mar 2026 | AO4: Apr 2026 | AP4: May 2026 | AQ4: Jun 2026
A5: MARKET RENT — HelloData executed (mix-weighted) + new-lease signings
A6: HD Market Rent / unit (asking) | G6: 1872 | H6: 1894 | I6: 1874 | J6: 1815 | K6: 1765 | L6: 1694 | M6: 1743 | N6: 1743 | O6: 2083 | P6: 1929 | Q6: 1906 | R6: 1941 | S6: 1860 | T6: 1817 | U6: 1707 | V6: 1765 | W6: 1683 | X6: 1681 | Y6: 1716 | Z6: 1700 | AA6: 1737 | AB6: 1861 | AC6: 1966 | AD6: 1864 | AE6: 2020 | AF6: 1931 | AG6: 1906 | AH6: 1942 | AI6: 1713 | AJ6: 1601 | AK6: 1720 | AL6: 1608 | AM6: 1758 | AN6: 1741 | AO6: 1860 | AP6: 1843 | AQ6: 1763
A7: HD Effective Rent / unit | G7: 1655 | H7: 1674 | I7: 1572 | J7: 1604 | K7: 1560 | L7: 1496 | M7: 1472 | N7: 1641 | O7: 2083 | P7: 1929 | Q7: 1906 | R7: 1941 | S7: 1860 | T7: 1817 | U7: 1674 | V7: 1691 | W7: 1538 | X7: 1681 | Y7: 1716 | Z7: 1584 | AA7: 1737 | AB7: 1677 | AC7: 1627 | AD7: 1624 | AE7: 2000 | AF7: 1706 | AG7: 1653 | AH7: 1641 | AI7: 1447 | AJ7: 1303 | AK7: 1460 | AL7: 1388 | AM7: 1440 | AN7: 1687 | AO7: 1650 | AP7: 1577 | AQ7: 1562
A8: HD Concession % (1 − eff/ask) | G8: 0.11541131 | H8: 0.11539492 | I8: 0.15963351 | J8: 0.11542785 | K8: 0.11542048 | L8: 0.11559008 | M8: 0.15368785 | N8: 0.058402 | U8: 0.01918986 | V8: 0.041583859 | W8: 0.085182544 | Z8: 0.067581357 | AB8: 0.097700042 | AC8: 0.17142091 | AD8: 0.12761874 | AE8: 0.0098442648 | AF8: 0.11549733 | AG8: 0.13165187 | AH8: 0.15403676 | AI8: 0.15386415 | AJ8: 0.18426114 | AK8: 0.15015862 | AL8: 0.13585994 | AM8: 0.17932818 | AN8: 0.03062942 | AO8: 0.11184282 | AP8: 0.14287094 | AQ8: 0.11279194
A9: HD Executed Leases (#) | G9: 8 | H9: 17 | I9: 12 | J9: 16 | K9: 17 | L9: 10 | M9: 13 | N9: 15 | O9: 9 | P9: 9 | Q9: 7 | R9: 11 | S9: 17 | T9: 11 | U9: 19 | V9: 5 | W9: 12 | X9: 18 | Y9: 14 | Z9: 18 | AA9: 25 | AB9: 8 | AC9: 9 | AD9: 13 | AE9: 8 | AF9: 7 | AG9: 7 | AH9: 14 | AI9: 8 | AJ9: 13 | AK9: 9 | AL9: 21 | AM9: 14 | AN9: 15 | AO9: 7 | AP9: 21 | AQ9: 5
A10: New-Lease Contract / unit (rent roll) | B10: 1733 | C10: 1620 | D10: 1819 | E10: 1850 | F10: 1876 | G10: 1870 | H10: 1820 | I10: 1858 | J10: 1845 | K10: 1817 | L10: 1746 | M10: 1583 | N10: 1791 | O10: 1912 | AC10: 1843 | AD10: 1746 | AE10: 1979 | AF10: 1843 | AG10: 1922 | AH10: 1895 | AI10: 1840 | AJ10: 1694 | AK10: 1621 | AL10: 1662 | AM10: 1716 | AN10: 1707 | AO10: 1824 | AP10: 2313
A11: New Leases (#) | B11: 8 | C11: 15 | D11: 12 | E11: 17 | F11: 23 | G11: 33 | H11: 26 | I11: 22 | J11: 18 | K11: 17 | L11: 10 | M11: 9 | N11: 18 | O11: 7 | AC11: 4 | AD11: 6 | AE11: 10 | AF11: 7 | AG11: 7 | AH11: 11 | AI11: 13 | AJ11: 9 | AK11: 11 | AL11: 12 | AM11: 21 | AN11: 9 | AO11: 9 | AP11: 11
A13: OCCUPANCY & RENT POSITION — from financial statements
A14: Physical Occupancy % (T12: 1 − vac/AGPR) | AD14: 0.93982639 | AE14: 0.9249804 | AF14: 0.93970019 | AG14: 0.93210151 | AH14: 0.91504856 | AI14: 0.93801351 | AJ14: 0.92557653 | AK14: 0.89750411 | AL14: 0.8823102 | AM14: 0.90406827 | AN14: 0.93017183 | AO14: 0.93037279
A15: Contract Rent / unit — AGPR (T12) | AD15: 1837 | AE15: 1836 | AF15: 1839 | AG15: 1843 | AH15: 1846 | AI15: 1848 | AJ15: 1844 | AK15: 1847 | AL15: 1847 | AM15: 1835 | AN15: 1833 | AO15: 1832
A16: Market Rent / unit — GPR basis (T12, ref only) | AD16: 1932 | AE16: 1932 | AF16: 1932 | AG16: 1930 | AH16: 1929 | AI16: 1930 | AJ16: 1929 | AK16: 1930 | AL16: 1930 | AM16: 1930 | AN16: 1931 | AO16: 1931
A17: Loss-to-Lease / unit (HD mkt − AGPR) | AD17: 27 | AE17: 184 | AF17: 92 | AG17: 62 | AH17: 96 | AI17: -135 | AJ17: -243 | AK17: -127 | AL17: -239 | AM17: -78 | AN17: -92 | AO17: 28
A18: Loss-to-Lease % (vs HD market) | AD18: 0.014279956 | AE18: 0.091127615 | AF18: 0.047644336 | AG18: 0.032715038 | AH18: 0.049553039 | AI18: -0.079107175 | AJ18: -0.15157241 | AK18: -0.073590753 | AL18: -0.14835645 | AM18: -0.044246614 | AN18: -0.052834047 | AO18: 0.015074403
A20: CONCESSIONS — T12 (portfolio) vs HelloData (new-lease)
A21: T12 Concessions ($/mo) | AD21: -51397 | AE21: -36344 | AF21: -41734 | AG21: -40560 | AH21: -23142 | AI21: -21380 | AJ21: -23729 | AK21: -23776 | AL21: -29614 | AM21: -31630 | AN21: -41572 | AO21: -45134
A22: T12 Concessions % of AGPR | AD22: 0.096469062 | AE22: 0.06824767 | AF22: 0.078250244 | AG22: 0.075875413 | AH22: 0.043225211 | AI22: 0.039885687 | AJ22: 0.044383219 | AK22: 0.044395898 | AL22: 0.055299979 | AM22: 0.059423149 | AN22: 0.078199941 | AO22: 0.084948436
A23: HD Concession % (new-lease) | G23: 0.11541131 | H23: 0.11539492 | I23: 0.15963351 | J23: 0.11542785 | K23: 0.11542048 | L23: 0.11559008 | M23: 0.15368785 | N23: 0.058402 | U23: 0.01918986 | V23: 0.041583859 | W23: 0.085182544 | Z23: 0.067581357 | AB23: 0.097700042 | AC23: 0.17142091 | AD23: 0.12761874 | AE23: 0.0098442648 | AF23: 0.11549733 | AG23: 0.13165187 | AH23: 0.15403676 | AI23: 0.15386415 | AJ23: 0.18426114 | AK23: 0.15015862 | AL23: 0.13585994 | AM23: 0.17932818 | AN23: 0.03062942 | AO23: 0.11184282 | AP23: 0.14287094 | AQ23: 0.11279194
A25: OPERATING TREND — from stitched T12
A26: Effective Gross Revenue | AD26: 489633 | AE26: 501457 | AF26: 494567 | AG26: 497846 | AH26: 516024 | AI26: 529843 | AJ26: 525790 | AK26: 493546 | AL26: 486860 | AM26: 490387 | AN26: 502231 | AO26: 504748
A27: Operating Expenses | AD27: 257324 | AE27: 232211 | AF27: 243449 | AG27: 219182 | AH27: 213094 | AI27: 282465 | AJ27: 123816 | AK27: 227798 | AL27: 204269 | AM27: 198020 | AN27: 190742 | AO27: 238843
A28: Net Operating Income | AD28: 232309 | AE28: 269246 | AF28: 251119 | AG28: 278664 | AH28: 302931 | AI28: 247378 | AJ28: 401975 | AK28: 265749 | AL28: 282591 | AM28: 292366 | AN28: 311489 | AO28: 265905
A30: TRAILING ANNUALIZATIONS
B31: T12 | C31: T6 | D31: T3
A32: EGR (annualized) | B32: 6032933 | C32: 6007125 | D32: 5989462
A33: Operating Expenses | B33: 2631212 | C33: 2366975 | D33: 2510419
A34: NOI | B34: 3401721 | C34: 3640150 | D34: 3479043
A36: Observations
A37: • HelloData reflects the website 'Total Monthly', which can bundle mandatory fees. HD market rent here is shown NET of $15.00/mo (explicit override). See 'Reconciliation → HelloData Asking: Fee Netting' for the full derivation.
A38: • New-Lease Contract / unit history draws on 2 rent rolls (current 05/23/2026 + older 02/26/2024); older rolls supply signings that have since turned over. The dashboard and unit mix use the current rent roll only.
A39: • Seasonality: executed asking rents peak in Apr and trough in Nov (~15% spread across the HelloData history).
A40: • HelloData asking-rent YoY (same calendar month): -1.7% average across 25 month-pair(s).
A41: • Concessions by source: the T12 books concessions across the WHOLE portfolio (~6.4% of AGPR here), while HelloData's is per NEW lease (~12.4% here). The portfolio figure ≈ new-lease concession × the share of units on a recently-signed lease — here ~0% of in-place leases are new (lease-up), so the two run close (little dilution). On a stabilized deal with ~40–50% annual turnover, expect the T12 figure nearer half the new-lease rate.
A44: Trailing-90-Day Executed by Floor Plan (HelloData)
A45: Base Plan | B45: T90 Asking | C45: T90 Effective | D45: Concession % | E45: Exec (n)
A46: A1-abi | B46: 1520 | C46: 1351 | D46: =IF(OR(B46="",B46=0),"-",1-C46/B46) -> 0.11118421 | E46: 4
A47: A2-abi | B47: 1605 | C47: 1463 | D47: =IF(OR(B47="",B47=0),"-",1-C47/B47) -> 0.08847352 | E47: 3
A48: A3-abi | B48: 1564 | C48: 1372 | D48: =IF(OR(B48="",B48=0),"-",1-C48/B48) -> 0.12276215 | E48: 10
A49: A5-abi | B49: 1580 | C49: 1354 | D49: =IF(OR(B49="",B49=0),"-",1-C49/B49) -> 0.14303797 | E49: 3
A50: A5.3-abi | B50: 1605 | C50: 1433 | D50: =IF(OR(B50="",B50=0),"-",1-C50/B50) -> 0.10716511 | E50: 1
A51: A6-abi | B51: 1732 | C51: 1484 | D51: =IF(OR(B51="",B51=0),"-",1-C51/B51) -> 0.14318707 | E51: 3
A52: A7-abi | B52: 1860 | C52: 1727 | D52: =IF(OR(B52="",B52=0),"-",1-C52/B52) -> 0.071505376 | E52: 2
A53: B1-abi | B53: 2215 | C53: 2029 | D53: =IF(OR(B53="",B53=0),"-",1-C53/B53) -> 0.083972912 | E53: 5
A54: B2-abi | B54: 2120 | C54: 1830 | D54: =IF(OR(B54="",B54=0),"-",1-C54/B54) -> 0.13679245 | E54: 3
A55: B3-abi | B55: 2160 | C55: 1851 | D55: =IF(OR(B55="",B55=0),"-",1-C55/B55) -> 0.14305556 | E55: 3
A56: TH-abi | B56: 3410 | C56: 2923 | D56: =IF(OR(B56="",B56=0),"-",1-C56/B56) -> 0.14281525 | E56: 1
A58: Last 5 New Leases by Floor Plan (rent roll)
A59: Floor Plan | B59: Unit | C59: Lease Start | D59: Contract Rent | E59: Rent PSF (mo.)
A60: A1-abi | B60: 4320 | D60: 1350 | E60: 1.96
A61: A1-abi | B61: 6303 | D61: 1350 | E61: 1.96
A62: A1-abi | B62: 6211 | D62: 1299 | E62: 1.88
A63: A1-abi | B63: 3220 | D63: 1499 | E63: 2.17
A64: A2-abi | B64: 2203 | D64: 1660 | E64: 2.38
A65: A2-abi | B65: 5205 | D65: 1399 | E65: 2
A66: A2-abi | B66: 1319 | D66: 1399 | E66: 2
A67: A2-abi | B67: 2307 | D67: 1399 | E67: 2
A68: A2-abi | B68: 7303 | D68: 1387 | E68: 1.99
A69: A3-abi | B69: 6206 | D69: 1550 | E69: 2.16
A70: A3-abi | B70: 4206 | D70: 1550 | E70: 2.16
A71: A3-abi | B71: 6309 | D71: 1595 | E71: 2.22
... A117: TH-abi | B117: 8103 | D117: 3410 | E117: 2.47

Sheet HelloData
A1: Property Name | B1: Floorplan | C1: Unit | D1: Floor | E1: Bedrooms | F1: Bathrooms | G1: Partial Bathrooms | H1: SF | I1: Available On | J1: Deposit | K1: Term | L1: AMI Level | M1: Last Asking Rent | N1: Asking Rent PSF | O1: Last Effective Rent | P1: Effective Rent PSF | Q1: On Market Date | R1: Off Market Date | S1: Days on Market | T1: Days Vacant | U1: Floorplan Mapped
A2: Aura Beacon Island | B2: A3 | C2: 2208 | D2: 2 | E2: 1 | F2: 1 | H2: 719 | I2: 45500 | K2: 15 | L2: 80% | M2: 1445 | N2: 2.01 | O2: 1445 | P2: 2.01 | Q2: 45433 | R2: 45539 | S2: 107 | T2: 40 | U2: A3
A3: Aura Beacon Island | B3: A3 | C3: 2208 | D3: 2 | E3: 1 | F3: 1 | H3: 719 | I3: 46001 | K3: 13 | L3: 80% | M3: 1299 | N3: 1.81 | O3: 1299 | P3: 1.81 | Q3: 45940 | R3: 46027 | S3: 88 | T3: 27 | U3: A3
A4: Aura Beacon Island | B4: A3 | C4: 6212 | D4: 2 | E4: 1 | F4: 1 | H4: 719 | I4: 45480 | K4: 12 | L4: 80% | M4: 1399 | N4: 1.95 | O4: 1237 | P4: 1.72 | Q4: 45413 | R4: 45582 | S4: 170 | T4: 103 | U4: A3
A5: Aura Beacon Island | B5: A3 | C5: 6212 | D5: 2 | E5: 1 | F5: 1 | H5: 719 | I5: 45998 | K5: 13 | L5: 80% | M5: 1306 | N5: 1.82 | O5: 1055 | P5: 1.47 | Q5: 45921 | R5: 46041 | S5: 121 | T5: 44 | U5: A3
A6: Aura Beacon Island | B6: A3 | C6: 3304 | D6: 3 | E6: 1 | F6: 1 | H6: 719 | I6: 45959 | K6: 13 | L6: 80% | M6: 1351 | N6: 1.88 | O6: 1091 | P6: 1.52 | Q6: 45892 | R6: 46046 | S6: 155 | T6: 88 | U6: A3
A7: Aura Beacon Island | B7: A3 | C7: 6112 | D7: 1 | E7: 1 | F7: 1 | H7: 719 | I7: 45094 | L7: 80% | M7: 1435 | N7: 2 | O7: 1186 | P7: 1.65 | R7: 45283 | U7: A3
A8: Aura Beacon Island | B8: A3 | C8: 6112 | D8: 1 | E8: 1 | F8: 1 | H8: 719 | I8: 45558 | K8: 12 | L8: 80% | M8: 1399 | N8: 1.95 | O8: 1399 | P8: 1.95 | Q8: 45491 | R8: 45603 | S8: 113 | T8: 46 | U8: A3
A9: Aura Beacon Island | B9: A3 | C9: 6112 | D9: 1 | E9: 1 | F9: 1 | H9: 719 | I9: 45947 | K9: 14 | L9: 80% | M9: 1386 | N9: 1.93 | O9: 1138 | P9: 1.58 | Q9: 45936 | R9: 46061 | S9: 126 | T9: 115 | U9: A3
A10: Aura Beacon Island | B10: A3 | C10: 2108 | D10: 1 | E10: 1 | F10: 1 | H10: 719 | I10: 45094 | L10: 80% | M10: 1410 | N10: 1.96 | O10: 1164 | P10: 1.62 | R10: 45272 | U10: A3
A11: Aura Beacon Island | B11: A3 | C11: 2108 | D11: 1 | E11: 1 | F11: 1 | H11: 719 | I11: 45481 | K11: 12 | L11: 80% | M11: 1630 | N11: 2.27 | O11: 1630 | P11: 2.27 | Q11: 45438 | R11: 45638 | S11: 201 | T11: 158 | U11: A3
A12: Aura Beacon Island | B12: A3 | C12: 2108 | D12: 1 | E12: 1 | F12: 1 | H12: 719 | I12: 46035 | K12: 14 | L12: 80% | M12: 1469 | N12: 2.04 | O12: 1469 | P12: 2.04 | Q12: 45923 | R12: 46084 | S12: 162 | T12: 50 | U12: A3
A13: Aura Beacon Island | B13: A3 | C13: 1206 | D13: 2 | E13: 1 | F13: 1 | H13: 719 | I13: 45168 | L13: 80% | M13: 1385 | N13: 1.93 | O13: 1225 | P13: 1.7 | Q13: 45168 | R13: 45264 | S13: 97 | T13: 97 | U13: A3
A14: Aura Beacon Island | B14: A3 | C14: 1206 | D14: 2 | E14: 1 | F14: 1 | H14: 719 | I14: 45709 | K14: 12 | L14: 80% | M14: 1375 | N14: 1.91 | O14: 1375 | P14: 1.91 | Q14: 45630 | R14: 45695 | S14: 66 | T14: 0 | U14: A3
A15: Aura Beacon Island | B15: A3 | C15: 1206 | D15: 2 | E15: 1 | F15: 1 | H15: 719 | I15: 46026 | K15: 14 | L15: 80% | M15: 1435 | N15: 2 | O15: 1179 | P15: 1.64 | Q15: 45940 | R15: 46064 | S15: 125 | T15: 39 | U15: A3
A16: Aura Beacon Island | B16: A3 | C16: 6209 | D16: 2 | E16: 1 | F16: 1 | H16: 719 | I16: 45505 | K16: 15 | L16: 80% | M16: 1465 | N16: 2.04 | O16: 1465 | P16: 2.04 | Q16: 45422 | R16: 45532 | S16: 111 | T16: 28 | U16: A3
A17: Aura Beacon Island | B17: A3 | C17: 6209 | D17: 2 | E17: 1 | F17: 1 | H17: 719 | I17: 45997 | K17: 12 | L17: 80% | M17: 1550 | N17: 2.16 | O17: 1252 | P17: 1.74 | Q17: 45910 | R17: 46000 | S17: 91 | T17: 4 | U17: A3
A18: Aura Beacon Island | B18: A1 | C18: 6211 | D18: 2 | E18: 1 | F18: 1 | H18: 690 | I18: 45156 | L18: 80% | M18: 1375 | N18: 1.99 | O18: 1216 | P18: 1.76 | R18: 45193 | U18: A1
A19: Aura Beacon Island | B19: A1 | C19: 6211 | D19: 2 | E19: 1 | F19: 1 | H19: 690 | I19: 46030 | K19: 14 | L19: 80% | M19: 1299 | N19: 1.88 | O19: 1067 | P19: 1.55 | Q19: 46026 | R19: 46057 | S19: 32 | T19: 28 | U19: A1
A20: Aura Beacon Island | B20: A1 | C20: 6303 | D20: 3 | E20: 1 | F20: 1 | H20: 690 | I20: 45739 | K20: 12 | L20: 80% | M20: 1620 | N20: 2.35 | O20: 1620 | P20: 2.35 | Q20: 45669 | R20: 45672 | S20: 4 | T20: 0 | U20: A1
A21: Aura Beacon Island | B21: A1 | C21: 6303 | D21: 3 | E21: 1 | F21: 1 | H21: 690 | I21: 46119 | K21: 14 | L21: 80% | M21: 1350 | N21: 1.96 | O21: 1157 | P21: 1.68 | Q21: 46038 | R21: 46098 | S21: 61 | T21: 0 | U21: A1
A22: Aura Beacon Island | B22: A1 | C22: 4320 | D22: 3 | E22: 1 | F22: 1 | H22: 690 | I22: 45094 | L22: 80% | M22: 1580 | N22: 2.29 | O22: 1398 | P22: 2.03 | R22: 45106 | U22: A1
A23: Aura Beacon Island | B23: A1 | C23: 4320 | D23: 3 | E23: 1 | F23: 1 | H23: 690 | I23: 45491 | K23: 15 | L23: 80% | M23: 1580 | N23: 2.29 | O23: 1580 | P23: 2.29 | Q23: 45428 | R23: 45433 | S23: 6 | T23: 0 | U23: A1
A24: Aura Beacon Island | B24: A1 | C24: 4320 | D24: 3 | E24: 1 | F24: 1 | H24: 690 | I24: 46009 | K24: 14 | L24: 80% | M24: 1350 | N24: 1.96 | O24: 1350 | P24: 1.96 | Q24: 45948 | R24: 46107 | S24: 160 | T24: 99 | U24: A1
A25: Aura Beacon Island | B25: A1 | C25: 4120 | D25: 1 | E25: 1 | F25: 1 | H25: 690 | I25: 45094 | L25: 80% | M25: 1375 | N25: 1.99 | O25: 1133 | P25: 1.64 | R25: 45277 | U25: A1
A26: Aura Beacon Island | B26: A1 | C26: 3320 | D26: 3 | E26: 1 | F26: 1 | H26: 690 | I26: 45094 | L26: 80% | M26: 1420 | N26: 2.06 | O26: 1256 | P26: 1.82 | R26: 45190 | U26: A1
A27: Aura Beacon Island | B27: A1 | C27: 6311 | D27: 3 | E27: 1 | F27: 1 | H27: 690 | I27: 45305 | L27: 80% | M27: 1505 | N27: 2.18 | O27: 1505 | P27: 2.18 | Q27: 45238 | R27: 45388 | S27: 151 | T27: 84 | U27: A1
A28: Aura Beacon Island | B28: A1 | C28: 4220 | D28: 2 | E28: 1 | F28: 1 | H28: 690 | I28: 45094 | L28: 80% | M28: 1375 | N28: 1.99 | O28: 1216 | P28: 1.76 | R28: 45249 | U28: A1
A29: Aura Beacon Island | B29: A1 | C29: 4220 | D29: 2 | E29: 1 | F29: 1 | H29: 690 | I29: 45645 | K29: 12 | L29: 80% | M29: 1370 | N29: 1.99 | O29: 1370 | P29: 1.99 | Q29: 45640 | R29: 45713 | S29: 74 | T29: 69 | U29: A1
A30: Aura Beacon Island | B30: A1 | C30: 4220 | D30: 2 | E30: 1 | F30: 1 | H30: 690 | I30: 46210 | K30: 14 | L30: 80% | M30: 1535 | N30: 2.22 | O30: 1316 | P30: 1.91 | Q30: 46143 | R30: 46149 | S30: 7 | T30: 0 | U30: A1
A31: Aura Beacon Island | B31: A1 | C31: 3220 | D31: 2 | E31: 1 | F31: 1 | H31: 690 | I31: 45773 | K31: 12 | L31: 80% | M31: 1499 | N31: 2.17 | O31: 1499 | P31: 2.17 | Q31: 45700 | R31: 45814 | S31: 115 | T31: 42 | U31: A1
A32: Aura Beacon Island | B32: A1 | C32: 6203 | D32: 2 | E32: 1 | F32: 1 | H32: 690 | I32: 45250 | L32: 80% | M32: 1415 | N32: 2.05 | O32: 1252 | P32: 1.81 | Q32: 45179 | R32: 45248 | S32: 70 | T32: 0 | U32: A1
A33: Aura Beacon Island | B33: A1 | C33: 6203 | D33: 2 | E33: 1 | F33: 1 | H33: 690 | I33: 46088 | K33: 14 | L33: 80% | M33: 1575 | N33: 2.28 | O33: 1350 | P33: 1.96 | Q33: 45999 | R33: 46147 | S33: 149 | T33: 60 | U33: A1
A34: Aura Beacon Island | B34: A1 | C34: 6205 | D34: 2 | E34: 1 | F34: 1 | H34: 690 | I34: 45751 | K34: 12 | L34: 80% | M34: 1575 | N34: 2.28 | O34: 1270 | P34: 1.84 | Q34: 45661 | R34: 45664 | S34: 4 | T34: 0 | U34: A1
A35: Aura Beacon Island | B35: A1 | C35: 6305 | D35: 3 | E35: 1 | F35: 1 | H35: 690 | I35: 45738 | K35: 12 | L35: 120% | M35: 1620 | N35: 2.35 | O35: 1620 | P35: 2.35 | Q35: 45664 | R35: 45700 | S35: 37 | T35: 0 | U35: A1
A36: Aura Beacon Island | B36: A1 | C36: 6305 | D36: 3 | E36: 1 | F36: 1 | H36: 690 | I36: 46116 | K36: 14 | L36: 120% | M36: 1620 | N36: 2.35 | O36: 1389 | P36: 2.01 | Q36: 46040 | R36: 46145 | S36: 106 | T36: 30 | U36: A1
A37: Aura Beacon Island | B37: A2 | C37: 2205 | D37: 2 | E37: 1 | F37: 1 | H37: 698 | I37: 45094 | L37: 80% | M37: 1570 | N37: 2.25 | O37: 1305 | P37: 1.87 | R37: 45165 | U37: A2
A38: Aura Beacon Island | B38: A2 | C38: 2205 | D38: 2 | E38: 1 | F38: 1 | H38: 698 | I38: 45603 | K38: 15 | L38: 80% | M38: 1570 | N38: 2.25 | O38: 1570 | P38: 2.25 | Q38: 45423 | R38: 45427 | S38: 5 | T38: 0 | U38: A2
A39: Aura Beacon Island | B39: A2 | C39: 2205 | D39: 2 | E39: 1 | F39: 1 | H39: 698 | I39: 45548 | K39: 12 | L39: 80% | M39: 1330 | N39: 1.91 | O39: 1176 | P39: 1.68 | Q39: 45517 | R39: 45575 | S39: 59 | T39: 28 | U39: A2
A40: Aura Beacon Island | B40: A2 | C40: 2205 | D40: 2 | E40: 1 | F40: 1 | H40: 698 | I40: 46004 | K40: 13 | L40: 80% | M40: 1312 | N40: 1.88 | O40: 1060 | P40: 1.52 | Q40: 45937 | R40: 46039 | S40: 103 | T40: 36 | U40: A2
A41: Aura Beacon Island | B41: A2 | C41: 7205 | D41: 2 | E41: 1 | F41: 1 | H41: 698 | I41: 45470 | K41: 15 | L41: 80% | M41: 1580 | N41: 2.26 | O41: 1580 | P41: 2.26 | Q41: 45351 | R41: 45531 | S41: 181 | T41: 62 | U41: A2
A42: Aura Beacon Island | B42: A2 | C42: 7205 | D42: 2 | E42: 1 | F42: 1 | H42: 698 | I42: 45954 | K42: 12 | L42: 80% | M42: 1330 | N42: 1.91 | O42: 1074 | P42: 1.54 | Q42: 45889 | R42: 45991 | S42: 103 | T42: 38 | U42: A2
A43: Aura Beacon Island | B43: A2 | C43: 7204 | D43: 2 | E43: 1 | F43: 1 | H43: 698 | I43: 45389 | L43: 80% | M43: 1485 | N43: 2.13 | O43: 1485 | P43: 2.13 | Q43: 45340 | R43: 45413 | S43: 74 | T43: 25 | U43: A2
A44: Aura Beacon Island | B44: A2 | C44: 7204 | D44: 2 | E44: 1 | F44: 1 | H44: 698 | I44: 45584 | K44: 12 | L44: 80% | M44: 1330 | N44: 1.91 | O44: 1176 | P44: 1.68 | Q44: 45517 | R44: 45573 | S44: 57 | T44: 0 | U44: A2
A45: Aura Beacon Island | B45: A2 | C45: 7304 | D45: 3 | E45: 1 | F45: 1 | H45: 698 | I45: 45876 | K45: 12 | L45: 80% | M45: 1340 | N45: 1.92 | O45: 1134 | P45: 1.62 | Q45: 45797 | R45: 45931 | S45: 135 | T45: 56 | U45: A2
A46: Aura Beacon Island | B46: A2 | C46: 7211 | D46: 2 | E46: 1 | F46: 1 | H46: 698 | I46: 45534 | K46: 15 | L46: 80% | M46: 1630 | N46: 2.34 | O46: 1630 | P46: 2.34 | Q46: 45441 | R46: 45454 | S46: 14 | T46: 0 | U46: A2
A47: Aura Beacon Island | B47: A2 | C47: 7211 | D47: 2 | E47: 1 | F47: 1 | H47: 698 | I47: 45998 | K47: 13 | L47: 80% | M47: 1342 | N47: 1.92 | O47: 1084 | P47: 1.55 | Q47: 45891 | R47: 46038 | S47: 148 | T47: 41 | U47: A2
A48: Aura Beacon Island | B48: A2 | C48: 1215 | D48: 2 | E48: 1 | F48: 1 | H48: 698 | I48: 45094 | L48: 80% | M48: 1585 | N48: 2.27 | O48: 1585 | P48: 2.27 | R48: 45397 | U48: A2
A49: Aura Beacon Island | B49: A2 | C49: 1215 | D49: 2 | E49: 1 | F49: 1 | H49: 698 | I49: 45983 | K49: 13 | L49: 80% | M49: 1364 | N49: 1.95 | O49: 1102 | P49: 1.58 | Q49: 45915 | R49: 46014 | S49: 100 | T49: 32 | U49: A2
A50: Aura Beacon Island | B50: A2 | C50: 7209 | D50: 2 | E50: 1 | F50: 1 | H50: 698 | I50: 45559 | K50: 12 | L50: 80% | M50: 1375 | N50: 1.97 | O50: 1375 | P50: 1.97 | Q50: 45553 | R50: 45615 | S50: 63 | T50: 57 | U50: A2
A51: Aura Beacon Island | B51: A2 | C51: 1217 | D51: 2 | E51: 1 | F51: 1 | H51: 698 | I51: 45094 | L51: 80% | M51: 1480 | N51: 2.12 | O51: 1309 | P51: 1.88 | R51: 45206 | U51: A2
A52: Aura Beacon Island | B52: A2 | C52: 1217 | D52: 2 | E52: 1 | F52: 1 | H52: 698 | I52: 45690 | K52: 12 | L52: 80% | M52: 1375 | N52: 1.97 | O52: 1375 | P52: 1.97 | Q52: 45623 | R52: 45703 | S52: 81 | T52: 14 | U52: A2
A53: Aura Beacon Island | B53: A2 | C53: 7303 | D53: 3 | E53: 1 | F53: 1 | H53: 698 | I53: 45542 | K53: 12 | L53: 80% | M53: 1500 | N53: 2.15 | O53: 1500 | P53: 2.15 | Q53: 45449 | R53: 45604 | S53: 156 | T53: 63 | U53: A2
A54: Aura Beacon Island | B54: A2 | C54: 7303 | D54: 3 | E54: 1 | F54: 1 | H54: 698 | I54: 46016 | K54: 14 | L54: 80% | M54: 1387 | N54: 1.99 | O54: 1139 | P54: 1.63 | Q54: 45975 | R54: 46061 | S54: 87 | T54: 46 | U54: A2
A55: Aura Beacon Island | B55: A2 | C55: 1319 | D55: 3 | E55: 1 | F55: 1 | H55: 698 | I55: 45094 | L55: 80% | M55: 1465 | N55: 2.1 | O55: 1296 | P55: 1.86 | R55: 45212 | U55: A2
A56: Aura Beacon Island | B56: A2 | C56: 1319 | D56: 3 | E56: 1 | F56: 1 | H56: 698 | I56: 46042 | K56: 14 | L56: 80% | M56: 1399 | N56: 2 | O56: 1399 | P56: 2 | Q56: 45976 | R56: 46104 | S56: 129 | T56: 63 | U56: A2
A57: Aura Beacon Island | B57: A2 | C57: 2307 | D57: 3 | E57: 1 | F57: 1 | H57: 698 | I57: 45950 | K57: 14 | L57: 80% | M57: 1399 | N57: 2 | O57: 1399 | P57: 2 | Q57: 45880 | R57: 46082 | S57: 203 | T57: 133 | U57: A2
A58: Aura Beacon Island | B58: A2 | C58: 5205 | D58: 2 | E58: 1 | F58: 1 | H58: 698 | I58: 45298 | L58: 80% | M58: 1755 | N58: 2.51 | O58: 1755 | P58: 2.51 | Q58: 45231 | R58: 45353 | S58: 123 | T58: 56 | U58: A2
A59: Aura Beacon Island | B59: A2 | C59: 5205 | D59: 2 | E59: 1 | F59: 1 | H59: 698 | I59: 45852 | K59: 12 | L59: 80% | M59: 1755 | N59: 2.51 | O59: 1552 | P59: 2.22 | Q59: 45777 | R59: 45850 | S59: 74 | T59: 0 | U59: A2
A60: Aura Beacon Island | B60: A2 | C60: 5205 | D60: 2 | E60: 1 | F60: 1 | H60: 698 | I60: 46038 | K60: 14 | L60: 80% | M60: 1399 | N60: 2 | O60: 1149 | P60: 1.65 | Q60: 46030 | R60: 46077 | S60: 48 | T60: 40 | U60: A2
A61: Aura Beacon Island | B61: A2 | C61: 1317 | D61: 3 | E61: 1 | F61: 1 | H61: 698 | I61: 45094 | L61: 80% | M61: 1675 | N61: 2.4 | O61: 1482 | P61: 2.12 | R61: 45116 | U61: A2
A62: Aura Beacon Island | B62: A2 | C62: 1317 | D62: 3 | E62: 1 | F62: 1 | H62: 698 | I62: 45511 | K62: 12 | L62: 80% | M62: 1400 | N62: 2.01 | O62: 1400 | P62: 2.01 | Q62: 45494 | R62: 45636 | S62: 143 | T62: 126 | U62: A2
A63: Aura Beacon Island | B63: A2 | C63: 7104 | D63: 1 | E63: 1 | F63: 1 | H63: 698 | I63: 45303 | L63: 80% | M63: 1565 | N63: 2.24 | O63: 1565 | P63: 2.24 | Q63: 45298 | R63: 45317 | S63: 20 | T63: 15 | U63: A2
A64: Aura Beacon Island | B64: A2 | C64: 7104 | D64: 1 | E64: 1 | F64: 1 | H64: 698 | I64: 45859 | K64: 12 | L64: 80% | M64: 1565 | N64: 2.24 | O64: 1565 | P64: 2.24 | Q64: 45750 | R64: 45808 | S64: 59 | T64: 0 | U64: A2
A65: Aura Beacon Island | B65: A2 | C65: 2203 | D65: 2 | E65: 1 | F65: 1 | H65: 698 | I65: 46061 | K65: 14 | L65: 120% | M65: 1660 | N65: 2.38 | O65: 1423 | P65: 2.04 | Q65: 45994 | R65: 46153 | S65: 160 | T65: 93 | U65: A2
A66: Aura Beacon Island | B66: A2 | C66: 1219 | D66: 2 | E66: 1 | F66: 1 | H66: 698 | I66: 45094 | L66: 120% | M66: 1580 | N66: 2.26 | O66: 1314 | P66: 1.88 | R66: 45145 | U66: A2
A67: Aura Beacon Island | B67: A2 | C67: 1219 | D67: 2 | E67: 1 | F67: 1 | H67: 698 | I67: 45676 | K67: 12 | L67: 120% | M67: 1660 | N67: 2.38 | O67: 1660 | P67: 2.38 | Q67: 45539 | R67: 45714 | S67: 176 | T67: 39 | U67: A2
A68: Aura Beacon Island | B68: A2 | C68: 1219 | D68: 2 | E68: 1 | F68: 1 | H68: 698 | I68: 46013 | K68: 13 | L68: 120% | M68: 1660 | N68: 2.38 | O68: 1660 | P68: 2.38 | Q68: 45829 | R68: 46022 | S68: 194 | T68: 10 | U68: A2
A69: Aura Beacon Island | B69: A2 | C69: 2207 | D69: 2 | E69: 1 | F69: 1 | H69: 698 | I69: 45094 | L69: 120% | M69: 1580 | N69: 2.26 | O69: 1398 | P69: 2 | R69: 45125 | U69: A2
A70: Aura Beacon Island | B70: A2 | C70: 2207 | D70: 2 | E70: 1 | F70: 1 | H70: 698 | I70: 45755 | K70: 12 | L70: 120% | M70: 1660 | N70: 2.38 | O70: 1321 | P70: 1.89 | Q70: 45693 | R70: 45736 | S70: 44 | T70: 0 | U70: A2
A71: Aura Beacon Island | B71: A2 | C71: 2305 | D71: 3 | E71: 1 | F71: 1 | H71: 698 | I71: 45169 | L71: 120% | M71: 1675 | N71: 2.4 | O71: 1398 | P71: 2 | Q71: 45164 | R71: 45272 | S71: 109 | T71: 104 | U71: A2
A72: Aura Beacon Island | B72: A2 | C72: 7309 | D72: 3 | E72: 1 | F72: 1 | H72: 698 | I72: 45480 | K72: 15 | L72: 120% | M72: 1700 | N72: 2.44 | O72: 1700 | P72: 2.44 | Q72: 45462 | R72: 45508 | S72: 47 | T72: 29 | U72: A2
A73: Aura Beacon Island | B73: A2 | C73: 1315 | D73: 3 | E73: 1 | F73: 1 | H73: 698 | I73: 45094 | L73: 120% | M73: 1525 | N73: 2.18 | O73: 1349 | P73: 1.93 | R73: 45234 | U73: A2
A74: Aura Beacon Island | B74: A2 | C74: 2303 | D74: 3 | E74: 1 | F74: 1 | H74: 698 | I74: 45094 | L74: 120% | M74: 1675 | N74: 2.4 | O74: 1482 | P74: 2.12 | R74: 45227 | U74: A2
A75: Aura Beacon Island | B75: A2 | C75: 2303 | D75: 3 | E75: 1 | F75: 1 | H75: 698 | I75: 45453 | K75: 15 | L75: 120% | M75: 1705 | N75: 2.44 | O75: 1705 | P75: 2.44 | Q75: 45441 | R75: 45453 | S75: 13 | T75: 1 | U75: A2
A76: Aura Beacon Island | B76: A2 | C76: 2303 | D76: 3 | E76: 1 | F76: 1 | H76: 698 | I76: 45648 | K76: 12 | L76: 120% | M76: 1375 | N76: 1.97 | O76: 1101 | P76: 1.58 | Q76: 45583 | R76: 45661 | S76: 79 | T76: 14 | U76: A2
A77: Aura Beacon Island | B77: A2 | C77: 2303 | D77: 3 | E77: 1 | F77: 1 | H77: 698 | I77: 45876 | K77: 12 | L77: 120% | M77: 1705 | N77: 2.44 | O77: 1442 | P77: 2.07 | Q77: 45867 | R77: 45905 | S77: 39 | T77: 30 | U77: A2
A78: Aura Beacon Island | B78: A2 | C78: 7203 | D78: 2 | E78: 1 | F78: 1 | H78: 698 | I78: 45094 | L78: 120% | M78: 1575 | N78: 2.26 | O78: 1393 | P78: 2 | R78: 45207 | U78: A2
A79: Aura Beacon Island | B79: A2 | C79: 7203 | D79: 2 | E79: 1 | F79: 1 | H79: 698 | I79: 45754 | K79: 12 | L79: 120% | M79: 1755 | N79: 2.51 | O79: 1755 | P79: 2.51 | Q79: 45672 | R79: 45722 | S79: 51 | T79: 0 | U79: A2
A80: Aura Beacon Island | B80: A2 | C80: 7207 | D80: 2 | E80: 1 | F80: 1 | H80: 698 | I80: 45094 | L80: 120% | M80: 1755 | N80: 2.51 | O80: 1469 | P80: 2.1 | R80: 45300 | U80: A2
A81: Aura Beacon Island | B81: A2 | C81: 7207 | D81: 2 | E81: 1 | F81: 1 | H81: 698 | I81: 45759 | K81: 12 | L81: 120% | M81: 1755 | N81: 2.51 | O81: 1485 | P81: 2.13 | Q81: 45662 | R81: 45795 | S81: 134 | T81: 37 | U81: A2
A82: Aura Beacon Island | B82: A2 | C82: 5203 | D82: 2 | E82: 1 | F82: 1 | H82: 698 | I82: 45675 | K82: 12 | L82: 120% | M82: 1340 | N82: 1.92 | O82: 1340 | P82: 1.92 | Q82: 45610 | R82: 45654 | S82: 45 | T82: 0 | U82: A2
A83: Aura Beacon Island | B83: A2 | C83: 5203 | D83: 2 | E83: 1 | F83: 1 | H83: 698 | I83: 46233 | K83: 14 | L83: 120% | M83: 1755 | N83: 2.51 | O83: 1567 | P83: 2.24 | Q83: 46177 | R83: 46181 | S83: 5 | T83: 0 | U83: A2
A84: Aura Beacon Island | B84: A2 | C84: 7311 | D84: 3 | E84: 1 | F84: 1 | H84: 698 | I84: 45376 | L84: 120% | M84: 1800 | N84: 2.58 | O84: 1800 | P84: 2.58 | Q84: 45300 | R84: 45349 | S84: 50 | T84: 0 | U84: A2
A85: Aura Beacon Island | B85: A2 | C85: 5305 | D85: 3 | E85: 1 | F85: 1 | H85: 698 | I85: 45183 | L85: 120% | M85: 1770 | N85: 2.54 | O85: 1566 | P85: 2.24 | Q85: 45178 | R85: 45212 | S85: 35 | T85: 30 | U85: A2
A86: Aura Beacon Island | B86: A2 | C86: 5305 | D86: 3 | E86: 1 | F86: 1 | H86: 698 | I86: 46021 | K86: 14 | L86: 120% | M86: 1800 | N86: 2.58 | O86: 1479 | P86: 2.12 | Q86: 45941 | R86: 46059 | S86: 119 | T86: 39 | U86: A2
A87: Aura Beacon Island | B87: A2 | C87: 7305 | D87: 3 | E87: 1 | F87: 1 | H87: 698 | I87: 45491 | K87: 15 | L87: 120% | M87: 1650 | N87: 2.36 | O87: 1498 | P87: 2.15 | Q87: 45309 | R87: 45515 | S87: 207 | T87: 25 | U87: A2
A88: Aura Beacon Island | B88: A2 | C88: 7305 | D88: 3 | E88: 1 | F88: 1 | H88: 698 | I88: 45845 | K88: 12 | L88: 120% | M88: 1800 | N88: 2.58 | O88: 1523 | P88: 2.18 | Q88: 45818 | R88: 45932 | S88: 115 | T88: 88 | U88: A2
A89: Aura Beacon Island | B89: A2 | C89: 5303 | D89: 3 | E89: 1 | F89: 1 | H89: 698 | I89: 45760 | K89: 12 | L89: 120% | M89: 1800 | N89: 2.58 | O89: 1523 | P89: 2.18 | Q89: 45706 | R89: 45799 | S89: 94 | T89: 40 | U89: A2
A90: Aura Beacon Island | B90: A3 | C90: 2104 | D90: 1 | E90: 1 | F90: 1 | H90: 719 | I90: 45094 | L90: 80% | M90: 1450 | N90: 2.02 | O90: 1283 | P90: 1.78 | R90: 45184 | U90: A3
A91: Aura Beacon Island | B91: A3 | C91: 2104 | D91: 1 | E91: 1 | F91: 1 | H91: 719 | I91: 45618 | K91: 12 | L91: 80% | M91: 1360 | N91: 1.89 | O91: 1088 | P91: 1.51 | Q91: 45546 | R91: 45660 | S91: 115 | T91: 43 | U91: A3
A92: Aura Beacon Island | B92: A3 | C92: 4306 | D92: 3 | E92: 1 | F92: 1 | H92: 719 | I92: 45954 | K92: 12 | L92: 80% | M92: 1365 | N92: 1.9 | O92: 1102 | P92: 1.53 | Q92: 45907 | R92: 45971 | S92: 65 | T92: 18 | U92: A3
A93: Aura Beacon Island | B93: A3 | C93: 1306 | D93: 3 | E93: 1 | F93: 1 | H93: 719 | I93: 45094 | L93: 80% | M93: 1415 | N93: 1.97 | O93: 1252 | P93: 1.74 | R93: 45216 | U93: A3
A94: Aura Beacon Island | B94: A3 | C94: 1306 | D94: 3 | E94: 1 | F94: 1 | H94: 719 | I94: 45653 | K94: 12 | L94: 80% | M94: 1380 | N94: 1.92 | O94: 1380 | P94: 1.92 | Q94: 45584 | R94: 45716 | S94: 133 | T94: 64 | U94: A3
A95: Aura Beacon Island | B95: A3 | C95: 6204 | D95: 2 | E95: 1 | F95: 1 | H95: 719 | I95: 45389 | L95: 80% | M95: 1385 | N95: 1.93 | O95: 1385 | P95: 1.93 | Q95: 45297 | R95: 45302 | S95: 6 | T95: 0 | U95: A3
A96: Aura Beacon Island | B96: A3 | C96: 6106 | D96: 1 | E96: 1 | F96: 1 | H96: 719 | I96: 45462 | K96: 12 | L96: 80% | M96: 1399 | N96: 1.95 | O96: 1399 | P96: 1.95 | Q96: 45399 | R96: 45606 | S96: 208 | T96: 145 | U96: A3
A97: Aura Beacon Island | B97: A3 | C97: 6306 | D97: 3 | E97: 1 | F97: 1 | H97: 719 | I97: 45888 | K97: 12 | L97: 80% | M97: 1399 | N97: 1.95 | O97: 1184 | P97: 1.65 | Q97: 45800 | R97: 45934 | S97: 135 | T97: 47 | U97: A3
A98: Aura Beacon Island | B98: A3 | C98: 2106 | D98: 1 | E98: 1 | F98: 1 | H98: 719 | I98: 45094 | L98: 80% | M98: 1410 | N98: 1.96 | O98: 1247 | P98: 1.73 | R98: 45248 | U98: A3
A99: Aura Beacon Island | B99: A3 | C99: 1104 | D99: 1 | E99: 1 | F99: 1 | H99: 719 | I99: 45094 | L99: 80% | M99: 1410 | N99: 1.96 | O99: 1164 | P99: 1.62 | R99: 45295 | U99: A3
A100: Aura Beacon Island | B100: A3 | C100: 6207 | D100: 2 | E100: 1 | F100: 1 | H100: 719 | I100: 46059 | K100: 14 | L100: 80% | M100: 1429 | N100: 1.99 | O100: 1429 | P100: 1.99 | Q100: 45990 | R100: 46112 | S100: 123 | T100: 54 | U100: A3
...

Sheet Reconciliation
A1: Reconciliation — Rent Roll ↔ T12
A2: Latest T12 month: Apr 2026. 'In Contract Rent?' flags which charges roll into contract rent.
A4: Control Tie-Outs (rent roll vs latest T12 month)
A5: Measure | B5: Rent Roll | C5: T12 (latest mo. / ann.) | D5: Variance | E5: Var % | F5: Note
A6: Gross Market Rent (asking), monthly | B6: 559150 | C6: 559886.66 | D6: =B6-C6 -> -736.66 | E6: =IF(C6=0,"-",D6/C6) -> -0.0013157306 | F6: RR Market column ↔ T12 GPR — both are seller-set ASKING rents and are NOT a market-rent signal (either can be set at will). True market rent = latest new-lease contract rents + HelloData executed asking; see the unit mix and Lease Trend tabs. Shown here only as a data-integrity check that the two files describe the same property/period.
A7: Contract Rent (occupied), monthly | B7: 497096.77 | C7: 491971.4 | D7: =B7-C7 -> 5125.37 | E7: =IF(C7=0,"-",D7/C7) -> 0.010418024 | F7: RR contract rent ↔ T12 contract net of vacancy (Rentinc+LtL+Vac+NonRev)
A8: T1 AGPR, annualized | B8: 5965161.2 | C8: 6375655.9 | D8: =B8-C8 -> -410494.68 | E8: =IF(C8=0,"-",D8/C8) -> -0.064384698 | F8: RR contract ×12 ↔ T12 latest-month AGPR ×12 (Rentinc+LtL).
A9: Other Income (recurring), monthly | B9: -8808.5 | C9: 57116.12 | D9: =B9-C9 -> -65924.62 | E9: =IF(C9=0,"-",D9/C9) -> -1.1542209 | F9: RR ancillary charges ↔ T12 other-income codes
A11: HelloData Market Rent: Fee Netting (asking AND effective)
A12: Measure | B12: Amount | F12: Note
A13: HelloData T90 asking — gross (mix-wtd) | B13: 1847.2741 | F13: What HelloData scrapes: the website 'Total Monthly', which can bundle mandatory fees.
A14: HelloData T90 effective — gross (mix-wtd) | B14: 1638.256 | F14: HD effective (net of concessions) — also carries the bundled fee, so it is netted too.
A15: Rent-roll new-lease base rent (T90) | B15: 1823.3624 | F15: Recently signed base/contract rent from the rent roll — no bundled fees.
A16: Implied gap (gross HD asking − base) | B16: 23.911706 | F16: If HD sits a roughly constant amount above base across units, that delta is a bundled fee.
A17: Fee netted (from BOTH asking & effective) | B17: 15 | F17: Explicit override (--hd-fee-offset) — confirmed against the property website 'Total Monthly'.
A18: HelloData T90 asking — net of fee | B18: 1832.2741 | F18: Net asking shown on the Lease Trend / Unit Mix tabs.
A19: HelloData T90 effective — net of fee | B19: 1623.256 | F19: Net effective shown on the Lease Trend / Unit Mix tabs. The same fee is removed from T365 and the YoY reads as well.
A20: Candidate flat fees on rent roll | B20: trtra $25.00, amfee $10.00 (disclosure only — NOT auto-netted; confirm against the property website before netting)
A22: Charge-Code Map (rent roll scheduled, monthly)
A23: Charge Code | B23: Mapped Code | C23: Yardi Type | D23: Monthly $ | E23: In Contract Rent?
A24: rent | B24: Rentinc | D24: 497096.77 | E24: Yes
A25: upco | B25: OI | D25: -42182.5 | E25: No
A26: garr | B26: OI | D26: 17965 | E26: No
A27: trtra | B27: OI | D27: 6760 | E27: No
A28: amfee | B28: OI | D28: 2780 | E28: No
A29: cpor | B29: OI | D29: 2050 | E29: No
A30: petp | B30: OI | D30: 1500 | E30: No
A31: petd | B31: OI | D31: 700 | E31: No
A32: mtom | B32: OI | D32: 650 | E32: No
A33: sdep | B33: OI | D33: 600 | E33: No
A34: stor | B34: OI | D34: 240 | E34: No
A35: trvtras | B35: OI | D35: 75 | E35: No
... A37: vtras | B37: OI | D37: 25 | E37: No
A39: Charge → T12 Placement (empirical contract-rent test)
A40: Where each rent-roll charge actually LANDS on the T12 — matched by $ (and name) to a real T12 line — decides what's in contract rent, not the charge name. RUBS recoveries are booked as contra-expenses, so both sides are searched.
A41: Charge | B41: RR $/mo | C41: T12 placement | D41: Conf. | E41: In contract rent? | F41: Basis
A42: rent | B42: 497096.77 | C42: Contract rent | D42: high | E42: Yes | F42: Base contract rent — ties to the T12 Rental Income section.
A43: upco | B43: -42182.5 | C43: Contract rent | D43: high | E43: Yes | F43: Ties to T12 'Vacancy' (-41,838/mo, Potential Rent); 1% from rent-roll -42,182/mo. ⚠ Categorization calls this non-contract, but the T12 placement says contract rent — review the Code column.
A44: garr | B44: 17965 | C44: Other income | D44: high | E44: No | F44: Ties to T12 'Garage' (17,953/mo, Other Income); 0% from rent-roll 17,965/mo.
A45: trtra | B45: 6760 | C45: Utility/RUBS recovery | D45: high | E45: No | F45: Ties to the T12's RUBS/utility-rebill block (~6,942/mo, booked as a contra-expense) — a resident recovery, not contract rent.
A46: amfee | B46: 2780 | C46: Other income | D46: high | E46: No | F46: Ties to T12 'Amenities Income' (2,739/mo, Other Income); 1% from rent-roll 2,780/mo.
A47: cpor | B47: 2050 | C47: Other income | D47: high | E47: No | F47: Ties to T12 'Carport' (2,100/mo, Other Income); 2% from rent-roll 2,050/mo.
A48: petp | B48: 1500 | C48: Other income | D48: med | E48: No | F48: Ties to T12 'Pet Premium' (1,371/mo, Other Income); 9% from rent-roll 1,500/mo.
A49: petd | B49: 700 | C49: Other income | D49: med | E49: No | F49: Ties to T12 'Initial Pet Fees' (851/mo, Other Income); 18% from rent-roll 700/mo.
A50: mtom | B50: 650 | C50: Other income | D50: low | E50: No | F50: No T12 income/rebill line ties to 650/mo — treated as other income / pass-through (per the charge categorization).
A51: sdep | B51: 600 | C51: Other income | D51: low | E51: No | F51: No T12 income/rebill line ties to 600/mo — treated as other income / pass-through (per the charge categorization).
A52: stor | B52: 240 | C52: Other income | D52: low | E52: No | F52: No T12 income/rebill line ties to 240/mo — treated as other income / pass-through (per the charge categorization).
A53: trvtras | B53: 75 | C53: Other income | D53: low | E53: No | F53: No T12 income/rebill line ties to 75/mo — treated as other income / pass-through (per the charge categorization).
... A55: vtras | B55: 25 | C55: Other income | D55: low | E55: No | F55: No T12 income/rebill line ties to 25/mo — treated as other income / pass-through (per the charge categorization).
A57: Correlated Cross-Checks (rent-roll counts/charges ↔ T12 income)
A58: Parking | B58: RR: 0 units billed parking, $0/mo (avg $0/space) ↔ T12 parking income $20,217/mo
A59: Utility recapture (RUBS) | B59: T12 utility expense $12,788/mo (UWS+UC+UF+UT) ↔ RUBS/billback income $14,261/mo (RWS+RT+RF) = 112% recaptured · water/sewer alone 86% ($6,942/$8,088)
A61: NOI Tie-Out to Operator Statement (each source statement, annual $)
A62: Statement | B62: Reported NOI | C62: Standardized NOI | D62: Δ | E62: Note
A63: 2026-04 | B63: 3401721 | C63: 3401721 | D63: 0 | E63: Ties to the operator's reported NOI (RUBS gross-up nets to zero).

Sheet Codes
A1: Standardized Code Legend
A2: Source list for the 'T12 Categorized' dropdown. Col A drives VLOOKUP & SUMIFS.
A4: Code | B4: Category | C4: Section
A5: Rentinc | B5: Rental Income | C5: rev
A6: OI | B6: Other Income | C6: rev
A7: RWS | B7: Rubs Water / Sewage | C7: rev
A8: RT | B8: Rubs Trash | C8: rev
A9: RF | B9: Rubs Fees | C9: rev
A10: park | B10: Garage / Parking | C10: rev
A11: CI | B11: Corporate Income | C11: rev
A12: cable | B12: Cable Income | C12: rev
A13: ltl | B13: (Loss to Lease) / Gain to Lease | C13: rev
A14: vac | B14: Vacancy | C14: rev
A15: cl | B15: Collection Loss / Bad Debt | C15: rev
... A59: onoe | B59: Other Non-Operating Expense | C59: nonop-exp
